Workbook

Sheet Data 
A1: *All figures in TND | C1: Net income | H1: Total revenues | M1: Liabilities | R1: Equity
A2: Name | B2: shares | C2: 2020 | D2: 2021 | E2: 2022 | F2: 2023 | G2: 2024 | H2: 2020 | I2: 2021 | J2: 2022 | K2: 2023 | L2: 2024 | M2: 2020 | N2: 2021 | O2: 2022 | P2: 2023 | Q2: 2024 | R2: 2020 | S2: 2021 | T2: 2022 | U2: 2023 | V2: 2024
A3: société de fabrication des boissons de tunisie | B3: 268125000 | C3: 210586454 | D3: 251025666 | E3: 257026776 | F3: 281681042 | G3: 282951677 | H3: 1202858757 | I3: 1197117395 | J3: 1329913407 | K3: 1369328653 | L3: 1396203653 | M3: 605198771 | N3: 582089575 | O3: 663900702 | P3: 674204914 | Q3: 702784435 | R3: 1044895289 | S3: 1128462280 | T3: 1214081074 | U3: 1330442193 | V3: 1419478330
A4: Banque Attijari De Tunisie | B4: 42000000 | C4: 275188000 | D4: 283034000 | E4: 332403000 | F4: 366478000 | G4: 356943000 | H4: 543892000 | I4: 601056000 | J4: 664428000 | K4: 692133000 | L4: 739756000 | M4: 9404191000 | N4: 10014188000 | O4: 10671334000 | P4: 10761871000 | Q4: 11218431000 | R4: 885704000 | S4: 944291000 | T4: 1012474000 | U4: 1119719000 | V4: 1182999000
A5: Poulina Group Holding | B5: 180003600 | C5: 74937220 | D5: 93285368 | E5: 65769556 | F5: 129654069 | G5: 162090645 | H5: 2293947835 | I5: 2882599824 | J5: 3164460391 | K5: 3477502364 | L5: 3447451207 | M5: 2811485344 | N5: 3996369427 | O5: 4270526977 | P5: 3367995642 | Q5: 3249814754 | R5: 942307377 | S5: 979707603 | T5: 978293945 | U5: 1062563406 | V5: 1151954920
A6: Societe Delice Holding | B6: 54907262 | C6: 57816018 | D6: 70352493 | E6: 78543635 | F6: 97781367 | G6: 101013371 | H6: 1046727484 | I6: 1164933467 | J6: 1266872997 | K6: 1388767638 | L6: 1442665250 | M6: 421245165 | N6: 404261860 | O6: 450915549 | P6: 522155650 | Q6: 564831339 | R6: 241147799 | S6: 304147184 | T6: 364189269 | U6: 422934128 | V6: 489797529
A7: One Tech Holding | B7: 80400000 | C7: 19769312 | D7: 30744092 | E7: 13791941 | F7: 38332438 | G7: 30197705 | H7: 718581103 | I7: 905056057 | J7: 1046772970 | K7: 1104751430 | L7: 1048199298 | M7: 310101478 | N7: 335686674 | O7: 366593922 | P7: 349239677 | Q7: 298618444 | R7: 346534054 | S7: 362643559 | T7: 354158354 | U7: 386546573 | V7: 394399831
A8: Carthage Cement | B8: 343624940 | C8: 19364586 | D8: 31509188 | E8: 35650372 | F8: 55193147 | G8: 70256035 | H8: 252976021 | I8: 325968814 | J8: 366979942 | K8: 431588146 | L8: 421573245 | M8: 708595935 | N8: 640245531 | O8: 658953060 | P8: 615719080 | Q8: 544934512 | R8: 135979012 | S8: 167488200 | T8: 203138572 | U8: 258331719 | V8: 328587754
A9: SOTUVER | B9: 39254475 | C9: 10651279 | D9: 19985560 | E9: 29905517 | F9: 46641768 | G9: 41791733 | H9: 91090533 | I9: 104902769 | J9: 156191940 | K9: 262355892 | L9: 235107783 | M9: 91956837 | N9: 170267584 | O9: 264579385 | P9: 334927249 | Q9: 401543583 | R9: 75018410 | S9: 85484294 | T9: 101921247 | U9: 130270434 | V9: 150579061
A10: Societe Tunisie Profiles Aluminium | B10: 50000000 | C10: 21220962 | D10: 19059221 | E10: 28965394 | F10: 41345385 | G10: 48271762 | H10: 180466964 | I10: 214886191 | J10: 284773841 | K10: 287981082 | L10: 340361979 | M10: 131432591 | N10: 155341106 | O10: 167089348 | P10: 160005488 | Q10: 208765994 | R10: 136745685 | S10: 137213594 | T10: 148247471 | U10: 180629473 | V10: 210685434
A11: SPDIT-SICAF | B11: 28000000 | C11: 16915587 | D11: 17431933 | E11: 21767036 | F11: 26798947 | G11: 31978317 | H11: 19682665 | I11: 20489302 | J11: 23671906 | K11: 31146141 | L11: 34548651 | M11: 2782823 | N11: 1921585 | O11: 2792929 | P11: 4279120 | Q11: 4487488 | R11: 70761043 | S11: 71392976 | T11: 76360012 | U11: 83558959 | V11: 91737276
A12: Automobile Reseau Tunisien Et Service SA | B12: 38250000 | C12: 33238344 | D12: 41292326 | E12: 29181541 | F12: 42191994 | G12: 42191994 | H12: 212270266 | I12: 270149720 | J12: 175328865 | K12: 307457210 | L12: 307457210 | M12: 83515129 | N12: 47123113 | O12: 69394960 | P12: 147330366 | Q12: 157502369 | R12: 202470049 | S12: 213751115 | T12: 212324796 | U12: 140945761 | V12: 223222609
A13: City Cars | B13: 18000000 | C13: 20997476 | D13: 33354791 | E13: 30325763 | F13: 31718596 | G13: 29518791 | H13: 236557895 | I13: 343752648 | J13: 343102459 | K13: 375037265 | L13: 378411694 | M13: 94479452 | N13: 125141075 | O13: 156681418 | P13: 178709683 | Q13: 188626944 | R13: 57993863 | S13: 75777791 | T13: 84264584 | U13: 93488979 | V13: 100515697
A14: Ste Assurances Magrebia SA | B14: 4500000 | C14: 53498963 | D14: 77138663 | E14: 81214552 | F14: 82043544 | G14: 100657148 | H14: 39437994 | I14: 25824239 | J14: 28099216 | K14: 58872202 | L14: 69462727 | M14: 705324780 | N14: 748804044 | O14: 818450849 | P14: 925960837 | Q14: 1000685399 | R14: =45000000+64915188 -> 109915188 | S14: 154247479 | T14: 180502400 | U14: 202661534 | V14: 222179266
A15: Tunisie Leasing | B15: 10800000 | C15: 8979580 | D15: 7219162 | E15: 20706291 | F15: 28217472 | G15: 37470534 | H15: 144274295 | I15: 135140038 | J15: 150119991 | K15: 159079516 | L15: 195436341 | M15: 1796491353 | N15: 1775948425 | O15: 1776253794 | P15: 1982538258 | Q15: 2701941948 | R15: 223423406 | S15: 219991497 | T15: 239740658 | U15: 262109131 | V15: 289189747
A16: Compagnie Internationale De Leasing | B16: 7000000 | C16: 12447280 | D16: 15554485 | E16: 17229686 | F16: 19604550 | G16: 20182707 | H16: 30371293 | I16: 37117968 | J16: 42675715 | K16: 43823948 | L16: 46075652 | M16: 519445701 | N16: 538160372 | O16: 526021032 | P16: 573586678 | Q16: 591321795 | R16: 102953690 | S16: 109669667 | T16: 117583196 | U16: 127006909 | V16: 134157467
A17: Tunis RE | B17: 20000000 | C17: 739837 | D17: 334289 | E17: 440431 | F17: 114589 | G17: 3559600 | H17: 26770378 | I17: 23989023 | J17: 26689229 | K17: 31460523 | L17: 34087211 | M17: 707669341 | N17: 688447995 | O17: 707235919 | P17: 679956517 | Q17: 764975240 | R17: 212407678 | S17: 223916077 | T17: 236382079 | U17: 246462733 | V17: 258375216
A18: Assurances Maghrebia Vie SA | B18: 25000000 | C18: 12061819 | D18: 13614231 | E18: 13631045 | F18: 14999019 | G18: 26535372 | H18: 15282744 | I18: 17646440 | J18: 19923333 | K18: 22261847 | L18: 24899687 | M18: 369823362 | N18: 433230835 | O18: 496111565 | P18: 695019447 | Q18: 776430083 | R18: 62863953 | S18: 72697316 | T18: 115471809 | U18: 127870307 | V18: 142842908
A19: SAH | B19: =84015979 -> 84015979 | C19: 33389210 | D19: 16220997 | E19: 35323742 | F19: 35650047 | G19: 61608801 | H19: 631666504 | I19: 673903901 | J19: 880620421 | K19: 901985011 | L19: 981989853 | M19: 571148278 | N19: 669145153 | O19: 715018763 | P19: 760318382 | Q19: 882318491 | R19: 314215854 | S19: 295909720 | T19: 312143492 | U19: 319267092 | V19: 353488673
A20: Arab Tunisian Lease | B20: 32500000 | C20: 5279696 | D20: 11132156 | E20: 16270427 | F20: 19975764 | G20: 22111702 | H20: 30224741 | I20: 39917653 | J20: 46605128 | K20: 51196690 | L20: 58431579 | M20: 101586485 | N20: 550778433 | O20: 511992456 | P20: 555632129 | Q20: 577991444 | R20: 529216961 | S20: 110283583 | T20: 120054439 | U20: 131251766 | V20: 143613469
A21: Societe Tunisienne des Marches de Gros SA | B21: 13200000 | C21: 4635285 | D21: 5846000 | E21: 6221525 | F21: 7650860 | G21: 7058807 | H21: 14953062 | I21: 15429133 | J21: 16508737 | K21: 17707272 | L21: 18543742 | M21: 4661439 | N21: 4534835 | O21: 5959719 | P21: 6392678 | Q21: 6362805 | R21: 29054683 | S21: 31809716 | T21: 32624556 | U21: 34528357 | V21: 34496586
A22: Hannibal Lease | B22: 11000000 | C22: -3178572 | D22: 5908464 | E22: 7977572 | F22: 13065086 | G22: 12638444 | H22: 18642707 | I22: 32461319 | J22: 43826623 | K22: 46219616 | L22: 48837921 | M22: 609669899 | N22: 546064460 | O22: 537406584 | P22: 567056088 | Q22: 636933102 | R22: 70402866 | S22: 76174587 | T22: 81775841 | U22: 91419671 | V22: 99902831
A23: ATB | B23: 128000000 | C23: 12458000 | D23: -61435000 | E23: 29600000 | F23: -158000 | G23: 31285000 | H23: 297547000 | I23: 333106000 | J23: 365930000 | K23: 406023000 | L23: 436785000 | M23: 7371459000 | N23: 7630042000 | O23: 7744312000 | P23: 7600100000 | Q23: 8360359000 | R23: 585655000 | S23: 594128000 | T23: 618059000 | U23: 617788000 | V23: 649326000
A24: BIAT | B24: 40800000 | C24: 277480000 | D24: 283431000 | E24: 312402000 | F24: 358591000 | G24: 379406000 | H24: 1034036000 | I24: 1134600000 | J24: 1415147000 | K24: 1603909000 | L24: 1750286000 | M24: 16106196000 | N24: 17356171000 | O24: 18948687000 | P24: 20633250000 | Q24: 22776769000 | R24: 1771111000 | S24: 1877408000 | T24: 2000681000 | U24: 2158755000 | V24: 2314276000
A25: BNA | B25: 64000000 | C25: 107639000 | D25: 173366000 | E25: 169910000 | F25: 212043000 | G25: 210906000 | H25: 691244000 | I25: 912190000 | J25: 946380000 | K25: 1047026000 | L25: 1044281000 | M25: 12684441000 | N25: 17590365000 | O25: 20071667000 | P25: 21323167000 | Q25: 20576496000 | R25: 1650596000 | S25: 1761097000 | T25: 1865475000 | U25: 2035541000 | V25: 2188321000
A26: BT | B26: 270000000 | C26: 94411000 | D26: 152124000 | E26: 168562000 | F26: 182322000 | G26: 199437000 | H26: 380424000 | I26: 385983000 | J26: 428815000 | K26: 493636000 | L26: 518336000 | M26: 5566025000 | N26: 5851368000 | O26: 6387792000 | P26: 6918575000 | Q26: 7783177000 | R26: 1089048000 | S26: 1163594000 | T26: 1281121000 | U26: 1385289000 | V26: 1457011000
A27: AMEN BANK | B27: 30264000 | C27: 98440000 | D27: 136147000 | E27: 152578000 | F27: 216546000 | G27: 243545000 | H27: 395028000 | I27: 453158000 | J27: 488396000 | K27: 538309000 | L27: 562660000 | M27: 7895119000 | N27: 8163618000 | O27: 8871857000 | P27: 9384043000 | Q27: 10072285000 | R27: 1169511000 | S27: 1241864000 | T27: 1366659000 | U27: 1564603000 | V27: 1703741000
A28: EURO-CYCLES | B28: 9801000 | C28: 16610924 | D28: 26619458 | E28: 16628745 | F28: 4959031.8 | G28: 10976341 | H28: 1.1983366e+08 | I28: 1.4913271e+08 | J28: 1.6271355e+08 | K28: 1.1321541e+08 | L28: 1.2225003e+08 | M28: 67110276 | N28: 1.5820675e+08 | O28: 1.6156741e+08 | P28: 1.1142387e+08 | Q28: 99591114 | R28: 46724056 | S28: =59646348.181-1616.184 -> 59644732 | T28: =61351391.438-1493.16 -> 61349898 | U28: =56259856.585-402.38 -> 56259454 | V28: =64094899.424-1105.968 -> 64093793
A29: ICF | B29: 2100000 | C29: -11366764 | D29: 9015089 | E29: 31090040 | F29: 7320560 | G29: 21453470 | H29: 117519304 | I29: 148047650 | J29: 230831878 | K29: 146579725 | L29: 169862009 | M29: 25293660 | N29: 47481668 | O29: 51268475 | P29: 25129700 | Q29: 55599127 | R29: 87466518 | S29: 93052722 | T29: 116093876 | U29: 107403020 | V29: 121626025
A30: STB | B30: 155375000 | C30: 72159000 | D30: 117019000 | E30: 87878000 | F30: 86035000 | G30: 102331000 | H30: 625657000 | I30: 650447000 | J30: 697492000 | K30: 714678000 | L30: 689336000 | M30: 11149312000 | N30: 12304641000 | O30: 13396948000 | P30: 13232421000 | Q30: 13480669000 | R30: 1100124000 | S30: 1267335000 | T30: 1356233000 | U30: 1323092000 | V30: 1419547000
A31: UIB | B31: 32560000 | C31: 65171000 | D31: 82782000 | E31: 132539000 | F31: 124983000 | G31: 71861000 | H31: 403016000 | I31: 444415000 | J31: 493246000 | K31: 522981000 | L31: 539825000 | M31: 5761185000 | N31: 6044581000 | O31: 6366819000 | P31: 6732963000 | Q31: 7268244000 | R31: 721311000 | S31: 780025000 | T31: 889994000 | U31: 987375000 | V31: 1030162000
A32: ENNAKL AUTOMOBILES | B32: 30000000 | C32: 14083691 | D32: 36056125 | E32: 43211101 | F32: 52798417 | G32: 55526338 | H32: 448683874 | I32: 538114892 | J32: 568542801 | K32: 348209795 | L32: 352118840 | M32: 202955633 | N32: 165667191 | O32: 291923651 | P32: 224228380 | Q32: 286727611 | R32: 163243575 | S32: 179686332 | T32: 203382280 | U32: 302335851 | V32: 331462189
A33: ASTREE | B33: 6000000 | C33: 25524992 | D33: 21056249 | E33: 17103870 | F33: 22678287 | G33: 28985751 | H33: =25863627+10533472+25395777 -> 61792876 | I33: =7762313+4208100+25190756 -> 37161169 | J33: =6846173+6959655+24305395 -> 38111223 | K33: =14782595+14560216+31466266 -> 60809077 | L33: =15541709+16950863+35701976 -> 68194548 | M33: =630810375-R33 -> 477472991 | N33: =686764477-S33 -> 529170844 | O33: =764430352-T33 -> 606532849 | P33: =864062717-U33 -> 695486928 | Q33: =817830616-V32 -> 486368427 | R33: 153337384 | S33: 157593633 | T33: 157897503 | U33: 168575789 | V33: 184361541
A34: BH LEASING | B34: 7000000 | C34: -513135 | D34: 1140342 | E34: 1961523 | F34: 3149573 | G34: 3898695 | H34: 8500405 | I34: 13704752 | J34: 15733748 | K34: 14960151 | L34: 18535404 | M34: 282858023 | N34: 254182700 | O34: 263947305 | P34: 251831404 | Q34: 270253037 | R34: 29189001 | S34: 30315318 | T34: 32265200 | U34: 35402071 | V34: 39285275
A35: CIMENTS DE BIZERTE | B35: 44047290 | C35: -421318 | D35: -6153262 | E35: -28950468 | F35: -34355944 | G35: -44790355 | H35: 111057228 | I35: 125207539 | J35: 120080846 | K35: 91323675 | L35: 27838606 | M35: 214816606 | N35: 201740080 | O35: 225797912 | P35: 219922350 | Q35: 245366150 | R35: 30569803 | S35: 85919313 | T35: 56754210 | U35: 21742193 | V35: 143302286
A36: ESSOUKNA | B36: 5050500 | C36: -172078 | D36: -952432 | E36: 672754 | F36: -2846051 | G36: -2501388 | H36: 17253957 | I36: 12015612 | J36: 17480481 | K36: 6652987 | L36: 389696 | M36: 34790177 | N36: 31046730 | O36: 23462088 | P36: 27128831 | Q36: 48126294 | R36: 34104440 | S36: 33606766 | T36: 34235231 | U36: 30336199 | V36: 28340886
A37: LAND'OR | B37: 13784285 | C37: 6980368 | D37: 9631470 | E37: -9932649 | F37: 6840834 | G37: 12631257 | H37: 133756032 | I37: 160856608 | J37: 192456617 | K37: 257094946 | L37: 261556427 | M37: 59383985 | N37: 103705103 | O37: 128463976 | P37: 134953183 | Q37: 129227282 | R37: 68431213 | S37: 77673850 | T37: 88613806 | U37: 97538786 | V37: 110868117
A38: MONOPRIX | B38: 25345736 | C38: -9586617 | D38: -3117449 | E38: -8392666 | F38: 1013684 | G38: 6872913 | H38: 649624978 | I38: 657548597 | J38: 665523304 | K38: 724783677 | L38: 775277935 | M38: 314223680 | N38: 323651502 | O38: 338300600 | P38: 298077011 | Q38: 299295661 | R38: 50037812 | S38: 46812093 | T38: 37261685 | U38: 44697377 | V38: 49423396
A39: NEW BODY LINE | B39: 4250400 | C39: 1216170 | D39: 2167848 | E39: 1135336 | F39: 1136892 | G39: -6120768 | H39: 4947403 | I39: 6843886 | J39: 5466474 | K39: 13057296 | L39: 8932846 | M39: 555272 | N39: 1334010 | O39: 1351167 | P39: 1719857 | Q39: 2016622 | R39: 12068397 | S39: 12687912 | T39: 12200418 | U39: 13120762 | V39: 5073268
A40: SIMPAR | B40: 1100000 | C40: -9375293 | D40: -8961870 | E40: -3341071 | F40: -5512252 | G40: -7700174 | H40: 44960783 | I40: 39563223 | J40: 66860622 | K40: 44448221 | L40: 17984310 | M40: 165713904 | N40: 166207065 | O40: 153733055 | P40: 169671737 | Q40: 230817868 | R40: 61794177 | S40: 52622689 | T40: 49084912 | U40: 48480225 | V40: 37809397
A41: SOTIPAPIER | B41: 28184091 | C41: 1621460 | D41: 18638969 | E41: 25980182 | F41: 2440312 | G41: 3110466 | H41: 82783819 | I41: 127900616 | J41: 159442785 | K41: 99053745 | L41: 111229349 | M41: 35568632 | N41: 40315206 | O41: 44581007 | P41: 49209724 | Q41: 71045620 | R41: 64946476 | S41: 71376034 | T41: 84827954 | U41: 74383286 | V41: 68616227
A42: STAR | B42: 2307693 | C42: 16398079 | D42: 21055608 | E42: 29341890 | F42: 23271441 | G42: 27492685 | H42: 17558266 | I42: 30162325 | J42: 19665311 | K42: 35330767 | L42: 40533534 | M42: 959370851 | N42: 981072774 | O42: 1041041053 | P42: 1113716118 | Q42: 1157457803 | R42: 365412862 | S42: 379642622 | T42: 400302433 | U42: 408932925 | V42: 421318516
A43: TELNET HOLDING | B43: 12130800 | C43: 7145624.4 | D43: 9063508.3 | E43: 8051777 | F43: -3951540.2 | G43: 9540002.7 | H43: 40634654 | I43: 49386787 | J43: 56863378 | K43: 61818228 | L43: 69331868 | M43: 22695949 | N43: 30334050 | O43: 30522709 | P43: 41528664 | Q43: 44329721 | R43: 32318117 | S43: 37209067 | T43: 37524263 | U43: 25095528 | V43: 29690929
A44: TUNINVEST SICAR | B44: 966000 | C44: 2790467 | D44: 489939 | E44: 142237 | F44: 416550 | G44: 787460 | H44: 5921854 | I44: 744297 | J44: 758996 | K44: 1052556 | L44: 1192821 | M44: =11810500-R44 -> 4505217 | N44: =3760000+339785 -> 4099785 | O44: =3896500+343752 -> 4240252 | P44: 4677768 | Q44: 4545077 | R44: 7305283 | S44: 6346222 | T44: 6005460 | U44: 5939010 | V44: 6243470
A45: UNIMED | B45: 32000000 | C45: 6979958 | D45: 8703199 | E45: 7830096 | F45: 5545876 | G45: 19371990 | H45: 91074505 | I45: 84549649 | J45: 96616277 | K45: 136146412 | L45: 147871511 | M45: =158416399-R45 -> 43269652 | N45: 45642269 | O45: 80166169 | P45: 103926136 | Q45: 100071407 | R45: 115146747 | S45: 108833938 | T45: 103698489 | U45: 94252712 | V45: 116206097
A46: WIFACK INTERNATIONAL BANK | B46: 30000000 | C46: -5765829 | D46: 1808344 | E46: 6340059 | F46: 8998657 | G46: 10126529 | H46: 32018292 | I46: 49934915 | J46: 68790330 | K46: 84718638 | L46: 103534618 | M46: 664750055 | N46: 833255508 | O46: 1066752060 | P46: 1264337588 | Q46: 1513574232 | R46: 155458203 | S46: 157269765 | T46: 163612043 | U46: 170081835 | V46: 179123397
A47: AETECH | B47: 2223334 | C47: 290537 | D47: -384549 | E47: -391079 | F47: -1413801 | G47: -714137 | H47: 6186198 | I47: 7925085 | J47: 7955547 | K47: 6271779 | L47: 4588790 | M47: 9407312 | N47: 10451909 | O47: 12514405 | P47: 12359552 | Q47: 12643889 | R47: -4795270 | S47: -5179818 | T47: -5911534 | U47: -7379313 | V47: -8160236
A48: AIR LIQUIDE TUNISIE | B48: 1637504 | C48: 15530807 | D48: 21323933 | E48: 19115474 | F48: 23540861 | G48: 27542392 | H48: 99769848 | I48: 128954528 | J48: 119230650 | K48: 131347248 | L48: 140071799 | M48: 55460152 | N48: 62317105 | O48: 60054598 | P48: 66268353 | Q48: 73418154 | R48: =60311198-586355+15530807 -> 75255650 | S48: =67998174-1217186+21323933 -> 88104921 | T48: =79563412-1189628+19115474 -> 97489258 | U48: =88946172-1225474+23540861 -> 111261559 | V48: =101636404-1450653+27542392 -> 127728143
A49: ALKIMIA | B49: 1947253 | C49: -40174933 | D49: -45846561 | E49: -24719789 | F49: -39309786 | G49: -44400661 | H49: 179605997 | I49: 184151492 | J49: 253834897 | K49: 193563960 | L49: 168509961 | M49: 266422126 | N49: 342310913 | O49: 389088179 | P49: 372906866 | Q49: 384422260 | R49: -55611143 | S49: -101511541 | T49: -126284291 | U49: -165653600 | V49: -190055502
A50: ASSAD | B50: 24000000 | C50: -4756960 | D50: -13168949 | E50: -8568749 | F50: -9649983 | G50: 3693042 | H50: 122749935 | I50: 124775213 | J50: 129454469 | K50: 117620623 | L50: 153403518 | M50: 111181507 | N50: 130247980 | O50: 131602517 | P50: 145488659 | Q50: 136786312 | R50: 47081827 | S50: 33852648 | T50: 25328875 | U50: 15673420 | V50: 19685979
A51: BEST LEASE | B51: 30000000 | C51: 13396097 | D51: 28819634 | E51: 18896541 | F51: 37815493 | G51: 61222876 | H51: 17837494 | I51: 24955019 | J51: 30215962 | K51: 28951503 | L51: 27449311 | M51: 281577533 | N51: 324692820 | O51: 307141873 | P51: 343784953 | Q51: 359051333 | R51: 88005294 | S51: 94932008 | T51: 103756822 | U51: 112467530 | V51: 111210504
A52: BNA ASSURANCES | B52: 87391790 | C52: 624641 | D52: 1766521 | E52: 5569995 | F52: 8577827 | G52: 16315042 | H52: 17974822 | I52: 18836747 | J52: 27878876 | K52: 30356888 | L52: 30737418 | M52: 473906727 | N52: 457167856 | O52: 509408579 | P52: 532572561 | Q52: 556237211 | R52: -64124657 | S52: 70457972 | T52: 76027967 | U52: 84605794 | V52: 100920836
A53: BTE | B53: 4500000 | C53: -18324000 | D53: -32427000 | E53: -30303000 | F53: -37874000 | G53: -30204000 | H53: 48869000 | I53: 75281000 | J53: 74332000 | K53: 78713000 | L53: 83432000 | M53: 1057972000 | N53: 1173663000 | O53: 1228991000 | P53: 1393027000 | Q53: 1472034000 | R53: 327290000 | S53: 349190000 | T53: 327643000 | U53: 170705000 | V53: 158713000
A54: CELLCOM | B54: 4461532 | C54: 804082 | D54: 10148 | E54: -3333845 | F54: 218409 | G54: 943507 | H54: 56227345 | I54: 66462113 | J54: 62392987 | K54: 62509056 | L54: 72475993 | M54: 19665844 | N54: 22114646 | O54: 21952580 | P54: 21769731 | Q54: 26582519 | R54: 9129693 | S54: 8845150 | T54: 5481331 | U54: 5674694 | V54: 6618201
A55: MAGASIN GENERAL | B55: 15777070 | C55: -37032899 | D55: -26898042 | E55: -39188000 | F55: -42372774 | G55: -10067663 | H55: 1018231699 | I55: 1018302242 | J55: 1030434817 | K55: 1109063173 | L55: 1139052949 | M55: 723507514 | N55: 720750372 | O55: 737209137 | P55: 692022783 | Q55: 678457677 | R55: -56534766 | S55: -42423295 | T55: -82679645 | U55: -6819474 | V55: -77338323
A56: MPBS | B56: 10334430 | C56: 759248 | D56: 7903399 | E56: 5715195 | F56: 2975079 | G56: 8365882 | H56: 89599099 | I56: 114990628 | J56: 116185518 | K56: 124709171 | L56: 162592160 | M56: 43593964 | N56: 48185799 | O56: 48053251 | P56: 48540549 | Q56: 63337467 | R56: 46555480 | S56: 53276717 | T56: 56806265 | U56: 57498899 | V56: 63212502
A57: SAM | B57: 5561635 | C57: 1056402 | D57: 1834726 | E57: 3314647 | F57: 3764171 | G57: 2816529 | H57: 18733455 | I57: 23347071 | J57: 28585109 | K57: 28768485 | L57: 29360090 | M57: 8677634 | N57: 9055388 | O57: 7830925 | P57: 9621387 | Q57: 9139031 | R57: 11672857 | S57: 12235522 | T57: 14359703 | U57: 16008448 | V57: 15583424
A58: SANIMED | B58: 12400000 | C58: -12968704 | D58: -194892 | E58: -9941027 | F58: -8687140 | G58: -11876483 | H58: 38670214 | I58: 63820219 | J58: 58395182 | K58: 40764050 | L58: 33030212 | M58: 121785155 | N58: 143261932 | O58: 152638866 | P58: 156745772 | Q58: 159586306 | R58: 21901561 | S58: 21634125 | T58: 11620553 | U58: 19871886 | V58: 18374915
A59: SIAME | B59: 15444000 | C59: 1676521 | D59: 4110684 | E59: -251665 | F59: 1432924 | G59: 2383035 | H59: 53952982 | I59: 64602126 | J59: 49298589 | K59: 63688596 | L59: 64170175 | M59: 36921391 | N59: 32824436 | O59: 33977649 | P59: 39436193 | Q59: 37576025 | R59: 28211521 | S59: 30184594 | T59: 29437205 | U59: 29653156 | V59: 29899264
A60: SITS | B60: 15600000 | C60: 10300180 | D60: 4664913 | E60: 1413255 | F60: 1873169 | G60: 720325 | H60: 46084011 | I60: 7234656 | J60: 7672136 | K60: 8689162 | L60: 5014410 | M60: 25239211 | N60: 19130051 | O60: 16877246 | P60: 20631104 | Q60: 27234964 | R60: 36766016 | S60: 37788968 | T60: 38948141 | U60: 40855316 | V60: 41670487
A61: SMART TUNISIE | B61: 10123443 | D61: 20163148 | E61: 18051261 | F61: 15074832 | G61: 15041631 | I61: 317951491 | J61: 363624072 | K61: 374533327 | L61: 436303760 | N61: 84759906 | O61: 110880734 | P61: 124436196 | Q61: 140262055 | S61: 96240590 | T61: 97546025 | U61: 99613283 | V61: 104921806
A62: SOMOCER | B62: 40656000 | C62: -15303588 | D62: 2253385 | E62: -13823702 | F62: -21107779 | G62: -43516501 | H62: 127256481 | I62: 152305834 | J62: 154210248 | K62: 131208983 | L62: 90570116 | M62: 305454994 | N62: 316539753 | O62: 326088991 | P62: 359225211 | Q62: 350617305 | R62: =69149625+2046712 -> 71196337 | S62: =72954483-622437 -> 72332046 | T62: =58531898+1957674 -> 60489572 | U62: =3655506+33571655 -> 37227161 | V62: =-15309408+5059348 -> -10250060
A63: SOTEMAIL | B63: 34513514 | C63: -5962275 | D63: 1025715 | E63: -4768161 | F63: -9767631 | G63: -14524034 | H63: 47785527 | I63: 62152220 | J63: 64601297 | K63: 56725256 | L63: 37616704 | M63: 93326817 | N63: 106228080 | O63: 104820102 | P63: 114751020 | Q63: 105744523 | R63: 42053675 | S63: 42900393 | T63: 37953233 | U63: 28006604 | V63: 36335543
A64: SOTETEL | B64: 4636800 | C64: 3882012 | D64: -254799 | E64: 1196336 | F64: 3878594 | G64: 4103909 | H64: 32710420 | I64: 40152788 | J64: 50742688 | K64: 66485835 | L64: 71866163 | M64: 44434391 | N64: 41405802 | O64: 44048001 | P64: 63317875 | Q64: 56536928 | R64: 26877165 | S64: 26158686 | T64: 27355022 | U64: 31233616 | V64: 33059249
A65: SOTRAPIL | B65: 4138200 | C65: 7162143 | D65: 7640593 | E65: 9377564 | F65: 8696848 | G65: 8933920 | H65: 9266440 | I65: 18060234 | J65: 20244337 | K65: 18331311 | L65: 18775419 | M65: 9710521 | N65: 11600471 | O65: 12121588 | P65: 15785857 | Q65: 9957265 | R65: 47622038 | S65: 50492949 | T65: 54711406 | U65: 57123495 | V65: 59669093
A66: STA | B66: 2000000 | D66: 4569765 | E66: 6369579 | F66: 1345754 | G66: 5823031 | I66: 71633801 | J66: 113049772 | K66: 79975827 | L66: 109190916 | N66: 30456876 | O66: 48321725 | P66: 41894683 | Q66: 75963070 | S66: 28153587 | T66: 30495386 | U66: 27241140 | V66: 31064171
A67: STIP | B67: 4207823 | C67: 142752222 | D67: 24184881 | E67: 11922736 | F67: -1570648 | G67: -9929154 | H67: 75983685 | I67: 123201339 | J67: 152426163 | K67: 139154927 | L67: 143206220 | M67: 182228196 | N67: 184860041 | O67: 211955616 | P67: 212597264 | Q67: 199452120 | R67: -93230691 | S67: 5037776 | T67: 16900924 | U67: 15139375 | V67: 5210221
A68: TAWASOL GH | B68: 108000000 | C68: -7254712 | D68: -7254712 | E68: -1903377 | F68: 1158519 | G68: -866039 | H68: 68673429 | I68: 68673429 | J68: 80599640 | K68: 97250752 | L68: 73976177 | M68: 152006162 | N68: 152006162 | O68: 147361163 | P68: 162037514 | Q68: 167651920 | R68: =26470182-97347 -> 26372835 | S68: =26470182-97347 -> 26372835 | T68: =24959374+178548 -> 25137922 | U68: =26729343+221735 -> 26951078 | V68: =19655434+286949 -> 19942383
A69: TUNISAIR | B69: 106199280 | D69: -239382 | E69: -209038 | F69: -317448 | G69: -335031 | I69: 1878415 | J69: 1935598 | K69: 646691 | L69: 809098 | N69: 1827202 | O69: 2148260 | P69: 2492442 | Q69: 2623051 | S69: -669556 | T69: -874048 | U69: -1187511 | V69: -1520391
A70: BH | B70: 47600000 | C70: 73065000 | D70: 137810000 | E70: 125148000 | F70: 142978000 | G70: 71028000 | H70: 559853000 | I70: 620842000 | J70: 711433000 | K70: 744647000 | L70: 840677000 | M70: 11884632000 | N70: 11578186000 | O70: 12804267000 | P70: 12694273000 | Q70: 13654610000 | R70: 1073447000 | S70: 1184175000 | T70: 1261158000 | U70: 1366864000 | V70: 1611089000
A71: BH ASSURANCES | B71: 2660000 | C71: 9662269 | D71: 13147954 | E71: 13306391 | F71: 13175452 | G71: 11013950 | H71: 8264619 | I71: =8542386+932988 -> 9475374 | J71: =11053493+279251 -> 11332744 | K71: =12890750+1035450 -> 13926200 | L71: =13902221+23062 -> 13925283 | M71: =348726782-70228626 -> 278498156 | N71: 301787701 | O71: 352386529 | P71: -864380431 | Q71: 456528739 | R71: 70228626 | S71: =80716549 -> 80716549 | T71: 91101614 | U71: 100951271 | V71: 107971569
A72: PLTU | B72: 1000000 | C72: 4488178 | D72: 3956985 | E72: 3168627 | F72: 1427160 | G72: 3111258 | H72: 5013258 | I72: 4552464 | J72: 3571192 | K72: 1762412 | L72: 3385480 | M72: 0 | N72: 0 | O72: 0 | P72: 0 | Q72: 0 | R72: 18951563 | S72: 18908548 | T72: 18177175 | U72: 17104333 | V72: 17715591
A73: TJL | B73: 2750000 | C73: 3228640 | D73: 8949492 | E73: 7486494 | F73: 8821558 | G73: 10003860 | H73: 20121646 | I73: 27620400 | J73: 29289523 | K73: 30548938 | L73: 32861075 | M73: 415665299 | N73: 371964961 | O73: 366550189 | P73: 374936592 | Q73: 400595522 | R73: 55147866 | S73: 62505568 | T73: 66451925 | U73: 70961372 | V73: 76542263
A74: UBCI | B74: 20001529 | C74: 42459000 | D74: 30510000 | E74: 59725000 | F74: 53358000 | G74: 54985000 | H74: 243516000 | I74: 264440000 | J74: 294936000 | K74: 302878000 | L74: 321657000 | M74: =2629166000+172172000+51451000 -> 2852789000 | N74: 3076418000 | O74: 3164097000 | P74: 4017611000 | Q74: 4618827000 | R74: 449129000 | S74: 457608000 | T74: 501442000 | U74: 529920000 | V74: 556941000

Sheet Ratios and Scoring System
A1: Name | B1: EPS | H1: EPS Growth | M1: Net profit margin | S1: ROE | Y1: D/E ratio (for banks LCR) | AE1: P/E
B2: 2020 | C2: 2021 | D2: 2022 | E2: 2023 | F2: 2024 | H2: 2021 | I2: 2022 | J2: 2023 | K2: 2024 | M2: 2020 | N2: 2021 | O2: 2022 | P2: 2023 | Q2: 2024 | S2: 2020 | T2: 2021 | U2: 2022 | V2: 2023 | W2: 2024 | Y2: 2020 | Z2: 2021 | AA2: 2022 | AB2: 2023 | AC2: 2024 | AE2: CURRENT
A3: Societe Frigorifique Et Brasserie | B3: ='Data '!C3/'Data '!$B$3 -> 0.78540402 | C3: ='Data '!D3/'Data '!$B$3 -> 0.93622626 | D3: ='Data '!E3/'Data '!$B$3 -> 0.95860802 | E3: ='Data '!F3/'Data '!$B$3 -> 1.0505587 | F3: ='Data '!G3/'Data '!$B$3 -> 1.0552976 | H3: =((C3-B3)/ABS(B3)) -> 0.1920314 | I3: =((D3-C3)/ABS(C3)) -> 0.02390636 | J3: =((E3-D3)/ABS(D3)) -> 0.095921002 | K3: =((F3-E3)/ABS(E3)) -> 0.0045109 | M3: ='Data '!C3/'Data '!H3 -> 0.17507164 | N3: ='Data '!D3/'Data '!I3 -> 0.20969177 | O3: ='Data '!E3/'Data '!J3 -> 0.1932658 | P3: ='Data '!F3/'Data '!K3 -> 0.2057074 | Q3: ='Data '!G3/'Data '!L3 -> 0.20265788 | S3: ='Data '!C3/'Data '!R3 -> 0.20153833 | T3: ='Data '!D3/'Data '!S3 -> 0.22244932 | U3: ='Data '!E3/'Data '!T3 -> 0.21170479 | V3: ='Data '!F3/'Data '!U3 -> 0.21171987 | W3: ='Data '!G3/'Data '!V3 -> 0.19933497 | Y3: ='Data '!M3/'Data '!R3 -> 0.57919562 | Z3: ='Data '!N3/'Data '!S3 -> 0.51582546 | AA3: ='Data '!O3/'Data '!T3 -> 0.54683391 | AB3: ='Data '!P3/'Data '!U3 -> 0.5067525 | AC3: ='Data '!Q3/'Data '!V3 -> 0.4951005 | AE3: 11.26
A4: Banque Attijari De Tunisie | B4: ='Data '!C4/'Data '!$B$4 -> 6.5520952 | C4: ='Data '!D4/'Data '!$B$4 -> 6.7389048 | D4: ='Data '!J4/'Data '!$B$4 -> 15.819714 | E4: ='Data '!F4/'Data '!$B$4 -> 8.7256667 | F4: ='Data '!G4/'Data '!$B$4 -> 8.4986429 | H4: =((C4-B4)/ABS(B4)) -> 0.028511418 | I4: =((D4-C4)/ABS(C4)) -> 1.3475201 | J4: =((E4-D4)/ABS(D4)) -> -0.44843083 | K4: =((F4-E4)/ABS(E4)) -> -0.026017933 | M4: ='Data '!C4/'Data '!H4 -> 0.50596074 | N4: ='Data '!D4/'Data '!I4 -> 0.47089456 | O4: ='Data '!E4/'Data '!J4 -> 0.50028446 | P4: ='Data '!F4/'Data '!K4 -> 0.52949072 | Q4: ='Data '!G4/'Data '!L4 -> 0.4825145 | S4: ='Data '!C4/'Data '!R4 -> 0.31069974 | T4: ='Data '!D4/'Data '!S4 -> 0.29973176 | U4: ='Data '!J4/'Data '!T4 -> 0.65624204 | V4: ='Data '!F4/'Data '!U4 -> 0.32729462 | W4: ='Data '!G4/'Data '!V4 -> 0.30172722 | Y4: 2.056 | Z4: 3.545 | AA4: 3.59 | AB4: 6.91 | AC4: ='Data '!Q4/'Data '!V4 -> 9.4830435 | AE4: 11.44
A5: Poulina Group Holding | B5: ='Data '!G5/'Data '!$B$5 -> 0.90048557 | C5: ='Data '!D5/'Data '!$B$5 -> 0.51824168 | D5: ='Data '!E5/'Data '!$B$5 -> 0.36537911 | E5: ='Data '!F5/'Data '!$B$5 -> 0.72028598 | F5: ='Data '!G5/'Data '!$B$5 -> 0.90048557 | H5: =((C5-B5)/ABS(B5)) -> -0.42448642 | I5: =((D5-C5)/ABS(C5)) -> -0.29496386 | J5: =((E5-D5)/ABS(D5)) -> 0.97133867 | K5: =((F5-E5)/ABS(E5)) -> 0.25017785 | M5: ='Data '!G5/'Data '!H5 -> 0.070660127 | N5: ='Data '!D5/'Data '!I5 -> 0.032361539 | O5: ='Data '!E5/'Data '!J5 -> 0.020783814 | P5: ='Data '!F5/'Data '!K5 -> 0.037283675 | Q5: ='Data '!G5/'Data '!L5 -> 0.047017531 | S5: ='Data '!G5/'Data '!R5 -> 0.17201462 | T5: ='Data '!D5/'Data '!S5 -> 0.095217561 | U5: ='Data '!E5/'Data '!T5 -> 0.067228829 | V5: ='Data '!F5/'Data '!U5 -> 0.12202008 | W5: ='Data '!G5/'Data '!V5 -> 0.14070919 | Y5: ='Data '!M5/'Data '!R5 -> 2.9836181 | Z5: ='Data '!N5/'Data '!S5 -> 4.0791451 | AA5: ='Data '!O5/'Data '!T5 -> 4.36528 | AB5: ='Data '!P5/'Data '!U5 -> 3.1696891 | AC5: ='Data '!Q5/'Data '!V5 -> 2.8211301 | AE5: 20.14
A6: Societe Delice Holding | B6: ='Data '!C6/'Data '!$B$6 -> 1.0529758 | C6: ='Data '!D6/'Data '!$B$6 -> 1.2812967 | D6: ='Data '!E6/'Data '!$B$6 -> 1.4304781 | E6: ='Data '!F6/'Data '!$B$6 -> 1.7808458 | F6: ='Data '!G6/'Data '!$B$6 -> 1.8397088 | H6: =((C6-B6)/ABS(B6)) -> 0.21683394 | I6: =((D6-C6)/ABS(C6)) -> 0.11643002 | J6: =((E6-D6)/ABS(D6)) -> 0.2449305 | K6: =((F6-E6)/ABS(E6)) -> 0.033053373 | M6: ='Data '!C6/'Data '!H6 -> 0.055235024 | N6: ='Data '!D6/'Data '!I6 -> 0.060391855 | O6: ='Data '!E6/'Data '!J6 -> 0.061998034 | P6: ='Data '!F6/'Data '!K6 -> 0.070408731 | Q6: ='Data '!G6/'Data '!L6 -> 0.070018579 | S6: ='Data '!C6/'Data '!R6 -> 0.23975346 | T6: ='Data '!D6/'Data '!S6 -> 0.23131068 | U6: ='Data '!E6/'Data '!T6 -> 0.21566708 | V6: ='Data '!F6/'Data '!U6 -> 0.23119763 | W6: ='Data '!G6/'Data '!V6 -> 0.20623495 | Y6: ='Data '!M6/'Data '!R6 -> 1.746834 | Z6: ='Data '!N6/'Data '!S6 -> 1.3291652 | AA6: ='Data '!O6/'Data '!T6 -> 1.2381352 | AB6: ='Data '!P6/'Data '!U6 -> 1.2346028 | AC6: ='Data '!Q6/'Data '!V6 -> 1.1531935 | AE6: 6.79
A7: One Tech Ho | B7: ='Data '!C7/'Data '!$B$7 -> 0.24588697 | C7: ='Data '!D7/'Data '!$B$7 -> 0.3823892 | D7: ='Data '!E7/'Data '!$B$7 -> 0.17154155 | E7: ='Data '!F7/'Data '!$B$7 -> 0.47677162 | F7: ='Data '!G7/'Data '!$B$7 -> 0.37559335 | H7: =((C7-B7)/ABS(B7)) -> 0.55514223 | I7: =((D7-C7)/ABS(C7)) -> -0.5513954 | J7: =((E7-D7)/ABS(D7)) -> 1.779336 | K7: =((F7-E7)/ABS(E7)) -> -0.21221538 | M7: ='Data '!C7/'Data '!H7 -> 0.027511595 | N7: ='Data '!D7/'Data '!I7 -> 0.033969268 | O7: ='Data '!E7/'Data '!J7 -> 0.013175676 | P7: ='Data '!F7/'Data '!K7 -> 0.034697794 | Q7: ='Data '!G7/'Data '!L7 -> 0.028809125 | S7: ='Data '!C7/'Data '!R7 -> 0.057048685 | T7: ='Data '!D7/'Data '!S7 -> 0.084777714 | U7: ='Data '!E7/'Data '!T7 -> 0.038942865 | V7: ='Data '!F7/'Data '!U7 -> 0.099166415 | W7: ='Data '!G7/'Data '!V7 -> 0.076566222 | Y7: ='Data '!M7/'Data '!R7 -> 0.89486581 | Z7: ='Data '!N7/'Data '!S7 -> 0.92566562 | AA7: ='Data '!O7/'Data '!T7 -> 1.035113 | AB7: ='Data '!P7/'Data '!U7 -> 0.90348667 | AC7: ='Data '!Q7/'Data '!V7 -> 0.75714648 | AE7: 24.26
A8: Carthage Cement | B8: ='Data '!C8/'Data '!$B$8 -> 0.056353843 | C8: ='Data '!D8/'Data '!$B$8 -> 0.091696453 | D8: ='Data '!E8/'Data '!$B$8 -> 0.10374792 | E8: ='Data '!F8/'Data '!$B$8 -> 0.16062032 | F8: ='Data '!G8/'Data '!$B$8 -> 0.20445558 | H8: =((C8-B8)/ABS(B8)) -> 0.62715526 | I8: =((D8-C8)/ABS(C8)) -> 0.13142782 | J8: =((E8-D8)/ABS(D8)) -> 0.54817871 | K8: =((F8-E8)/ABS(E8)) -> 0.27291229 | M8: ='Data '!C8/'Data '!H8 -> 0.076547121 | N8: ='Data '!D8/'Data '!I8 -> 0.096663198 | O8: ='Data '!E8/'Data '!J8 -> 0.097145288 | P8: ='Data '!F8/'Data '!K8 -> 0.12788383 | Q8: ='Data '!G8/'Data '!L8 -> 0.16665203 | S8: ='Data '!C8/'Data '!R8 -> 0.14240864 | T8: ='Data '!D8/'Data '!S8 -> 0.18812781 | U8: ='Data '!E8/'Data '!T8 -> 0.1754978 | V8: ='Data '!F8/'Data '!U8 -> 0.21365223 | W8: ='Data '!G8/'Data '!V8 -> 0.21381209 | Y8: ='Data '!M8/'Data '!R8 -> 5.2110684 | Z8: ='Data '!N8/'Data '!S8 -> 3.8226307 | AA8: ='Data '!O8/'Data '!T8 -> 3.2438599 | AB8: ='Data '!P8/'Data '!U8 -> 2.3834436 | AC8: ='Data '!Q8/'Data '!V8 -> 1.6584139 | AE8: 8.87
A9: Societe Tunisienne De Verreries | B9: ='Data '!C9/'Data '!$B$9 -> 0.27133923 | C9: ='Data '!D9/'Data '!$B$9 -> 0.50912819 | D9: ='Data '!E9/'Data '!$B$9 -> 0.76183714 | E9: ='Data '!F9/'Data '!$B$9 -> 1.1881898 | F9: ='Data '!G9/'Data '!$B$9 -> 1.0646361 | H9: =((C9-B9)/ABS(B9)) -> 0.87635307 | I9: =((D9-C9)/ABS(C9)) -> 0.49635622 | J9: =((E9-D9)/ABS(D9)) -> 0.55963757 | K9: =((F9-E9)/ABS(E9)) -> -0.1039848 | M9: ='Data '!C9/'Data '!H9 -> 0.11693069 | N9: ='Data '!D9/'Data '!I9 -> 0.19051509 | O9: ='Data '!E9/'Data '!J9 -> 0.19146645 | P9: ='Data '!F9/'Data '!K9 -> 0.17778052 | Q9: ='Data '!G9/'Data '!L9 -> 0.17775563 | S9: ='Data '!C9/'Data '!R9 -> 0.1419822 | T9: ='Data '!D9/'Data '!S9 -> 0.23379219 | U9: ='Data '!E9/'Data '!T9 -> 0.29341789 | V9: ='Data '!F9/'Data '!U9 -> 0.35803802 | W9: ='Data '!G9/'Data '!V9 -> 0.27754014 | Y9: ='Data '!M9/'Data '!R9 -> 1.2257903 | Z9: ='Data '!N9/'Data '!S9 -> 1.9917996 | AA9: ='Data '!O9/'Data '!T9 -> 2.5959198 | AB9: ='Data '!P9/'Data '!U9 -> 2.5710151 | AC9: ='Data '!Q9/'Data '!V9 -> 2.6666628 | AE9: 12.44
A10: Societe Tunisie Profiles Aluminium | B10: ='Data '!C10/'Data '!$B$10 -> 0.42441924 | C10: ='Data '!D10/'Data '!$B$10 -> 0.38118442 | D10: ='Data '!E10/'Data '!$B$10 -> 0.57930788 | E10: ='Data '!F10/'Data '!$B$10 -> 0.8269077 | F10: ='Data '!G10/'Data '!$B$10 -> 0.96543524 | H10: =((C10-B10)/ABS(B10)) -> -0.10186819 | I10: =((D10-C10)/ABS(C10)) -> 0.5197575 | J10: =((E10-D10)/ABS(D10)) -> 0.42740627 | K10: =((F10-E10)/ABS(E10)) -> 0.16752479 | M10: ='Data '!C10/'Data '!H10 -> 0.11758918 | N10: ='Data '!D10/'Data '!I10 -> 0.088694489 | O10: ='Data '!E10/'Data '!J10 -> 0.10171368 | P10: ='Data '!F10/'Data '!K10 -> 0.1435698 | Q10: ='Data '!G10/'Data '!L10 -> 0.14182478 | S10: ='Data '!C10/'Data '!R10 -> 0.15518561 | T10: ='Data '!D10/'Data '!S10 -> 0.13890184 | U10: ='Data '!E10/'Data '!T10 -> 0.19538542 | V10: ='Data '!F10/'Data '!U10 -> 0.22889612 | W10: ='Data '!G10/'Data '!V10 -> 0.2291177 | Y10: ='Data '!M10/'Data '!R10 -> 0.96114617 | Z10: ='Data '!N10/'Data '!S10 -> 1.1321116 | AA10: ='Data '!O10/'Data '!T10 -> 1.1270975 | AB10: ='Data '!P10/'Data '!U10 -> 0.8858216 | AC10: ='Data '!Q10/'Data '!V10 -> 0.99088955 | AE10: 10.56
A11: SPDIT-SICAF | B11: ='Data '!C11/'Data '!$B$11 -> 0.60412811 | C11: ='Data '!D11/'Data '!$B$11 -> 0.62256904 | D11: ='Data '!E11/'Data '!$B$11 -> 0.77739414 | E11: ='Data '!F11/'Data '!$B$11 -> 0.95710525 | F11: ='Data '!G11/'Data '!$B$11 -> 1.1420827 | H11: =((C11-B11)/ABS(B11)) -> 0.030524864 | I11: =((D11-C11)/ABS(C11)) -> 0.24868745 | J11: =((E11-D11)/ABS(D11)) -> 0.23117116 | K11: =((F11-E11)/ABS(E11)) -> 0.19326767 | M11: ='Data '!C11/'Data '!H11 -> 0.85941548 | N11: ='Data '!D11/'Data '!I11 -> 0.85078218 | O11: ='Data '!E11/'Data '!J11 -> 0.91953035 | P11: ='Data '!F11/'Data '!K11 -> 0.86042592 | Q11: ='Data '!G11/'Data '!L11 -> 0.92560248 | S11: ='Data '!C11/'Data '!R11 -> 0.23905226 | T11: ='Data '!D11/'Data '!S11 -> 0.24416874 | U11: ='Data '!E11/'Data '!T11 -> 0.28505805 | V11: ='Data '!F11/'Data '!U11 -> 0.32071901 | W11: ='Data '!G11/'Data '!V11 -> 0.34858586 | Y11: ='Data '!M11/'Data '!R11 -> 0.039327049 | Z11: ='Data '!N11/'Data '!S11 -> 0.026915603 | AA11: ='Data '!O11/'Data '!T11 -> 0.036575806 | AB11: ='Data '!P11/'Data '!U11 -> 0.051210786 | AC11: ='Data '!Q11/'Data '!V11 -> 0.048916735 | AE11: 11.27
A12: Automobile Reseau Tunisien Et Service SA | B12: ='Data '!C12/'Data '!$B$12 -> 0.86897631 | C12: ='Data '!H12/'Data '!$B$12 -> 5.5495494 | D12: ='Data '!E12/'Data '!$B$12 -> 0.7629161 | E12: ='Data '!F12/'Data '!$B$12 -> 1.1030587 | F12: ='Data '!G12/'Data '!$B$12 -> 1.1030587 | H12: =((C12-B12)/ABS(B12)) -> 5.3863069 | I12: =((D12-C12)/ABS(C12)) -> -0.86252648 | J12: =((E12-D12)/ABS(D12)) -> 0.4458453 | K12: =((F12-E12)/ABS(E12)) -> 0 | M12: ='Data '!C12/'Data '!H12 -> 0.15658502 | N12: ='Data '!H12/'Data '!I12 -> 0.78575046 | O12: ='Data '!E12/'Data '!J12 -> 0.16643889 | P12: ='Data '!F12/'Data '!K12 -> 0.13722883 | Q12: ='Data '!G12/'Data '!L12 -> 0.13722883 | S12: ='Data '!C12/'Data '!R12 -> 0.16416425 | T12: ='Data '!H12/'Data '!S12 -> 0.99307209 | U12: ='Data '!E12/'Data '!T12 -> 0.13743822 | V12: ='Data '!F12/'Data '!U12 -> 0.29934915 | W12: ='Data '!G12/'Data '!V12 -> 0.18901309 | Y12: ='Data '!M12/'Data '!R12 -> 0.4124814 | Z12: ='Data '!N12/'Data '!S12 -> 0.22045786 | AA12: ='Data '!O12/'Data '!T12 -> 0.32683399 | AB12: ='Data '!P12/'Data '!U12 -> 1.0452983 | AC12: ='Data '!Q12/'Data '!V12 -> 0.7055843 | AE12: 10.79
A13: City Cars | B13: ='Data '!C13/'Data '!$B$13 -> 1.1665264 | C13: ='Data '!D13/'Data '!$B$13 -> 1.8530439 | D13: ='Data '!E13/'Data '!$B$13 -> 1.6847646 | E13: ='Data '!F13/'Data '!$B$13 -> 1.7621442 | F13: ='Data '!G13/'Data '!$B$13 -> 1.6399328 | H13: =((C13-B13)/ABS(B13)) -> 0.58851431 | I13: =((D13-C13)/ABS(C13)) -> -0.090812381 | J13: =((E13-D13)/ABS(D13)) -> 0.045929034 | K13: =((F13-E13)/ABS(E13)) -> -0.069353795 | M13: ='Data '!C13/'Data '!H13 -> 0.088762525 | N13: ='Data '!D13/'Data '!I13 -> 0.097031372 | O13: ='Data '!E13/'Data '!J13 -> 0.088386901 | P13: ='Data '!F13/'Data '!K13 -> 0.084574518 | Q13: ='Data '!G13/'Data '!L13 -> 0.078007079 | S13: ='Data '!C13/'Data '!R13 -> 0.36206376 | T13: ='Data '!D13/'Data '!S13 -> 0.44016579 | U13: ='Data '!E13/'Data '!T13 -> 0.35988741 | V13: ='Data '!F13/'Data '!U13 -> 0.33927631 | W13: ='Data '!G13/'Data '!V13 -> 0.29367344 | Y13: ='Data '!M12/'Data '!R13 -> 1.4400684 | Z13: ='Data '!N13/'Data '!S13 -> 1.6514215 | AA13: ='Data '!O13/'Data '!T13 -> 1.8593982 | AB13: ='Data '!P13/'Data '!U13 -> 1.9115588 | AC13: ='Data '!Q13/'Data '!V13 -> 1.8765919 | AE13: 11.88
A14: Ste Assurances Maghrebia SA | B14: ='Data '!C14/'Data '!$B$14 -> 11.888658 | C14: ='Data '!D14/'Data '!$B$14 -> 17.141925 | D14: ='Data '!E14/'Data '!$B$14 -> 18.047678 | E14: ='Data '!F14/'Data '!$B$14 -> 18.231899 | F14: ='Data '!G14/'Data '!$B$14 -> 22.368255 | H14: =((C14-B14)/ABS(B14)) -> 0.44187212 | I14: =((D14-C14)/ABS(C14)) -> 0.052838471 | J14: =((E14-D14)/ABS(D14)) -> 0.010207432 | K14: =((F14-E14)/ABS(E14)) -> 0.22687469 | M14: ='Data '!C14/'Data '!H14 -> 1.3565336 | N14: ='Data '!D14/'Data '!I14 -> 2.9870643 | O14: ='Data '!E14/'Data '!J14 -> 2.8902782 | P14: ='Data '!F14/'Data '!K14 -> 1.3935871 | Q14: ='Data '!G14/'Data '!L14 -> 1.4490814 | S14: ='Data '!C14/'Data '!R14 -> 0.48672949 | T14: ='Data '!D14/'Data '!S14 -> 0.50009675 | U14: ='Data '!E14/'Data '!T14 -> 0.44993613 | V14: ='Data '!F14/'Data '!U14 -> 0.40483037 | W14: ='Data '!G14/'Data '!V14 -> 0.45304474 | Y14: 0.7492 | Z14: 0.7708 | AA14: 0.7725 | AB14: 0.8038 | AC14: ='Data '!Q14/'Data '!V14 -> 4.5039549 | AE14: 8.66
A15: Tunisie Leasing | B15: ='Data '!C15/'Data '!$B$15 -> 0.83144259 | C15: ='Data '!D15/'Data '!$B$15 -> 0.66844093 | D15: ='Data '!E15/'Data '!$B$15 -> 1.9172492 | E15: ='Data '!F15/'Data '!$B$15 -> 2.6127289 | F15: ='Data '!G15/'Data '!$B$15 -> 3.4694939 | H15: =((C15-B15)/ABS(B15)) -> -0.19604681 | I15: =((D15-C15)/ABS(C15)) -> 1.8682402 | J15: =((E15-D15)/ABS(D15)) -> 0.36274874 | K15: =((F15-E15)/ABS(E15)) -> 0.3279196 | M15: ='Data '!C15/'Data '!H15 -> 0.062239639 | N15: ='Data '!D15/'Data '!I15 -> 0.053419861 | O15: ='Data '!E15/'Data '!J15 -> 0.1379316 | P15: ='Data '!F15/'Data '!K15 -> 0.17737967 | Q15: ='Data '!G15/'Data '!L15 -> 0.19172757 | S15: ='Data '!C15/'Data '!R15 -> 0.040190865 | T15: ='Data '!D15/'Data '!S15 -> 0.032815641 | U15: ='Data '!E15/'Data '!T15 -> 0.086369543 | V15: ='Data '!F15/'Data '!U15 -> 0.10765543 | W15: ='Data '!G15/'Data '!V15 -> 0.12957076 | Y15: ='Data '!M15/'Data '!R15 -> 8.0407482 | Z15: ='Data '!N15/'Data '!S15 -> 8.0728049 | AA15: ='Data '!O15/'Data '!T15 -> 7.4090636 | AB15: ='Data '!P15/'Data '!U15 -> 7.5637894 | AC15: ='Data '!Q15/'Data '!V15 -> 9.3431457 | AE15: 9.22
A16: Compagnie Internationale De Leasing | B16: 2.616 | C16: 3.185 | D16: 2.59 | E16: 2.884 | F16: 3.884 | H16: =((C16-B16)/ABS(B16)) -> 0.21750765 | I16: =((D16-C16)/ABS(C16)) -> -0.18681319 | J16: =((E16-D16)/ABS(D16)) -> 0.11351351 | K16: =((F16-E16)/ABS(E16)) -> 0.34674064 | M16: ='Data '!C16/'Data '!H16 -> 0.40983701 | N16: ='Data '!D16/'Data '!I16 -> 0.4190554 | O16: ='Data '!E16/'Data '!J16 -> 0.40373515 | P16: ='Data '!F16/'Data '!K16 -> 0.44734787 | Q16: ='Data '!G16/'Data '!L16 -> 0.43803411 | S16: ='Data '!C16/'Data '!R16 -> 0.12090174 | T16: ='Data '!D16/'Data '!S16 -> 0.14183033 | U16: ='Data '!E16/'Data '!O16 -> 0.032754747 | V16: ='Data '!F16/'Data '!U16 -> 0.15435814 | W16: ='Data '!G16/'Data '!V16 -> 0.15044043 | Y16: ='Data '!M16/'Data '!R16 -> 5.0454306 | Z16: ='Data '!N16/'Data '!S16 -> 4.9071032 | AA16: ='Data '!T16/'Data '!O16 -> 0.22353326 | AB16: ='Data '!P16/'Data '!U16 -> 4.5161848 | AC16: ='Data '!Q16/'Data '!V16 -> 4.4076696 | AE16: 9.38
A17: Tunis Re | B17: ='Data '!C17/'Data '!$B$17 -> 0.03699185 | C17: ='Data '!D17/'Data '!$B$17 -> 0.01671445 | D17: ='Data '!E17/'Data '!$B$17 -> 0.02202155 | E17: ='Data '!F17/'Data '!$B$17 -> 0.00572945 | F17: ='Data '!G17/'Data '!$B$17 -> 0.17798 | H17: =((C17-B17)/ABS(B17)) -> -0.54815858 | I17: =((D17-C17)/ABS(C17)) -> 0.31751568 | J17: =((E17-D17)/ABS(D17)) -> -0.73982531 | K17: =((F17-E17)/ABS(E17)) -> 30.064064 | M17: ='Data '!C17/'Data '!H17 -> 0.027636405 | N17: ='Data '!D17/'Data '!I17 -> 0.013935082 | O17: ='Data '!E17/'Data '!J17 -> 0.0165022 | P17: ='Data '!F17/'Data '!K17 -> 0.0036423107 | Q17: ='Data '!G17/'Data '!L17 -> 0.10442626 | S17: ='Data '!C17/'Data '!R17 -> 0.0034830991 | T17: ='Data '!D17/'Data '!S17 -> 0.0014929209 | U17: ='Data '!E17/'Data '!T17 -> 0.0018632165 | V17: ='Data '!F17/'Data '!U17 -> 0.00046493439 | W17: ='Data '!G17/'Data '!V17 -> 0.013776863 | Y17: ='Data '!M17/'Data '!R17 -> 3.3316561 | Z17: ='Data '!N17/'Data '!S17 -> 3.0745805 | AA17: ='Data '!T17/'Data '!O17 -> 0.3342337 | AB17: ='Data '!P17/'Data '!U17 -> 2.7588614 | AC17: ='Data '!Q17/'Data '!V17 -> 2.9607145 | AE17: 8.4
A18: Assurances Maghrebia Vie SA | B18: ='Data '!C18/'Data '!$B$18 -> 0.48247276 | C18: ='Data '!I18/'Data '!$B$18 -> 0.7058576 | D18: ='Data '!J18/'Data '!$B$18 -> 0.79693332 | E18: ='Data '!F18/'Data '!$B$18 -> 0.59996076 | F18: ='Data '!G18/'Data '!$B$18 -> 1.0614149 | H18: =((C18-B18)/ABS(B18)) -> 0.4629999 | I18: =((D18-C18)/ABS(C18)) -> 0.12902846 | J18: =((E18-D18)/ABS(D18)) -> -0.24716316 | K18: =((F18-E18)/ABS(E18)) -> 0.7691405 | M18: ='Data '!C18/'Data '!H18 -> 0.78924433 | N18: ='Data '!D18/'Data '!I18 -> 0.77150014 | O18: ='Data '!E18/'Data '!J18 -> 0.68417493 | P18: ='Data '!F18/'Data '!K18 -> 0.67375447 | Q18: ='Data '!G18/'Data '!L18 -> 1.065691 | S18: ='Data '!C18/'Data '!R18 -> 0.19187179 | T18: ='Data '!I18/'Data '!S18 -> 0.24273854 | U18: ='Data '!J18/'Data '!T18 -> 0.1725385 | V18: ='Data '!F18/'Data '!U18 -> 0.11729869 | W18: ='Data '!G18/'Data '!V18 -> 0.18576611 | Y18: 0.52836501 | Z18: 0.61652507 | AA18: 0.65330327 | AB18: 0.61603615 | AC18: ='Data '!Q18/'Data '!V18 -> 5.4355522 | AE18: 0.7
A19: SAH | B19: ='Data '!C19/'Data '!$B$19 -> 0.397415 | C19: ='Data '!D19/'Data '!$B$19 -> 0.19307038 | D19: ='Data '!E19/'Data '!$B$19 -> 0.42044076 | E19: ='Data '!F19/'Data '!$B$19 -> 0.4243246 | F19: ='Data '!G19/'Data '!$B$19 -> 0.73329861 | H19: =((C19-B19)/ABS(B19)) -> -0.51418446 | I19: =((D19-C19)/ABS(C19)) -> 1.1776554 | J19: =((E19-D19)/ABS(D19)) -> 0.0092375547 | K19: =((F19-E19)/ABS(E19)) -> 0.72815483 | M19: ='Data '!C19/'Data '!H19 -> 0.052858921 | N19: ='Data '!D19/'Data '!I19 -> 0.024070193 | O19: ='Data '!E19/'Data '!J19 -> 0.040112336 | P19: ='Data '!F19/'Data '!K19 -> 0.03952399 | Q19: ='Data '!G19/'Data '!L19 -> 0.062738735 | S19: ='Data '!C19/'Data '!R19 -> 0.10626202 | T19: ='Data '!D19/'Data '!S19 -> 0.054817385 | U19: ='Data '!E19/'Data '!T19 -> 0.11316508 | V19: ='Data '!F19/'Data '!U19 -> 0.11166214 | W19: ='Data '!G19/'Data '!V19 -> 0.17428791 | Y19: ='Data '!M19/'Data '!R19 -> 1.817694 | Z19: ='Data '!N19/'Data '!S19 -> 2.2613152 | AA19: ='Data '!O19/'Data '!T19 -> 2.2906733 | AB19: ='Data '!P19/'Data '!U19 -> 2.3814493 | AC19: ='Data '!Q19/'Data '!V19 -> 2.4960304 | AE19: 18.83
A20: Arab Tunisian Lease | B20: ='Data '!C20/'Data '!$B$20 -> 0.16245218 | C20: ='Data '!D20/'Data '!$B$20 -> 0.34252788 | D20: ='Data '!E20/'Data '!$B$20 -> 0.50062852 | E20: ='Data '!F20/'Data '!$B$20 -> 0.61463889 | F20: ='Data '!G20/'Data '!$B$20 -> 0.68036006 | H20: =((C20-B20)/ABS(B20)) -> 1.1084843 | I20: =((D20-C20)/ABS(C20)) -> 0.46157016 | J20: =((E20-D20)/ABS(D20)) -> 0.22773447 | K20: =((F20-E20)/ABS(E20)) -> 0.10692647 | M20: ='Data '!C20/'Data '!H20 -> 0.17468127 | N20: ='Data '!D20/'Data '!I20 -> 0.27887802 | O20: ='Data '!E20/'Data '!J20 -> 0.34911238 | P20: ='Data '!F20/'Data '!K20 -> 0.39017686 | Q20: ='Data '!G20/'Data '!L20 -> 0.37842041 | S20: ='Data '!C20/'Data '!R20 -> 0.0099764301 | T20: ='Data '!D20/'Data '!S20 -> 0.10094119 | U20: ='Data '!E20/'Data '!T20 -> 0.13552541 | V20: ='Data '!F20/'Data '!U20 -> 0.15219425 | W20: ='Data '!G20/'Data '!V20 -> 0.15396677 | Y20: ='Data '!M20/'Data '!R20 -> 0.19195622 | Z20: ='Data '!N20/'Data '!S20 -> 4.9942015 | AA20: ='Data '!O20/'Data '!T20 -> 4.2646691 | AB20: ='Data '!P20/'Data '!U20 -> 4.2333307 | AC20: ='Data '!Q20/'Data '!V20 -> 4.0246326 | AE20: 8.69
A21: Societe Tunisienne des Marches de Gros SA | B21: ='Data '!C21/'Data '!$B$21 -> 0.35115795 | C21: ='Data '!D21/'Data '!$B$21 -> 0.44287879 | D21: ='Data '!E21/'Data '!$B$21 -> 0.47132765 | E21: ='Data '!F21/'Data '!$B$21 -> 0.57961061 | F21: ='Data '!G21/'Data '!$B$21 -> 0.53475811 | H21: =((C21-B21)/ABS(B21)) -> 0.26119537 | I21: =((D21-C21)/ABS(C21)) -> 0.06423623 | J21: =((E21-D21)/ABS(D21)) -> 0.2297403 | K21: =((F21-E21)/ABS(E21)) -> -0.07738385 | M21: ='Data '!C21/'Data '!H21 -> 0.30998902 | N21: ='Data '!D21/'Data '!I21 -> 0.37889362 | O21: ='Data '!E21/'Data '!J21 -> 0.37686257 | P21: ='Data '!F21/'Data '!K21 -> 0.43207446 | Q21: ='Data '!G21/'Data '!L21 -> 0.3806571 | S21: ='Data '!C21/'Data '!R21 -> 0.15953659 | T21: ='Data '!D21/'Data '!S21 -> 0.18378033 | U21: ='Data '!E21/'Data '!T21 -> 0.19070068 | V21: ='Data '!F21/'Data '!U21 -> 0.22158193 | W21: ='Data '!G21/'Data '!V21 -> 0.20462335 | Y21: ='Data '!M21/'Data '!R21 -> 0.16043675 | Z21: ='Data '!N21/'Data '!S21 -> 0.14256132 | AA21: ='Data '!O21/'Data '!T21 -> 0.18267587 | AB21: ='Data '!P21/'Data '!U21 -> 0.18514284 | AC21: ='Data '!Q21/'Data '!V21 -> 0.18444738 | AE21: 17.01
A22: Hannibal Lease | B22: ='Data '!C22/'Data '!$B$22 -> -0.28896109 | C22: ='Data '!D22/'Data '!$B$22 -> 0.53713309 | D22: ='Data '!E22/'Data '!$B$22 -> 0.72523382 | E22: ='Data '!K22/'Data '!$B$22 -> 4.2017833 | F22: ='Data '!L22/'Data '!$B$22 -> 4.439811 | H22: =((C22-B22)/ABS(B22)) -> 2.8588423 | I22: =((D22-C22)/ABS(C22)) -> 0.35019389 | J22: =((E22-D22)/ABS(D22)) -> 4.7936946 | K22: =((F22-E22)/ABS(E22)) -> 0.056649216 | M22: ='Data '!C22/'Data '!H22 -> -0.17049949 | N22: ='Data '!D22/'Data '!I22 -> 0.18201552 | O22: ='Data '!E22/'Data '!J22 -> 0.18202571 | P22: ='Data '!F22/'Data '!K22 -> 0.28267405 | Q22: ='Data '!G22/'Data '!L22 -> 0.25878342 | S22: ='Data '!C22/'Data '!R22 -> -0.045148332 | T22: ='Data '!D22/'Data '!S22 -> 0.077564766 | U22: ='Data '!E22/'Data '!T22 -> 0.097554142 | V22: ='Data '!K22/'Data '!U22 -> 0.50557627 | W22: ='Data '!G22/'Data '!V22 -> 0.12650737 | Y22: ='Data '!M22/'Data '!R22 -> 8.6597313 | Z22: ='Data '!N22/'Data '!S22 -> 7.168591 | AA22: ='Data '!O22/'Data '!T22 -> 6.5717035 | AB22: ='Data '!P22/'Data '!U22 -> 6.2027798 | AC22: ='Data '!Q22/'Data '!V22 -> 6.3755261 | AE22: 6.61
A23: ATB | B23: ='Data '!C23/'Data '!$B$22 -> 1.1325455 | C23: ='Data '!D23/'Data '!$B$22 -> -5.585 | D23: ='Data '!E23/'Data '!$B$22 -> 2.6909091 | E23: ='Data '!K23/'Data '!$B$22 -> 36.911182 | F23: ='Data '!L23/'Data '!$B$22 -> 39.707727 | H23: =((C23-B23)/ABS(B23)) -> -5.9313694 | I23: =((D23-C23)/ABS(C23)) -> 1.48181 | J23: =((E23-D23)/ABS(D23)) -> 12.716993 | K23: =((F23-E23)/ABS(E23)) -> 0.075764181 | M23: ='Data '!C23/'Data '!H23 -> 0.041869016 | N23: ='Data '!D23/'Data '!I23 -> -0.18443078 | O23: ='Data '!E23/'Data '!J23 -> 0.080889788 | P23: ='Data '!F23/'Data '!K23 -> -0.00038914052 | Q23: ='Data '!G23/'Data '!L23 -> 0.071625628 | S23: ='Data '!C23/'Data '!R23 -> 0.021271909 | T23: ='Data '!D23/'Data '!S23 -> -0.10340364 | U23: ='Data '!E23/'Data '!T23 -> 0.047891868 | V23: ='Data '!K23/'Data '!U23 -> 0.6572206 | W23: ='Data '!G23/'Data '!V23 -> 0.048180729 | Y23: ='Data '!M23/'Data '!R23 -> 12.586692 | Z23: ='Data '!N23/'Data '!S23 -> 12.842421 | AA23: ='Data '!O23/'Data '!T23 -> 12.530053 | AB23: ='Data '!P23/'Data '!U23 -> 12.302117 | AC23: ='Data '!Q23/'Data '!V23 -> 12.875442 | AE23: 14.96
A24: BIAT | B24: ='Data '!C24/'Data '!$B$22 -> 25.225455 | C24: ='Data '!D24/'Data '!$B$22 -> 25.766455 | D24: ='Data '!E24/'Data '!$B$22 -> 28.400182 | E24: ='Data '!K24/'Data '!$B$22 -> 145.80991 | F24: ='Data '!L24/'Data '!$B$22 -> 159.11691 | H24: =((C24-B24)/ABS(B24)) -> 0.021446591 | I24: =((D24-C24)/ABS(C24)) -> 0.10221535 | J24: =((E24-D24)/ABS(D24)) -> 4.1341189 | K24: =((F24-E24)/ABS(E24)) -> 0.091262659 | M24: ='Data '!C24/'Data '!H24 -> 0.26834656 | N24: ='Data '!D24/'Data '!I24 -> 0.24980698 | O24: ='Data '!E24/'Data '!J24 -> 0.22075586 | P24: ='Data '!F24/'Data '!K24 -> 0.22357316 | Q24: ='Data '!G24/'Data '!L24 -> 0.216768 | S24: ='Data '!C24/'Data '!R24 -> 0.15667002 | T24: ='Data '!D24/'Data '!S24 -> 0.15096932 | U24: ='Data '!E24/'Data '!T24 -> 0.15614783 | V24: ='Data '!K24/'Data '!U24 -> 0.74297871 | W24: ='Data '!G24/'Data '!V24 -> 0.16394155 | Y24: ='Data '!M24/'Data '!R24 -> 9.0938377 | Z24: ='Data '!N24/'Data '!S24 -> 9.2447518 | AA24: ='Data '!O24/'Data '!T24 -> 9.4711186 | AB24: ='Data '!P24/'Data '!U24 -> 9.5579396 | AC24: ='Data '!Q24/'Data '!V24 -> 9.8418551 | AE24: 5.18
A25: BNA | B25: ='Data '!C25/'Data '!$B$22 -> 9.7853636 | C25: ='Data '!D25/'Data '!$B$22 -> 15.760545 | D25: ='Data '!E25/'Data '!$B$22 -> 15.446364 | E25: ='Data '!K25/'Data '!$B$22 -> 95.184182 | F25: ='Data '!L25/'Data '!$B$22 -> 94.934636 | H25: =((C25-B25)/ABS(B25)) -> 0.6106244 | I25: =((D25-C25)/ABS(C25)) -> -0.019934705 | J25: =((E25-D25)/ABS(D25)) -> 5.1622388 | K25: =((F25-E25)/ABS(E25)) -> -0.0026217114 | M25: ='Data '!C25/'Data '!H25 -> 0.15571781 | N25: ='Data '!D25/'Data '!I25 -> 0.1900547 | O25: ='Data '!E25/'Data '!J25 -> 0.17953676 | P25: ='Data '!F25/'Data '!K25 -> 0.20251933 | Q25: ='Data '!G25/'Data '!L25 -> 0.20196288 | S25: ='Data '!C25/'Data '!R25 -> 0.065212202 | T25: ='Data '!D25/'Data '!S25 -> 0.098442051 | U25: ='Data '!E25/'Data '!T25 -> 0.09108136 | V25: ='Data '!K25/'Data '!U25 -> 0.51437235 | W25: ='Data '!G25/'Data '!V25 -> 0.096377999 | Y25: ='Data '!M25/'Data '!R25 -> 7.6847642 | Z25: ='Data '!N25/'Data '!S25 -> 9.9882999 | AA25: ='Data '!O25/'Data '!T25 -> 10.759548 | AB25: ='Data '!P25/'Data '!U25 -> 10.47543 | AC25: ='Data '!Q25/'Data '!V25 -> 9.4028691 | AE25: 3.11
A26: BT | B26: ='Data '!C26/'Data '!$B$22 -> 8.5828182 | C26: ='Data '!D26/'Data '!$B$22 -> 13.829455 | D26: ='Data '!E26/'Data '!$B$22 -> 15.323818 | E26: ='Data '!K26/'Data '!$B$22 -> 44.876 | F26: ='Data '!L26/'Data '!$B$22 -> 47.121455 | H26: =((C26-B26)/ABS(B26)) -> 0.61129529 | I26: =((D26-C26)/ABS(C26)) -> 0.10805659 | J26: =((E26-D26)/ABS(D26)) -> 1.928513 | K26: =((F26-E26)/ABS(E26)) -> 0.050036869 | M26: ='Data '!C26/'Data '!H26 -> 0.24817309 | N26: ='Data '!D26/'Data '!I26 -> 0.39412098 | O26: ='Data '!E26/'Data '!J26 -> 0.39308793 | P26: ='Data '!F26/'Data '!K26 -> 0.36934502 | Q26: ='Data '!G26/'Data '!L26 -> 0.38476394 | S26: ='Data '!C26/'Data '!R26 -> 0.086691312 | T26: ='Data '!D26/'Data '!S26 -> 0.13073632 | U26: ='Data '!E26/'Data '!T26 -> 0.13157383 | V26: ='Data '!K26/'Data '!U26 -> 0.35634153 | W26: ='Data '!G26/'Data '!V26 -> 0.13688092 | Y26: ='Data '!M26/'Data '!R26 -> 5.1109088 | Z26: ='Data '!N26/'Data '!S26 -> 5.0287025 | AA26: ='Data '!O26/'Data '!T26 -> 4.9860958 | AB26: ='Data '!P26/'Data '!U26 -> 4.9943189 | AC26: ='Data '!Q26/'Data '!V26 -> 5.3418794 | AE26: 9.01
A27: AMEN BANK | B27: ='Data '!C27/'Data '!$B$22 -> 8.9490909 | C27: ='Data '!D27/'Data '!$B$22 -> 12.377 | D27: ='Data '!E27/'Data '!$B$22 -> 13.870727 | E27: ='Data '!K27/'Data '!$B$22 -> 48.937182 | F27: ='Data '!L27/'Data '!$B$22 -> 51.150909 | H27: =((C27-B27)/ABS(B27)) -> 0.38304551 | I27: =((D27-C27)/ABS(C27)) -> 0.12068573 | J27: =((E27-D27)/ABS(D27)) -> 2.5280906 | K27: =((F27-E27)/ABS(E27)) -> 0.0452361 | M27: ='Data '!C27/'Data '!H27 -> 0.24919753 | N27: ='Data '!D27/'Data '!I27 -> 0.30044046 | O27: ='Data '!E27/'Data '!J27 -> 0.31240633 | P27: ='Data '!F27/'Data '!K27 -> 0.40227081 | Q27: ='Data '!G27/'Data '!L27 -> 0.43284577 | S27: ='Data '!C27/'Data '!R27 -> 0.084171932 | T27: ='Data '!D27/'Data '!S27 -> 0.10963117 | U27: ='Data '!E27/'Data '!T27 -> 0.11164307 | V27: ='Data '!K27/'Data '!U27 -> 0.34405469 | W27: ='Data '!G27/'Data '!V27 -> 0.1429472 | Y27: ='Data '!M27/'Data '!R27 -> 6.7507864 | Z27: ='Data '!N27/'Data '!S27 -> 6.5736812 | AA27: ='Data '!O27/'Data '!T27 -> 6.4916391 | AB27: ='Data '!P27/'Data '!U27 -> 5.9977151 | AC27: ='Data '!Q27/'Data '!V27 -> 5.911864 | AE27: 6.81
A28: EURO-CYCLES | B28: ='Data '!C28/'Data '!$B$22 -> 1.510084 | C28: ='Data '!D28/'Data '!$B$22 -> 2.4199508 | D28: ='Data '!E28/'Data '!$B$22 -> 1.5117041 | E28: ='Data '!K28/'Data '!$B$22 -> 10.29231 | F28: ='Data '!L28/'Data '!$B$22 -> 11.113639 | H28: =((C28-B28)/ABS(B28)) -> 0.60252725 | I28: =((D28-C28)/ABS(C28)) -> -0.37531616 | J28: =((E28-D28)/ABS(D28)) -> 5.8084155 | K28: =((F28-E28)/ABS(E28)) -> 0.079800263 | M28: ='Data '!C28/'Data '!H28 -> 0.13861651 | N28: ='Data '!D28/'Data '!I28 -> 0.1784951 | O28: ='Data '!E28/'Data '!J28 -> 0.10219644 | P28: ='Data '!F28/'Data '!K28 -> 0.04380174 | Q28: ='Data '!G28/'Data '!L28 -> 0.089786001 | S28: ='Data '!C28/'Data '!R28 -> 0.35551118 | T28: ='Data '!D28/'Data '!S28 -> 0.44630024 | U28: ='Data '!E28/'Data '!T28 -> 0.27104764 | V28: ='Data '!K28/'Data '!U28 -> 2.0123801 | W28: ='Data '!G28/'Data '!V28 -> 0.17125435 | Y28: ='Data '!M28/'Data '!R28 -> 1.436311 | Z28: ='Data '!N28/'Data '!S28 -> 2.652485 | AA28: ='Data '!O28/'Data '!T28 -> 2.63354 | AB28: ='Data '!P28/'Data '!U28 -> 1.9805358 | AC28: ='Data '!Q28/'Data '!V28 -> 1.553834 | AE28: 10.97
A29: ICF | B29: ='Data '!C29/'Data '!$B$22 -> -1.0333422 | C29: ='Data '!D29/'Data '!$B$22 -> 0.81955355 | D29: ='Data '!E29/'Data '!$B$22 -> 2.8263673 | E29: ='Data '!K29/'Data '!$B$22 -> 13.32543 | F29: ='Data '!L29/'Data '!$B$22 -> 15.442001 | H29: =((C29-B29)/ABS(B29)) -> 1.7931095 | I29: =((D29-C29)/ABS(C29)) -> 2.448667 | J29: =((E29-D29)/ABS(D29)) -> 3.7146843 | K29: =((F29-E29)/ABS(E29)) -> 0.158837 | M29: ='Data '!C29/'Data '!H29 -> -0.096722527 | N29: ='Data '!D29/'Data '!I29 -> 0.060893158 | O29: ='Data '!E29/'Data '!J29 -> 0.13468694 | P29: ='Data '!F29/'Data '!K29 -> 0.049942514 | Q29: ='Data '!G29/'Data '!L29 -> 0.1262994 | S29: ='Data '!C29/'Data '!R29 -> -0.1299556 | T29: ='Data '!D29/'Data '!S29 -> 0.096881518 | U29: ='Data '!E29/'Data '!T29 -> 0.26780086 | V29: ='Data '!K29/'Data '!U29 -> 1.3647635 | W29: ='Data '!G29/'Data '!V29 -> 0.17638881 | Y29: ='Data '!M29/'Data '!R29 -> 0.28918106 | Z29: ='Data '!N29/'Data '!S29 -> 0.5102663 | AA29: ='Data '!O29/'Data '!T29 -> 0.44161223 | AB29: ='Data '!P29/'Data '!U29 -> 0.23397573 | AC29: ='Data '!Q29/'Data '!V29 -> 0.45713183 | AE29: 8.13
A30: STB | B30: ='Data '!C30/'Data '!$B$22 -> 6.5599091 | C30: ='Data '!D30/'Data '!$B$22 -> 10.638091 | D30: ='Data '!E30/'Data '!$B$22 -> 7.9889091 | E30: ='Data '!K30/'Data '!$B$22 -> 64.970727 | F30: ='Data '!L30/'Data '!$B$22 -> 62.666909 | H30: =((C30-B30)/ABS(B30)) -> 0.62168267 | I30: =((D30-C30)/ABS(C30)) -> -0.24902794 | J30: =((E30-D30)/ABS(D30)) -> 7.1326157 | K30: =((F30-E30)/ABS(E30)) -> -0.035459326 | M30: ='Data '!C30/'Data '!H30 -> 0.11533316 | N30: ='Data '!D30/'Data '!I30 -> 0.17990551 | O30: ='Data '!E30/'Data '!J30 -> 0.12599141 | P30: ='Data '!F30/'Data '!K30 -> 0.12038289 | Q30: ='Data '!G30/'Data '!L30 -> 0.14844865 | S30: ='Data '!C30/'Data '!R30 -> 0.065591697 | T30: ='Data '!D30/'Data '!S30 -> 0.092334702 | U30: ='Data '!E30/'Data '!T30 -> 0.064795651 | V30: ='Data '!K30/'Data '!U30 -> 0.54015745 | W30: ='Data '!G30/'Data '!V30 -> 0.072087081 | Y30: ='Data '!M30/'Data '!R30 -> 10.134596 | Z30: ='Data '!N30/'Data '!S30 -> 9.7090675 | AA30: ='Data '!O30/'Data '!T30 -> 9.8780578 | AB30: ='Data '!P30/'Data '!U30 -> 10.001134 | AC30: ='Data '!Q30/'Data '!V30 -> 9.4964584 | AE30: 6.29
A31: UIB | B31: ='Data '!C31/'Data '!$B$22 -> 5.9246364 | C31: ='Data '!D31/'Data '!$B$22 -> 7.5256364 | D31: ='Data '!E31/'Data '!$B$22 -> 12.049 | E31: ='Data '!K31/'Data '!$B$22 -> 47.543727 | F31: ='Data '!L31/'Data '!$B$22 -> 49.075 | H31: =((C31-B31)/ABS(B31)) -> 0.27022756 | I31: =((D31-C31)/ABS(C31)) -> 0.60106062 | J31: =((E31-D31)/ABS(D31)) -> 2.945865 | K31: =((F31-E31)/ABS(E31)) -> 0.032207671 | M31: ='Data '!C31/'Data '!H31 -> 0.16170822 | N31: ='Data '!D31/'Data '!I31 -> 0.18627184 | O31: ='Data '!E31/'Data '!J31 -> 0.2687077 | P31: ='Data '!F31/'Data '!K31 -> 0.23898191 | Q31: ='Data '!G31/'Data '!L31 -> 0.13311907 | S31: ='Data '!C31/'Data '!R31 -> 0.090350764 | T31: ='Data '!D31/'Data '!S31 -> 0.10612737 | U31: ='Data '!E31/'Data '!T31 -> 0.14892123 | V31: ='Data '!K31/'Data '!U31 -> 0.52966806 | W31: ='Data '!G31/'Data '!V31 -> 0.06975699 | Y31: ='Data '!M31/'Data '!R31 -> 7.9871027 | Z31: ='Data '!N31/'Data '!S31 -> 7.7492144 | AA31: ='Data '!O31/'Data '!T31 -> 7.1537774 | AB31: ='Data '!P31/'Data '!U31 -> 6.8190536 | AC31: ='Data '!Q31/'Data '!V31 -> 7.0554379 | AE31: 11.78
A32: ENNAKL AUTOMOBILES | B32: ='Data '!C32/'Data '!$B$22 -> 1.2803355 | C32: ='Data '!D32/'Data '!$B$22 -> 3.2778295 | D32: ='Data '!E32/'Data '!$B$22 -> 3.9282819 | E32: ='Data '!K32/'Data '!$B$22 -> 31.655436 | F32: ='Data '!L32/'Data '!$B$22 -> 32.010804 | H32: =((C32-B32)/ABS(B32)) -> 1.5601332 | I32: =((D32-C32)/ABS(C32)) -> 0.19843996 | J32: =((E32-D32)/ABS(D32)) -> 7.0583412 | K32: =((F32-E32)/ABS(E32)) -> 0.01122612 | M32: ='Data '!C32/'Data '!H32 -> 0.031388895 | N32: ='Data '!D32/'Data '!I32 -> 0.067004511 | O32: ='Data '!E32/'Data '!J32 -> 0.076003251 | P32: ='Data '!F32/'Data '!K32 -> 0.15162818 | Q32: ='Data '!G32/'Data '!L32 -> 0.15769204 | S32: ='Data '!C32/'Data '!R32 -> 0.086274091 | T32: ='Data '!D32/'Data '!S32 -> 0.20066148 | U32: ='Data '!E32/'Data '!T32 -> 0.21246247 | V32: ='Data '!K32/'Data '!U32 -> 1.1517317 | W32: ='Data '!G32/'Data '!V32 -> 0.16751937 | Y32: ='Data '!M32/'Data '!R32 -> 1.2432687 | Z32: ='Data '!N32/'Data '!S32 -> 0.92197993 | AA32: ='Data '!O32/'Data '!T32 -> 1.4353446 | AB32: ='Data '!P32/'Data '!U32 -> 0.74165329 | AC32: ='Data '!Q32/'Data '!V32 -> 0.86503867 | AE32: 9.16
A33: ASTREE | B33: ='Data '!C33/'Data '!$B$22 -> 2.3204538 | C33: ='Data '!D33/'Data '!$B$22 -> 1.9142045 | D33: ='Data '!E33/'Data '!$B$22 -> 1.5548973 | E33: ='Data '!K33/'Data '!$B$22 -> 5.5280979 | F33: ='Data '!L33/'Data '!$B$22 -> 6.1995044 | H33: =((C33-B33)/ABS(B33)) -> -0.17507324 | I33: =((D33-C33)/ABS(C33)) -> -0.18770575 | J33: =((E33-D33)/ABS(D33)) -> 2.5552818 | K33: =((F33-E33)/ABS(E33)) -> 0.12145343 | M33: ='Data '!C33/'Data '!H33 -> 0.41307338 | N33: ='Data '!D33/'Data '!I33 -> 0.56661966 | O33: ='Data '!E33/'Data '!J33 -> 0.44878827 | P33: ='Data '!F33/'Data '!K33 -> 0.37294246 | Q33: ='Data '!G33/'Data '!L33 -> 0.42504499 | S33: ='Data '!C33/'Data '!R33 -> 0.16646294 | T33: ='Data '!D33/'Data '!S33 -> 0.13361104 | U33: ='Data '!E33/'Data '!T33 -> 0.10832261 | V33: ='Data '!K33/'Data '!U33 -> 0.36072248 | W33: ='Data '!G33/'Data '!V33 -> 0.15722233 | Y33: ='Data '!M33/'Data '!R33 -> 3.113872 | Z33: ='Data '!N33/'Data '!S33 -> 3.3578187 | AA33: ='Data '!O33/'Data '!T33 -> 3.8413074 | AB33: ='Data '!P33/'Data '!U33 -> 4.1256632 | AC33: ='Data '!Q33/'Data '!V33 -> 2.638123 | AE33: 8.06
A34: BH LEASING | B34: ='Data '!C34/'Data '!$B$22 -> -0.046648636 | C34: ='Data '!D34/'Data '!$B$22 -> 0.10366745 | D34: ='Data '!E34/'Data '!$B$22 -> 0.17832027 | E34: ='Data '!K34/'Data '!$B$22 -> 1.3600137 | F34: ='Data '!L34/'Data '!$B$22 -> 1.6850367 | H34: =((C34-B34)/ABS(B34)) -> 3.2223041 | I34: =((D34-C34)/ABS(C34)) -> 0.72011818 | J34: =((E34-D34)/ABS(D34)) -> 6.6268038 | K34: =((F34-E34)/ABS(E34)) -> 0.23898509 | M34: ='Data '!C34/'Data '!H34 -> -0.060365947 | N34: ='Data '!D34/'Data '!I34 -> 0.083207781 | O34: ='Data '!E34/'Data '!J34 -> 0.12466979 | P34: ='Data '!F34/'Data '!K34 -> 0.21053083 | Q34: ='Data '!G34/'Data '!L34 -> 0.21033774 | S34: ='Data '!C34/'Data '!R34 -> -0.017579738 | T34: ='Data '!D34/'Data '!S34 -> 0.037616033 | U34: ='Data '!E34/'Data '!T34 -> 0.060793765 | V34: ='Data '!K34/'Data '!U34 -> 0.42257841 | W34: ='Data '!G34/'Data '!V34 -> 0.099240619 | Y34: ='Data '!M34/'Data '!R34 -> 9.6905688 | Z34: ='Data '!N34/'Data '!S34 -> 8.3846292 | AA34: ='Data '!O34/'Data '!T34 -> 8.1805569 | AB34: ='Data '!P34/'Data '!U34 -> 7.1134653 | AC34: ='Data '!Q34/'Data '!V34 -> 6.8792451 | AE34: 7.13
A35: CIMENTS DE BIZERTE | B35: ='Data '!C35/'Data '!$B$22 -> -0.038301636 | C35: ='Data '!D35/'Data '!$B$22 -> -0.55938745 | D35: ='Data '!E35/'Data '!$B$22 -> -2.6318607 | E35: ='Data '!K35/'Data '!$B$22 -> 8.3021523 | F35: ='Data '!L35/'Data '!$B$22 -> 2.5307824 | H35: =((C35-B35)/ABS(B35)) -> -13.604793 | I35: =((D35-C35)/ABS(C35)) -> -3.7048977 | J35: =((E35-D35)/ABS(D35)) -> 4.1544801 | K35: =((F35-E35)/ABS(E35)) -> -0.69516551 | M35: ='Data '!C35/'Data '!H35 -> -0.0037937017 | N35: ='Data '!D35/'Data '!I35 -> -0.049144501 | O35: ='Data '!E35/'Data '!J35 -> -0.24109147 | P35: ='Data '!F35/'Data '!K35 -> -0.37619975 | Q35: ='Data '!G35/'Data '!L35 -> -1.6089295 | S35: ='Data '!C35/'Data '!R35 -> -0.013782163 | T35: ='Data '!D35/'Data '!S35 -> -0.07161675 | U35: ='Data '!E35/'Data '!T35 -> -0.51010256 | V35: ='Data '!K35/'Data '!U35 -> 4.2002973 | W35: ='Data '!G35/'Data '!V35 -> -0.31255855 | Y35: ='Data '!M35/'Data '!R35 -> 7.0270851 | Z35: ='Data '!N35/'Data '!S35 -> 2.3480178 | AA35: ='Data '!O35/'Data '!T35 -> 3.9785227 | AB35: ='Data '!P35/'Data '!U35 -> 10.115003 | AC35: ='Data '!Q35/'Data '!V35 -> 1.7122277
A36: ESSOUKNA | B36: ='Data '!C36/'Data '!$B$22 -> -0.015643455 | C36: ='Data '!D36/'Data '!$B$22 -> -0.086584727 | D36: ='Data '!E36/'Data '!$B$22 -> 0.061159455 | E36: ='Data '!K36/'Data '!$B$22 -> 0.604817 | F36: ='Data '!L36/'Data '!$B$22 -> 0.035426909 | H36: =((C36-B36)/ABS(B36)) -> -4.5348853 | I36: =((D36-C36)/ABS(C36)) -> 1.7063538 | J36: =((E36-D36)/ABS(D36)) -> 8.8891824 | K36: =((F36-E36)/ABS(E36)) -> -0.94142541 | M36: ='Data '!C36/'Data '!H36 -> -0.0099732485 | N36: ='Data '!D36/'Data '!I36 -> -0.079266208 | O36: ='Data '!E36/'Data '!J36 -> 0.038486012 | P36: ='Data '!F36/'Data '!K36 -> -0.42778544 | Q36: ='Data '!G36/'Data '!L36 -> -6.4188188 | S36: ='Data '!C36/'Data '!R36 -> -0.0050456187 | T36: ='Data '!D36/'Data '!S36 -> -0.028340484 | U36: ='Data '!E36/'Data '!T36 -> 0.019650926 | V36: ='Data '!K36/'Data '!U36 -> 0.21930852 | W36: ='Data '!G36/'Data '!V36 -> -0.088260755 | Y36: ='Data '!M36/'Data '!R36 -> 1.020107 | Z36: ='Data '!N36/'Data '!S36 -> 0.92382379 | AA36: ='Data '!O36/'Data '!T36 -> 0.68531999 | AB36: ='Data '!P36/'Data '!U36 -> 0.89427258 | AC36: ='Data '!Q36/'Data '!V36 -> 1.6981224
A37: LAND'OR | B37: ='Data '!C37/'Data '!$B$22 -> 0.63457891 | C37: ='Data '!D37/'Data '!$B$22 -> 0.87558818 | D37: ='Data '!E37/'Data '!$B$22 -> -0.90296809 | E37: ='Data '!K37/'Data '!$B$22 -> 23.372268 | F37: ='Data '!L37/'Data '!$B$22 -> 23.777857 | H37: =((C37-B37)/ABS(B37)) -> 0.37979402 | I37: =((D37-C37)/ABS(C37)) -> -2.0312703 | J37: =((E37-D37)/ABS(D37)) -> 26.883825 | K37: =((F37-E37)/ABS(E37)) -> 0.017353437 | M37: ='Data '!C37/'Data '!H37 -> 0.052187314 | N37: ='Data '!D37/'Data '!I37 -> 0.059876123 | O37: ='Data '!E37/'Data '!J37 -> -0.051609808 | P37: ='Data '!F37/'Data '!K37 -> 0.026608201 | Q37: ='Data '!G37/'Data '!L37 -> 0.048292665 | S37: ='Data '!C37/'Data '!R37 -> 0.10200562 | T37: ='Data '!D37/'Data '!S37 -> 0.12399887 | U37: ='Data '!E37/'Data '!T37 -> -0.11208918 | V37: ='Data '!K37/'Data '!U37 -> 2.6358227 | W37: ='Data '!G37/'Data '!V37 -> 0.11393047 | Y37: ='Data '!M37/'Data '!R37 -> 0.86779092 | Z37: ='Data '!N37/'Data '!S37 -> 1.3351354 | AA37: ='Data '!O37/'Data '!T37 -> 1.4497061 | AB37: ='Data '!P37/'Data '!U37 -> 1.3835848 | AC37: ='Data '!Q37/'Data '!V37 -> 1.1655946 | AE37: 15.67
A38: MONOPRIX | B38: ='Data '!C38/'Data '!$B$22 -> -0.87151064 | C38: ='Data '!D38/'Data '!$B$22 -> -0.28340445 | D38: ='Data '!E38/'Data '!$B$22 -> -0.76296964 | E38: ='Data '!K38/'Data '!$B$22 -> 65.889425 | F38: ='Data '!L38/'Data '!$B$22 -> 70.479812 | H38: =((C38-B38)/ABS(B38)) -> 0.6748124 | I38: =((D38-C38)/ABS(C38)) -> -1.6921582 | J38: =((E38-D38)/ABS(D38)) -> 87.359171 | K38: =((F38-E38)/ABS(E38)) -> 0.06966804 | M38: ='Data '!C38/'Data '!H38 -> -0.014757156 | N38: ='Data '!D38/'Data '!I38 -> -0.0047410169 | O38: ='Data '!E38/'Data '!J38 -> -0.012610627 | P38: ='Data '!F38/'Data '!K38 -> 0.0013986021 | Q38: ='Data '!G38/'Data '!L38 -> 0.0088650956 | S38: ='Data '!C38/'Data '!R38 -> -0.19158745 | T38: ='Data '!D38/'Data '!S38 -> -0.06659495 | U38: ='Data '!E38/'Data '!T38 -> -0.22523582 | V38: ='Data '!K38/'Data '!U38 -> 16.215351 | W38: ='Data '!G38/'Data '!V38 -> 0.13906193 | Y38: ='Data '!M38/'Data '!R38 -> 6.2797246 | Z38: ='Data '!N38/'Data '!S38 -> 6.9138439 | AA38: ='Data '!O38/'Data '!T38 -> 9.0790473 | AB38: ='Data '!P38/'Data '!U38 -> 6.6687808 | AC38: ='Data '!Q38/'Data '!V38 -> 6.0557486 | AE38: 23.21
A39: NEW BODY LINE | B39: ='Data '!C39/'Data '!$B$22 -> 0.11056091 | C39: ='Data '!D39/'Data '!$B$22 -> 0.19707709 | D39: ='Data '!E39/'Data '!$B$22 -> 0.10321236 | E39: ='Data '!K39/'Data '!$B$22 -> 1.1870269 | F39: ='Data '!L39/'Data '!$B$22 -> 0.81207691 | H39: =((C39-B39)/ABS(B39)) -> 0.78252054 | I39: =((D39-C39)/ABS(C39)) -> -0.47628432 | J39: =((E39-D39)/ABS(D39)) -> 10.500821 | K39: =((F39-E39)/ABS(E39)) -> -0.31587321 | M39: ='Data '!C39/'Data '!H39 -> 0.24581988 | N39: ='Data '!D39/'Data '!I39 -> 0.31675688 | O39: ='Data '!E39/'Data '!J39 -> 0.20769073 | P39: ='Data '!F39/'Data '!K39 -> 0.087069482 | Q39: ='Data '!G39/'Data '!L39 -> -0.68519798 | S39: ='Data '!C39/'Data '!R39 -> 0.10077312 | T39: ='Data '!D39/'Data '!S39 -> 0.17085932 | U39: ='Data '!E39/'Data '!T39 -> 0.09305714 | V39: ='Data '!K39/'Data '!U39 -> 0.99516293 | W39: ='Data '!G39/'Data '!V39 -> -1.2064744 | Y39: ='Data '!M39/'Data '!R39 -> 0.046010419 | Z39: ='Data '!N39/'Data '!S39 -> 0.10514023 | AA39: ='Data '!O39/'Data '!T39 -> 0.1107476 | AB39: ='Data '!P39/'Data '!U39 -> 0.13107905 | AC39: ='Data '!Q39/'Data '!V39 -> 0.3974996
A40: SIMPAR | B40: ='Data '!C40/'Data '!$B$22 -> -0.85229936 | C40: ='Data '!D40/'Data '!$B$22 -> -0.81471545 | D40: ='Data '!E40/'Data '!$B$22 -> -0.30373373 | E40: ='Data '!K40/'Data '!$B$22 -> 4.0407474 | F40: ='Data '!L40/'Data '!$B$22 -> 1.6349373 | H40: =((C40-B40)/ABS(B40)) -> 0.044097075 | I40: =((D40-C40)/ABS(C40)) -> 0.62719042 | J40: =((E40-D40)/ABS(D40)) -> 14.303585 | K40: =((F40-E40)/ABS(E40)) -> -0.59538741 | M40: ='Data '!C40/'Data '!H40 -> -0.20852157 | N40: ='Data '!D40/'Data '!I40 -> -0.22652022 | O40: ='Data '!E40/'Data '!J40 -> -0.049970684 | P40: ='Data '!F40/'Data '!K40 -> -0.12401513 | Q40: ='Data '!G40/'Data '!L40 -> -0.42816066 | S40: ='Data '!C40/'Data '!R40 -> -0.15171807 | T40: ='Data '!D40/'Data '!S40 -> -0.1703043 | U40: ='Data '!E40/'Data '!T40 -> -0.068067169 | V40: ='Data '!K40/'Data '!U40 -> 0.91683199 | W40: ='Data '!G40/'Data '!V40 -> -0.20365768 | Y40: ='Data '!M40/'Data '!R40 -> 2.6817074 | Z40: ='Data '!N40/'Data '!S40 -> 3.1584677 | AA40: ='Data '!O40/'Data '!T40 -> 3.1319819 | AB40: ='Data '!P40/'Data '!U40 -> 3.4998133 | AC40: ='Data '!Q40/'Data '!V40 -> 6.1047752
A41: SOTIPAPIER | B41: ='Data '!C41/'Data '!$B$22 -> 0.14740545 | C41: ='Data '!D41/'Data '!$B$22 -> 1.6944517 | D41: ='Data '!E41/'Data '!$B$22 -> 2.3618347 | E41: ='Data '!K41/'Data '!$B$22 -> 9.0048859 | F41: ='Data '!L41/'Data '!$B$22 -> 10.111759 | H41: =((C41-B41)/ABS(B41)) -> 10.495177 | I41: =((D41-C41)/ABS(C41)) -> 0.39386368 | J41: =((E41-D41)/ABS(D41)) -> 2.8126656 | K41: =((F41-E41)/ABS(E41)) -> 0.12291917 | M41: ='Data '!C41/'Data '!H41 -> 0.019586678 | N41: ='Data '!D41/'Data '!I41 -> 0.1457301 | O41: ='Data '!E41/'Data '!J41 -> 0.1629436 | P41: ='Data '!F41/'Data '!K41 -> 0.024636242 | Q41: ='Data '!G41/'Data '!L41 -> 0.027964436 | S41: ='Data '!C41/'Data '!R41 -> 0.024966097 | T41: ='Data '!D41/'Data '!S41 -> 0.26113764 | U41: ='Data '!E41/'Data '!T41 -> 0.30626911 | V41: ='Data '!K41/'Data '!U41 -> 1.3316667 | W41: ='Data '!G41/'Data '!V41 -> 0.045331347 | Y41: ='Data '!M41/'Data '!R41 -> 0.54766069 | Z41: ='Data '!N41/'Data '!S41 -> 0.56482833 | AA41: ='Data '!O41/'Data '!T41 -> 0.52554618 | AB41: ='Data '!P41/'Data '!U41 -> 0.66156964 | AC41: ='Data '!Q41/'Data '!V41 -> 1.0354055 | AE41: 25.45
A42: STAR | B42: ='Data '!C42/'Data '!$B$22 -> 1.4907345 | C42: ='Data '!D42/'Data '!$B$22 -> 1.9141462 | D42: ='Data '!E42/'Data '!$B$22 -> 2.6674445 | E42: ='Data '!K42/'Data '!$B$22 -> 3.2118879 | F42: ='Data '!L42/'Data '!$B$22 -> 3.6848667 | H42: =((C42-B42)/ABS(B42)) -> 0.28402894 | I42: =((D42-C42)/ABS(C42)) -> 0.39354276 | J42: =((E42-D42)/ABS(D42)) -> 0.20410672 | K42: =((F42-E42)/ABS(E42)) -> 0.14725882 | M42: ='Data '!C42/'Data '!H42 -> 0.9339236 | N42: ='Data '!D42/'Data '!I42 -> 0.69807642 | O42: ='Data '!E42/'Data '!J42 -> 1.4920634 | P42: ='Data '!F42/'Data '!K42 -> 0.65867353 | Q42: ='Data '!G42/'Data '!L42 -> 0.67827012 | S42: ='Data '!C42/'Data '!R42 -> 0.044875484 | T42: ='Data '!D42/'Data '!S42 -> 0.055461655 | U42: ='Data '!E42/'Data '!T42 -> 0.073299305 | V42: ='Data '!K42/'Data '!U42 -> 0.086397462 | W42: ='Data '!G42/'Data '!V42 -> 0.065253921 | Y42: ='Data '!M42/'Data '!R42 -> 2.6254436 | Z42: ='Data '!N42/'Data '!S42 -> 2.5842008 | AA42: ='Data '!O42/'Data '!T42 -> 2.6006363 | AB42: ='Data '!P42/'Data '!U42 -> 2.7234689 | AC42: ='Data '!Q42/'Data '!V42 -> 2.7472275 | AE42: 18.22
A43: TELNET HOLDING | B43: ='Data '!C43/'Data '!$B$22 -> 0.64960222 | C43: ='Data '!D43/'Data '!$B$22 -> 0.8239553 | D43: ='Data '!E43/'Data '!$B$22 -> 0.73197973 | E43: ='Data '!K43/'Data '!$B$22 -> 5.6198389 | F43: ='Data '!L43/'Data '!$B$22 -> 6.3028971 | H43: =((C43-B43)/ABS(B43)) -> 0.26839976 | I43: =((D43-C43)/ABS(C43)) -> -0.11162689 | J43: =((E43-D43)/ABS(D43)) -> 6.6775881 | K43: =((F43-E43)/ABS(E43)) -> 0.1215441 | M43: ='Data '!C43/'Data '!H43 -> 0.17585051 | N43: ='Data '!D43/'Data '!I43 -> 0.18352092 | O43: ='Data '!E43/'Data '!J43 -> 0.14159864 | P43: ='Data '!F43/'Data '!K43 -> -0.063921927 | Q43: ='Data '!G43/'Data '!L43 -> 0.1375991 | S43: ='Data '!C43/'Data '!R43 -> 0.22110275 | T43: ='Data '!D43/'Data '!S43 -> 0.24358333 | U43: ='Data '!E43/'Data '!T43 -> 0.21457522 | V43: ='Data '!K43/'Data '!U43 -> 2.4633165 | W43: ='Data '!G43/'Data '!V43 -> 0.32131035 | Y43: ='Data '!M43/'Data '!R43 -> 0.70226706 | Z43: ='Data '!N43/'Data '!S43 -> 0.81523277 | AA43: ='Data '!O43/'Data '!T43 -> 0.81341261 | AB43: ='Data '!P43/'Data '!U43 -> 1.6548233 | AC43: ='Data '!Q43/'Data '!V43 -> 1.4930392 | AE43: 8.02
A44: TUNINVEST SICAR | B44: ='Data '!C44/'Data '!$B$22 -> 0.25367882 | C44: ='Data '!D44/'Data '!$B$22 -> 0.044539909 | D44: ='Data '!E44/'Data '!$B$22 -> 0.012930636 | E44: ='Data '!K44/'Data '!$B$22 -> 0.095686909 | F44: ='Data '!L44/'Data '!$B$22 -> 0.10843827 | H44: =((C44-B44)/ABS(B44)) -> -0.82442401 | I44: =((D44-C44)/ABS(C44)) -> -0.70968427 | J44: =((E44-D44)/ABS(D44)) -> 6.4000155 | K44: =((F44-E44)/ABS(E44)) -> 0.13326132 | M44: ='Data '!C44/'Data '!H44 -> 0.4712151 | N44: ='Data '!D44/'Data '!I44 -> 0.65825739 | O44: ='Data '!E44/'Data '!J44 -> 0.18740151 | P44: ='Data '!F44/'Data '!K44 -> 0.39575091 | Q44: ='Data '!G44/'Data '!L44 -> 0.66016611 | S44: ='Data '!C44/'Data '!R44 -> 0.38197932 | T44: ='Data '!D44/'Data '!S44 -> 0.07720168 | U44: ='Data '!E44/'Data '!T44 -> 0.023684614 | V44: ='Data '!K44/'Data '!U44 -> 0.17722752 | W44: ='Data '!G44/'Data '!V44 -> 0.12612538 | Y44: ='Data '!M44/'Data '!R44 -> 0.6167067 | Z44: ='Data '!N44/'Data '!S44 -> 0.64601979 | AA44: ='Data '!O44/'Data '!T44 -> 0.70606615 | AB44: ='Data '!P44/'Data '!U44 -> 0.7876343 | AC44: ='Data '!Q44/'Data '!V44 -> 0.72797291 | AE44: 49.08
A45: UNIMED | B45: ='Data '!C45/'Data '!$B$22 -> 0.63454164 | C45: ='Data '!D45/'Data '!$B$22 -> 0.79119991 | D45: ='Data '!E45/'Data '!$B$22 -> 0.71182691 | E45: ='Data '!K45/'Data '!$B$22 -> 12.376947 | F45: ='Data '!L45/'Data '!$B$22 -> 13.442865 | H45: =((C45-B45)/ABS(B45)) -> 0.24688415 | I45: =((D45-C45)/ABS(C45)) -> -0.10031978 | J45: =((E45-D45)/ABS(D45)) -> 16.387579 | K45: =((F45-E45)/ABS(E45)) -> 0.086121249 | M45: ='Data '!C45/'Data '!H45 -> 0.076640087 | N45: ='Data '!D45/'Data '!I45 -> 0.10293596 | O45: ='Data '!E45/'Data '!J45 -> 0.081043239 | P45: ='Data '!F45/'Data '!K45 -> 0.040734647 | Q45: ='Data '!G45/'Data '!L45 -> 0.13100556 | S45: ='Data '!C45/'Data '!R45 -> 0.060617935 | T45: ='Data '!D45/'Data '!S45 -> 0.079967694 | U45: ='Data '!E45/'Data '!T45 -> 0.075508294 | V45: ='Data '!K45/'Data '!U45 -> 1.4444827 | W45: ='Data '!G45/'Data '!V45 -> 0.16670373 | Y45: ='Data '!M45/'Data '!R45 -> 0.37577833 | Z45: ='Data '!N45/'Data '!S45 -> 0.41937533 | AA45: ='Data '!O45/'Data '!T45 -> 0.77306979 | AB45: ='Data '!P45/'Data '!U45 -> 1.1026328 | AC45: ='Data '!Q45/'Data '!V45 -> 0.86115453 | AE45: 14.55
A46: WIFACK INTERNATIONAL BANK | B46: ='Data '!C46/'Data '!$B$22 -> -0.52416627 | C46: ='Data '!D46/'Data '!$B$22 -> 0.16439491 | D46: ='Data '!E46/'Data '!$B$22 -> 0.576369 | E46: ='Data '!K46/'Data '!$B$22 -> 7.7016944 | F46: ='Data '!L46/'Data '!$B$22 -> 9.412238 | H46: =((C46-B46)/ABS(B46)) -> 1.3136312 | I46: =((D46-C46)/ABS(C46)) -> 2.5060027 | J46: =((E46-D46)/ABS(D46)) -> 12.362437 | K46: =((F46-E46)/ABS(E46)) -> 0.22209965 | M46: ='Data '!C46/'Data '!H46 -> -0.18007922 | N46: ='Data '!D46/'Data '!I46 -> 0.03621402 | O46: ='Data '!E46/'Data '!J46 -> 0.092164974 | P46: ='Data '!F46/'Data '!K46 -> 0.10621815 | Q46: ='Data '!G46/'Data '!L46 -> 0.097808146 | S46: ='Data '!C46/'Data '!R46 -> -0.037089255 | T46: ='Data '!D46/'Data '!S46 -> 0.011498358 | U46: ='Data '!E46/'Data '!T46 -> 0.038750564 | V46: ='Data '!K46/'Data '!U46 -> 0.49810515 | W46: ='Data '!G46/'Data '!V46 -> 0.056533815 | Y46: ='Data '!M46/'Data '!R46 -> 4.2760693 | Z46: ='Data '!N46/'Data '!S46 -> 5.2982562 | AA46: ='Data '!O46/'Data '!T46 -> 6.5200094 | AB46: ='Data '!P46/'Data '!U46 -> 7.4337015 | AC46: ='Data '!Q46/'Data '!V46 -> 8.4498969 | AE46: 23.02
A47: AETECH | B47: ='Data '!C47/'Data '!$B$22 -> 0.026412455 | C47: ='Data '!D47/'Data '!$B$22 -> -0.034959 | D47: ='Data '!E47/'Data '!$B$22 -> -0.035552636 | E47: ='Data '!K47/'Data '!$B$22 -> 0.57016173 | F47: ='Data '!L47/'Data '!$B$22 -> 0.41716273 | H47: =((C47-B47)/ABS(B47)) -> -2.3235801 | I47: =((D47-C47)/ABS(C47)) -> -0.016980931 | J47: =((E47-D47)/ABS(D47)) -> 17.037115 | K47: =((F47-E47)/ABS(E47)) -> -0.26834316 | M47: ='Data '!C47/'Data '!H47 -> 0.046965357 | N47: ='Data '!D47/'Data '!I47 -> -0.048523013 | O47: ='Data '!E47/'Data '!J47 -> -0.049158028 | P47: ='Data '!F47/'Data '!K47 -> -0.22542264 | Q47: ='Data '!G47/'Data '!L47 -> -0.15562643 | S47: ='Data '!C47/'Data '!R47 -> -0.060588246 | T47: ='Data '!D47/'Data '!S47 -> 0.074239867 | U47: ='Data '!E47/'Data '!T47 -> 0.066155248 | V47: ='Data '!K47/'Data '!U47 -> -0.84991367 | W47: ='Data '!G47/'Data '!V47 -> 0.087514258 | Y47: ='Data '!M47/'Data '!R47 -> -1.9617898 | Z47: ='Data '!N47/'Data '!S47 -> -2.0178139 | AA47: ='Data '!O47/'Data '!T47 -> -2.1169471 | AB47: ='Data '!P47/'Data '!U47 -> -1.674892 | AC47: ='Data '!Q47/'Data '!V47 -> -1.5494514
A48: AIR LIQUIDE TUNISIE | B48: ='Data '!C48/'Data '!$B$22 -> 1.4118915 | C48: ='Data '!D48/'Data '!$B$22 -> 1.9385394 | D48: ='Data '!E48/'Data '!$B$22 -> 1.7377704 | E48: ='Data '!K48/'Data '!$B$22 -> 11.940659 | F48: ='Data '!L48/'Data '!$B$22 -> 12.7338 | H48: =((C48-B48)/ABS(B48)) -> 0.37300869 | I48: =((D48-C48)/ABS(C48)) -> -0.10356715 | J48: =((E48-D48)/ABS(D48)) -> 5.8712525 | K48: =((F48-E48)/ABS(E48)) -> 0.066423554 | M48: ='Data '!C48/'Data '!H48 -> 0.15566634 | N48: ='Data '!D48/'Data '!I48 -> 0.16536009 | O48: ='Data '!E48/'Data '!J48 -> 0.16032349 | P48: ='Data '!F48/'Data '!K48 -> 0.17922615 | Q48: ='Data '!G48/'Data '!L48 -> 0.19663053 | S48: ='Data '!C48/'Data '!R48 -> 0.20637397 | T48: ='Data '!D48/'Data '!S48 -> 0.24202885 | U48: ='Data '!E48/'Data '!T48 -> 0.19607775 | V48: ='Data '!K48/'Data '!U48 -> 1.1805268 | W48: ='Data '!G48/'Data '!V48 -> 0.21563292 | Y48: ='Data '!M48/'Data '!R48 -> 0.73695665 | Z48: ='Data '!N48/'Data '!S48 -> 0.70730561 | AA48: ='Data '!O48/'Data '!T48 -> 0.61601246 | AB48: ='Data '!P48/'Data '!U48 -> 0.5956087 | AC48: ='Data '!Q48/'Data '!V48 -> 0.57480014 | AE48: 9.1
A49: ALKIMIA | B49: ='Data '!C49/'Data '!$B$22 -> -3.6522666 | C49: ='Data '!D49/'Data '!$B$22 -> -4.1678692 | D49: ='Data '!E49/'Data '!$B$22 -> -2.2472535 | E49: ='Data '!K49/'Data '!$B$22 -> 17.596724 | F49: ='Data '!L49/'Data '!$B$22 -> 15.319087 | H49: =((C49-B49)/ABS(B49)) -> -0.1411733 | I49: =((D49-C49)/ABS(C49)) -> 0.46081476 | J49: =((E49-D49)/ABS(D49)) -> 8.8303241 | K49: =((F49-E49)/ABS(E49)) -> -0.12943525 | M49: ='Data '!C49/'Data '!H49 -> -0.22368369 | N49: ='Data '!D49/'Data '!I49 -> -0.24896112 | O49: ='Data '!E49/'Data '!J49 -> -0.097385306 | P49: ='Data '!F49/'Data '!K49 -> -0.20308422 | Q49: ='Data '!G49/'Data '!L49 -> -0.26348983 | S49: ='Data '!C49/'Data '!R49 -> 0.72242595 | T49: ='Data '!D49/'Data '!S49 -> 0.4516389 | U49: ='Data '!E49/'Data '!T49 -> 0.19574714 | V49: ='Data '!K49/'Data '!U49 -> -1.1684863 | W49: ='Data '!G49/'Data '!V49 -> 0.23361945 | Y49: ='Data '!M49/'Data '!R49 -> -4.7908047 | Z49: ='Data '!N49/'Data '!S49 -> -3.3721379 | AA49: ='Data '!O49/'Data '!T49 -> -3.0810497 | AB49: ='Data '!P49/'Data '!U49 -> -2.2511244 | AC49: ='Data '!Q49/'Data '!V49 -> -2.0226842
A50: ASSAD | B50: ='Data '!C50/'Data '!$B$22 -> -0.43245091 | C50: ='Data '!D50/'Data '!$B$22 -> -1.1971772 | D50: ='Data '!E50/'Data '!$B$22 -> -0.77897718 | E50: ='Data '!K50/'Data '!$B$22 -> 10.692784 | F50: ='Data '!L50/'Data '!$B$22 -> 13.945774 | H50: =((C50-B50)/ABS(B50)) -> -1.7683539 | I50: =((D50-C50)/ABS(C50)) -> 0.34932173 | J50: =((E50-D50)/ABS(D50)) -> 14.726697 | K50: =((F50-E50)/ABS(E50)) -> 0.30422297 | M50: ='Data '!C50/'Data '!H50 -> -0.038753259 | N50: ='Data '!D50/'Data '!I50 -> -0.10554139 | O50: ='Data '!E50/'Data '!J50 -> -0.066191218 | P50: ='Data '!F50/'Data '!K50 -> -0.082043291 | Q50: ='Data '!G50/'Data '!L50 -> 0.024074037 | S50: ='Data '!C50/'Data '!R50 -> -0.10103601 | T50: ='Data '!D50/'Data '!S50 -> -0.38900794 | U50: ='Data '!E50/'Data '!T50 -> -0.33829963 | V50: ='Data '!K50/'Data '!U50 -> 7.5044644 | W50: ='Data '!G50/'Data '!V50 -> 0.18759758 | Y50: ='Data '!M50/'Data '!R50 -> 2.3614527 | Z50: ='Data '!N50/'Data '!S50 -> 3.8474975 | AA50: ='Data '!O50/'Data '!T50 -> 5.1957506 | AB50: ='Data '!P50/'Data '!U50 -> 9.2825088 | AC50: ='Data '!Q50/'Data '!V50 -> 6.948413 | AE50: 21.17
A51: BEST LEASE | B51: ='Data '!C51/'Data '!$B$22 -> 1.217827 | C51: ='Data '!D51/'Data '!$B$22 -> 2.6199667 | D51: ='Data '!E51/'Data '!$B$22 -> 1.7178674 | E51: ='Data '!K51/'Data '!$B$22 -> 2.6319548 | F51: ='Data '!L51/'Data '!$B$22 -> 2.4953919 | H51: =((C51-B51)/ABS(B51)) -> 1.1513456 | I51: =((D51-C51)/ABS(C51)) -> -0.34431711 | J51: =((E51-D51)/ABS(D51)) -> 0.53210596 | K51: =((F51-E51)/ABS(E51)) -> -0.051886494 | M51: ='Data '!C51/'Data '!H51 -> 0.75100779 | N51: ='Data '!D51/'Data '!I51 -> 1.1548632 | O51: ='Data '!E51/'Data '!J51 -> 0.62538274 | P51: ='Data '!F51/'Data '!K51 -> 1.3061668 | Q51: ='Data '!G51/'Data '!L51 -> 2.2303975 | S51: ='Data '!C51/'Data '!R51 -> 0.15221922 | T51: ='Data '!D51/'Data '!S51 -> 0.30358184 | U51: ='Data '!E51/'Data '!T51 -> 0.18212336 | V51: ='Data '!K51/'Data '!U51 -> 0.25742099 | W51: ='Data '!G51/'Data '!V51 -> 0.55051343 | Y51: ='Data '!M51/'Data '!R51 -> 3.1995522 | Z51: ='Data '!N51/'Data '!S51 -> 3.4202671 | AA51: ='Data '!O51/'Data '!T51 -> 2.9602089 | AB51: ='Data '!P51/'Data '!U51 -> 3.0567485 | AC51: ='Data '!Q51/'Data '!V51 -> 3.2285739 | AE51: 6.52
A52: BNA ASSURANCES | B52: ='Data '!C52/'Data '!$B$22 -> 0.056785545 | C52: ='Data '!D52/'Data '!$B$22 -> 0.16059282 | D52: ='Data '!E52/'Data '!$B$22 -> 0.50636318 | E52: ='Data '!K52/'Data '!$B$22 -> 2.7597171 | F52: ='Data '!L52/'Data '!$B$22 -> 2.7943107 | H52: =((C52-B52)/ABS(B52)) -> 1.828058 | I52: =((D52-C52)/ABS(C52)) -> 2.1530873 | J52: =((E52-D52)/ABS(D52)) -> 4.4500746 | K52: =((F52-E52)/ABS(E52)) -> 0.012535211 | M52: ='Data '!C52/'Data '!H52 -> 0.034750887 | N52: ='Data '!D52/'Data '!I52 -> 0.093780577 | O52: ='Data '!E52/'Data '!J52 -> 0.19979267 | P52: ='Data '!F52/'Data '!K52 -> 0.28256609 | Q52: ='Data '!G52/'Data '!L52 -> 0.53078765 | S52: ='Data '!C52/'Data '!R52 -> -0.0097410424 | T52: ='Data '!D52/'Data '!S52 -> 0.025071982 | U52: ='Data '!E52/'Data '!T52 -> 0.073262448 | V52: ='Data '!K52/'Data '!U52 -> 0.35880389 | W52: ='Data '!G52/'Data '!V52 -> 0.16166178 | Y52: ='Data '!M52/'Data '!R52 -> -7.3903978 | Z52: ='Data '!N52/'Data '!S52 -> 6.4885185 | AA52: ='Data '!O52/'Data '!T52 -> 6.7002788 | AB52: ='Data '!P52/'Data '!U52 -> 6.2947528 | AC52: ='Data '!Q52/'Data '!V52 -> 5.5116191 | AE52: 17.43
A53: BTE | B53: ='Data '!C53/'Data '!$B$22 -> -1.6658182 | C53: ='Data '!D53/'Data '!$B$22 -> -2.9479091 | D53: ='Data '!E53/'Data '!$B$22 -> -2.7548182 | E53: ='Data '!K53/'Data '!$B$22 -> 7.1557273 | F53: ='Data '!L53/'Data '!$B$22 -> 7.5847273 | H53: =((C53-B53)/ABS(B53)) -> -0.76964637 | I53: =((D53-C53)/ABS(C53)) -> 0.065500971 | J53: =((E53-D53)/ABS(D53)) -> 3.5975316 | K53: =((F53-E53)/ABS(E53)) -> 0.059951977 | M53: ='Data '!C53/'Data '!H53 -> -0.37496163 | N53: ='Data '!D53/'Data '!I53 -> -0.43074614 | O53: ='Data '!E53/'Data '!J53 -> -0.40767099 | P53: ='Data '!F53/'Data '!K53 -> -0.48116575 | Q53: ='Data '!G53/'Data '!L53 -> -0.36201937 | S53: ='Data '!C53/'Data '!R53 -> -0.055987045 | T53: ='Data '!D53/'Data '!S53 -> -0.092863484 | U53: ='Data '!E53/'Data '!T53 -> -0.09248786 | V53: ='Data '!K53/'Data '!U53 -> 0.46110542 | W53: ='Data '!G53/'Data '!V53 -> -0.19030577 | Y53: ='Data '!M53/'Data '!R53 -> 3.2325216 | Z53: ='Data '!N53/'Data '!S53 -> 3.3611014 | AA53: ='Data '!O53/'Data '!T53 -> 3.7510064 | AB53: ='Data '!P53/'Data '!U53 -> 8.1604347 | AC53: ='Data '!Q53/'Data '!V53 -> 9.2748168
A54: CELLCOM | B54: ='Data '!C54/'Data '!$B$22 -> 0.073098364 | C54: ='Data '!D54/'Data '!$B$22 -> 0.00092254545 | D54: ='Data '!E54/'Data '!$B$22 -> -0.30307682 | E54: ='Data '!K54/'Data '!$B$22 -> 5.6826415 | F54: ='Data '!L54/'Data '!$B$22 -> 6.5887266 | H54: =((C54-B54)/ABS(B54)) -> -0.9873794 | I54: =((D54-C54)/ABS(C54)) -> -329.52237 | J54: =((E54-D54)/ABS(D54)) -> 19.749839 | K54: =((F54-E54)/ABS(E54)) -> 0.15944789 | M54: ='Data '!C54/'Data '!H54 -> 0.014300551 | N54: ='Data '!D54/'Data '!I54 -> 0.00015268849 | O54: ='Data '!E54/'Data '!J54 -> -0.053433008 | P54: ='Data '!F54/'Data '!K54 -> 0.0034940377 | Q54: ='Data '!G54/'Data '!L54 -> 0.0130182 | S54: ='Data '!C54/'Data '!R54 -> 0.088073279 | T54: ='Data '!D54/'Data '!S54 -> 0.0011472954 | U54: ='Data '!E54/'Data '!T54 -> -0.60821815 | V54: ='Data '!K54/'Data '!U54 -> 11.015406 | W54: ='Data '!G54/'Data '!V54 -> 0.14256246 | Y54: ='Data '!M54/'Data '!R54 -> 2.1540532 | Z54: ='Data '!N54/'Data '!S54 -> 2.5002002 | AA54: ='Data '!O54/'Data '!T54 -> 4.0049725 | AB54: ='Data '!P54/'Data '!U54 -> 3.8362828 | AC54: ='Data '!Q54/'Data '!V54 -> 4.0165778 | AE54: 13.18
A55: MAGASIN GENERAL | B55: ='Data '!C55/'Data '!$B$22 -> -3.3666272 | C55: ='Data '!D55/'Data '!$B$22 -> -2.4452765 | D55: ='Data '!E55/'Data '!$B$22 -> -3.5625455 | E55: ='Data '!K55/'Data '!$B$22 -> 100.82392 | F55: ='Data '!L55/'Data '!$B$22 -> 103.55027 | H55: =((C55-B55)/ABS(B55)) -> 0.27367172 | I55: =((D55-C55)/ABS(C55)) -> -0.45690902 | J55: =((E55-D55)/ABS(D55)) -> 29.301091 | K55: =((F55-E55)/ABS(E55)) -> 0.027040638 | M55: ='Data '!C55/'Data '!H55 -> -0.036369815 | N55: ='Data '!D55/'Data '!I55 -> -0.026414596 | O55: ='Data '!E55/'Data '!J55 -> -0.038030547 | P55: ='Data '!F55/'Data '!K55 -> -0.038205916 | Q55: ='Data '!G55/'Data '!L55 -> -0.008838626 | S55: ='Data '!C55/'Data '!R55 -> 0.65504647 | T55: ='Data '!D55/'Data '!S55 -> 0.63403944 | U55: ='Data '!E55/'Data '!T55 -> 0.47397398 | V55: ='Data '!K55/'Data '!U55 -> -162.63178 | W55: ='Data '!G55/'Data '!V55 -> 0.1301769 | Y55: ='Data '!M55/'Data '!R55 -> -12.797568 | Z55: ='Data '!N55/'Data '!S55 -> -16.989495 | AA55: ='Data '!O55/'Data '!T55 -> -8.9164526 | AB55: ='Data '!P55/'Data '!U55 -> -101.47744 | AC55: ='Data '!Q55/'Data '!V55 -> -8.7725936
A56: MPBS | B56: ='Data '!C56/'Data '!$B$22 -> 0.069022545 | C56: ='Data '!D56/'Data '!$B$22 -> 0.71849082 | D56: ='Data '!E56/'Data '!$B$22 -> 0.51956318 | E56: ='Data '!K56/'Data '!$B$22 -> 11.337197 | F56: ='Data '!L56/'Data '!$B$22 -> 14.781105 | H56: =((C56-B56)/ABS(B56)) -> 9.4095091 | I56: =((D56-C56)/ABS(C56)) -> -0.27686872 | J56: =((E56-D56)/ABS(D56)) -> 20.820633 | K56: =((F56-E56)/ABS(E56)) -> 0.30377067 | M56: ='Data '!C56/'Data '!H56 -> 0.0084738352 | N56: ='Data '!D56/'Data '!I56 -> 0.06873081 | O56: ='Data '!E56/'Data '!J56 -> 0.049190253 | P56: ='Data '!F56/'Data '!K56 -> 0.023856136 | Q56: ='Data '!G56/'Data '!L56 -> 0.05145317 | S56: ='Data '!C56/'Data '!R56 -> 0.016308456 | T56: ='Data '!D56/'Data '!S56 -> 0.14834621 | U56: ='Data '!E56/'Data '!T56 -> 0.10060853 | V56: ='Data '!K56/'Data '!U56 -> 2.1688967 | W56: ='Data '!G56/'Data '!V56 -> 0.13234537 | Y56: ='Data '!M56/'Data '!R56 -> 0.93638738 | Z56: ='Data '!N56/'Data '!S56 -> 0.90444385 | AA56: ='Data '!O56/'Data '!T56 -> 0.84591464 | AB56: ='Data '!P56/'Data '!U56 -> 0.84419963 | AC56: ='Data '!Q56/'Data '!V56 -> 1.0019769 | AE56: 10.02
A57: SAM | B57: ='Data '!C57/'Data '!$B$22 -> 0.096036545 | C57: ='Data '!D57/'Data '!$B$22 -> 0.16679327 | D57: ='Data '!E57/'Data '!$B$22 -> 0.30133155 | E57: ='Data '!K57/'Data '!$B$22 -> 2.6153168 | F57: ='Data '!L57/'Data '!$B$22 -> 2.6690991 | H57: =((C57-B57)/ABS(B57)) -> 0.73676877 | I57: =((D57-C57)/ABS(C57)) -> 0.8066169 | J57: =((E57-D57)/ABS(D57)) -> 7.6792002 | K57: =((F57-E57)/ABS(E57)) -> 0.020564343 | M57: ='Data '!C57/'Data '!H57 -> 0.0563912 | N57: ='Data '!D57/'Data '!I57 -> 0.078584847 | O57: ='Data '!E57/'Data '!J57 -> 0.11595712 | P57: ='Data '!F57/'Data '!K57 -> 0.13084356 | Q57: ='Data '!G57/'Data '!L57 -> 0.09593053 | S57: ='Data '!C57/'Data '!R57 -> 0.090500723 | T57: ='Data '!D57/'Data '!S57 -> 0.14995077 | U57: ='Data '!E57/'Data '!T57 -> 0.23082977 | V57: ='Data '!K57/'Data '!U57 -> 1.7970815 | W57: ='Data '!G57/'Data '!V57 -> 0.18073878 | Y57: ='Data '!M57/'Data '!R57 -> 0.74340275 | Z57: ='Data '!N57/'Data '!S57 -> 0.74009004 | AA57: ='Data '!O57/'Data '!T57 -> 0.54534032 | AB57: ='Data '!P57/'Data '!U57 -> 0.60101935 | AC57: ='Data '!Q57/'Data '!V57 -> 0.58645847
A58: SANIMED | B58: ='Data '!C58/'Data '!$B$22 -> -1.1789731 | C58: ='Data '!D58/'Data '!$B$22 -> -0.017717455 | D58: ='Data '!E58/'Data '!$B$22 -> -0.90372973 | E58: ='Data '!K58/'Data '!$B$22 -> 3.7058227 | F58: ='Data '!L58/'Data '!$B$22 -> 3.0027465 | H58: =((C58-B58)/ABS(B58)) -> 0.98497213 | I58: =((D58-C58)/ABS(C58)) -> -50.007876 | J58: =((E58-D58)/ABS(D58)) -> 5.1005874 | K58: =((F58-E58)/ABS(E58)) -> -0.18972202 | M58: ='Data '!C58/'Data '!H58 -> -0.33536675 | N58: ='Data '!D58/'Data '!I58 -> -0.0030537658 | O58: ='Data '!E58/'Data '!J58 -> -0.17023711 | P58: ='Data '!F58/'Data '!K58 -> -0.21310787 | Q58: ='Data '!G58/'Data '!L58 -> -0.35956424 | S58: ='Data '!C58/'Data '!R58 -> -0.59213606 | T58: ='Data '!D58/'Data '!S58 -> -0.0090085455 | U58: ='Data '!E58/'Data '!T58 -> -0.85546936 | V58: ='Data '!K58/'Data '!U58 -> 2.0513428 | W58: ='Data '!G58/'Data '!V58 -> -0.6463422 | Y58: ='Data '!M58/'Data '!R58 -> 5.5605696 | Z58: ='Data '!N58/'Data '!S58 -> 6.622035 | AA58: ='Data '!O58/'Data '!T58 -> 13.13525 | AB58: ='Data '!P58/'Data '!U58 -> 7.8878156 | AC58: ='Data '!Q58/'Data '!V58 -> 8.6850092
A59: SIAME | B59: ='Data '!C59/'Data '!$B$22 -> 0.152411 | C59: ='Data '!D59/'Data '!$B$22 -> 0.37369855 | D59: ='Data '!E59/'Data '!$B$22 -> -0.022878636 | E59: ='Data '!K59/'Data '!$B$22 -> 5.7898724 | F59: ='Data '!L59/'Data '!$B$22 -> 5.8336523 | H59: =((C59-B59)/ABS(B59)) -> 1.4519132 | I59: =((D59-C59)/ABS(C59)) -> -1.0612222 | J59: =((E59-D59)/ABS(D59)) -> 254.06894 | K59: =((F59-E59)/ABS(E59)) -> 0.0075614636 | M59: ='Data '!C59/'Data '!H59 -> 0.031073741 | N59: ='Data '!D59/'Data '!I59 -> 0.063630785 | O59: ='Data '!E59/'Data '!J59 -> -0.0051049128 | P59: ='Data '!F59/'Data '!K59 -> 0.02249891 | Q59: ='Data '!G59/'Data '!L59 -> 0.037136177 | S59: ='Data '!C59/'Data '!R59 -> 0.059426821 | T59: ='Data '!D59/'Data '!S59 -> 0.13618484 | U59: ='Data '!E59/'Data '!T59 -> -0.0085492152 | V59: ='Data '!K59/'Data '!U59 -> 2.1477847 | W59: ='Data '!G59/'Data '!V59 -> 0.079702129 | Y59: ='Data '!M59/'Data '!R59 -> 1.3087345 | Z59: ='Data '!N59/'Data '!S59 -> 1.0874566 | AA59: ='Data '!O59/'Data '!T59 -> 1.1542417 | AB59: ='Data '!P59/'Data '!U59 -> 1.3299155 | AC59: ='Data '!Q59/'Data '!V59 -> 1.2567542 | AE59: 18.51
A60: SITS | B60: ='Data '!C60/'Data '!$B$22 -> 0.93638 | C60: ='Data '!D60/'Data '!$B$22 -> 0.424083 | D60: ='Data '!E60/'Data '!$B$22 -> 0.12847773 | E60: ='Data '!K60/'Data '!$B$22 -> 0.78992382 | F60: ='Data '!L60/'Data '!$B$22 -> 0.45585545 | H60: =((C60-B60)/ABS(B60)) -> -0.54710374 | I60: =((D60-C60)/ABS(C60)) -> -0.6970458 | J60: =((E60-D60)/ABS(D60)) -> 5.1483327 | K60: =((F60-E60)/ABS(E60)) -> -0.42291213 | M60: ='Data '!C60/'Data '!H60 -> 0.22350876 | N60: ='Data '!D60/'Data '!I60 -> 0.64480094 | O60: ='Data '!E60/'Data '!J60 -> 0.1842062 | P60: ='Data '!F60/'Data '!K60 -> 0.21557533 | Q60: ='Data '!G60/'Data '!L60 -> 0.143651 | S60: ='Data '!C60/'Data '!R60 -> 0.28015491 | T60: ='Data '!D60/'Data '!S60 -> 0.12344642 | U60: ='Data '!E60/'Data '!T60 -> 0.036285557 | V60: ='Data '!K60/'Data '!U60 -> 0.21268131 | W60: ='Data '!G60/'Data '!V60 -> 0.017286215 | Y60: ='Data '!M60/'Data '!R60 -> 0.68648208 | Z60: ='Data '!N60/'Data '!S60 -> 0.50623375 | AA60: ='Data '!O60/'Data '!T60 -> 0.4333261 | AB60: ='Data '!P60/'Data '!U60 -> 0.50497967 | AC60: ='Data '!Q60/'Data '!V60 -> 0.65357921 | AE60: 62.08
A61: SMART TUNISIE | C61: ='Data '!D61/'Data '!$B$22 -> 1.8330135 | D61: ='Data '!E61/'Data '!$B$22 -> 1.6410237 | E61: ='Data '!K61/'Data '!$B$22 -> 34.048484 | F61: ='Data '!L61/'Data '!$B$22 -> 39.663978 | I61: =((D61-C61)/ABS(C61)) -> -0.10473994 | J61: =((E61-D61)/ABS(D61)) -> 19.748319 | K61: =((F61-E61)/ABS(E61)) -> 0.1649264 | N61: ='Data '!D61/'Data '!I61 -> 0.063415799 | O61: ='Data '!E61/'Data '!J61 -> 0.049642646 | P61: ='Data '!F61/'Data '!K61 -> 0.040249641 | Q61: ='Data '!G61/'Data '!L61 -> 0.034475135 | T61: ='Data '!D61/'Data '!S61 -> 0.20950773 | U61: ='Data '!E61/'Data '!T61 -> 0.18505378 | V61: ='Data '!K61/'Data '!U61 -> 3.7598733 | W61: ='Data '!G61/'Data '!V61 -> 0.14336039 | Z61: ='Data '!N61/'Data '!S61 -> 0.8807085 | AA61: ='Data '!O61/'Data '!T61 -> 1.1367017 | AB61: ='Data '!P61/'Data '!U61 -> 1.2491928 | AC61: ='Data '!Q61/'Data '!V61 -> 1.3368246 | AE61: 12.56
A62: SOMOCER | B62: ='Data '!C62/'Data '!$B$22 -> -1.3912353 | C62: ='Data '!D62/'Data '!$B$22 -> 0.20485318 | D62: ='Data '!E62/'Data '!$B$22 -> -1.2567002 | E62: ='Data '!K62/'Data '!$B$22 -> 11.928089 | F62: ='Data '!L62/'Data '!$B$22 -> 8.2336469 | H62: =((C62-B62)/ABS(B62)) -> 1.1472455 | I62: =((D62-C62)/ABS(C62)) -> -7.1346383 | J62: =((E62-D62)/ABS(D62)) -> 10.491595 | K62: =((F62-E62)/ABS(E62)) -> -0.30972626 | M62: ='Data '!C62/'Data '!H62 -> -0.12025783 | N62: ='Data '!D62/'Data '!I62 -> 0.014795133 | O62: ='Data '!E62/'Data '!J62 -> -0.089641915 | P62: ='Data '!F62/'Data '!K62 -> -0.16087145 | Q62: ='Data '!G62/'Data '!L62 -> -0.48047306 | S62: ='Data '!C62/'Data '!R62 -> -0.21494909 | T62: ='Data '!D62/'Data '!S62 -> 0.031153342 | U62: ='Data '!E62/'Data '!T62 -> -0.22853033 | V62: ='Data '!K62/'Data '!U62 -> 3.5245498 | W62: ='Data '!G62/'Data '!V62 -> 4.2454874 | Y62: ='Data '!M62/'Data '!R62 -> 4.290319 | Z62: ='Data '!N62/'Data '!S62 -> 4.3762035 | AA62: ='Data '!O62/'Data '!T62 -> 5.3908299 | AB62: ='Data '!P62/'Data '!U62 -> 9.6495462 | AC62: ='Data '!Q62/'Data '!V62 -> -34.206366
A63: SOTEMAIL | B63: ='Data '!C63/'Data '!$B$22 -> -0.542025 | C63: ='Data '!D63/'Data '!$B$22 -> 0.093246818 | D63: ='Data '!E63/'Data '!$B$22 -> -0.43346918 | E63: ='Data '!K63/'Data '!$B$22 -> 5.1568415 | F63: ='Data '!L63/'Data '!$B$22 -> 3.4197004 | H63: =((C63-B63)/ABS(B63)) -> 1.1720342 | I63: =((D63-C63)/ABS(C63)) -> -5.6486217 | J63: =((E63-D63)/ABS(D63)) -> 12.896674 | K63: =((F63-E63)/ABS(E63)) -> -0.33686145 | M63: ='Data '!C63/'Data '!H63 -> -0.12477157 | N63: ='Data '!D63/'Data '!I63 -> 0.016503272 | O63: ='Data '!E63/'Data '!J63 -> -0.07380906 | P63: ='Data '!F63/'Data '!K63 -> -0.17219192 | Q63: ='Data '!G63/'Data '!L63 -> -0.38610597 | S63: ='Data '!C63/'Data '!R63 -> -0.14177774 | T63: ='Data '!D63/'Data '!S63 -> 0.023909222 | U63: ='Data '!E63/'Data '!T63 -> -0.12563254 | V63: ='Data '!K63/'Data '!U63 -> 2.0254243 | W63: ='Data '!G63/'Data '!V63 -> -0.39971975 | Y63: ='Data '!M63/'Data '!R63 -> 2.2192309 | Z63: ='Data '!N63/'Data '!S63 -> 2.4761563 | AA63: ='Data '!O63/'Data '!T63 -> 2.7618227 | AB63: ='Data '!P63/'Data '!U63 -> 4.0972843 | AC63: ='Data '!Q63/'Data '!V63 -> 2.9102227
A64: SOTETEL | B64: ='Data '!C64/'Data '!$B$22 -> 0.35291018 | C64: ='Data '!D64/'Data '!$B$22 -> -0.023163545 | D64: ='Data '!E64/'Data '!$B$22 -> 0.10875782 | E64: ='Data '!K64/'Data '!$B$22 -> 6.0441668 | F64: ='Data '!L64/'Data '!$B$22 -> 6.5332875 | H64: =((C64-B64)/ABS(B64)) -> -1.0656358 | I64: =((D64-C64)/ABS(C64)) -> 5.6952147 | J64: =((E64-D64)/ABS(D64)) -> 54.57455 | K64: =((F64-E64)/ABS(E64)) -> 0.080924425 | M64: ='Data '!C64/'Data '!H64 -> 0.11867815 | N64: ='Data '!D64/'Data '!I64 -> -0.0063457362 | O64: ='Data '!E64/'Data '!J64 -> 0.02357652 | P64: ='Data '!F64/'Data '!K64 -> 0.058337148 | Q64: ='Data '!G64/'Data '!L64 -> 0.057104885 | S64: ='Data '!C64/'Data '!R64 -> 0.14443532 | T64: ='Data '!D64/'Data '!S64 -> -0.0097405122 | U64: ='Data '!E64/'Data '!T64 -> 0.043733688 | V64: ='Data '!K64/'Data '!U64 -> 2.1286628 | W64: ='Data '!G64/'Data '!V64 -> 0.124138 | Y64: ='Data '!M64/'Data '!R64 -> 1.6532395 | Z64: ='Data '!N64/'Data '!S64 -> 1.5828701 | AA64: ='Data '!O64/'Data '!T64 -> 1.6102345 | AB64: ='Data '!P64/'Data '!U64 -> 2.0272349 | AC64: ='Data '!Q64/'Data '!V64 -> 1.7101698 | AE64: 5.65
A65: SOTRAPIL | B65: ='Data '!C65/'Data '!$B$22 -> 0.65110391 | C65: ='Data '!D65/'Data '!$B$22 -> 0.69459936 | D65: ='Data '!E65/'Data '!$B$22 -> 0.85250582 | E65: ='Data '!K65/'Data '!$B$22 -> 1.6664828 | F65: ='Data '!L65/'Data '!$B$22 -> 1.7068563 | H65: =((C65-B65)/ABS(B65)) -> 0.066802632 | I65: =((D65-C65)/ABS(C65)) -> 0.22733458 | J65: =((E65-D65)/ABS(D65)) -> 0.95480521 | K65: =((F65-E65)/ABS(E65)) -> 0.024226745 | M65: ='Data '!C65/'Data '!H65 -> 0.77291204 | N65: ='Data '!D65/'Data '!I65 -> 0.42306168 | O65: ='Data '!E65/'Data '!J65 -> 0.46321912 | P65: ='Data '!F65/'Data '!K65 -> 0.47442586 | Q65: ='Data '!G65/'Data '!L65 -> 0.47583066 | S65: ='Data '!C65/'Data '!R65 -> 0.15039556 | T65: ='Data '!D65/'Data '!S65 -> 0.15132 | U65: ='Data '!E65/'Data '!T65 -> 0.17140053 | V65: ='Data '!K65/'Data '!U65 -> 0.32090668 | W65: ='Data '!G65/'Data '!V65 -> 0.14972441 | Y65: ='Data '!M65/'Data '!R65 -> 0.20390814 | Z65: ='Data '!N65/'Data '!S65 -> 0.22974437 | AA65: ='Data '!O65/'Data '!T65 -> 0.22155504 | AB65: ='Data '!P65/'Data '!U65 -> 0.27634613 | AC65: ='Data '!Q65/'Data '!V65 -> 0.16687475 | AE65: 10.69
A66: STA | C66: ='Data '!D66/'Data '!$B$22 -> 0.41543318 | D66: ='Data '!E66/'Data '!$B$22 -> 0.57905264 | E66: ='Data '!K66/'Data '!$B$22 -> 7.2705297 | F66: ='Data '!L66/'Data '!$B$22 -> 9.9264469 | I66: =((D66-C66)/ABS(C66)) -> 0.39385264 | J66: =((E66-D66)/ABS(D66)) -> 11.555905 | K66: =((F66-E66)/ABS(E66)) -> 0.36529899 | N66: ='Data '!D66/'Data '!I66 -> 0.063793418 | O66: ='Data '!E66/'Data '!J66 -> 0.056343139 | P66: ='Data '!F66/'Data '!K66 -> 0.016827009 | Q66: ='Data '!G66/'Data '!L66 -> 0.053328896 | T66: ='Data '!D66/'Data '!S66 -> 0.16231555 | U66: ='Data '!E66/'Data '!T66 -> 0.20887025 | V66: ='Data '!K66/'Data '!U66 -> 2.9358473 | W66: ='Data '!G66/'Data '!V66 -> 0.18745168 | Z66: ='Data '!N66/'Data '!S66 -> 1.0818116 | AA66: ='Data '!O66/'Data '!T66 -> 1.5845586 | AB66: ='Data '!P66/'Data '!U66 -> 1.5379196 | AC66: ='Data '!Q66/'Data '!V66 -> 2.4453596 | AE66: 13.25
A67: STIP | B67: ='Data '!C67/'Data '!$B$22 -> 12.977475 | C67: ='Data '!D67/'Data '!$B$22 -> 2.1986255 | D67: ='Data '!E67/'Data '!$B$22 -> 1.0838851 | E67: ='Data '!K67/'Data '!$B$22 -> 12.650448 | F67: ='Data '!L67/'Data '!$B$22 -> 13.018747 | H67: =((C67-B67)/ABS(B67)) -> -0.8305814 | I67: =((D67-C67)/ABS(C67)) -> -0.50701697 | J67: =((E67-D67)/ABS(D67)) -> 10.671392 | K67: =((F67-E67)/ABS(E67)) -> 0.029113543 | M67: ='Data '!C67/'Data '!H67 -> 1.878722 | N67: ='Data '!D67/'Data '!I67 -> 0.19630372 | O67: ='Data '!E67/'Data '!J67 -> 0.078219748 | P67: ='Data '!F67/'Data '!K67 -> -0.011287046 | Q67: ='Data '!G67/'Data '!L67 -> -0.069334656 | S67: ='Data '!C67/'Data '!R67 -> -1.531172 | T67: ='Data '!D67/'Data '!S67 -> 4.8007059 | U67: ='Data '!E67/'Data '!T67 -> 0.70544877 | V67: ='Data '!K67/'Data '!U67 -> 9.1915899 | W67: ='Data '!G67/'Data '!V67 -> -1.9057069 | Y67: ='Data '!M67/'Data '!R67 -> -1.9545945 | Z67: ='Data '!N67/'Data '!S67 -> 36.694772 | AA67: ='Data '!O67/'Data '!T67 -> 12.541067 | AB67: ='Data '!P67/'Data '!U67 -> 14.042671 | AC67: ='Data '!Q67/'Data '!V67 -> 38.280933
A68: TAWASOL GH | B68: ='Data '!C68/'Data '!$B$22 -> -0.65951927 | C68: ='Data '!D68/'Data '!$B$22 -> -0.65951927 | D68: ='Data '!E68/'Data '!$B$22 -> -0.17303427 | E68: ='Data '!K68/'Data '!$B$22 -> 8.8409775 | F68: ='Data '!L68/'Data '!$B$22 -> 6.725107 | H68: =((C68-B68)/ABS(B68)) -> 0 | I68: =((D68-C68)/ABS(C68)) -> 0.73763576 | J68: =((E68-D68)/ABS(D68)) -> 52.093794 | K68: =((F68-E68)/ABS(E68)) -> -0.2393254 | M68: ='Data '!C68/'Data '!H68 -> -0.10564074 | N68: ='Data '!D68/'Data '!I68 -> -0.10564074 | O68: ='Data '!E68/'Data '!J68 -> -0.023615205 | P68: ='Data '!F68/'Data '!K68 -> 0.0119127 | Q68: ='Data '!G68/'Data '!L68 -> -0.011706999 | S68: ='Data '!C68/'Data '!R68 -> -0.27508275 | T68: ='Data '!D68/'Data '!S68 -> -0.27508275 | U68: ='Data '!E68/'Data '!T68 -> -0.075717356 | V68: ='Data '!K68/'Data '!U68 -> 3.6084179 | W68: ='Data '!G68/'Data '!V68 -> -0.043427057 | Y68: ='Data '!M68/'Data '!R68 -> 5.7637399 | Z68: ='Data '!N68/'Data '!S68 -> 5.7637399 | AA68: ='Data '!O68/'Data '!T68 -> 5.862106 | AB68: ='Data '!P68/'Data '!U68 -> 6.0122832 | AC68: ='Data '!Q68/'Data '!V68 -> 8.4068148
A69: TUNISAIR | C69: ='Data '!D69/'Data '!$B$22 -> -0.021762 | D69: ='Data '!E69/'Data '!$B$22 -> -0.019003455 | E69: ='Data '!K69/'Data '!$B$22 -> 0.058790091 | F69: ='Data '!L69/'Data '!$B$22 -> 0.073554364 | I69: =((D69-C69)/ABS(C69)) -> 0.12675974 | J69: =((E69-D69)/ABS(D69)) -> 4.0936528 | K69: =((F69-E69)/ABS(E69)) -> 0.2511354 | N69: ='Data '!D69/'Data '!I69 -> -0.12743829 | O69: ='Data '!E69/'Data '!J69 -> -0.1079966 | P69: ='Data '!F69/'Data '!K69 -> -0.4908805 | Q69: ='Data '!G69/'Data '!L69 -> -0.41407963 | T69: ='Data '!D69/'Data '!S69 -> 0.35752349 | U69: ='Data '!E69/'Data '!T69 -> 0.23916078 | V69: ='Data '!K69/'Data '!U69 -> -0.54457685 | W69: ='Data '!G69/'Data '!V69 -> 0.22035845 | Z69: ='Data '!N69/'Data '!S69 -> -2.7289756 | AA69: ='Data '!O69/'Data '!T69 -> -2.4578284 | AB69: ='Data '!P69/'Data '!U69 -> -2.0988791 | AC69: ='Data '!Q69/'Data '!V69 -> -1.7252477
A70: BH | B70: ='Data '!C70/'Data '!$B$22 -> 6.6422727 | C70: ='Data '!D70/'Data '!$B$22 -> 12.528182 | D70: ='Data '!E70/'Data '!$B$22 -> 11.377091 | E70: ='Data '!K70/'Data '!$B$22 -> 67.695182 | F70: ='Data '!L70/'Data '!$B$22 -> 76.425182 | H70: =((C70-B70)/ABS(B70)) -> 0.88612879 | I70: =((D70-C70)/ABS(C70)) -> -0.091880125 | J70: =((E70-D70)/ABS(D70)) -> 4.950131 | K70: =((F70-E70)/ABS(E70)) -> 0.12896043 | M70: ='Data '!C70/'Data '!H70 -> 0.13050747 | N70: ='Data '!D70/'Data '!I70 -> 0.22197274 | O70: ='Data '!E70/'Data '!J70 -> 0.17590975 | P70: ='Data '!F70/'Data '!K70 -> 0.19200776 | Q70: ='Data '!G70/'Data '!L70 -> 0.084489049 | S70: ='Data '!C70/'Data '!R70 -> 0.068065773 | T70: ='Data '!D70/'Data '!S70 -> 0.11637638 | U70: ='Data '!E70/'Data '!T70 -> 0.09923261 | V70: ='Data '!K70/'Data '!U70 -> 0.544785 | W70: ='Data '!G70/'Data '!V70 -> 0.04408695 | Y70: ='Data '!M70/'Data '!R70 -> 11.071466 | Z70: ='Data '!N70/'Data '!S70 -> 9.7774282 | AA70: ='Data '!O70/'Data '!T70 -> 10.152786 | AB70: ='Data '!P70/'Data '!U70 -> 9.2871515 | AC70: ='Data '!Q70/'Data '!V70 -> 8.4753915 | AE70: 4.57
A71: BH ASSURANCES | B71: ='Data '!C71/'Data '!$B$22 -> 0.87838809 | C71: ='Data '!D71/'Data '!$B$22 -> 1.1952685 | D71: ='Data '!E71/'Data '!$B$22 -> 1.2096719 | E71: ='Data '!K71/'Data '!$B$22 -> 1.2660182 | F71: ='Data '!L71/'Data '!$B$22 -> 1.2659348 | H71: =((C71-B71)/ABS(B71)) -> 0.36075222 | I71: =((D71-C71)/ABS(C71)) -> 0.012050316 | J71: =((E71-D71)/ABS(D71)) -> 0.046579798 | K71: =((F71-E71)/ABS(E71)) -> -6.5847108e-05 | M71: ='Data '!C71/'Data '!H71 -> 1.1691125 | N71: ='Data '!D71/'Data '!I71 -> 1.3875921 | O71: ='Data '!E71/'Data '!J71 -> 1.1741544 | P71: ='Data '!F71/'Data '!K71 -> 0.94609097 | Q71: ='Data '!G71/'Data '!L71 -> 0.79093186 | S71: ='Data '!C71/'Data '!R71 -> 0.13758306 | T71: ='Data '!D71/'Data '!S71 -> 0.16289044 | U71: ='Data '!E71/'Data '!T71 -> 0.14606098 | V71: ='Data '!K71/'Data '!U71 -> 0.13794972 | W71: ='Data '!G71/'Data '!V71 -> 0.10200787 | Y71: ='Data '!M71/'Data '!R71 -> 3.9655931 | Z71: ='Data '!N71/'Data '!S71 -> 3.7388578 | AA71: ='Data '!O71/'Data '!T71 -> 3.8680602 | AB71: ='Data '!P71/'Data '!U71 -> -8.5623531 | AC71: ='Data '!Q71/'Data '!V71 -> 4.228231 | AE71: 15.21
A72: PLTU | B72: ='Data '!C72/'Data '!$B$22 -> 0.40801618 | C72: ='Data '!D72/'Data '!$B$22 -> 0.35972591 | D72: ='Data '!E72/'Data '!$B$22 -> 0.288057 | E72: ='Data '!K72/'Data '!$B$22 -> 0.16021927 | F72: ='Data '!L72/'Data '!$B$22 -> 0.30777091 | H72: =((C72-B72)/ABS(B72)) -> -0.11835382 | I72: =((D72-C72)/ABS(C72)) -> -0.19923199 | J72: =((E72-D72)/ABS(D72)) -> -0.44379316 | K72: =((F72-E72)/ABS(E72)) -> 0.92093563 | M72: ='Data '!C72/'Data '!H72 -> 0.89526172 | N72: ='Data '!D72/'Data '!I72 -> 0.86919633 | O72: ='Data '!E72/'Data '!J72 -> 0.88727433 | P72: ='Data '!F72/'Data '!K72 -> 0.8097766 | Q72: ='Data '!G72/'Data '!L72 -> 0.91900056 | S72: ='Data '!C72/'Data '!R72 -> 0.23682363 | T72: ='Data '!D72/'Data '!S72 -> 0.20926964 | U72: ='Data '!E72/'Data '!T72 -> 0.174319 | V72: ='Data '!K72/'Data '!U72 -> 0.10303892 | W72: ='Data '!G72/'Data '!V72 -> 0.17562259 | Y72: ='Data '!M72/'Data '!R72 -> 0 | Z72: ='Data '!N72/'Data '!S72 -> 0 | AA72: ='Data '!O72/'Data '!T72 -> 0 | AB72: ='Data '!P72/'Data '!U72 -> 0 | AC72: ='Data '!Q72/'Data '!V72 -> 0 | AE72: 13.44
A73: TJL | B73: ='Data '!C73/'Data '!$B$22 -> 0.29351273 | C73: ='Data '!D73/'Data '!$B$22 -> 0.81359018 | D73: ='Data '!E73/'Data '!$B$22 -> 0.68059036 | E73: ='Data '!K73/'Data '!$B$22 -> 2.7771762 | F73: ='Data '!L73/'Data '!$B$22 -> 2.9873705 | H73: =((C73-B73)/ABS(B73)) -> 1.7719077 | I73: =((D73-C73)/ABS(C73)) -> -0.16347274 | J73: =((E73-D73)/ABS(D73)) -> 3.08054 | K73: =((F73-E73)/ABS(E73)) -> 0.07568633 | M73: ='Data '!C73/'Data '!H73 -> 0.16045606 | N73: ='Data '!D73/'Data '!I73 -> 0.32401747 | O73: ='Data '!E73/'Data '!J73 -> 0.25560314 | P73: ='Data '!F73/'Data '!K73 -> 0.28876807 | Q73: ='Data '!G73/'Data '!L73 -> 0.30442887 | S73: ='Data '!C73/'Data '!R73 -> 0.058545148 | T73: ='Data '!D73/'Data '!S73 -> 0.14317912 | U73: ='Data '!E73/'Data '!T73 -> 0.1126603 | V73: ='Data '!K73/'Data '!U73 -> 0.43050095 | W73: ='Data '!G73/'Data '!V73 -> 0.13069721 | Y73: ='Data '!M73/'Data '!R73 -> 7.5372871 | Z73: ='Data '!N73/'Data '!S73 -> 5.9509092 | AA73: ='Data '!O73/'Data '!T73 -> 5.5160206 | AB73: ='Data '!P73/'Data '!U73 -> 5.2836717 | AC73: ='Data '!Q73/'Data '!V73 -> 5.2336514 | AE73: 7.83
A74: UBCI | B74: ='Data '!C74/'Data '!$B$22 -> 3.8599091 | C74: ='Data '!D74/'Data '!$B$22 -> 2.7736364 | D74: ='Data '!E74/'Data '!$B$22 -> 5.4295455 | E74: ='Data '!K74/'Data '!$B$22 -> 27.534364 | F74: ='Data '!L74/'Data '!$B$22 -> 29.241545 | H74: =((C74-B74)/ABS(B74)) -> -0.28142443 | I74: =((D74-C74)/ABS(C74)) -> 0.9575549 | J74: =((E74-D74)/ABS(D74)) -> 4.0712097 | K74: =((F74-E74)/ABS(E74)) -> 0.062001862 | M74: ='Data '!C74/'Data '!H74 -> 0.17435815 | N74: ='Data '!D74/'Data '!I74 -> 0.11537589 | O74: ='Data '!E74/'Data '!J74 -> 0.20250156 | P74: ='Data '!F74/'Data '!K74 -> 0.17616994 | Q74: ='Data '!G74/'Data '!L74 -> 0.17094296 | S74: ='Data '!C74/'Data '!R74 -> 0.094536314 | T74: ='Data '!D74/'Data '!S74 -> 0.066672785 | U74: ='Data '!E74/'Data '!T74 -> 0.1191065 | V74: ='Data '!K74/'Data '!U74 -> 0.5715542 | W74: ='Data '!G74/'Data '!V74 -> 0.098726795 | Y74: ='Data '!M74/'Data '!R74 -> 6.3518254 | Z74: ='Data '!N74/'Data '!S74 -> 6.7228239 | AA74: ='Data '!O74/'Data '!T74 -> 6.309996 | AB74: ='Data '!P74/'Data '!U74 -> 7.5815425 | AC74: ='Data '!Q74/'Data '!V74 -> 8.293207 | AE74: 12.43
A75: SCORING SYSYTEM
B76: =0.1 -> 0.1 | G76: average EPS | H76: =0.15 -> 0.15 | L76: average EPS g | M76: 0.2 | R76: average NPM | S76: 0.3 | X76: average ROE | Y76: 0.2 | AD76: average DE | AE76: 0.05
A77: Societe Frigorifique Et Brasserie | B77: {=(B3-MIN($B$3:$B$74))/(MAX($B$3:$B$74-MIN($B$3:$B$74)))} -> 0.15367108 | C77: {=(C3-MIN($B$3:$B$74))/(MAX($B$3:$B$74-MIN($B$3:$B$74)))} -> 0.15889387 | D77: {=(D3-MIN($B$3:$B$74))/(MAX($B$3:$B$74-MIN($B$3:$B$74)))} -> 0.15966892 | E77: {=(E3-MIN($B$3:$B$74))/(MAX($B$3:$B$74-MIN($B$3:$B$74)))} -> 0.16285306 | F77: {=(F3-MIN($B$3:$B$74))/(MAX($B$3:$B$74-MIN($B$3:$B$74)))} -> 0.16301717 | G77: =AVERAGEA(B77:E77) -> 0.15877173 | H77: {=(H3-MIN($H$3:$H$74))/(MAX($H$3:$H$74-MIN($H$3:$H$74)))} -> 0.57248306 | I77: {=(I3-MIN($H$3:$H$74))/(MAX($H$3:$H$74-MIN($H$3:$H$74)))} -> 0.5655069 | J77: {=(J3-MIN($H$3:$H$74))/(MAX($H$3:$H$74-MIN($H$3:$H$74)))} -> 0.56849507 | K77: {=(K3-MIN($H$3:$H$74))/(MAX($H$3:$H$74-MIN($H$3:$H$74)))} -> 0.56470211 | L77: =AVERAGE(H77:J77) -> 0.56882834 | M77: {=(M3-MIN($N$3:$N$74))/(MAX($N$3:$N$74-MIN($N$3:$N$74)))} -> 0.17725318 | N77: {=(N3-MIN($N$3:$N$74))/(MAX($N$3:$N$74-MIN($N$3:$N$74)))} -> 0.18738251 | O77: {=(O3-MIN($N$3:$N$74))/(MAX($N$3:$N$74-MIN($N$3:$N$74)))} -> 0.18257652 | P77: {=(P3-MIN($N$3:$N$74))/(MAX($N$3:$N$74-MIN($N$3:$N$74)))} -> 0.18621675 | Q77: {=(Q3-MIN($N$3:$N$74))/(MAX($N$3:$N$74-MIN($N$3:$N$74)))} -> 0.1853245 | R77: =AVERAGE(M77:P77) -> 0.18335724 | S77: {=(S3-MIN($S$3:$S$74))/(MAX($S$3:$S$74-MIN($S$3:$S$74)))} -> 0.768864 | T77: {=(T3-MIN($T$3:$T$74))/(MAX($T$3:$T$74-MIN($T$3:$T$74)))} -> 0.117821 | U77: {=(U3-MIN($T$3:$T$74))/(MAX($T$3:$T$74-MIN($T$3:$T$74)))} -> 0.11575065 | V77: {=(V3-MIN($T$3:$T$74))/(MAX($T$3:$T$74-MIN($T$3:$T$74)))} -> 0.11575355 | W77: {=(W3-MIN($T$3:$T$74))/(MAX($T$3:$T$74-MIN($T$3:$T$74)))} -> 0.11336712 | X77: =AVERAGE(S77:V77) -> 0.2795473 | Y77: =(Y3-MIN($Y$3:$Y$74))/(MAX($Y$3:$Y$74)-MIN($Y$3:$Y$74)) -> 0.5269708 | Z77: =(Z3-MIN($Z$3:$Z$74))/(MAX($Z$3:$Z$74)-MIN($Z$3:$Z$74)) -> 0.32607916 | AA77: =(AA3-MIN($Z$3:$Z$74))/(MAX($Z$3:$Z$74)-MIN($Z$3:$Z$74)) -> 0.32665677 | AB77: =(AB3-MIN($Z$3:$Z$74))/(MAX($Z$3:$Z$74)-MIN($Z$3:$Z$74)) -> 0.32591015 | AC77: =(AC3-MIN($Z$3:$Z$74))/(MAX($Z$3:$Z$74)-MIN($Z$3:$Z$74)) -> 0.32569311 | AD77: =AVERAGE(Y77:AB77) -> 0.37640422 | AE77: =(AE3-MIN($AE$3:$AE$74))/(MAX($AE$3:$AE$74)-MIN($AE$3:$AE$74)) -> 0.17204301
A78: Banque Attijari De Tunisie | B78: {=(B4-MIN($B$3:$B$74))/(MAX($B$3:$B$74-MIN($B$3:$B$74)))} -> 0.35336451 | C78: {=(C4-MIN($B$3:$B$74))/(MAX($B$3:$B$74-MIN($B$3:$B$74)))} -> 0.3598335 | D78: {=(D4-MIN($B$3:$B$74))/(MAX($B$3:$B$74-MIN($B$3:$B$74)))} -> 0.67429077 | E78: {=(E4-MIN($B$3:$B$74))/(MAX($B$3:$B$74-MIN($B$3:$B$74)))} -> 0.42863262 | F78: {=(F4-MIN($B$3:$B$74))/(MAX($B$3:$B$74-MIN($B$3:$B$74)))} -> 0.42077106 | G78: =AVERAGEA(B78:E78) -> 0.45403035 | H78: {=(H4-MIN($H$3:$H$74))/(MAX($H$3:$H$74-MIN($H$3:$H$74)))} -> 0.56569799 | I78: {=(I4-MIN($H$3:$H$74))/(MAX($H$3:$H$74-MIN($H$3:$H$74)))} -> 0.62042871 | J78: {=(J4-MIN($H$3:$H$74))/(MAX($H$3:$H$74-MIN($H$3:$H$74)))} -> 0.54590783 | K78: {=(K4-MIN($H$3:$H$74))/(MAX($H$3:$H$74-MIN($H$3:$H$74)))} -> 0.56343535 | L78: =AVERAGE(H78:J78) -> 0.57734484 | M78: {=(M4-MIN($N$3:$N$74))/(MAX($N$3:$N$74-MIN($N$3:$N$74)))} -> 0.27406636 | N78: {=(N4-MIN($N$3:$N$74))/(MAX($N$3:$N$74-MIN($N$3:$N$74)))} -> 0.26380652 | O78: {=(O4-MIN($N$3:$N$74))/(MAX($N$3:$N$74-MIN($N$3:$N$74)))} -> 0.27240557 | P78: {=(P4-MIN($N$3:$N$74))/(MAX($N$3:$N$74-MIN($N$3:$N$74)))} -> 0.28095088 | Q78: {=(Q4-MIN($N$3:$N$74))/(MAX($N$3:$N$74-MIN($N$3:$N$74)))} -> 0.26720635 | R78: =AVERAGE(M78:P78) -> 0.27280733 | S78: {=(S4-MIN($S$3:$S$74))/(MAX($S$3:$S$74-MIN($S$3:$S$74)))} -> 0.81730272 | T78: {=(T4-MIN($T$3:$T$74))/(MAX($T$3:$T$74-MIN($T$3:$T$74)))} -> 0.13271246 | U78: {=(U4-MIN($T$3:$T$74))/(MAX($T$3:$T$74-MIN($T$3:$T$74)))} -> 0.20140802 | V78: {=(V4-MIN($T$3:$T$74))/(MAX($T$3:$T$74-MIN($T$3:$T$74)))} -> 0.13802352 | W78: {=(W4-MIN($T$3:$T$74))/(MAX($T$3:$T$74-MIN($T$3:$T$74)))} -> 0.13309697 | X78: =AVERAGE(S78:V78) -> 0.32236168 | Y78: =(Y4-MIN($Y$3:$Y$74))/(MAX($Y$3:$Y$74)-MIN($Y$3:$Y$74)) -> 0.58514875 | Z78: =(Z4-MIN($Z$3:$Z$74))/(MAX($Z$3:$Z$74)-MIN($Z$3:$Z$74)) -> 0.3825049 | AA78: =(AA4-MIN($Z$3:$Z$74))/(MAX($Z$3:$Z$74)-MIN($Z$3:$Z$74)) -> 0.38334314 | AB78: =(AB4-MIN($Z$3:$Z$74))/(MAX($Z$3:$Z$74)-MIN($Z$3:$Z$74)) -> 0.44518621 | AC78: =(AC4-MIN($Z$3:$Z$74))/(MAX($Z$3:$Z$74)-MIN($Z$3:$Z$74)) -> 0.4931154 | AD78: =AVERAGE(Y78:AB78) -> 0.44904575 | AE78: =(AE4-MIN($AE$3:$AE$74))/(MAX($AE$3:$AE$74)-MIN($AE$3:$AE$74)) -> 0.17497556
A79: Poulina Group Holding | B79: {=(B5-MIN($B$3:$B$74))/(MAX($B$3:$B$74-MIN($B$3:$B$74)))} -> 0.15765621 | C79: {=(C5-MIN($B$3:$B$74))/(MAX($B$3:$B$74-MIN($B$3:$B$74)))} -> 0.14441958 | D79: {=(D5-MIN($B$3:$B$74))/(MAX($B$3:$B$74-MIN($B$3:$B$74)))} -> 0.13912614 | E79: {=(E5-MIN($B$3:$B$74))/(MAX($B$3:$B$74-MIN($B$3:$B$74)))} -> 0.15141612 | F79: {=(F5-MIN($B$3:$B$74))/(MAX($B$3:$B$74-MIN($B$3:$B$74)))} -> 0.15765621 | G79: =AVERAGEA(B79:E79) -> 0.14815451 | H79: {=(H5-MIN($H$3:$H$74))/(MAX($H$3:$H$74-MIN($H$3:$H$74)))} -> 0.54690137 | I79: {=(I5-MIN($H$3:$H$74))/(MAX($H$3:$H$74-MIN($H$3:$H$74)))} -> 0.55227576 | J79: {=(J5-MIN($H$3:$H$74))/(MAX($H$3:$H$74-MIN($H$3:$H$74)))} -> 0.6048195 | K79: {=(K5-MIN($H$3:$H$74))/(MAX($H$3:$H$74-MIN($H$3:$H$74)))} -> 0.57489577 | L79: =AVERAGE(H79:J79) -> 0.56799888 | M79: {=(M5-MIN($N$3:$N$74))/(MAX($N$3:$N$74-MIN($N$3:$N$74)))} -> 0.14670394 | N79: {=(N5-MIN($N$3:$N$74))/(MAX($N$3:$N$74-MIN($N$3:$N$74)))} -> 0.13549835 | O79: {=(O5-MIN($N$3:$N$74))/(MAX($N$3:$N$74-MIN($N$3:$N$74)))} -> 0.13211088 | P79: {=(P5-MIN($N$3:$N$74))/(MAX($N$3:$N$74-MIN($N$3:$N$74)))} -> 0.13693849 | Q79: {=(Q5-MIN($N$3:$N$74))/(MAX($N$3:$N$74-MIN($N$3:$N$74)))} -> 0.13978647 | R79: =AVERAGE(M79:P79) -> 0.13781292 | S79: {=(S5-MIN($S$3:$S$74))/(MAX($S$3:$S$74-MIN($S$3:$S$74)))} -> 0.7557633 | T79: {=(T5-MIN($T$3:$T$74))/(MAX($T$3:$T$74-MIN($T$3:$T$74)))} -> 0.093304856 | U79: {=(U5-MIN($T$3:$T$74))/(MAX($T$3:$T$74-MIN($T$3:$T$74)))} -> 0.08791174 | V79: {=(V5-MIN($T$3:$T$74))/(MAX($T$3:$T$74-MIN($T$3:$T$74)))} -> 0.098469402 | W79: {=(W5-MIN($T$3:$T$74))/(MAX($T$3:$T$74-MIN($T$3:$T$74)))} -> 0.10207059 | X79: =AVERAGE(S79:V79) -> 0.25886232 | Y79: =(Y5-MIN($Y$3:$Y$74))/(MAX($Y$3:$Y$74)-MIN($Y$3:$Y$74)) -> 0.6216918 | Z79: =(Z5-MIN($Z$3:$Z$74))/(MAX($Z$3:$Z$74)-MIN($Z$3:$Z$74)) -> 0.39245465 | AA79: =(AA5-MIN($Z$3:$Z$74))/(MAX($Z$3:$Z$74)-MIN($Z$3:$Z$74)) -> 0.39778461 | AB79: =(AB5-MIN($Z$3:$Z$74))/(MAX($Z$3:$Z$74)-MIN($Z$3:$Z$74)) -> 0.37551382 | AC79: =(AC5-MIN($Z$3:$Z$74))/(MAX($Z$3:$Z$74)-MIN($Z$3:$Z$74)) -> 0.36902107 | AD79: =AVERAGE(Y79:AB79) -> 0.44686122 | AE79: =(AE5-MIN($AE$3:$AE$74))/(MAX($AE$3:$AE$74)-MIN($AE$3:$AE$74)) -> 0.31671554
A80: Societe Delice Holding | B80: {=(B6-MIN($B$3:$B$74))/(MAX($B$3:$B$74-MIN($B$3:$B$74)))} -> 0.16293676 | C80: {=(C6-MIN($B$3:$B$74))/(MAX($B$3:$B$74-MIN($B$3:$B$74)))} -> 0.17084324 | D80: {=(D6-MIN($B$3:$B$74))/(MAX($B$3:$B$74-MIN($B$3:$B$74)))} -> 0.1760092 | E80: {=(E6-MIN($B$3:$B$74))/(MAX($B$3:$B$74-MIN($B$3:$B$74)))} -> 0.18814201 | F80: {=(F6-MIN($B$3:$B$74))/(MAX($B$3:$B$74-MIN($B$3:$B$74)))} -> 0.19018036 | G80: =AVERAGEA(B80:E80) -> 0.1744828 | H80: {=(H6-MIN($H$3:$H$74))/(MAX($H$3:$H$74-MIN($H$3:$H$74)))} -> 0.57351221 | I80: {=(I6-MIN($H$3:$H$74))/(MAX($H$3:$H$74-MIN($H$3:$H$74)))} -> 0.56934606 | J80: {=(J6-MIN($H$3:$H$74))/(MAX($H$3:$H$74-MIN($H$3:$H$74)))} -> 0.57467804 | K80: {=(K6-MIN($H$3:$H$74))/(MAX($H$3:$H$74-MIN($H$3:$H$74)))} -> 0.56588645 | L80: =AVERAGE(H80:J80) -> 0.5725121 | M80: {=(M6-MIN($N$3:$N$74))/(MAX($N$3:$N$74-MIN($N$3:$N$74)))} -> 0.14219079 | N80: {=(N6-MIN($N$3:$N$74))/(MAX($N$3:$N$74-MIN($N$3:$N$74)))} -> 0.1436996 | O80: {=(O6-MIN($N$3:$N$74))/(MAX($N$3:$N$74-MIN($N$3:$N$74)))} -> 0.14416954 | P80: {=(P6-MIN($N$3:$N$74))/(MAX($N$3:$N$74-MIN($N$3:$N$74)))} -> 0.14663039 | Q80: {=(Q6-MIN($N$3:$N$74))/(MAX($N$3:$N$74-MIN($N$3:$N$74)))} -> 0.14651623 | R80: =AVERAGE(M80:P80) -> 0.14417258 | S80: {=(S6-MIN($S$3:$S$74))/(MAX($S$3:$S$74-MIN($S$3:$S$74)))} -> 0.78582138 | T80: {=(T6-MIN($T$3:$T$74))/(MAX($T$3:$T$74-MIN($T$3:$T$74)))} -> 0.11952848 | U80: {=(U6-MIN($T$3:$T$74))/(MAX($T$3:$T$74-MIN($T$3:$T$74)))} -> 0.11651414 | V80: {=(V6-MIN($T$3:$T$74))/(MAX($T$3:$T$74-MIN($T$3:$T$74)))} -> 0.1195067 | W80: {=(W6-MIN($T$3:$T$74))/(MAX($T$3:$T$74-MIN($T$3:$T$74)))} -> 0.11469667 | X80: =AVERAGE(S80:V80) -> 0.28534267 | Y80: =(Y6-MIN($Y$3:$Y$74))/(MAX($Y$3:$Y$74)-MIN($Y$3:$Y$74)) -> 0.57296932 | Z80: =(Z6-MIN($Z$3:$Z$74))/(MAX($Z$3:$Z$74)-MIN($Z$3:$Z$74)) -> 0.34122959 | AA80: =(AA6-MIN($Z$3:$Z$74))/(MAX($Z$3:$Z$74)-MIN($Z$3:$Z$74)) -> 0.33953394 | AB80: =(AB6-MIN($Z$3:$Z$74))/(MAX($Z$3:$Z$74)-MIN($Z$3:$Z$74)) -> 0.33946814 | AC80: =(AC6-MIN($Z$3:$Z$74))/(MAX($Z$3:$Z$74)-MIN($Z$3:$Z$74)) -> 0.33795169 | AD80: =AVERAGE(Y80:AB80) -> 0.39830024 | AE80: =(AE6-MIN($AE$3:$AE$74))/(MAX($AE$3:$AE$74)-MIN($AE$3:$AE$74)) -> 0.099217986
A81: One Tech Ho | B81: {=(B7-MIN($B$3:$B$74))/(MAX($B$3:$B$74-MIN($B$3:$B$74)))} -> 0.13498827 | C81: {=(C7-MIN($B$3:$B$74))/(MAX($B$3:$B$74-MIN($B$3:$B$74)))} -> 0.13971517 | D81: {=(D7-MIN($B$3:$B$74))/(MAX($B$3:$B$74-MIN($B$3:$B$74)))} -> 0.13241378 | E81: {=(E7-MIN($B$3:$B$74))/(MAX($B$3:$B$74-MIN($B$3:$B$74)))} -> 0.14298352 | F81: {=(F7-MIN($B$3:$B$74))/(MAX($B$3:$B$74-MIN($B$3:$B$74)))} -> 0.13947984 | G81: =AVERAGEA(B81:E81) -> 0.13752519 | H81: {=(H7-MIN($H$3:$H$74))/(MAX($H$3:$H$74-MIN($H$3:$H$74)))} -> 0.58754991 | I81: {=(I7-MIN($H$3:$H$74))/(MAX($H$3:$H$74-MIN($H$3:$H$74)))} -> 0.54163543 | J81: {=(J7-MIN($H$3:$H$74))/(MAX($H$3:$H$74-MIN($H$3:$H$74)))} -> 0.6383464 | K81: {=(K7-MIN($H$3:$H$74))/(MAX($H$3:$H$74-MIN($H$3:$H$74)))} -> 0.55570931 | L81: =AVERAGE(H81:J81) -> 0.58917725 | M81: {=(M7-MIN($N$3:$N$74))/(MAX($N$3:$N$74-MIN($N$3:$N$74)))} -> 0.13407933 | N81: {=(N7-MIN($N$3:$N$74))/(MAX($N$3:$N$74-MIN($N$3:$N$74)))} -> 0.13596875 | O81: {=(O7-MIN($N$3:$N$74))/(MAX($N$3:$N$74-MIN($N$3:$N$74)))} -> 0.12988485 | P81: {=(P7-MIN($N$3:$N$74))/(MAX($N$3:$N$74-MIN($N$3:$N$74)))} -> 0.1361819 | Q81: {=(Q7-MIN($N$3:$N$74))/(MAX($N$3:$N$74-MIN($N$3:$N$74)))} -> 0.13445897 | R81: =AVERAGE(M81:P81) -> 0.13402871 | S81: {=(S7-MIN($S$3:$S$74))/(MAX($S$3:$S$74-MIN($S$3:$S$74)))} -> 0.7047489 | T81: {=(T7-MIN($T$3:$T$74))/(MAX($T$3:$T$74-MIN($T$3:$T$74)))} -> 0.091293214 | U81: {=(U7-MIN($T$3:$T$74))/(MAX($T$3:$T$74-MIN($T$3:$T$74)))} -> 0.08246135 | V81: {=(V7-MIN($T$3:$T$74))/(MAX($T$3:$T$74-MIN($T$3:$T$74)))} -> 0.094065757 | W81: {=(W7-MIN($T$3:$T$74))/(MAX($T$3:$T$74-MIN($T$3:$T$74)))} -> 0.089710951 | X81: =AVERAGE(S81:V81) -> 0.24314231 | Y81: =(Y7-MIN($Y$3:$Y$74))/(MAX($Y$3:$Y$74)-MIN($Y$3:$Y$74)) -> 0.53940646 | Z81: =(Z7-MIN($Z$3:$Z$74))/(MAX($Z$3:$Z$74)-MIN($Z$3:$Z$74)) -> 0.33371343 | AA81: =(AA7-MIN($Z$3:$Z$74))/(MAX($Z$3:$Z$74)-MIN($Z$3:$Z$74)) -> 0.33575215 | AB81: =(AB7-MIN($Z$3:$Z$74))/(MAX($Z$3:$Z$74)-MIN($Z$3:$Z$74)) -> 0.33330029 | AC81: =(AC7-MIN($Z$3:$Z$74))/(MAX($Z$3:$Z$74)-MIN($Z$3:$Z$74)) -> 0.33057435 | AD81: =AVERAGE(Y81:AB81) -> 0.38554309 | AE81: =(AE7-MIN($AE$3:$AE$74))/(MAX($AE$3:$AE$74)-MIN($AE$3:$AE$74)) -> 0.38383838
A82: Carthage Cement | B82: {=(B8-MIN($B$3:$B$74))/(MAX($B$3:$B$74-MIN($B$3:$B$74)))} -> 0.12842497 | C82: {=(C8-MIN($B$3:$B$74))/(MAX($B$3:$B$74-MIN($B$3:$B$74)))} -> 0.12964884 | D82: {=(D8-MIN($B$3:$B$74))/(MAX($B$3:$B$74-MIN($B$3:$B$74)))} -> 0.13006617 | E82: {=(E8-MIN($B$3:$B$74))/(MAX($B$3:$B$74-MIN($B$3:$B$74)))} -> 0.13203559 | F82: {=(F8-MIN($B$3:$B$74))/(MAX($B$3:$B$74-MIN($B$3:$B$74)))} -> 0.13355355 | G82: =AVERAGEA(B82:E82) -> 0.13004389 | H82: {=(H8-MIN($H$3:$H$74))/(MAX($H$3:$H$74-MIN($H$3:$H$74)))} -> 0.59053801 | I82: {=(I8-MIN($H$3:$H$74))/(MAX($H$3:$H$74-MIN($H$3:$H$74)))} -> 0.56996838 | J82: {=(J8-MIN($H$3:$H$74))/(MAX($H$3:$H$74-MIN($H$3:$H$74)))} -> 0.58726097 | K82: {=(K8-MIN($H$3:$H$74))/(MAX($H$3:$H$74-MIN($H$3:$H$74)))} -> 0.57583911 | L82: =AVERAGE(H82:J82) -> 0.58258912 | M82: {=(M8-MIN($N$3:$N$74))/(MAX($N$3:$N$74-MIN($N$3:$N$74)))} -> 0.14842639 | N82: {=(N8-MIN($N$3:$N$74))/(MAX($N$3:$N$74-MIN($N$3:$N$74)))} -> 0.15431205 | O82: {=(O8-MIN($N$3:$N$74))/(MAX($N$3:$N$74-MIN($N$3:$N$74)))} -> 0.1544531 | P82: {=(P8-MIN($N$3:$N$74))/(MAX($N$3:$N$74-MIN($N$3:$N$74)))} -> 0.16344674 | Q82: {=(Q8-MIN($N$3:$N$74))/(MAX($N$3:$N$74-MIN($N$3:$N$74)))} -> 0.17478973 | R82: =AVERAGE(M82:P82) -> 0.15515957 | S82: {=(S8-MIN($S$3:$S$74))/(MAX($S$3:$S$74-MIN($S$3:$S$74)))} -> 0.74262609 | T82: {=(T8-MIN($T$3:$T$74))/(MAX($T$3:$T$74-MIN($T$3:$T$74)))} -> 0.11120763 | U82: {=(U8-MIN($T$3:$T$74))/(MAX($T$3:$T$74-MIN($T$3:$T$74)))} -> 0.10877396 | V82: {=(V8-MIN($T$3:$T$74))/(MAX($T$3:$T$74-MIN($T$3:$T$74)))} -> 0.1161259 | W82: {=(W8-MIN($T$3:$T$74))/(MAX($T$3:$T$74-MIN($T$3:$T$74)))} -> 0.1161567 | X82: =AVERAGE(S82:V82) -> 0.26968339 | Y82: =(Y8-MIN($Y$3:$Y$74))/(MAX($Y$3:$Y$74)-MIN($Y$3:$Y$74)) -> 0.70944107 | Z82: =(Z8-MIN($Z$3:$Z$74))/(MAX($Z$3:$Z$74)-MIN($Z$3:$Z$74)) -> 0.38767645 | AA82: =(AA8-MIN($Z$3:$Z$74))/(MAX($Z$3:$Z$74)-MIN($Z$3:$Z$74)) -> 0.37689543 | AB82: =(AB8-MIN($Z$3:$Z$74))/(MAX($Z$3:$Z$74)-MIN($Z$3:$Z$74)) -> 0.36086809 | AC82: =(AC8-MIN($Z$3:$Z$74))/(MAX($Z$3:$Z$74)-MIN($Z$3:$Z$74)) -> 0.34736265 | AD82: =AVERAGE(Y82:AB82) -> 0.45872026 | AE82: =(AE8-MIN($AE$3:$AE$74))/(MAX($AE$3:$AE$74)-MIN($AE$3:$AE$74)) -> 0.13310525
A83: Societe Tunisienne De Verreries | B83: {=(B9-MIN($B$3:$B$74))/(MAX($B$3:$B$74-MIN($B$3:$B$74)))} -> 0.13586965 | C83: {=(C9-MIN($B$3:$B$74))/(MAX($B$3:$B$74-MIN($B$3:$B$74)))} -> 0.14410399 | D83: {=(D9-MIN($B$3:$B$74))/(MAX($B$3:$B$74-MIN($B$3:$B$74)))} -> 0.15285499 | E83: {=(E9-MIN($B$3:$B$74))/(MAX($B$3:$B$74-MIN($B$3:$B$74)))} -> 0.16761906 | F83: {=(F9-MIN($B$3:$B$74))/(MAX($B$3:$B$74-MIN($B$3:$B$74)))} -> 0.16334055 | G83: =AVERAGEA(B83:E83) -> 0.15011192 | H83: {=(H9-MIN($H$3:$H$74))/(MAX($H$3:$H$74-MIN($H$3:$H$74)))} -> 0.60087818 | I83: {=(I9-MIN($H$3:$H$74))/(MAX($H$3:$H$74-MIN($H$3:$H$74)))} -> 0.58511066 | J83: {=(J9-MIN($H$3:$H$74))/(MAX($H$3:$H$74-MIN($H$3:$H$74)))} -> 0.58773644 | K83: {=(K9-MIN($H$3:$H$74))/(MAX($H$3:$H$74-MIN($H$3:$H$74)))} -> 0.56020021 | L83: =AVERAGE(H83:J83) -> 0.59124176 | M83: {=(M9-MIN($N$3:$N$74))/(MAX($N$3:$N$74-MIN($N$3:$N$74)))} -> 0.16024201 | N83: {=(N9-MIN($N$3:$N$74))/(MAX($N$3:$N$74-MIN($N$3:$N$74)))} -> 0.1817717 | O83: {=(O9-MIN($N$3:$N$74))/(MAX($N$3:$N$74-MIN($N$3:$N$74)))} -> 0.18205006 | P83: {=(P9-MIN($N$3:$N$74))/(MAX($N$3:$N$74-MIN($N$3:$N$74)))} -> 0.17804576 | Q83: {=(Q9-MIN($N$3:$N$74))/(MAX($N$3:$N$74-MIN($N$3:$N$74)))} -> 0.17803848 | R83: =AVERAGE(M83:P83) -> 0.17552738 | S83: {=(S9-MIN($S$3:$S$74))/(MAX($S$3:$S$74-MIN($S$3:$S$74)))} -> 0.74243686 | T83: {=(T9-MIN($T$3:$T$74))/(MAX($T$3:$T$74-MIN($T$3:$T$74)))} -> 0.12000664 | U83: {=(U9-MIN($T$3:$T$74))/(MAX($T$3:$T$74-MIN($T$3:$T$74)))} -> 0.13149585 | V83: {=(V9-MIN($T$3:$T$74))/(MAX($T$3:$T$74-MIN($T$3:$T$74)))} -> 0.14394743 | W83: {=(W9-MIN($T$3:$T$74))/(MAX($T$3:$T$74-MIN($T$3:$T$74)))} -> 0.12843638 | X83: =AVERAGE(S83:V83) -> 0.2844717 | Y83: =(Y9-MIN($Y$3:$Y$74))/(MAX($Y$3:$Y$74)-MIN($Y$3:$Y$74)) -> 0.55244306 | Z83: =(Z9-MIN($Z$3:$Z$74))/(MAX($Z$3:$Z$74)-MIN($Z$3:$Z$74)) -> 0.35357277 | AA83: =(AA9-MIN($Z$3:$Z$74))/(MAX($Z$3:$Z$74)-MIN($Z$3:$Z$74)) -> 0.36482598 | AB83: =(AB9-MIN($Z$3:$Z$74))/(MAX($Z$3:$Z$74)-MIN($Z$3:$Z$74)) -> 0.36436206 | AC83: =(AC9-MIN($Z$3:$Z$74))/(MAX($Z$3:$Z$74)-MIN($Z$3:$Z$74)) -> 0.36614374 | AD83: =AVERAGE(Y83:AB83) -> 0.40880097 | AE83: =(AE9-MIN($AE$3:$AE$74))/(MAX($AE$3:$AE$74)-MIN($AE$3:$AE$74)) -> 0.19126751
A84: Societe Tunisie Profiles Aluminium | B84: {=(B10-MIN($B$3:$B$74))/(MAX($B$3:$B$74-MIN($B$3:$B$74)))} -> 0.14117062 | C84: {=(C10-MIN($B$3:$B$74))/(MAX($B$3:$B$74-MIN($B$3:$B$74)))} -> 0.13967345 | D84: {=(D10-MIN($B$3:$B$74))/(MAX($B$3:$B$74-MIN($B$3:$B$74)))} -> 0.14653423 | E84: {=(E10-MIN($B$3:$B$74))/(MAX($B$3:$B$74-MIN($B$3:$B$74)))} -> 0.1551083 | F84: {=(F10-MIN($B$3:$B$74))/(MAX($B$3:$B$74-MIN($B$3:$B$74)))} -> 0.15990534 | G84: =AVERAGEA(B84:E84) -> 0.14562165 | H84: {=(H10-MIN($H$3:$H$74))/(MAX($H$3:$H$74-MIN($H$3:$H$74)))} -> 0.56028804 | I84: {=(I10-MIN($H$3:$H$74))/(MAX($H$3:$H$74-MIN($H$3:$H$74)))} -> 0.58608167 | J84: {=(J10-MIN($H$3:$H$74))/(MAX($H$3:$H$74-MIN($H$3:$H$74)))} -> 0.58224966 | K84: {=(K10-MIN($H$3:$H$74))/(MAX($H$3:$H$74-MIN($H$3:$H$74)))} -> 0.57146618 | L84: =AVERAGE(H84:J84) -> 0.57620645 | M84: {=(M10-MIN($N$3:$N$74))/(MAX($N$3:$N$74-MIN($N$3:$N$74)))} -> 0.16043468 | N84: {=(N10-MIN($N$3:$N$74))/(MAX($N$3:$N$74-MIN($N$3:$N$74)))} -> 0.15198052 | O84: {=(O10-MIN($N$3:$N$74))/(MAX($N$3:$N$74-MIN($N$3:$N$74)))} -> 0.15578974 | P84: {=(P10-MIN($N$3:$N$74))/(MAX($N$3:$N$74-MIN($N$3:$N$74)))} -> 0.16803621 | Q84: {=(Q10-MIN($N$3:$N$74))/(MAX($N$3:$N$74-MIN($N$3:$N$74)))} -> 0.16752565 | R84: =AVERAGE(M84:P84) -> 0.15906029 | S84: {=(S10-MIN($S$3:$S$74))/(MAX($S$3:$S$74-MIN($S$3:$S$74)))} -> 0.74829568 | T84: {=(T10-MIN($T$3:$T$74))/(MAX($T$3:$T$74-MIN($T$3:$T$74)))} -> 0.10172233 | U84: {=(U10-MIN($T$3:$T$74))/(MAX($T$3:$T$74-MIN($T$3:$T$74)))} -> 0.11260609 | V84: {=(V10-MIN($T$3:$T$74))/(MAX($T$3:$T$74-MIN($T$3:$T$74)))} -> 0.11906322 | W84: {=(W10-MIN($T$3:$T$74))/(MAX($T$3:$T$74-MIN($T$3:$T$74)))} -> 0.11910592 | X84: =AVERAGE(S84:V84) -> 0.27042183 | Y84: =(Y10-MIN($Y$3:$Y$74))/(MAX($Y$3:$Y$74)-MIN($Y$3:$Y$74)) -> 0.54201754 | Z84: =(Z10-MIN($Z$3:$Z$74))/(MAX($Z$3:$Z$74)-MIN($Z$3:$Z$74)) -> 0.33755899 | AA84: =(AA10-MIN($Z$3:$Z$74))/(MAX($Z$3:$Z$74)-MIN($Z$3:$Z$74)) -> 0.33746559 | AB84: =(AB10-MIN($Z$3:$Z$74))/(MAX($Z$3:$Z$74)-MIN($Z$3:$Z$74)) -> 0.33297124 | AC84: =(AC10-MIN($Z$3:$Z$74))/(MAX($Z$3:$Z$74)-MIN($Z$3:$Z$74)) -> 0.33492838 | AD84: =AVERAGE(Y84:AB84) -> 0.38750334 | AE84: =(AE10-MIN($AE$3:$AE$74))/(MAX($AE$3:$AE$74)-MIN($AE$3:$AE$74)) -> 0.16063864
A85: SPDIT-SICAF | B85: {=(B11-MIN($B$3:$B$74))/(MAX($B$3:$B$74-MIN($B$3:$B$74)))} -> 0.14739372 | C85: {=(C11-MIN($B$3:$B$74))/(MAX($B$3:$B$74-MIN($B$3:$B$74)))} -> 0.14803231 | D85: {=(D11-MIN($B$3:$B$74))/(MAX($B$3:$B$74-MIN($B$3:$B$74)))} -> 0.15339371 | E85: {=(E11-MIN($B$3:$B$74))/(MAX($B$3:$B$74-MIN($B$3:$B$74)))} -> 0.15961688 | F85: {=(F11-MIN($B$3:$B$74))/(MAX($B$3:$B$74-MIN($B$3:$B$74)))} -> 0.16602243 | G85: =AVERAGEA(B85:E85) -> 0.15210916 | H85: {=(H11-MIN($H$3:$H$74))/(MAX($H$3:$H$74-MIN($H$3:$H$74)))} -> 0.56578153 | I85: {=(I11-MIN($H$3:$H$74))/(MAX($H$3:$H$74-MIN($H$3:$H$74)))} -> 0.57483393 | J85: {=(J11-MIN($H$3:$H$74))/(MAX($H$3:$H$74-MIN($H$3:$H$74)))} -> 0.57410711 | K85: {=(K11-MIN($H$3:$H$74))/(MAX($H$3:$H$74-MIN($H$3:$H$74)))} -> 0.57253435 | L85: =AVERAGE(H85:J85) -> 0.57157419 | M85: {=(M11-MIN($N$3:$N$74))/(MAX($N$3:$N$74-MIN($N$3:$N$74)))} -> 0.37748191 | N85: {=(N11-MIN($N$3:$N$74))/(MAX($N$3:$N$74-MIN($N$3:$N$74)))} -> 0.37495593 | O85: {=(O11-MIN($N$3:$N$74))/(MAX($N$3:$N$74-MIN($N$3:$N$74)))} -> 0.39507062 | P85: {=(P11-MIN($N$3:$N$74))/(MAX($N$3:$N$74-MIN($N$3:$N$74)))} -> 0.37777755 | Q85: {=(Q11-MIN($N$3:$N$74))/(MAX($N$3:$N$74-MIN($N$3:$N$74)))} -> 0.39684723 | R85: =AVERAGE(M85:P85) -> 0.3813215 | S85: {=(S11-MIN($S$3:$S$74))/(MAX($S$3:$S$74-MIN($S$3:$S$74)))} -> 0.78551023 | T85: {=(T11-MIN($T$3:$T$74))/(MAX($T$3:$T$74-MIN($T$3:$T$74)))} -> 0.12200609 | U85: {=(U11-MIN($T$3:$T$74))/(MAX($T$3:$T$74-MIN($T$3:$T$74)))} -> 0.129885 | V85: {=(V11-MIN($T$3:$T$74))/(MAX($T$3:$T$74-MIN($T$3:$T$74)))} -> 0.13675647 | W85: {=(W11-MIN($T$3:$T$74))/(MAX($T$3:$T$74-MIN($T$3:$T$74)))} -> 0.1421261 | X85: =AVERAGE(S85:V85) -> 0.29353945 | Y85: =(Y11-MIN($Y$3:$Y$74))/(MAX($Y$3:$Y$74)-MIN($Y$3:$Y$74)) -> 0.50570295 | Z85: =(Z11-MIN($Z$3:$Z$74))/(MAX($Z$3:$Z$74)-MIN($Z$3:$Z$74)) -> 0.31697203 | AA85: =(AA11-MIN($Z$3:$Z$74))/(MAX($Z$3:$Z$74)-MIN($Z$3:$Z$74)) -> 0.31715197 | AB85: =(AB11-MIN($Z$3:$Z$74))/(MAX($Z$3:$Z$74)-MIN($Z$3:$Z$74)) -> 0.31742458 | AC85: =(AC11-MIN($Z$3:$Z$74))/(MAX($Z$3:$Z$74)-MIN($Z$3:$Z$74)) -> 0.31738185 | AD85: =AVERAGE(Y85:AB85) -> 0.36431288 | AE85: =(AE11-MIN($AE$3:$AE$74))/(MAX($AE$3:$AE$74)-MIN($AE$3:$AE$74)) -> 0.17220593
A86: Automobile Reseau Tunisien Et Service SA | B86: {=(B12-MIN($B$3:$B$74))/(MAX($B$3:$B$74-MIN($B$3:$B$74)))} -> 0.15656509 | C86: {=(C12-MIN($B$3:$B$74))/(MAX($B$3:$B$74-MIN($B$3:$B$74)))} -> 0.31864758 | D86: {=(D12-MIN($B$3:$B$74))/(MAX($B$3:$B$74-MIN($B$3:$B$74)))} -> 0.15289235 | E86: {=(E12-MIN($B$3:$B$74))/(MAX($B$3:$B$74-MIN($B$3:$B$74)))} -> 0.16467107 | F86: {=(F12-MIN($B$3:$B$74))/(MAX($B$3:$B$74-MIN($B$3:$B$74)))} -> 0.16467107 | G86: =AVERAGEA(B86:E86) -> 0.19819402 | H86: {=(H12-MIN($H$3:$H$74))/(MAX($H$3:$H$74-MIN($H$3:$H$74)))} -> 0.78801344 | I86: {=(I12-MIN($H$3:$H$74))/(MAX($H$3:$H$74-MIN($H$3:$H$74)))} -> 0.52872541 | J86: {=(J12-MIN($H$3:$H$74))/(MAX($H$3:$H$74-MIN($H$3:$H$74)))} -> 0.58301477 | K86: {=(K12-MIN($H$3:$H$74))/(MAX($H$3:$H$74-MIN($H$3:$H$74)))} -> 0.56451494 | L86: =AVERAGE(H86:J86) -> 0.6332512 | M86: {=(M12-MIN($N$3:$N$74))/(MAX($N$3:$N$74-MIN($N$3:$N$74)))} -> 0.17184427 | N86: {=(N12-MIN($N$3:$N$74))/(MAX($N$3:$N$74-MIN($N$3:$N$74)))} -> 0.35592863 | O86: {=(O12-MIN($N$3:$N$74))/(MAX($N$3:$N$74-MIN($N$3:$N$74)))} -> 0.17472737 | P86: {=(P12-MIN($N$3:$N$74))/(MAX($N$3:$N$74-MIN($N$3:$N$74)))} -> 0.16618094 | Q86: {=(Q12-MIN($N$3:$N$74))/(MAX($N$3:$N$74-MIN($N$3:$N$74)))} -> 0.16618094 | R86: =AVERAGE(M86:P86) -> 0.2171703 | S86: {=(S12-MIN($S$3:$S$74))/(MAX($S$3:$S$74-MIN($S$3:$S$74)))} -> 0.75227981 | T86: {=(T12-MIN($T$3:$T$74))/(MAX($T$3:$T$74-MIN($T$3:$T$74)))} -> 0.26631141 | U86: {=(U12-MIN($T$3:$T$74))/(MAX($T$3:$T$74-MIN($T$3:$T$74)))} -> 0.10144031 | V86: {=(V12-MIN($T$3:$T$74))/(MAX($T$3:$T$74-MIN($T$3:$T$74)))} -> 0.13263874 | W86: {=(W12-MIN($T$3:$T$74))/(MAX($T$3:$T$74-MIN($T$3:$T$74)))} -> 0.11137821 | X86: =AVERAGE(S86:V86) -> 0.31316757 | Y86: =(Y12-MIN($Y$3:$Y$74))/(MAX($Y$3:$Y$74)-MIN($Y$3:$Y$74)) -> 0.52040318 | Z86: =(Z12-MIN($Z$3:$Z$74))/(MAX($Z$3:$Z$74)-MIN($Z$3:$Z$74)) -> 0.32057722 | AA86: =(AA12-MIN($Z$3:$Z$74))/(MAX($Z$3:$Z$74)-MIN($Z$3:$Z$74)) -> 0.32255874 | AB86: =(AB12-MIN($Z$3:$Z$74))/(MAX($Z$3:$Z$74)-MIN($Z$3:$Z$74)) -> 0.33594188 | AC86: =(AC12-MIN($Z$3:$Z$74))/(MAX($Z$3:$Z$74)-MIN($Z$3:$Z$74)) -> 0.32961388 | AD86: =AVERAGE(Y86:AB86) -> 0.37487025 | AE86: =(AE12-MIN($AE$3:$AE$74))/(MAX($AE$3:$AE$74)-MIN($AE$3:$AE$74)) -> 0.16438579
A87: City Cars | B87: {=(B13-MIN($B$3:$B$74))/(MAX($B$3:$B$74-MIN($B$3:$B$74)))} -> 0.16686888 | C87: {=(C13-MIN($B$3:$B$74))/(MAX($B$3:$B$74-MIN($B$3:$B$74)))} -> 0.19064214 | D87: {=(D13-MIN($B$3:$B$74))/(MAX($B$3:$B$74-MIN($B$3:$B$74)))} -> 0.18481483 | E87: {=(E13-MIN($B$3:$B$74))/(MAX($B$3:$B$74-MIN($B$3:$B$74)))} -> 0.18749439 | F87: {=(F13-MIN($B$3:$B$74))/(MAX($B$3:$B$74-MIN($B$3:$B$74)))} -> 0.18326236 | G87: =AVERAGEA(B87:E87) -> 0.18245506 | H87: {=(H13-MIN($H$3:$H$74))/(MAX($H$3:$H$74-MIN($H$3:$H$74)))} -> 0.58893465 | I87: {=(I13-MIN($H$3:$H$74))/(MAX($H$3:$H$74-MIN($H$3:$H$74)))} -> 0.56074678 | J87: {=(J13-MIN($H$3:$H$74))/(MAX($H$3:$H$74-MIN($H$3:$H$74)))} -> 0.56642071 | K87: {=(K13-MIN($H$3:$H$74))/(MAX($H$3:$H$74-MIN($H$3:$H$74)))} -> 0.56163718 | L87: =AVERAGE(H87:J87) -> 0.57203405 | M87: {=(M13-MIN($N$3:$N$74))/(MAX($N$3:$N$74-MIN($N$3:$N$74)))} -> 0.15200043 | N87: {=(N13-MIN($N$3:$N$74))/(MAX($N$3:$N$74-MIN($N$3:$N$74)))} -> 0.15441977 | O87: {=(O13-MIN($N$3:$N$74))/(MAX($N$3:$N$74-MIN($N$3:$N$74)))} -> 0.15189053 | P87: {=(P13-MIN($N$3:$N$74))/(MAX($N$3:$N$74-MIN($N$3:$N$74)))} -> 0.15077508 | Q87: {=(Q13-MIN($N$3:$N$74))/(MAX($N$3:$N$74-MIN($N$3:$N$74)))} -> 0.14885355 | R87: =AVERAGE(M87:P87) -> 0.15227145 | S87: {=(S13-MIN($S$3:$S$74))/(MAX($S$3:$S$74-MIN($S$3:$S$74)))} -> 0.84009473 | T87: {=(T13-MIN($T$3:$T$74))/(MAX($T$3:$T$74-MIN($T$3:$T$74)))} -> 0.15977253 | U87: {=(U13-MIN($T$3:$T$74))/(MAX($T$3:$T$74-MIN($T$3:$T$74)))} -> 0.14430379 | V87: {=(V13-MIN($T$3:$T$74))/(MAX($T$3:$T$74-MIN($T$3:$T$74)))} -> 0.14033226 | W87: {=(W13-MIN($T$3:$T$74))/(MAX($T$3:$T$74-MIN($T$3:$T$74)))} -> 0.13154509 | X87: =AVERAGE(S87:V87) -> 0.32112583 | Y87: =(Y13-MIN($Y$3:$Y$74))/(MAX($Y$3:$Y$74)-MIN($Y$3:$Y$74)) -> 0.56088444 | Z87: =(Z13-MIN($Z$3:$Z$74))/(MAX($Z$3:$Z$74)-MIN($Z$3:$Z$74)) -> 0.3472324 | AA87: =(AA13-MIN($Z$3:$Z$74))/(MAX($Z$3:$Z$74)-MIN($Z$3:$Z$74)) -> 0.35110647 | AB87: =(AB13-MIN($Z$3:$Z$74))/(MAX($Z$3:$Z$74)-MIN($Z$3:$Z$74)) -> 0.35207809 | AC87: =(AC13-MIN($Z$3:$Z$74))/(MAX($Z$3:$Z$74)-MIN($Z$3:$Z$74)) -> 0.35142674 | AD87: =AVERAGE(Y87:AB87) -> 0.40282535 | AE87: =(AE13-MIN($AE$3:$AE$74))/(MAX($AE$3:$AE$74)-MIN($AE$3:$AE$74)) -> 0.18214402
A88: Ste Assurances Magrebia SA | B88: {=(B14-MIN($B$3:$B$74))/(MAX($B$3:$B$74-MIN($B$3:$B$74)))} -> 0.53816314 | C88: {=(C14-MIN($B$3:$B$74))/(MAX($B$3:$B$74-MIN($B$3:$B$74)))} -> 0.72007731 | D88: {=(D14-MIN($B$3:$B$74))/(MAX($B$3:$B$74-MIN($B$3:$B$74)))} -> 0.75144243 | E88: {=(E14-MIN($B$3:$B$74))/(MAX($B$3:$B$74-MIN($B$3:$B$74)))} -> 0.75782175 | F88: {=(F14-MIN($B$3:$B$74))/(MAX($B$3:$B$74-MIN($B$3:$B$74)))} -> 0.90105869 | G88: =AVERAGEA(B88:E88) -> 0.69187616 | H88: {=(H14-MIN($H$3:$H$74))/(MAX($H$3:$H$74-MIN($H$3:$H$74)))} -> 0.5828499 | I88: {=(I14-MIN($H$3:$H$74))/(MAX($H$3:$H$74-MIN($H$3:$H$74)))} -> 0.56670741 | J88: {=(J14-MIN($H$3:$H$74))/(MAX($H$3:$H$74-MIN($H$3:$H$74)))} -> 0.56493848 | K88: {=(K14-MIN($H$3:$H$74))/(MAX($H$3:$H$74-MIN($H$3:$H$74)))} -> 0.57392884 | L88: =AVERAGE(H88:J88) -> 0.5714986 | M88: {=(M14-MIN($N$3:$N$74))/(MAX($N$3:$N$74-MIN($N$3:$N$74)))} -> 0.5229312 | N88: {=(N14-MIN($N$3:$N$74))/(MAX($N$3:$N$74-MIN($N$3:$N$74)))} -> 1 | O88: {=(O14-MIN($N$3:$N$74))/(MAX($N$3:$N$74-MIN($N$3:$N$74)))} -> 0.97168184 | P88: {=(P14-MIN($N$3:$N$74))/(MAX($N$3:$N$74-MIN($N$3:$N$74)))} -> 0.53377251 | Q88: {=(Q14-MIN($N$3:$N$74))/(MAX($N$3:$N$74-MIN($N$3:$N$74)))} -> 0.55000931 | R88: =AVERAGE(M88:P88) -> 0.75709639 | S88: {=(S14-MIN($S$3:$S$74))/(MAX($S$3:$S$74-MIN($S$3:$S$74)))} -> 0.89541326 | T88: {=(T14-MIN($T$3:$T$74))/(MAX($T$3:$T$74-MIN($T$3:$T$74)))} -> 0.17132056 | U88: {=(U14-MIN($T$3:$T$74))/(MAX($T$3:$T$74-MIN($T$3:$T$74)))} -> 0.16165517 | V88: {=(V14-MIN($T$3:$T$74))/(MAX($T$3:$T$74-MIN($T$3:$T$74)))} -> 0.15296379 | W88: {=(W14-MIN($T$3:$T$74))/(MAX($T$3:$T$74-MIN($T$3:$T$74)))} -> 0.16225416 | X88: =AVERAGE(S88:V88) -> 0.3453382 | Y88: =(Y14-MIN($Y$3:$Y$74))/(MAX($Y$3:$Y$74)-MIN($Y$3:$Y$74)) -> 0.53366803 | Z88: =(Z14-MIN($Z$3:$Z$74))/(MAX($Z$3:$Z$74)-MIN($Z$3:$Z$74)) -> 0.33082868 | AA88: =(AA14-MIN($Z$3:$Z$74))/(MAX($Z$3:$Z$74)-MIN($Z$3:$Z$74)) -> 0.33086035 | AB88: =(AB14-MIN($Z$3:$Z$74))/(MAX($Z$3:$Z$74)-MIN($Z$3:$Z$74)) -> 0.33144339 | AC88: =(AC14-MIN($Z$3:$Z$74))/(MAX($Z$3:$Z$74)-MIN($Z$3:$Z$74)) -> 0.40036777 | AD88: =AVERAGE(Y88:AB88) -> 0.38170011 | AE88: =(AE14-MIN($AE$3:$AE$74))/(MAX($AE$3:$AE$74)-MIN($AE$3:$AE$74)) -> 0.12968394
... A134: SITS | B134: {=(B60-MIN($B$3:$B$74))/(MAX($B$3:$B$74-MIN($B$3:$B$74)))} -> 0.15889919 | C134: {=(C60-MIN($B$3:$B$74))/(MAX($B$3:$B$74-MIN($B$3:$B$74)))} -> 0.14115898 | D134: {=(D60-MIN($B$3:$B$74))/(MAX($B$3:$B$74-MIN($B$3:$B$74)))} -> 0.13092253 | E134: {=(E60-MIN($B$3:$B$74))/(MAX($B$3:$B$74-MIN($B$3:$B$74)))} -> 0.1538276 | F134: {=(F60-MIN($B$3:$B$74))/(MAX($B$3:$B$74-MIN($B$3:$B$74)))} -> 0.14225922 | G134: =AVERAGEA(B134:E134) -> 0.14620208 | H134: {=(H60-MIN($H$3:$H$74))/(MAX($H$3:$H$74-MIN($H$3:$H$74)))} -> 0.54181351 | I134: {=(I60-MIN($H$3:$H$74))/(MAX($H$3:$H$74-MIN($H$3:$H$74)))} -> 0.53559184 | J134: {=(J60-MIN($H$3:$H$74))/(MAX($H$3:$H$74-MIN($H$3:$H$74)))} -> 0.77813898 | K134: {=(K60-MIN($H$3:$H$74))/(MAX($H$3:$H$74-MIN($H$3:$H$74)))} -> 0.54696669 | L134: =AVERAGE(H134:J134) -> 0.61851477 | M134: {=(M60-MIN($N$3:$N$74))/(MAX($N$3:$N$74-MIN($N$3:$N$74)))} -> 0.19142515 | N134: {=(N60-MIN($N$3:$N$74))/(MAX($N$3:$N$74-MIN($N$3:$N$74)))} -> 0.31468892 | O134: {=(O60-MIN($N$3:$N$74))/(MAX($N$3:$N$74-MIN($N$3:$N$74)))} -> 0.17992582 | P134: {=(P60-MIN($N$3:$N$74))/(MAX($N$3:$N$74-MIN($N$3:$N$74)))} -> 0.18910395 | Q134: {=(Q60-MIN($N$3:$N$74))/(MAX($N$3:$N$74-MIN($N$3:$N$74)))} -> 0.16805997 | R134: =AVERAGE(M134:P134) -> 0.21878596 | S134: {=(S60-MIN($S$3:$S$74))/(MAX($S$3:$S$74-MIN($S$3:$S$74)))} -> 0.80374891 | T134: {=(T60-MIN($T$3:$T$74))/(MAX($T$3:$T$74-MIN($T$3:$T$74)))} -> 0.098744244 | U134: {=(U60-MIN($T$3:$T$74))/(MAX($T$3:$T$74-MIN($T$3:$T$74)))} -> 0.081949316 | V134: {=(V60-MIN($T$3:$T$74))/(MAX($T$3:$T$74-MIN($T$3:$T$74)))} -> 0.11593881 | W134: {=(W60-MIN($T$3:$T$74))/(MAX($T$3:$T$74-MIN($T$3:$T$74)))} -> 0.078288355 | X134: =AVERAGE(S134:V134) -> 0.27509532 | Y134: =(Y60-MIN($Y$3:$Y$74))/(MAX($Y$3:$Y$74)-MIN($Y$3:$Y$74)) -> 0.53119729 | Z134: =(Z60-MIN($Z$3:$Z$74))/(MAX($Z$3:$Z$74)-MIN($Z$3:$Z$74)) -> 0.32590049 | AA134: =(AA60-MIN($Z$3:$Z$74))/(MAX($Z$3:$Z$74)-MIN($Z$3:$Z$74)) -> 0.32454241 | AB134: =(AB60-MIN($Z$3:$Z$74))/(MAX($Z$3:$Z$74)-MIN($Z$3:$Z$74)) -> 0.32587713 | AC134: =(AC60-MIN($Z$3:$Z$74))/(MAX($Z$3:$Z$74)-MIN($Z$3:$Z$74)) -> 0.32864516 | AD134: =AVERAGE(Y134:AB134) -> 0.37687933 | AE134: =(AE60-MIN($AE$3:$AE$74))/(MAX($AE$3:$AE$74)-MIN($AE$3:$AE$74)) -> 1
A135: SMART TUNISIE | C135: {=(C61-MIN($B$3:$B$74))/(MAX($B$3:$B$74-MIN($B$3:$B$74)))} -> 0.18994851 | D135: {=(D61-MIN($B$3:$B$74))/(MAX($B$3:$B$74-MIN($B$3:$B$74)))} -> 0.18330014 | E135: {=(E61-MIN($B$3:$B$74))/(MAX($B$3:$B$74-MIN($B$3:$B$74)))} -> 1.3055307 | F135: {=(F61-MIN($B$3:$B$74))/(MAX($B$3:$B$74-MIN($B$3:$B$74)))} -> 1.4999883 | G135: =AVERAGEA(B135:E135) -> 0.55959311 | I135: {=(I61-MIN($H$3:$H$74))/(MAX($H$3:$H$74-MIN($H$3:$H$74)))} -> 0.56016888 | J135: {=(J61-MIN($H$3:$H$74))/(MAX($H$3:$H$74-MIN($H$3:$H$74)))} -> 1.3839483 | K135: {=(K61-MIN($H$3:$H$74))/(MAX($H$3:$H$74-MIN($H$3:$H$74)))} -> 0.57135837 | L135: =AVERAGE(H135:J135) -> 0.9720586 | N135: {=(N61-MIN($N$3:$N$74))/(MAX($N$3:$N$74-MIN($N$3:$N$74)))} -> 0.14458436 | O135: {=(O61-MIN($N$3:$N$74))/(MAX($N$3:$N$74-MIN($N$3:$N$74)))} -> 0.14055454 | P135: {=(P61-MIN($N$3:$N$74))/(MAX($N$3:$N$74-MIN($N$3:$N$74)))} -> 0.13780629 | Q135: {=(Q61-MIN($N$3:$N$74))/(MAX($N$3:$N$74-MIN($N$3:$N$74)))} -> 0.13611676 | R135: =AVERAGE(M135:P135) -> 0.14098173 | T135: {=(T61-MIN($T$3:$T$74))/(MAX($T$3:$T$74-MIN($T$3:$T$74)))} -> 0.1153273 | U135: {=(U61-MIN($T$3:$T$74))/(MAX($T$3:$T$74-MIN($T$3:$T$74)))} -> 0.11061529 | V135: {=(V61-MIN($T$3:$T$74))/(MAX($T$3:$T$74-MIN($T$3:$T$74)))} -> 0.79944317 | W135: {=(W61-MIN($T$3:$T$74))/(MAX($T$3:$T$74-MIN($T$3:$T$74)))} -> 0.10258144 | X135: =AVERAGE(S135:V135) -> 0.34179525 | Z135: =(Z61-MIN($Z$3:$Z$74))/(MAX($Z$3:$Z$74)-MIN($Z$3:$Z$74)) -> 0.33287599 | AA135: =(AA61-MIN($Z$3:$Z$74))/(MAX($Z$3:$Z$74)-MIN($Z$3:$Z$74)) -> 0.33764449 | AB135: =(AB61-MIN($Z$3:$Z$74))/(MAX($Z$3:$Z$74)-MIN($Z$3:$Z$74)) -> 0.33973991 | AC135: =(AC61-MIN($Z$3:$Z$74))/(MAX($Z$3:$Z$74)-MIN($Z$3:$Z$74)) -> 0.34137227 | AD135: =AVERAGE(Y135:AB135) -> 0.33675347 | AE135: =(AE61-MIN($AE$3:$AE$74))/(MAX($AE$3:$AE$74)-MIN($AE$3:$AE$74)) -> 0.19322255
A136: SOMOCER | B136: {=(B62-MIN($B$3:$B$74))/(MAX($B$3:$B$74-MIN($B$3:$B$74)))} -> 0.078296738 | C136: {=(C62-MIN($B$3:$B$74))/(MAX($B$3:$B$74-MIN($B$3:$B$74)))} -> 0.13356732 | D136: {=(D62-MIN($B$3:$B$74))/(MAX($B$3:$B$74-MIN($B$3:$B$74)))} -> 0.082955523 | E136: {=(E62-MIN($B$3:$B$74))/(MAX($B$3:$B$74-MIN($B$3:$B$74)))} -> 0.53952858 | F136: {=(F62-MIN($B$3:$B$74))/(MAX($B$3:$B$74-MIN($B$3:$B$74)))} -> 0.41159458 | G136: =AVERAGEA(B136:E136) -> 0.20858704 | H136: {=(H62-MIN($H$3:$H$74))/(MAX($H$3:$H$74-MIN($H$3:$H$74)))} -> 0.61211855 | I136: {=(I62-MIN($H$3:$H$74))/(MAX($H$3:$H$74-MIN($H$3:$H$74)))} -> 0.26847147 | J136: {=(J62-MIN($H$3:$H$74))/(MAX($H$3:$H$74-MIN($H$3:$H$74)))} -> 0.99985139 | K136: {=(K62-MIN($H$3:$H$74))/(MAX($H$3:$H$74-MIN($H$3:$H$74)))} -> 0.55166321 | L136: =AVERAGE(H136:J136) -> 0.62681381 | M136: {=(M62-MIN($N$3:$N$74))/(MAX($N$3:$N$74-MIN($N$3:$N$74)))} -> 0.090844215 | N136: {=(N62-MIN($N$3:$N$74))/(MAX($N$3:$N$74-MIN($N$3:$N$74)))} -> 0.13035868 | O136: {=(O62-MIN($N$3:$N$74))/(MAX($N$3:$N$74-MIN($N$3:$N$74)))} -> 0.099801972 | P136: {=(P62-MIN($N$3:$N$74))/(MAX($N$3:$N$74-MIN($N$3:$N$74)))} -> 0.07896128 | Q136: {=(Q62-MIN($N$3:$N$74))/(MAX($N$3:$N$74-MIN($N$3:$N$74)))} -> -0.014549351 | R136: =AVERAGE(M136:P136) -> 0.099991538 | S136: {=(S62-MIN($S$3:$S$74))/(MAX($S$3:$S$74-MIN($S$3:$S$74)))} -> 0.584054 | T136: {=(T62-MIN($T$3:$T$74))/(MAX($T$3:$T$74-MIN($T$3:$T$74)))} -> 0.080960396 | U136: {=(U62-MIN($T$3:$T$74))/(MAX($T$3:$T$74-MIN($T$3:$T$74)))} -> 0.030922247 | V136: {=(V62-MIN($T$3:$T$74))/(MAX($T$3:$T$74-MIN($T$3:$T$74)))} -> 0.75409895 | W136: {=(W62-MIN($T$3:$T$74))/(MAX($T$3:$T$74-MIN($T$3:$T$74)))} -> 0.89301559 | X136: =AVERAGE(S136:V136) -> 0.3625089 | Y136: {=(Y62-MIN($Y$3:$Y$74))/(MAX($Y$3:$Y$74-MIN($Y$3:$Y$74)))} -> 0.67316861 | Z136: =(Z62-MIN($Z$3:$Z$74))/(MAX($Z$3:$Z$74)-MIN($Z$3:$Z$74)) -> 0.39798809 | AA136: =(AA62-MIN($Z$3:$Z$74))/(MAX($Z$3:$Z$74)-MIN($Z$3:$Z$74)) -> 0.41688797 | AB136: =(AB62-MIN($Z$3:$Z$74))/(MAX($Z$3:$Z$74)-MIN($Z$3:$Z$74)) -> 0.49621692 | AC136: =(AC62-MIN($Z$3:$Z$74))/(MAX($Z$3:$Z$74)-MIN($Z$3:$Z$74)) -> -0.32070608 | AD136: =AVERAGE(Y136:AB136) -> 0.4960654 | AE136: =(AE62-MIN($AE$3:$AE$74))/(MAX($AE$3:$AE$74)-MIN($AE$3:$AE$74)) -> -0.011404366
A137: SOTEMAIL | B137: {=(B63-MIN($B$3:$B$74))/(MAX($B$3:$B$74-MIN($B$3:$B$74)))} -> 0.10770385 | C137: {=(C63-MIN($B$3:$B$74))/(MAX($B$3:$B$74-MIN($B$3:$B$74)))} -> 0.12970253 | D137: {=(D63-MIN($B$3:$B$74))/(MAX($B$3:$B$74-MIN($B$3:$B$74)))} -> 0.111463 | E137: {=(E63-MIN($B$3:$B$74))/(MAX($B$3:$B$74-MIN($B$3:$B$74)))} -> 0.30504859 | F137: {=(F63-MIN($B$3:$B$74))/(MAX($B$3:$B$74-MIN($B$3:$B$74)))} -> 0.24489353 | G137: =AVERAGEA(B137:E137) -> 0.16347949 | H137: {=(H63-MIN($H$3:$H$74))/(MAX($H$3:$H$74-MIN($H$3:$H$74)))} -> 0.61314712 | I137: {=(I63-MIN($H$3:$H$74))/(MAX($H$3:$H$74-MIN($H$3:$H$74)))} -> 0.33013199 | J137: {=(J63-MIN($H$3:$H$74))/(MAX($H$3:$H$74-MIN($H$3:$H$74)))} -> 1.0996473 | K137: {=(K63-MIN($H$3:$H$74))/(MAX($H$3:$H$74-MIN($H$3:$H$74)))} -> 0.55053727 | L137: =AVERAGE(H137:J137) -> 0.68097548 | M137: {=(M63-MIN($N$3:$N$74))/(MAX($N$3:$N$74-MIN($N$3:$N$74)))} -> 0.089523564 | N137: {=(N63-MIN($N$3:$N$74))/(MAX($N$3:$N$74-MIN($N$3:$N$74)))} -> 0.13085846 | O137: {=(O63-MIN($N$3:$N$74))/(MAX($N$3:$N$74-MIN($N$3:$N$74)))} -> 0.10443443 | P137: {=(P63-MIN($N$3:$N$74))/(MAX($N$3:$N$74-MIN($N$3:$N$74)))} -> 0.075649079 | Q137: {=(Q63-MIN($N$3:$N$74))/(MAX($N$3:$N$74-MIN($N$3:$N$74)))} -> 0.013061042 | R137: =AVERAGE(M137:P137) -> 0.10011638 | S137: {=(S63-MIN($S$3:$S$74))/(MAX($S$3:$S$74-MIN($S$3:$S$74)))} -> 0.61652268 | T137: {=(T63-MIN($T$3:$T$74))/(MAX($T$3:$T$74-MIN($T$3:$T$74)))} -> 0.079564534 | U137: {=(U63-MIN($T$3:$T$74))/(MAX($T$3:$T$74-MIN($T$3:$T$74)))} -> 0.050749504 | V137: {=(V63-MIN($T$3:$T$74))/(MAX($T$3:$T$74-MIN($T$3:$T$74)))} -> 0.46523417 | W137: {=(W63-MIN($T$3:$T$74))/(MAX($T$3:$T$74-MIN($T$3:$T$74)))} -> -0.0020640447 | X137: =AVERAGE(S137:V137) -> 0.30301772 | Y137: {=(Y63-MIN($Y$3:$Y$74))/(MAX($Y$3:$Y$74-MIN($Y$3:$Y$74)))} -> 0.59157915 | Z137: =(Z63-MIN($Z$3:$Z$74))/(MAX($Z$3:$Z$74)-MIN($Z$3:$Z$74)) -> 0.36259509 | AA137: =(AA63-MIN($Z$3:$Z$74))/(MAX($Z$3:$Z$74)-MIN($Z$3:$Z$74)) -> 0.36791632 | AB137: =(AB63-MIN($Z$3:$Z$74))/(MAX($Z$3:$Z$74)-MIN($Z$3:$Z$74)) -> 0.39279254 | AC137: =(AC63-MIN($Z$3:$Z$74))/(MAX($Z$3:$Z$74)-MIN($Z$3:$Z$74)) -> 0.37068063 | AD137: =AVERAGE(Y137:AB137) -> 0.42872078 | AE137: =(AE63-MIN($AE$3:$AE$74))/(MAX($AE$3:$AE$74)-MIN($AE$3:$AE$74)) -> -0.011404366
A138: SOTETEL | B138: {=(B64-MIN($B$3:$B$74))/(MAX($B$3:$B$74-MIN($B$3:$B$74)))} -> 0.13869435 | C138: {=(C64-MIN($B$3:$B$74))/(MAX($B$3:$B$74-MIN($B$3:$B$74)))} -> 0.12567138 | D138: {=(D64-MIN($B$3:$B$74))/(MAX($B$3:$B$74-MIN($B$3:$B$74)))} -> 0.13023966 | E138: {=(E64-MIN($B$3:$B$74))/(MAX($B$3:$B$74-MIN($B$3:$B$74)))} -> 0.33577558 | F138: {=(F64-MIN($B$3:$B$74))/(MAX($B$3:$B$74-MIN($B$3:$B$74)))} -> 0.35271323 | G138: =AVERAGEA(B138:E138) -> 0.18259524 | H138: {=(H64-MIN($H$3:$H$74))/(MAX($H$3:$H$74-MIN($H$3:$H$74)))} -> 0.52029763 | I138: {=(I64-MIN($H$3:$H$74))/(MAX($H$3:$H$74-MIN($H$3:$H$74)))} -> 0.8008312 | J138: {=(J64-MIN($H$3:$H$74))/(MAX($H$3:$H$74-MIN($H$3:$H$74)))} -> 2.829022 | K138: {=(K64-MIN($H$3:$H$74))/(MAX($H$3:$H$74-MIN($H$3:$H$74)))} -> 0.5678728 | L138: =AVERAGE(H138:J138) -> 1.3833836 | M138: {=(M64-MIN($N$3:$N$74))/(MAX($N$3:$N$74-MIN($N$3:$N$74)))} -> 0.16075329 | N138: {=(N64-MIN($N$3:$N$74))/(MAX($N$3:$N$74-MIN($N$3:$N$74)))} -> 0.12417318 | O138: {=(O64-MIN($N$3:$N$74))/(MAX($N$3:$N$74-MIN($N$3:$N$74)))} -> 0.13292799 | P138: {=(P64-MIN($N$3:$N$74))/(MAX($N$3:$N$74-MIN($N$3:$N$74)))} -> 0.14309842 | Q138: {=(Q64-MIN($N$3:$N$74))/(MAX($N$3:$N$74-MIN($N$3:$N$74)))} -> 0.14273788 | R138: =AVERAGE(M138:P138) -> 0.14023822 | S138: {=(S64-MIN($S$3:$S$74))/(MAX($S$3:$S$74-MIN($S$3:$S$74)))} -> 0.7435254 | T138: {=(T64-MIN($T$3:$T$74))/(MAX($T$3:$T$74-MIN($T$3:$T$74)))} -> 0.073080606 | U138: {=(U64-MIN($T$3:$T$74))/(MAX($T$3:$T$74-MIN($T$3:$T$74)))} -> 0.083384488 | V138: {=(V64-MIN($T$3:$T$74))/(MAX($T$3:$T$74-MIN($T$3:$T$74)))} -> 0.48512707 | W138: {=(W64-MIN($T$3:$T$74))/(MAX($T$3:$T$74-MIN($T$3:$T$74)))} -> 0.098877502 | X138: =AVERAGE(S138:V138) -> 0.34627939 | Y138: {=(Y64-MIN($Y$3:$Y$74))/(MAX($Y$3:$Y$74-MIN($Y$3:$Y$74)))} -> 0.56928221 | Z138: =(Z64-MIN($Z$3:$Z$74))/(MAX($Z$3:$Z$74)-MIN($Z$3:$Z$74)) -> 0.34595546 | AA138: =(AA64-MIN($Z$3:$Z$74))/(MAX($Z$3:$Z$74)-MIN($Z$3:$Z$74)) -> 0.34646519 | AB138: =(AB64-MIN($Z$3:$Z$74))/(MAX($Z$3:$Z$74)-MIN($Z$3:$Z$74)) -> 0.35423284 | AC138: =(AC64-MIN($Z$3:$Z$74))/(MAX($Z$3:$Z$74)-MIN($Z$3:$Z$74)) -> 0.34832673 | AD138: =AVERAGE(Y138:AB138) -> 0.40398392 | AE138: =(AE64-MIN($AE$3:$AE$74))/(MAX($AE$3:$AE$74)-MIN($AE$3:$AE$74)) -> 0.080645161
A139: SOTRAPIL | B139: {=(B65-MIN($B$3:$B$74))/(MAX($B$3:$B$74-MIN($B$3:$B$74)))} -> 0.14902043 | C139: {=(C65-MIN($B$3:$B$74))/(MAX($B$3:$B$74-MIN($B$3:$B$74)))} -> 0.15052663 | D139: {=(D65-MIN($B$3:$B$74))/(MAX($B$3:$B$74-MIN($B$3:$B$74)))} -> 0.15599473 | E139: {=(E65-MIN($B$3:$B$74))/(MAX($B$3:$B$74-MIN($B$3:$B$74)))} -> 0.18418176 | F139: {=(F65-MIN($B$3:$B$74))/(MAX($B$3:$B$74-MIN($B$3:$B$74)))} -> 0.18557984 | G139: =AVERAGEA(B139:E139) -> 0.15993089 | H139: {=(H65-MIN($H$3:$H$74))/(MAX($H$3:$H$74-MIN($H$3:$H$74)))} -> 0.56728683 | I139: {=(I65-MIN($H$3:$H$74))/(MAX($H$3:$H$74-MIN($H$3:$H$74)))} -> 0.57394792 | J139: {=(J65-MIN($H$3:$H$74))/(MAX($H$3:$H$74-MIN($H$3:$H$74)))} -> 0.60413346 | K139: {=(K65-MIN($H$3:$H$74))/(MAX($H$3:$H$74-MIN($H$3:$H$74)))} -> 0.5655202 | L139: =AVERAGE(H139:J139) -> 0.58178941 | M139: {=(M65-MIN($N$3:$N$74))/(MAX($N$3:$N$74-MIN($N$3:$N$74)))} -> 0.3521723 | N139: {=(N65-MIN($N$3:$N$74))/(MAX($N$3:$N$74-MIN($N$3:$N$74)))} -> 0.24981134 | O139: {=(O65-MIN($N$3:$N$74))/(MAX($N$3:$N$74-MIN($N$3:$N$74)))} -> 0.26156081 | P139: {=(P65-MIN($N$3:$N$74))/(MAX($N$3:$N$74-MIN($N$3:$N$74)))} -> 0.26483973 | Q139: {=(Q65-MIN($N$3:$N$74))/(MAX($N$3:$N$74-MIN($N$3:$N$74)))} -> 0.26525075 | R139: =AVERAGE(M139:P139) -> 0.28209604 | S139: {=(S65-MIN($S$3:$S$74))/(MAX($S$3:$S$74-MIN($S$3:$S$74)))} -> 0.74617016 | T139: {=(T65-MIN($T$3:$T$74))/(MAX($T$3:$T$74-MIN($T$3:$T$74)))} -> 0.10411517 | U139: {=(U65-MIN($T$3:$T$74))/(MAX($T$3:$T$74-MIN($T$3:$T$74)))} -> 0.10798447 | V139: {=(V65-MIN($T$3:$T$74))/(MAX($T$3:$T$74-MIN($T$3:$T$74)))} -> 0.13679263 | W139: {=(W65-MIN($T$3:$T$74))/(MAX($T$3:$T$74-MIN($T$3:$T$74)))} -> 0.10380772 | X139: =AVERAGE(S139:V139) -> 0.27376561 | Y139: {=(Y65-MIN($Y$3:$Y$74))/(MAX($Y$3:$Y$74-MIN($Y$3:$Y$74)))} -> 0.51218654 | Z139: =(Z65-MIN($Z$3:$Z$74))/(MAX($Z$3:$Z$74)-MIN($Z$3:$Z$74)) -> 0.3207502 | AA139: =(AA65-MIN($Z$3:$Z$74))/(MAX($Z$3:$Z$74)-MIN($Z$3:$Z$74)) -> 0.32059766 | AB139: =(AB65-MIN($Z$3:$Z$74))/(MAX($Z$3:$Z$74)-MIN($Z$3:$Z$74)) -> 0.32161828 | AC139: =(AC65-MIN($Z$3:$Z$74))/(MAX($Z$3:$Z$74)-MIN($Z$3:$Z$74)) -> 0.31957911 | AD139: =AVERAGE(Y139:AB139) -> 0.36878817 | AE139: =(AE65-MIN($AE$3:$AE$74))/(MAX($AE$3:$AE$74)-MIN($AE$3:$AE$74)) -> 0.1627566
A140: STA | C140: {=(C66-MIN($B$3:$B$74))/(MAX($B$3:$B$74-MIN($B$3:$B$74)))} -> 0.14085945 | D140: {=(D66-MIN($B$3:$B$74))/(MAX($B$3:$B$74-MIN($B$3:$B$74)))} -> 0.14652539 | E140: {=(E66-MIN($B$3:$B$74))/(MAX($B$3:$B$74-MIN($B$3:$B$74)))} -> 0.37824302 | F140: {=(F66-MIN($B$3:$B$74))/(MAX($B$3:$B$74-MIN($B$3:$B$74)))} -> 0.47021416 | G140: =AVERAGEA(B140:E140) -> 0.22187595 | I140: {=(I66-MIN($H$3:$H$74))/(MAX($H$3:$H$74-MIN($H$3:$H$74)))} -> 0.58085739 | J140: {=(J66-MIN($H$3:$H$74))/(MAX($H$3:$H$74-MIN($H$3:$H$74)))} -> 1.0440137 | K140: {=(K66-MIN($H$3:$H$74))/(MAX($H$3:$H$74-MIN($H$3:$H$74)))} -> 0.57967259 | L140: =AVERAGE(H140:J140) -> 0.81243553 | N140: {=(N66-MIN($N$3:$N$74))/(MAX($N$3:$N$74-MIN($N$3:$N$74)))} -> 0.14469485 | O140: {=(O66-MIN($N$3:$N$74))/(MAX($N$3:$N$74-MIN($N$3:$N$74)))} -> 0.14251501 | P140: {=(P66-MIN($N$3:$N$74))/(MAX($N$3:$N$74-MIN($N$3:$N$74)))} -> 0.13095318 | Q140: {=(Q66-MIN($N$3:$N$74))/(MAX($N$3:$N$74-MIN($N$3:$N$74)))} -> 0.14163308 | R140: =AVERAGE(M140:P140) -> 0.13938768 | T140: {=(T66-MIN($T$3:$T$74))/(MAX($T$3:$T$74-MIN($T$3:$T$74)))} -> 0.10623389 | U140: {=(U66-MIN($T$3:$T$74))/(MAX($T$3:$T$74-MIN($T$3:$T$74)))} -> 0.11520446 | V140: {=(V66-MIN($T$3:$T$74))/(MAX($T$3:$T$74-MIN($T$3:$T$74)))} -> 0.64066254 | W140: {=(W66-MIN($T$3:$T$74))/(MAX($T$3:$T$74-MIN($T$3:$T$74)))} -> 0.11107734 | X140: =AVERAGE(S140:V140) -> 0.28736696 | Z140: =(Z66-MIN($Z$3:$Z$74))/(MAX($Z$3:$Z$74)-MIN($Z$3:$Z$74)) -> 0.33662203 | AA140: =(AA66-MIN($Z$3:$Z$74))/(MAX($Z$3:$Z$74)-MIN($Z$3:$Z$74)) -> 0.34598691 | AB140: =(AB66-MIN($Z$3:$Z$74))/(MAX($Z$3:$Z$74)-MIN($Z$3:$Z$74)) -> 0.34511815 | AC140: =(AC66-MIN($Z$3:$Z$74))/(MAX($Z$3:$Z$74)-MIN($Z$3:$Z$74)) -> 0.36202143 | AD140: =AVERAGE(Y140:AB140) -> 0.3425757 | AE140: =(AE66-MIN($AE$3:$AE$74))/(MAX($AE$3:$AE$74)-MIN($AE$3:$AE$74)) -> 0.20446399
A141: STIP | B141: {=(B67-MIN($B$3:$B$74))/(MAX($B$3:$B$74-MIN($B$3:$B$74)))} -> 0.57586751 | C141: {=(C67-MIN($B$3:$B$74))/(MAX($B$3:$B$74-MIN($B$3:$B$74)))} -> 0.20260921 | D141: {=(D67-MIN($B$3:$B$74))/(MAX($B$3:$B$74-MIN($B$3:$B$74)))} -> 0.16400711 | E141: {=(E67-MIN($B$3:$B$74))/(MAX($B$3:$B$74-MIN($B$3:$B$74)))} -> 0.56454297 | F141: {=(F67-MIN($B$3:$B$74))/(MAX($B$3:$B$74-MIN($B$3:$B$74)))} -> 0.57729673 | G141: =AVERAGEA(B141:E141) -> 0.3767567 | H141: {=(H67-MIN($H$3:$H$74))/(MAX($H$3:$H$74-MIN($H$3:$H$74)))} -> 0.53005093 | I141: {=(I67-MIN($H$3:$H$74))/(MAX($H$3:$H$74-MIN($H$3:$H$74)))} -> 0.54347686 | J141: {=(J67-MIN($H$3:$H$74))/(MAX($H$3:$H$74-MIN($H$3:$H$74)))} -> 1.0073119 | K141: {=(K67-MIN($H$3:$H$74))/(MAX($H$3:$H$74-MIN($H$3:$H$74)))} -> 0.56572297 | L141: =AVERAGE(H141:J141) -> 0.69361322 | M141: {=(M67-MIN($N$3:$N$74))/(MAX($N$3:$N$74-MIN($N$3:$N$74)))} -> 0.67571569 | N141: {=(N67-MIN($N$3:$N$74))/(MAX($N$3:$N$74-MIN($N$3:$N$74)))} -> 0.18346537 | O141: {=(O67-MIN($N$3:$N$74))/(MAX($N$3:$N$74-MIN($N$3:$N$74)))} -> 0.14891577 | P141: {=(P67-MIN($N$3:$N$74))/(MAX($N$3:$N$74-MIN($N$3:$N$74)))} -> 0.12272743 | Q141: {=(Q67-MIN($N$3:$N$74))/(MAX($N$3:$N$74-MIN($N$3:$N$74)))} -> 0.10574357 | R141: =AVERAGE(M141:P141) -> 0.28270607 | S141: {=(S67-MIN($S$3:$S$74))/(MAX($S$3:$S$74-MIN($S$3:$S$74)))} -> 0 | T141: {=(T67-MIN($T$3:$T$74))/(MAX($T$3:$T$74-MIN($T$3:$T$74)))} -> 1 | U141: {=(U67-MIN($T$3:$T$74))/(MAX($T$3:$T$74-MIN($T$3:$T$74)))} -> 0.21088961 | V141: {=(V67-MIN($T$3:$T$74))/(MAX($T$3:$T$74-MIN($T$3:$T$74)))} -> 1.8460744 | W141: {=(W67-MIN($T$3:$T$74))/(MAX($T$3:$T$74-MIN($T$3:$T$74)))} -> -0.29225098 | X141: =AVERAGE(S141:V141) -> 0.764241 | Y141: {=(Y67-MIN($Y$3:$Y$74))/(MAX($Y$3:$Y$74-MIN($Y$3:$Y$74)))} -> 0.42715342 | Z141: =(Z67-MIN($Z$3:$Z$74))/(MAX($Z$3:$Z$74)-MIN($Z$3:$Z$74)) -> 1 | AA141: =(AA67-MIN($Z$3:$Z$74))/(MAX($Z$3:$Z$74)-MIN($Z$3:$Z$74)) -> 0.55007852 | AB141: =(AB67-MIN($Z$3:$Z$74))/(MAX($Z$3:$Z$74)-MIN($Z$3:$Z$74)) -> 0.57804955 | AC141: =(AC67-MIN($Z$3:$Z$74))/(MAX($Z$3:$Z$74)-MIN($Z$3:$Z$74)) -> 1.0295461 | AD141: =AVERAGE(Y141:AB141) -> 0.63882037 | AE141: =(AE67-MIN($AE$3:$AE$74))/(MAX($AE$3:$AE$74)-MIN($AE$3:$AE$74)) -> -0.011404366
A142: TAWASOL GH | B142: {=(B68-MIN($B$3:$B$74))/(MAX($B$3:$B$74-MIN($B$3:$B$74)))} -> 0.10363516 | C142: {=(C68-MIN($B$3:$B$74))/(MAX($B$3:$B$74-MIN($B$3:$B$74)))} -> 0.10363516 | D142: {=(D68-MIN($B$3:$B$74))/(MAX($B$3:$B$74-MIN($B$3:$B$74)))} -> 0.12048154 | E142: {=(E68-MIN($B$3:$B$74))/(MAX($B$3:$B$74-MIN($B$3:$B$74)))} -> 0.43262569 | F142: {=(F68-MIN($B$3:$B$74))/(MAX($B$3:$B$74-MIN($B$3:$B$74)))} -> 0.3593557 | G142: =AVERAGEA(B142:E142) -> 0.19009439 | H142: {=(H68-MIN($H$3:$H$74))/(MAX($H$3:$H$74-MIN($H$3:$H$74)))} -> 0.56451494 | I142: {=(I68-MIN($H$3:$H$74))/(MAX($H$3:$H$74-MIN($H$3:$H$74)))} -> 0.59512227 | J142: {=(J68-MIN($H$3:$H$74))/(MAX($H$3:$H$74-MIN($H$3:$H$74)))} -> 2.7260859 | K142: {=(K68-MIN($H$3:$H$74))/(MAX($H$3:$H$74-MIN($H$3:$H$74)))} -> 0.55458441 | L142: =AVERAGE(H142:J142) -> 1.295241 | M142: {=(M68-MIN($N$3:$N$74))/(MAX($N$3:$N$74-MIN($N$3:$N$74)))} -> 0.095120955 | N142: {=(N68-MIN($N$3:$N$74))/(MAX($N$3:$N$74-MIN($N$3:$N$74)))} -> 0.095120955 | O142: {=(O68-MIN($N$3:$N$74))/(MAX($N$3:$N$74-MIN($N$3:$N$74)))} -> 0.1191204 | P142: {=(P68-MIN($N$3:$N$74))/(MAX($N$3:$N$74-MIN($N$3:$N$74)))} -> 0.12951533 | Q142: {=(Q68-MIN($N$3:$N$74))/(MAX($N$3:$N$74-MIN($N$3:$N$74)))} -> 0.12260456 | R142: =AVERAGE(M142:P142) -> 0.10971941 | S142: {=(S68-MIN($S$3:$S$74))/(MAX($S$3:$S$74-MIN($S$3:$S$74)))} -> 0.5573706 | T142: {=(T68-MIN($T$3:$T$74))/(MAX($T$3:$T$74-MIN($T$3:$T$74)))} -> 0.021952115 | U142: {=(U68-MIN($T$3:$T$74))/(MAX($T$3:$T$74-MIN($T$3:$T$74)))} -> 0.060367603 | V142: {=(V68-MIN($T$3:$T$74))/(MAX($T$3:$T$74-MIN($T$3:$T$74)))} -> 0.77025939 | W142: {=(W68-MIN($T$3:$T$74))/(MAX($T$3:$T$74-MIN($T$3:$T$74)))} -> 0.066589584 | X142: =AVERAGE(S142:V142) -> 0.35248743 | Y142: {=(Y68-MIN($Y$3:$Y$74))/(MAX($Y$3:$Y$74-MIN($Y$3:$Y$74)))} -> 0.73121328 | Z142: =(Z68-MIN($Z$3:$Z$74))/(MAX($Z$3:$Z$74)-MIN($Z$3:$Z$74)) -> 0.42383433 | AA142: =(AA68-MIN($Z$3:$Z$74))/(MAX($Z$3:$Z$74)-MIN($Z$3:$Z$74)) -> 0.42566663 | AB142: =(AB68-MIN($Z$3:$Z$74))/(MAX($Z$3:$Z$74)-MIN($Z$3:$Z$74)) -> 0.42846405 | AC142: =(AC68-MIN($Z$3:$Z$74))/(MAX($Z$3:$Z$74)-MIN($Z$3:$Z$74)) -> 0.47306802 | AD142: =AVERAGE(Y142:AB142) -> 0.50229457 | AE142: =(AE68-MIN($AE$3:$AE$74))/(MAX($AE$3:$AE$74)-MIN($AE$3:$AE$74)) -> -0.011404366
A143: TUNISAIR | C143: {=(C69-MIN($B$3:$B$74))/(MAX($B$3:$B$74-MIN($B$3:$B$74)))} -> 0.12571991 | D143: {=(D69-MIN($B$3:$B$74))/(MAX($B$3:$B$74-MIN($B$3:$B$74)))} -> 0.12581544 | E143: {=(E69-MIN($B$3:$B$74))/(MAX($B$3:$B$74-MIN($B$3:$B$74)))} -> 0.12850933 | F143: {=(F69-MIN($B$3:$B$74))/(MAX($B$3:$B$74-MIN($B$3:$B$74)))} -> 0.1290206 | G143: =AVERAGEA(B143:E143) -> 0.12668156 | I143: {=(I69-MIN($H$3:$H$74))/(MAX($H$3:$H$74-MIN($H$3:$H$74)))} -> 0.56977468 | J143: {=(J69-MIN($H$3:$H$74))/(MAX($H$3:$H$74-MIN($H$3:$H$74)))} -> 0.73437627 | K143: {=(K69-MIN($H$3:$H$74))/(MAX($H$3:$H$74-MIN($H$3:$H$74)))} -> 0.57493551 | L143: =AVERAGE(H143:J143) -> 0.65207548 | N143: {=(N69-MIN($N$3:$N$74))/(MAX($N$3:$N$74-MIN($N$3:$N$74)))} -> 0.088743319 | O143: {=(O69-MIN($N$3:$N$74))/(MAX($N$3:$N$74-MIN($N$3:$N$74)))} -> 0.094431667 | P143: {=(P69-MIN($N$3:$N$74))/(MAX($N$3:$N$74-MIN($N$3:$N$74)))} -> -0.01759441 | Q143: {=(Q69-MIN($N$3:$N$74))/(MAX($N$3:$N$74-MIN($N$3:$N$74)))} -> 0.00487637 | R143: =AVERAGE(M143:P143) -> 0.055193525 | T143: {=(T69-MIN($T$3:$T$74))/(MAX($T$3:$T$74-MIN($T$3:$T$74)))} -> 0.14384829 | U143: {=(U69-MIN($T$3:$T$74))/(MAX($T$3:$T$74-MIN($T$3:$T$74)))} -> 0.12104111 | V143: {=(V69-MIN($T$3:$T$74))/(MAX($T$3:$T$74-MIN($T$3:$T$74)))} -> -0.029976394 | W143: {=(W69-MIN($T$3:$T$74))/(MAX($T$3:$T$74-MIN($T$3:$T$74)))} -> 0.11741811 | X143: =AVERAGE(S143:V143) -> 0.078304334 | Z143: =(Z69-MIN($Z$3:$Z$74))/(MAX($Z$3:$Z$74)-MIN($Z$3:$Z$74)) -> 0.26563685 | AA143: =(AA69-MIN($Z$3:$Z$74))/(MAX($Z$3:$Z$74)-MIN($Z$3:$Z$74)) -> 0.27068763 | AB143: =(AB69-MIN($Z$3:$Z$74))/(MAX($Z$3:$Z$74)-MIN($Z$3:$Z$74)) -> 0.27737393 | AC143: =(AC69-MIN($Z$3:$Z$74))/(MAX($Z$3:$Z$74)-MIN($Z$3:$Z$74)) -> 0.28433373 | AD143: =AVERAGE(Y143:AB143) -> 0.2712328 | AE143: =(AE69-MIN($AE$3:$AE$74))/(MAX($AE$3:$AE$74)-MIN($AE$3:$AE$74)) -> -0.011404366
A144: BH | B144: {=(B70-MIN($B$3:$B$74))/(MAX($B$3:$B$74-MIN($B$3:$B$74)))} -> 0.35648725 | C144: {=(C70-MIN($B$3:$B$74))/(MAX($B$3:$B$74-MIN($B$3:$B$74)))} -> 0.56030905 | D144: {=(D70-MIN($B$3:$B$74))/(MAX($B$3:$B$74-MIN($B$3:$B$74)))} -> 0.52044818 | E144: {=(E70-MIN($B$3:$B$74))/(MAX($B$3:$B$74-MIN($B$3:$B$74)))} -> 2.4706745 | F144: {=(F70-MIN($B$3:$B$74))/(MAX($B$3:$B$74-MIN($B$3:$B$74)))} -> 2.7729836 | G144: =AVERAGEA(B144:E144) -> 0.97697974 | H144: {=(H70-MIN($H$3:$H$74))/(MAX($H$3:$H$74-MIN($H$3:$H$74)))} -> 0.60128381 | I144: {=(I70-MIN($H$3:$H$74))/(MAX($H$3:$H$74-MIN($H$3:$H$74)))} -> 0.56070248 | J144: {=(J70-MIN($H$3:$H$74))/(MAX($H$3:$H$74-MIN($H$3:$H$74)))} -> 0.76991483 | K144: {=(K70-MIN($H$3:$H$74))/(MAX($H$3:$H$74-MIN($H$3:$H$74)))} -> 0.569866 | L144: =AVERAGE(H144:J144) -> 0.64396704 | M144: {=(M70-MIN($N$3:$N$74))/(MAX($N$3:$N$74-MIN($N$3:$N$74)))} -> 0.16421438 | N144: {=(N70-MIN($N$3:$N$74))/(MAX($N$3:$N$74-MIN($N$3:$N$74)))} -> 0.19097574 | O144: {=(O70-MIN($N$3:$N$74))/(MAX($N$3:$N$74-MIN($N$3:$N$74)))} -> 0.1774984 | P144: {=(P70-MIN($N$3:$N$74))/(MAX($N$3:$N$74-MIN($N$3:$N$74)))} -> 0.18220843 | Q144: {=(Q70-MIN($N$3:$N$74))/(MAX($N$3:$N$74-MIN($N$3:$N$74)))} -> 0.15075008 | R144: =AVERAGE(M144:P144) -> 0.17872424 | S144: {=(S70-MIN($S$3:$S$74))/(MAX($S$3:$S$74-MIN($S$3:$S$74)))} -> 0.70963757 | T144: {=(T70-MIN($T$3:$T$74))/(MAX($T$3:$T$74-MIN($T$3:$T$74)))} -> 0.097381925 | U144: {=(U70-MIN($T$3:$T$74))/(MAX($T$3:$T$74-MIN($T$3:$T$74)))} -> 0.094078511 | V144: {=(V70-MIN($T$3:$T$74))/(MAX($T$3:$T$74-MIN($T$3:$T$74)))} -> 0.17993149 | W144: {=(W70-MIN($T$3:$T$74))/(MAX($T$3:$T$74-MIN($T$3:$T$74)))} -> 0.083452558 | X144: =AVERAGE(S144:V144) -> 0.27025737 | Y144: {=(Y70-MIN($Y$3:$Y$74))/(MAX($Y$3:$Y$74-MIN($Y$3:$Y$74)))} -> 0.94030845 | Z144: =(Z70-MIN($Z$3:$Z$74))/(MAX($Z$3:$Z$74)-MIN($Z$3:$Z$74)) -> 0.49859903 | AA144: =(AA70-MIN($Z$3:$Z$74))/(MAX($Z$3:$Z$74)-MIN($Z$3:$Z$74)) -> 0.50559098 | AB144: =(AB70-MIN($Z$3:$Z$74))/(MAX($Z$3:$Z$74)-MIN($Z$3:$Z$74)) -> 0.48946643 | AC144: =(AC70-MIN($Z$3:$Z$74))/(MAX($Z$3:$Z$74)-MIN($Z$3:$Z$74)) -> 0.47434543 | AD144: =AVERAGE(Y144:AB144) -> 0.60849122 | AE144: =(AE70-MIN($AE$3:$AE$74))/(MAX($AE$3:$AE$74)-MIN($AE$3:$AE$74)) -> 0.063049853
A145: BH ASSURANCES | B145: {=(B71-MIN($B$3:$B$74))/(MAX($B$3:$B$74-MIN($B$3:$B$74)))} -> 0.15689101 | C145: {=(C71-MIN($B$3:$B$74))/(MAX($B$3:$B$74-MIN($B$3:$B$74)))} -> 0.16786419 | D145: {=(D71-MIN($B$3:$B$74))/(MAX($B$3:$B$74-MIN($B$3:$B$74)))} -> 0.16836296 | E145: {=(E71-MIN($B$3:$B$74))/(MAX($B$3:$B$74-MIN($B$3:$B$74)))} -> 0.17031416 | F145: {=(F71-MIN($B$3:$B$74))/(MAX($B$3:$B$74-MIN($B$3:$B$74)))} -> 0.17031127 | G145: =AVERAGEA(B145:E145) -> 0.16585808 | H145: {=(H71-MIN($H$3:$H$74))/(MAX($H$3:$H$74-MIN($H$3:$H$74)))} -> 0.57948393 | I145: {=(I71-MIN($H$3:$H$74))/(MAX($H$3:$H$74-MIN($H$3:$H$74)))} -> 0.56501495 | J145: {=(J71-MIN($H$3:$H$74))/(MAX($H$3:$H$74-MIN($H$3:$H$74)))} -> 0.56644771 | K145: {=(K71-MIN($H$3:$H$74))/(MAX($H$3:$H$74-MIN($H$3:$H$74)))} -> 0.56451221 | L145: =AVERAGE(H145:J145) -> 0.57031553 | M145: {=(M71-MIN($N$3:$N$74))/(MAX($N$3:$N$74-MIN($N$3:$N$74)))} -> 0.46809459 | N145: {=(N71-MIN($N$3:$N$74))/(MAX($N$3:$N$74-MIN($N$3:$N$74)))} -> 0.53201845 | O145: {=(O71-MIN($N$3:$N$74))/(MAX($N$3:$N$74-MIN($N$3:$N$74)))} -> 0.46956978 | P145: {=(P71-MIN($N$3:$N$74))/(MAX($N$3:$N$74-MIN($N$3:$N$74)))} -> 0.40284185 | Q145: {=(Q71-MIN($N$3:$N$74))/(MAX($N$3:$N$74-MIN($N$3:$N$74)))} -> 0.35744463 | R145: =AVERAGE(M145:P145) -> 0.46813117 | S145: {=(S71-MIN($S$3:$S$74))/(MAX($S$3:$S$74-MIN($S$3:$S$74)))} -> 0.74048481 | T145: {=(T71-MIN($T$3:$T$74))/(MAX($T$3:$T$74-MIN($T$3:$T$74)))} -> 0.10634467 | U145: {=(U71-MIN($T$3:$T$74))/(MAX($T$3:$T$74-MIN($T$3:$T$74)))} -> 0.10310182 | V145: {=(V71-MIN($T$3:$T$74))/(MAX($T$3:$T$74-MIN($T$3:$T$74)))} -> 0.10153887 | W145: {=(W71-MIN($T$3:$T$74))/(MAX($T$3:$T$74-MIN($T$3:$T$74)))} -> 0.094613274 | X145: =AVERAGE(S145:V145) -> 0.26286754 | Y145: {=(Y71-MIN($Y$3:$Y$74))/(MAX($Y$3:$Y$74-MIN($Y$3:$Y$74)))} -> 0.6603762 | Z145: =(Z71-MIN($Z$3:$Z$74))/(MAX($Z$3:$Z$74)-MIN($Z$3:$Z$74)) -> 0.38611597 | AA145: =(AA71-MIN($Z$3:$Z$74))/(MAX($Z$3:$Z$74)-MIN($Z$3:$Z$74)) -> 0.38852268 | AB145: =(AB71-MIN($Z$3:$Z$74))/(MAX($Z$3:$Z$74)-MIN($Z$3:$Z$74)) -> 0.15697601 | AC145: =(AC71-MIN($Z$3:$Z$74))/(MAX($Z$3:$Z$74)-MIN($Z$3:$Z$74)) -> 0.39523174 | AD145: =AVERAGE(Y145:AB145) -> 0.39799772 | AE145: =(AE71-MIN($AE$3:$AE$74))/(MAX($AE$3:$AE$74)-MIN($AE$3:$AE$74)) -> 0.23639622
...

Sheet Sheet1
A1: Column1 | B1: average EPS | C1: Average EPS growth | D1: Average NPM | E1: Average ROE | F1: Average D/E | G1: Average P/E | H1: Score
A2: SIAME | B2: 0.18095411 | C2: 4.0840165 | D2: 0.13422944 | E2: 0.34228119 | F2: 0.39291314 | G2: 0.29015966 | H2: =B2*0.1+C2*0.2+D2*0.15+E2*0.25+F2*0.15+G2*0.15 -> 1.0430643
A3: MONOPRIX | B3: 0.68028747 | C3: 1.7587326 | D3: 0.12378351 | E3: 0.97189444 | F3: 0.53077024 | G3: 0.36673183 | H3: 0.77265431
A4: STIP | B4: 0.3767567 | C4: 0.69361322 | D4: 0.28270607 | E4: 0.764241 | F4: 0.63882037 | G4: -0.011404366 | H4: 0.55472502
A5: BIAT | B5: 2.0760906 | C5: 0.62340548 | D5: 0.19643183 | E5: 0.29404215 | F5: 0.5846203 | G5: 0.072987944 | H5: =B5*0.1+C5*0.2+D5*0.15+E5*0.25+F5*0.15+G5*0.15 -> 0.53390671
A6: Ste Assurances Magrebia SA | B6: 0.69187616 | C6: 0.5714986 | D6: 0.75709639 | E6: 0.3453382 | F6: 0.38170011 | G6: 0.12968394 | H6: 0.49275736
A7: SOTETEL | B7: 0.18259524 | C7: 1.3833836 | D7: 0.14023822 | E7: 0.34627939 | F7: 0.40398392 | G7: 0.080645161 | H7: =B7*0.1+C7*0.2+D7*0.15+E7*0.25+F7*0.15+G7*0.15 -> 0.47523619
A8: BNA | B8: 1.3053793 | C8: 0.64408528 | D8: 0.17926778 | E8: 0.26721917 | F8: 0.58447812 | G8: 0.039263604 | H8: =B8*0.1+C8*0.2+D8*0.15+E8*0.25+F8*0.15+G8*0.15 -> 0.44661121
A9: SITS | B9: 0.14620208 | C9: 0.61851477 | D9: 0.21878596 | E9: 0.27509532 | F9: 0.37687933 | G9: 1 | H9: =B9*0.1+C9*0.2+D9*0.15+E9*0.25+F9*0.15+G9*0.15 -> 0.44644679
A10: ASSAD | B10: 0.19819124 | C10: 0.74857693 | D10: 0.10463244 | E10: 0.54133906 | F10: 0.47198891 | G10: 0.33349625 | H10: =B10*0.1+C10*0.2+D10*0.15+E10*0.25+F10*0.15+G10*0.15 -> 0.44138692
A11: TAWASOL GH | B11: 0.19009439 | C11: 1.295241 | D11: 0.10971941 | E11: 0.35248743 | F11: 0.50229457 | G11: -0.011404366 | H11: 0.4408744
A12: SMART TUNISIE | B12: 0.55959311 | C12: 0.9720586 | D12: 0.14098173 | E12: 0.34179525 | F12: 0.33675347 | G12: 0.19322255 | H12: =B12*0.1+C12*0.2+D12*0.15+E12*0.25+F12*0.15+G12*0.15 -> 0.43646351
A13: LAND'OR | B13: 0.33406837 | C13: 0.91351052 | D13: 0.1323981 | E13: 0.36493971 | F13: 0.39134973 | G13: 0.24389052 | H13: =B13*0.1+C13*0.2+D13*0.15+E13*0.25+F13*0.15+G13*0.15 -> 0.42248962
A14: BH | B14: 0.97697974 | C14: 0.64396704 | D14: 0.17872424 | E14: 0.27025737 | F14: 0.60849122 | G14: 0.063049853 | H14: =B14*0.1+C14*0.2+D14*0.15+E14*0.25+F14*0.15+G14*0.15 -> 0.42159552
A15: STB | B15: 0.90698555 | C15: 0.66832241 | D15: 0.1656468 | E15: 0.26694295 | F15: 0.60099154 | G15: 0.09107201 | H15: =B15*0.1+C15*0.2+D15*0.15+E15*0.25+F15*0.15+G15*0.15 -> 0.41975533
A16: MPBS | B16: 0.23593742 | C16: 0.97880694 | D16: 0.13702015 | E16: 0.34435913 | F16: 0.38469603 | G16: 0.15184099 | H16: =B16*0.1+C16*0.2+D16*0.15+E16*0.25+F16*0.15+G16*0.15 -> 0.40647849
A17: UIB | B17: 0.75882084 | C17: 0.61731104 | D17: 0.18861887 | E17: 0.27390121 | F17: 0.54320985 | G17: 0.18051483 | H17: =B17*0.1+C17*0.2+D17*0.15+E17*0.25+F17*0.15+G17*0.15 -> 0.40467113
A18: AMEN BANK | B18: 0.85483777 | C18: 0.6064489 | D18: 0.21850975 | E18: 0.26264737 | F18: 0.51865121 | G18: 0.099543825 | H18: =B18*0.1+C18*0.2+D18*0.15+E18*0.25+F18*0.15+G18*0.15 -> 0.39794112
A19: BT | B19: 0.8416623 | C19: 0.60113829 | D19: 0.22878036 | E19: 0.26549553 | F19: 0.48362215 | G19: 0.13538612 | H19: =B19*0.1+C19*0.2+D19*0.15+E19*0.25+F19*0.15+G19*0.15 -> 0.39793607
A20: ATB | B20: 0.43077068 | C20: 0.6788641 | D20: 0.12149031 | E20: 0.25742214 | F20: 0.66279821 | G20: 0.23232323 | H20: =B20*0.1+C20*0.2+D20*0.15+E20*0.25+F20*0.15+G20*0.15 -> 0.39569719
A21: SOTIPAPIER | B21: 0.24082271 | C21: 0.75402702 | D21: 0.15184291 | E21: 0.32032888 | F21: 0.37694367 | G21: 0.40322581 | H21: =B21*0.1+C21*0.2+D21*0.15+E21*0.25+F21*0.15+G21*0.15 -> 0.39477175
A22: WIFACK INTERNATIONAL BANK | B22: 0.19502369 | C22: 0.78833363 | D22: 0.13001763 | E22: 0.2483777 | F22: 0.49515848 | G22: 0.36363636 | H22: =B22*0.1+C22*0.2+D22*0.15+E22*0.25+F22*0.15+G22*0.15 -> 0.38758539
A23: Banque Attijari De Tunisie | B23: 0.45403035 | C23: 0.57734484 | D23: 0.27280733 | E23: 0.32236168 | F23: 0.44904575 | G23: 0.17497556 | H23: =B23*0.1+C23*0.2+D23*0.15+E23*0.25+F23*0.15+G23*0.15 -> 0.37598672
A24: UNIMED | B24: 0.25212846 | C24: 0.79320324 | D24: 0.14807276 | E24: 0.30987485 | F24: 0.37778016 | G24: 0.22564353 | H24: =B24*0.1+C24*0.2+D24*0.15+E24*0.25+F24*0.15+G24*0.15 -> 0.37404667
A25: UBCI | B25: 0.4692763 | C25: 0.63017671 | D25: 0.1749212 | E25: 0.27304642 | F25: 0.5219463 | G25: 0.19110459 | H25: 0.37229679
A26: BH ASSURANCES | B26: 0.16585808 | C26: 0.57031553 | D26: 0.46813117 | E26: 0.26286754 | F26: 0.39799772 | G26: 0.23639622 | H26: 0.36603899
A27: EURO-CYCLES | B27: 0.2626862 | C27: 0.64799536 | D27: 0.15990459 | E27: 0.39701194 | F27: 0.41137644 | G27: 0.16731834 | H27: =B27*0.1+C27*0.2+D27*0.15+E27*0.25+F27*0.15+G27*0.15 -> 0.36591058
A28: BEST LEASE | B28: 0.19735528 | C28: 0.58303688 | D28: 0.40672276 | E28: 0.278761 | F28: 0.43885041 | G28: 0.094819159 | H28: 0.36467495
A29: ENNAKL AUTOMOBILES | B29: 0.47398953 | C29: 0.68646412 | D29: 0.14987734 | E29: 0.31102999 | F29: 0.3900674 | G29: 0.13782991 | H29: =B29*0.1+C29*0.2+D29*0.15+E29*0.25+F29*0.15+G29*0.15 -> 0.36411547
A30: STAR | B30: 0.20684873 | C30: 0.57670968 | D30: 0.40272285 | E30: 0.24141958 | F30: 0.42607627 | G30: 0.285435 | H30: 0.35964877
A31: TUNINVEST SICAR | B31: 0.12999557 | C31: 0.63181664 | D31: 0.25130193 | E31: 0.28184847 | F31: 0.3794295 | G31: 0.78820463 | H31: 0.35788311
A32: TELNET HOLDING | B32: 0.1942193 | C32: 0.65904287 | D32: 0.15799828 | E32: 0.39133839 | F32: 0.38559842 | G32: 0.11925709 | H32: 0.35036207
A33: SPDIT-SICAF | B33: 0.15210916 | C33: 0.57157419 | D33: 0.3813215 | E33: 0.29353945 | F33: 0.36431288 | G33: 0.17220593 | H33: 0.34674605
A34: BH LEASING | B34: 0.14028478 | C34: 0.71070082 | D34: 0.15221931 | E34: 0.24922369 | F34: 0.56909828 | G34: 0.10475725 | H34: 0.34490209
A35: ASTREE | B35: 0.22445261 | C35: 0.59484005 | D35: 0.25779723 | E35: 0.27357436 | F35: 0.4467967 | G35: 0.11990877 | H35: 0.3406578
A36: AIR LIQUIDE TUNISIE | B36: 0.27389563 | C36: 0.64944857 | D36: 0.17434851 | E36: 0.32694371 | F36: 0.37958559 | G36: 0.13685239 | H36: 0.3405194
A37: TJL | B37: 0.16599246 | C37: 0.62936945 | D37: 0.20128598 | E37: 0.26563389 | F37: 0.51562848 | G37: 0.11616162 | H37: 0.3398858
A38: Hannibal Lease | B38: 0.17127612 | C38: 0.67520292 | D38: 0.16086325 | E38: 0.25385884 | F38: 0.5415499 | G38: 0.096285435 | H38: 0.3398626
A39: PLTU | B39: 0.13700081 | C39: 0.55398409 | D39: 0.37922623 | E39: 0.27579038 | F39: 0.36339141 | G39: 0.20755947 | H39: 0.33843631
A40: Automobile Reseau Tunisien Et Service SA | B40: 0.19819402 | C40: 0.6332512 | D40: 0.2171703 | E40: 0.31316757 | F40: 0.37487025 | G40: 0.16438579 | H40: =B40*0.1+C40*0.2+D40*0.15+E40*0.25+F40*0.15+G40*0.15 -> 0.33822549
A41: BNA ASSURANCES | B41: 0.15663048 | C41: 0.68112947 | D41: 0.17071417 | E41: 0.24701748 | F41: 0.3813383 | G41: 0.27256435 | H41: =B41*0.1+C41*0.2+D41*0.15+E41*0.25+F41*0.15+G41*0.15 -> 0.33733583
A42: STA | B42: 0.22187595 | C42: 0.81243553 | D42: 0.13938768 | E42: 0.28736696 | F42: 0.3425757 | G42: 0.20446399 | H42: 0.33687889
A43: Compagnie Internationale De Leasing | B43: 0.22408335 | C43: 0.56650952 | D43: 0.24891374 | E43: 0.25533472 | F43: 0.45800583 | G43: 0.14141414 | H43: 0.3324398
A44: ICF | B44: 0.26445192 | C44: 0.67456295 | D44: 0.13691402 | E44: 0.2949715 | F44: 0.3717618 | G44: 0.1210492 | H44: =B44*0.1+C44*0.2+D44*0.15+E44*0.25+F44*0.15+G44*0.15 -> 0.32955941
A45: Poulina Group Holding | B45: 0.14815451 | C45: 0.56799888 | D45: 0.13781292 | E45: 0.25886232 | F45: 0.44686122 | G45: 0.31671554 | H45: =B45*0.1+C45*0.2+D45*0.15+E45*0.25+F45*0.15+G45*0.15 -> 0.32833926
A46: One Tech Ho | B46: 0.13752519 | C46: 0.58917725 | D46: 0.13402871 | E46: 0.24314231 | F46: 0.38554309 | G46: 0.38383838 | H46: =B46*0.1+C46*0.2+D46*0.15+E46*0.25+F46*0.15+G46*0.15 -> 0.32788507
A47: Tunisie Leasing | B47: 0.17867518 | C47: 0.59266079 | D47: 0.15755374 | E47: 0.24146266 | F47: 0.54990206 | G47: 0.13880743 | H47: 0.32763697
A48: Societe Tunisienne des Marches de Gros SA | B48: 0.14244581 | C48: 0.57219367 | D48: 0.23558973 | E48: 0.27248838 | F48: 0.36734826 | G48: 0.26572173 | H48: =B48*0.1+C48*0.2+D48*0.15+E48*0.25+F48*0.15+G48*0.15 -> 0.32710437
A49: Assurances Maghrebia Vie SA | B49: 0.14885429 | C49: 0.56928486 | D49: 0.33951988 | E49: 0.27301712 | F49: 0.37737728 | G49: 0 | H49: 0.32556273
A50: SOMOCER | B50: 0.20858704 | C50: 0.62681381 | D50: 0.099991538 | E50: 0.3625089 | F50: 0.4960654 | G50: -0.011404366 | H50: =B50*0.1+C50*0.2+D50*0.15+E50*0.25+F50*0.15+G50*0.15 -> 0.32454657
A51: SOTRAPIL | B51: 0.15993089 | C51: 0.58178941 | D51: 0.28209604 | E51: 0.27376561 | F51: 0.36878817 | G51: 0.1627566 | H51: 0.32370585
A52: City Cars | B52: 0.18245506 | C52: 0.57203405 | D52: 0.15227145 | E52: 0.32112583 | F52: 0.40282535 | G52: 0.18214402 | H52: =B52*0.1+C52*0.2+D52*0.15+E52*0.25+F52*0.15+G52*0.15 -> 0.3235199
A53: Societe Tunisienne De Verreries | B53: 0.15011192 | C53: 0.59124176 | D53: 0.17552738 | E53: 0.2844717 | F53: 0.40880097 | G53: 0.19126751 | H53: =B53*0.1+C53*0.2+D53*0.15+E53*0.25+F53*0.15+G53*0.15 -> 0.32071685
A54: SAH | B54: 0.13889875 | C54: 0.57381935 | D54: 0.13748202 | E54: 0.25133586 | F54: 0.41358123 | G54: 0.29537309 | H54: =B54*0.1+C54*0.2+D54*0.15+E54*0.25+F54*0.15+G54*0.15 -> 0.31845316
A55: SAM | B55: 0.15399886 | C55: 0.69207507 | D55: 0.15395538 | E55: 0.34102874 | F55: 0.37949783 | G55: -0.011404366 | H55: =B55*0.1+C55*0.2+D55*0.15+E55*0.25+F55*0.15+G55*0.15 -> 0.31737941
A56: SOTEMAIL | B56: 0.16347949 | C56: 0.68097548 | D56: 0.10011638 | E56: 0.30301772 | F56: 0.42872078 | G56: -0.011404366 | H56: 0.3145968
A57: NEW BODY LINE | B57: 0.14030664 | C57: 0.71399033 | D57: 0.18874083 | E57: 0.2979085 | F57: 0.36546033 | G57: -0.011404366 | H57: =B57*0.1+C57*0.2+D57*0.15+E57*0.25+F57*0.15+G57*0.15 -> 0.31272537
A58: CIMENTS DE BIZERTE | B58: 0.170388 | C58: 0.38256159 | D58: 0.077005084 | E58: 0.39886273 | F58: 0.50916445 | G58: -0.011404366 | H58: 0.31074555
A59: Societe Frigorifique Et Brasserie | B59: 0.15877173 | C59: 0.56882834 | D59: 0.18335724 | E59: 0.2795473 | F59: 0.37640422 | G59: 0.17204301 | H59: =B59*0.1+C59*0.2+D59*0.15+E59*0.25+F59*0.15+G59*0.15 -> 0.30930034
A60: Arab Tunisian Lease | B60: 0.1405003 | C60: 0.58938065 | D60: 0.21328224 | E60: 0.2459061 | F60: 0.42811318 | G60: 0.13017269 | H60: =B60*0.1+C60*0.2+D60*0.15+E60*0.25+F60*0.15+G60*0.15 -> 0.3091379
A61: Carthage Cement | B61: 0.13004389 | C61: 0.58258912 | D61: 0.15515957 | E61: 0.26968339 | F61: 0.45872026 | G61: 0.13310525 | H61: =B61*0.1+C61*0.2+D61*0.15+E61*0.25+F61*0.15+G61*0.15 -> 0.30899082
A62: SIMPAR | B62: 0.14439388 | C62: 0.77163653 | D62: 0.081481767 | E62: 0.24192902 | F62: 0.4353944 | G62: -0.011404366 | H62: 0.30556859
A63: Societe Tunisie Profiles Aluminium | B63: 0.14562165 | C63: 0.57620645 | D63: 0.15906029 | E63: 0.27042183 | F63: 0.38750334 | G63: 0.16063864 | H63: =B63*0.1+C63*0.2+D63*0.15+E63*0.25+F63*0.15+G63*0.15 -> 0.30348925
A64: Societe Delice Holding | B64: 0.1744828 | C64: 0.5725121 | D64: 0.14417258 | E64: 0.28534267 | F64: 0.39830024 | G64: 0.099217986 | H64: =B64*0.1+C64*0.2+D64*0.15+E64*0.25+F64*0.15+G64*0.15 -> 0.29953999
A65: Tunis Re | B65: 0.1271787 | C65: 0.55109212 | D65: 0.13054414 | E65: 0.22664719 | F65: 0.42492563 | G65: 0.12544803 | H65: =B65*0.1+C65*0.2+D65*0.15+E65*0.25+F65*0.15+G65*0.15 -> 0.28173576
A66: ESSOUKNA | B66: 0.13135398 | C66: 0.64834147 | D66: 0.091026527 | E66: 0.23566298 | F66: 0.38509612 | G66: -0.011404366 | H66: 0.27573982
A67: ALKIMIA | B67: 0.1916564 | C67: 0.69107064 | D67: 0.069479439 | E67: 0.28111557 | F67: 0.27567384 | G67: -0.011404366 | H67: 0.27562134
A68: AETECH | B68: 0.13102773 | C68: 0.76778704 | D68: 0.10583137 | E68: 0.18517636 | F68: 0.31701576 | G68: -0.011404366 | H68: 0.26782295
A69: BTE | B69: 0.1246311 | C69: 0.60453416 | D69: 0.0020802819 | E69: 0.23314956 | F69: 0.46634936 | G69: -0.011404366 | H69: 0.26620381
A70: TUNISAIR | B70: 0.12668156 | C70: 0.65207548 | D70: 0.055193525 | E70: 0.078304334 | F70: 0.2712328 | G70: -0.011404366 | H70: 0.19868583
A71: SANIMED | B71: 0.14037178 | C71: -0.042986762 | D71: 0.073235414 | E71: 0.21756278 | F71: 0.54689467 | G71: -0.011404366 | H71: 0.19631379
A72: CELLCOM | B72: 0.17368625 | C72: -3.7336913 | D72: 0.1234342 | E72: 0.73723953 | F72: 0.43276456 | G72: 0.20332356 | H72: -0.20010727
A73: MAGASIN GENERAL | B73: 0.91816925 | C73: 0.96725203 | D73: 0.11586099 | E73: -7.4822136 | F73: -0.35585335 | G73: -0.011404366 | H73: -2.0563281
