Workbook

Sheet Added Value By Sector
A1: Year | B1: Added value of Agriculture, forestry and fishing sector | C1: Added value of Oil and natural gas extraction sector | D1: Added value of Extraction of mining products sector | E1: Added value of Agrifoods industries sector | F1: Added value of Textile, clothing and leather industry sector | G1: Added value of Oil refinery sector | H1: Added value of Chemical industries sector | I1: Added value of Building materials industry, ceramics and glass sector | J1: Added value of Mechanical and electrical industries sector | K1: Added value of Various industries sector | L1: Added value of Production and distribution of electricity and gas sector | M1: Added value of Water distribution and treatment of wastewater and waste sector | N1: Added value of Construction sector | O1: Added value of Trade, maintenance and repair sector | P1: Added value of Transportation and warehousing services sector | Q1: Added value of Hotel, cafe and restaurant services sector | R1: Added value of Information and communication sector | S1: Added value of Financial activities sector | T1: Added value of Public administration and defense services sector | U1: Added value of Private and public education sector | V1: Added value of Private and public health and social action sector | W1: Added value of Other market services sector | X1: Added value of Other household activities sector | Y1: Added value of Services provided by associative organizations sector | Z1: Added Values of Market activities sector | AA1: Added Values of Nonmarket activities sector
A2: Q4 2010 | B2: 0.059994193 | C2: -0.16577538 | D2: 0.11157135 | E2: -0.015227047 | F2: 0.027219433 | G2: -0.23412152 | H2: 0.066722111 | I2: 0.024739849 | J2: 0.052155646 | K2: 0.019619332 | L2: -0.044615657 | M2: 0.18754026 | N2: 0.11591881 | O2: 0.027506989 | P2: -0.0051114448 | Q2: -0.055389465 | R2: 0.054597987 | S2: -0.014813723 | T2: 0.055922294 | U2: 0.024954572 | V2: -0.0045468807 | W2: -0.041423444 | X2: 8.3778004e-05 | Y2: 0.038332081 | Z2: 0.0033272802 | AA2: 0.040784933
A3: Q4 2011 | B3: 0.11329542 | C3: -0.062364142 | D3: -0.45352155 | E3: 0.070075421 | F3: -0.055979545 | G3: 2.0145093 | H3: -0.23672866 | I3: -0.0094614197 | J3: 0.042108142 | K3: 0.0033615232 | L3: 0.031017104 | M3: -0.068121514 | N3: -0.078424108 | O3: -0.0012704838 | P3: -0.10524702 | Q3: -0.16089633 | R3: 0.038801678 | S3: 0.032649443 | T3: 0.11274506 | U3: 0.049460949 | V3: 0.06144416 | W3: -0.077967234 | X3: 0.023264019 | Y3: 0.062290521 | Z3: -0.027296686 | AA3: 0.078786159
A4: Q4 2012 | B4: 0.07645301 | C4: 0.0715827 | D4: -0.091130511 | E4: 0.040225961 | F4: -0.025056767 | G4: -0.28091999 | H4: 0.16236963 | I4: 0.056704446 | J4: -0.0030201871 | K4: -0.02534443 | L4: 0.11509814 | M4: -0.017177052 | N4: 0.050677975 | O4: 0.050215278 | P4: 0.05961857 | Q4: 0.082138445 | R4: 0.083449573 | S4: 0.070468575 | T4: 0.059033181 | U4: 0.0095878937 | V4: 0.11179522 | W4: 0.06614263 | X4: 0.012404775 | Y4: 0.018717275 | Z4: 0.048913304 | AA4: 0.04342461
A5: Q4 2013 | B5: -0.035729913 | C5: -0.20195816 | D5: 0.51276257 | E5: -0.025911823 | F5: 0.0067807299 | G5: -0.058203759 | H5: 0.12176978 | I5: 0.0071441634 | J5: -0.015246693 | K5: 0.018258572 | L5: 0.049848154 | M5: 0.19806645 | N5: 0.032784292 | O5: 0.039838201 | P5: 0.024767316 | Q5: -0.013829606 | R5: 0.083024547 | S5: 0.016717386 | T5: 0.064492857 | U5: 0.029895115 | V5: 0.077683509 | W5: 0.041806544 | X5: 0.0083181315 | Y5: 0.051779136 | Z5: 0.006620645 | AA5: 0.053427417
A6: Q4 2014 | B6: 0.078973143 | C6: -0.051262347 | D6: -0.088731852 | E6: 0.046567391 | F6: -0.013708488 | G6: -0.046332428 | H6: -0.13005655 | I6: 0.0095820919 | J6: 0.051802938 | K6: -0.0012186574 | L6: -0.0017570776 | M6: 0.03508697 | N6: 0.012102036 | O6: 0.025886863 | P6: 0.00056309055 | Q6: -0.024697864 | R6: 0.037527965 | S6: 0.050808054 | T6: 0.025640178 | U6: 0.046869128 | V6: 0.068546232 | W6: 0.031584643 | X6: 0.015384622 | Y6: 0.052919459 | Z6: 0.020619459 | AA6: 0.03123172
A7: Q4 2015 | B7: 0.060402637 | C7: -0.13790543 | D7: 0.40501208 | E7: -0.0099572301 | F7: -0.041255321 | G7: -0.25111819 | H7: 0.070246515 | I7: -0.00020888804 | J7: -0.0058624394 | K7: -0.019282118 | L7: 0.017694523 | M7: 0.042887111 | N7: -0.0068966107 | O7: 0.011232754 | P7: -0.041215435 | Q7: -0.15245524 | R7: 0.028154998 | S7: 0.031167304 | T7: 0.023308962 | U7: 0.036821954 | V7: 0.042637224 | W7: 0.037222959 | X7: 0.020004784 | Y7: 0.041401841 | Z7: -0.00098807179 | AA7: 0.027053302
A8: Q4 2016 | B8: -0.055476312 | C8: -0.080323809 | D8: 0.12715879 | E8: 0.043951237 | F8: -0.0010989432 | G8: -0.85557448 | H8: 0.0059230561 | I8: -0.022392629 | J8: 0.026290959 | K8: 0.0035925634 | L8: 0.040944243 | M8: 0.00092402706 | N8: -0.0044806284 | O8: 0.021948036 | P8: 0.053280529 | Q8: 0.10851414 | R8: 0.044123168 | S8: 0.041318997 | T8: 0.0050548341 | U8: 0.041254738 | V8: 0.030401758 | W8: 0.035328152 | X8: 0.023576943 | Y8: 0.041456342 | Z8: 0.012475517 | AA8: 0.018453626
A9: Q4 2017 | B9: 0.036950392 | C9: -0.0054887239 | D9: -0.11382816 | E9: 0.067356841 | F9: 0.021392978 | G9: 0.16320268 | H9: 0.022776467 | I9: -0.079123191 | J9: 0.051387856 | K9: -0.0088123213 | L9: 0.039497204 | M9: 0.034088388 | N9: -0.017640436 | O9: 0.011066655 | P9: 0.062650966 | Q9: 0.077444186 | R9: 0.018473683 | S9: 0.11303992 | T9: -0.00013078889 | U9: 0.019372879 | V9: 0.019689014 | W9: 0.020765133 | X9: 0.012868315 | Y9: 0.039805922 | Z9: 0.02799032 | AA9: 0.0025692709
A10: Q4 2018 | B10: 0.065311154 | C10: -0.13010539 | D10: 0.11532848 | E10: -0.015667748 | F10: 0.0091321753 | G10: 0.39924713 | H10: 0.015961428 | I10: 0.014158059 | J10: -0.0029087723 | K10: -3.1362323e-05 | L10: 0.012072638 | M10: 0.027097258 | N10: 0.005401525 | O10: 0.016265634 | P10: 0.030325519 | Q10: 0.050489817 | R10: 0.081250902 | S10: 0.025720339 | T10: 0.0025377928 | U10: 0.012103376 | V10: 0.04360567 | W10: 0.035838971 | X10: 0.027200569 | Y10: 0.039881586 | Z10: 0.023259924 | AA10: 0.0053124555
A11: Q4 2019 | B11: 0.039519365 | C11: -0.077475179 | D11: 0.39493906 | E11: 0.062326477 | F11: -0.058913118 | G11: 0.74670607 | H11: 0.0036820267 | I11: 0.016529514 | J11: -0.029335561 | K11: -0.013785147 | L11: -0.023667187 | M11: 0.046253195 | N11: 0.00016547029 | O11: 0.0055108004 | P11: -0.028872111 | Q11: 0.05299175 | R11: 0.045549087 | S11: 0.0041149009 | T11: 0.013822266 | U11: 0.025888805 | V11: 0.042490461 | W11: -0.0049721169 | X11: 0.013426755 | Y11: 0.0051320531 | Z11: 0.009939922 | AA11: 0.019647681
A12: Q4 2020 | B12: 0.012870884 | C12: 0.051316171 | D12: -0.43382457 | E12: -0.061435286 | F12: 0.17115464 | G12: 0.20715172 | H12: -0.12276883 | I12: 0.17681163 | J12: 0.0048319568 | K12: -0.014669232 | L12: -0.1230768 | M12: 0.096298945 | N12: 0.16195923 | O12: 0.015590124 | P12: -0.044627319 | Q12: 0.33027665 | R12: 0.053629956 | S12: 0.0024216241 | T12: -0.044145442 | U12: -0.01175047 | V12: 0.11097079 | W12: -0.069248944 | X12: -0.018763549 | Y12: -0.087757223 | Z12: -0.045329087 | AA12: -0.0089155346
A13: Q4 2021 | B13: -0.014652997 | C13: 0.18231561 | D13: 0.57522189 | E13: 0.062318341 | F13: 0.028819154 | G13: 1.9787215 | H13: 0.25541252 | I13: -0.018170783 | J13: 0.0006633038 | K13: 0.038939396 | L13: 0.17291781 | M13: 0.11237733 | N13: -0.040379321 | O13: -0.0033272611 | P13: 0.15851725 | Q13: 0.254695 | R13: 0.029285389 | S13: -0.018804832 | T13: 0.014272086 | U13: 0.021568834 | V13: 0.07074806 | W13: -0.00033921634 | X13: 0.016217277 | Y13: 0.003943109 | Z13: 0.038123807 | AA13: 0.0097103168
... A16: Q4 2024 | B16: 0.12230027 | C16: -0.16406656 | D16: 0.26918524 | E16: 0.023746057 | F16: -0.027943685 | G16: -0.32473311 | H16: 0.042605586 | I16: 0.0085369918 | J16: 0.030171647 | K16: -0.004425753 | L16: -0.082983278 | M16: -0.0091767797 | N16: 0.019040965 | O16: 0.026113427 | P16: 0.051612425 | Q16: 0.026039709 | R16: 0.011763263 | S16: -0.021560419 | T16: 0.021898978 | U16: 0.023934031 | V16: 0.014721381 | W16: 0.019468645 | X16: 0.022825744 | Y16: 0.006246006 | Z16: 0.024395035 | AA16: 0.020416884

Sheet National Account By Sector
A1: Quarterly national accounts | B1: Attribute | C1: Constant Prices | D1: QoQ Real GDP | E1: YoY Real GDP | G1: QoQ Real GDP Growth by sector
A2: Added value of Agriculture, forestry and fishing sector | B2: Q4 2024 | C2: 2128.7 | D2: 0.033148903 | E2: 0.12623671 | G2: Sectors | H2: Q1 2025 | I2: Q2 2025
A3: Added value of Oil and natural gas extraction sector | B3: Q4 2024 | C3: 426.9 | D3: 0.0025833725 | E3: -0.17010109 | G3: Agriculture | H3: =D33 -> 0.026260159 | I3: =D64 -> 0.031905154
A4: Added value of Extraction of mining products sector | B4: Q4 2024 | C4: 183.7 | D4: 0.16931891 | E4: 0.24796196 | G4: Industries | H4: =SUMPRODUCT(C3:C16,D34:D47)/SUM(C3:C16) -> -0.0072279133 | I4: =SUMPRODUCT(C34:C47,D65:D78)/SUM(C34:C47) -> 0.026084224
A5: Added value of Agrifoods industries sector | B5: Q4 2024 | C5: 819.3 | D5: -0.0067887017 | E5: 0.023101898 | G5: Services | H5: =SUMPRODUCT(C17:C27,D48:D58)/SUM(C17:C27) -> -0.00027326917 | I5: =SUMPRODUCT(C48:C58,D79:D89)/SUM(C48:C58) -> 0.01580288
A6: Added value of Textile, clothing and leather industry sector | B6: Q4 2024 | C6: 562 | D6: -0.041609823 | E6: -0.030533034
A7: Added value of Oil refinery sector | B7: Q4 2024 | C7: -1.4 | D7: -1.0693069 | E7: -1.1238938
A8: Added value of Chemical industries sector | B8: Q4 2024 | C8: 264.6 | D8: -0.02 | E8: 0.032383925 | G8: YoY Real GDP Growth by sector
A9: Added value of Building materials industry, ceramics and glass sector | B9: Q4 2024 | C9: 204.9 | D9: -0.060522696 | E9: 0.0034280118 | G9: Sectors | H9: Q1 2025 | I9: Q2 2025
A10: Added value of Mechanical and electrical industries sector | B10: Q4 2024 | C10: 1025.2 | D10: 0.020404101 | E10: 0.028904055 | G10: Agriculture | H10: =E33 -> 0.072880856 | I10: =E64 -> 0.098372637
A11: Added value of Various industries sector | B11: Q4 2024 | C11: 401 | D11: -0.0019910403 | E11: -0.0064420218 | G11: Industries | H11: =SUMPRODUCT(C3:C16,E34:E47)/SUM(C3:C16) -> 0.013731089 | I11: =SUMPRODUCT(C34:C47,E65:E78)/SUM(C34:C47) -> 0.039740012
A12: Added value of Production and distribution of electricity and gas sector | B12: Q4 2024 | C12: 238.9 | D12: -0.1483066 | E12: -0.09712774 | G12: Services | H12: =SUMPRODUCT(C17:C27,E48:E58)/SUM(C17:C27) -> 0.014849809 | I12: =SUMPRODUCT(C48:C58,E79:E89)/SUM(C48:C58) -> 0.027746696
A13: Added value of Water distribution and treatment of wastewater and waste sector | B13: Q4 2024 | C13: 187.8 | D13: 0.031301483 | E13: -0.010537408
A14: Added value of Construction sector | B14: Q4 2024 | C14: 1018.8 | D14: 0.024228411 | E14: 0.018596281
A15: Added value of Trade, maintenance and repair sector | B15: Q4 2024 | C15: 2878.6 | D15: 0.015665796 | E15: 0.026238859
A16: Added value of Transportation and warehousing services sector | B16: Q4 2024 | C16: 1405.2 | D16: -0.01644852 | E16: 0.051638976
A17: Added value of Hotel, cafe and restaurant services sector | B17: Q4 2024 | C17: 782.7 | D17: 0.011632416 | E17: 0.02622263
A18: Added value of Information and communication sector | B18: Q4 2024 | C18: 894.9 | D18: 0.0075433461 | E18: 0.011758055
A19: Added value of Financial activities sector | B19: Q4 2024 | C19: 1002.6 | D19: -0.0019908421 | E19: -0.022425897
A20: Added value of Public administration and defense services sector | B20: Q4 2024 | C20: 2237.5 | D20: 0.016721952 | E20: 0.021922813
A21: Added value of Private and public education sector | B21: Q4 2024 | C21: 1608.5 | D21: 0.01106292 | E21: 0.024130905
A22: Added value of Private and public health and social action sector | B22: Q4 2024 | C22: 1075 | D22: 0.01109857 | E22: 0.014725316
A23: Added value of Other market services sector | B23: Q4 2024 | C23: 1476.9 | D23: 0.0025795941 | E23: 0.019606489
A24: Added value of Other household activities sector | B24: Q4 2024 | C24: 1634.1 | D24: 0 | E24: 0.022974834
... A30: Gross domestic product value sector | B30: Q4 2024 | C30: 24355 | D30: 0.0067544106 | E30: 0.024679827
A32: Quarterly national accounts | B32: Attribute | C32: Constant Prices | D32: QoQ Real GDP | E32: YoY Real GDP
A33: Added value of Agriculture, forestry and fishing sector | B33: Q1 2025 | C33: 2184.6 | D33: 0.026260159 | E33: 0.072880856
A34: Added value of Oil and natural gas extraction sector | B34: Q1 2025 | C34: 384.4 | D34: -0.099554931 | E34: -0.072169925
A35: Added value of Extraction of mining products sector | B35: Q1 2025 | C35: 173.1 | D35: -0.057702776 | E35: 0.16880486
A36: Added value of Agrifoods industries sector | B36: Q1 2025 | C36: 890.2 | D36: 0.086537288 | E36: 0.071110576
A37: Added value of Textile, clothing and leather industry sector | B37: Q1 2025 | C37: 571.5 | D37: 0.016903915 | E37: -0.01516457
A38: Added value of Oil refinery sector | B38: Q1 2025 | C38: 1 | D38: -1.7142857 | E38: -0.91150442
A39: Added value of Chemical industries sector | B39: Q1 2025 | C39: 251.2 | D39: -0.050642479 | E39: -0.039020658
A40: Added value of Building materials industry, ceramics and glass sector | B40: Q1 2025 | C40: 207.3 | D40: 0.011713031 | E40: -0.0067081936
A41: Added value of Mechanical and electrical industries sector | B41: Q1 2025 | C41: 968.3 | D41: -0.055501366 | E41: 0.01064607
A42: Added value of Various industries sector | B42: Q1 2025 | C42: 385.3 | D42: -0.03915212 | E42: -0.0018134715
A43: Added value of Production and distribution of electricity and gas sector | B43: Q1 2025 | C43: 247.1 | D43: 0.034323985 | E43: -0.00040453074
A44: Added value of Water distribution and treatment of wastewater and waste sector | B44: Q1 2025 | C44: 189 | D44: 0.0063897764 | E44: 0.029972752
... A61: Gross domestic product value sector | B61: Q1 2025 | C61: 24320.3 | D61: -0.0014247588 | E61: 0.01645449
A63: Quarterly national accounts | B63: Attribute | C63: Constant Prices | D63: QoQ Real GDP | E63: YoY Real GDP
A64: Added value of Agriculture, forestry and fishing sector | B64: Q2 2025 | C64: 2254.3 | D64: 0.031905154 | E64: 0.098372637
A65: Added value of Oil and natural gas extraction sector | B65: Q2 2025 | C65: 376.6 | D65: -0.020291363 | E65: -0.12050444
A66: Added value of Extraction of mining products sector | B66: Q2 2025 | C66: 206.6 | D66: 0.19352975 | E66: 0.31508593
A67: Added value of Agrifoods industries sector | B67: Q2 2025 | C67: 819.6 | D67: -0.079308021 | E67: 0.0029368576
A68: Added value of Textile, clothing and leather industry sector | B68: Q2 2025 | C68: 551.6 | D68: -0.034820647 | E68: -0.0096947935
A69: Added value of Oil refinery sector | B69: Q2 2025 | C69: 7.2 | D69: 6.2 | E69: -0.62105263
A70: Added value of Chemical industries sector | B70: Q2 2025 | C70: 264.9 | D70: 0.054538217 | E70: 0.1014553
A71: Added value of Building materials industry, ceramics and glass sector | B71: Q2 2025 | C71: 218.8 | D71: 0.055475157 | E71: 0.077301822
A72: Added value of Mechanical and electrical industries sector | B72: Q2 2025 | C72: 1063 | D72: 0.097800269 | E72: 0.096441465
A73: Added value of Various industries sector | B73: Q2 2025 | C73: 389.4 | D73: 0.010641059 | E73: 0.0140625
A74: Added value of Production and distribution of electricity and gas sector | B74: Q2 2025 | C74: 279 | D74: 0.12909753 | E74: 0.034099333
A75: Added value of Water distribution and treatment of wastewater and waste sector | B75: Q2 2025 | C75: 191.4 | D75: 0.012698413 | E75: 0.027375201
... A92: Gross domestic product value sector | B92: Q2 2025 | C92: 24766.5 | D92: 0.018346813 | E92: 0.031559262

Sheet GDP
A1: Quarterly national accounts | B1: Attribute | C1: Constant Prices | D1: QoQ Real GDP | E1: YoY Real GDP | F1: Current Prices | G1: QoQ Nominal GDP | H1: YoY Nominal GDP | I1: index
A2: Added value of Agriculture, forestry and fishing sector | B2: Q1 2010 | C2: 1498.5 | F2: 1098
A3: Added value of Agriculture, forestry and fishing sector | B3: Q2 2010 | C3: 1525.7 | D3: =(Table2_1[[#This Row],[Constant Prices]]-C2)/C2 -> 0.018151485 | F3: 1110.2 | G3: =(Table2_1[[#This Row],[Current Prices]]-F2)/F2 -> 0.011111111
A4: Added value of Agriculture, forestry and fishing sector | B4: Q3 2010 | C4: 1554.3 | D4: =(Table2_1[[#This Row],[Constant Prices]]-C3)/C3 -> 0.018745494 | F4: 1160.9 | G4: =(Table2_1[[#This Row],[Current Prices]]-F3)/F3 -> 0.045667447
A5: Added value of Agriculture, forestry and fishing sector | B5: Q4 2010 | C5: 1590.2 | D5: =(Table2_1[[#This Row],[Constant Prices]]-C4)/C4 -> 0.023097214 | F5: 1158.9 | G5: =(Table2_1[[#This Row],[Current Prices]]-F4)/F4 -> -0.0017228013
A6: Added value of Agriculture, forestry and fishing sector | B6: Q1 2011 | C6: 1659.6 | D6: =(Table2_1[[#This Row],[Constant Prices]]-C5)/C5 -> 0.043642309 | E6: =(Table2_1[[#This Row],[Constant Prices]]-C2)/C2 -> 0.10750751 | F6: 1231.3 | G6: =(Table2_1[[#This Row],[Current Prices]]-F5)/F5 -> 0.062473035 | H6: =(Table2_1[[#This Row],[Current Prices]]-F2)/F2 -> 0.12140255
A7: Added value of Agriculture, forestry and fishing sector | B7: Q2 2011 | C7: 1696.8 | D7: =(Table2_1[[#This Row],[Constant Prices]]-C6)/C6 -> 0.02241504 | E7: =(Table2_1[[#This Row],[Constant Prices]]-C3)/C3 -> 0.11214524 | F7: 1241.5 | G7: =(Table2_1[[#This Row],[Current Prices]]-F6)/F6 -> 0.0082839276 | H7: =(Table2_1[[#This Row],[Current Prices]]-F3)/F3 -> 0.11826698
A8: Added value of Agriculture, forestry and fishing sector | B8: Q3 2011 | C8: 1736.4 | D8: =(Table2_1[[#This Row],[Constant Prices]]-C7)/C7 -> 0.023338048 | E8: =(Table2_1[[#This Row],[Constant Prices]]-C4)/C4 -> 0.11715885 | F8: 1311.5 | G8: =(Table2_1[[#This Row],[Current Prices]]-F7)/F7 -> 0.056383407 | H8: =(Table2_1[[#This Row],[Current Prices]]-F4)/F4 -> 0.12972694
A9: Added value of Agriculture, forestry and fishing sector | B9: Q4 2011 | C9: 1777.9 | D9: =(Table2_1[[#This Row],[Constant Prices]]-C8)/C8 -> 0.023900023 | E9: =(Table2_1[[#This Row],[Constant Prices]]-C5)/C5 -> 0.11803547 | F9: 1348.8 | G9: =(Table2_1[[#This Row],[Current Prices]]-F8)/F8 -> 0.028440717 | H9: =(Table2_1[[#This Row],[Current Prices]]-F5)/F5 -> 0.16386228 | I9: 1
A10: Added value of Agriculture, forestry and fishing sector | B10: Q1 2012 | C10: 1808.4 | D10: =(Table2_1[[#This Row],[Constant Prices]]-C9)/C9 -> 0.017155071 | E10: =(Table2_1[[#This Row],[Constant Prices]]-C6)/C6 -> 0.089660159 | F10: 1472.1 | G10: =(Table2_1[[#This Row],[Current Prices]]-F9)/F9 -> 0.091414591 | H10: =(Table2_1[[#This Row],[Current Prices]]-F6)/F6 -> 0.19556566
A11: Added value of Agriculture, forestry and fishing sector | B11: Q2 2012 | C11: 1855.3 | D11: =(Table2_1[[#This Row],[Constant Prices]]-C10)/C10 -> 0.025934528 | E11: =(Table2_1[[#This Row],[Constant Prices]]-C7)/C7 -> 0.093411127 | F11: 1516.6 | G11: =(Table2_1[[#This Row],[Current Prices]]-F10)/F10 -> 0.030228925 | H11: =(Table2_1[[#This Row],[Current Prices]]-F7)/F7 -> 0.22158679
A12: Added value of Agriculture, forestry and fishing sector | B12: Q3 2012 | C12: 1891.6 | D12: =(Table2_1[[#This Row],[Constant Prices]]-C11)/C11 -> 0.019565569 | E12: =(Table2_1[[#This Row],[Constant Prices]]-C8)/C8 -> 0.089380327 | F12: 1562.1 | G12: =(Table2_1[[#This Row],[Current Prices]]-F11)/F11 -> 0.030001319 | H12: =(Table2_1[[#This Row],[Current Prices]]-F8)/F8 -> 0.19107892
A13: Added value of Agriculture, forestry and fishing sector | B13: Q4 2012 | C13: 1917.7 | D13: =(Table2_1[[#This Row],[Constant Prices]]-C12)/C12 -> 0.013797843 | E13: =(Table2_1[[#This Row],[Constant Prices]]-C9)/C9 -> 0.078632094 | F13: 1582.7 | G13: =(Table2_1[[#This Row],[Current Prices]]-F12)/F12 -> 0.013187376 | H13: =(Table2_1[[#This Row],[Current Prices]]-F9)/F9 -> 0.1734134 | I13: 2
A14: Added value of Agriculture, forestry and fishing sector | B14: Q1 2013 | C14: 1718 | D14: =(Table2_1[[#This Row],[Constant Prices]]-C13)/C13 -> -0.10413516 | E14: =(Table2_1[[#This Row],[Constant Prices]]-C10)/C10 -> -0.04998894 | F14: 1536.6 | G14: =(Table2_1[[#This Row],[Current Prices]]-F13)/F13 -> -0.02912744 | H14: =(Table2_1[[#This Row],[Current Prices]]-F10)/F10 -> 0.043814958
A15: Added value of Agriculture, forestry and fishing sector | B15: Q2 2013 | C15: 1754.5 | D15: =(Table2_1[[#This Row],[Constant Prices]]-C14)/C14 -> 0.021245634 | E15: =(Table2_1[[#This Row],[Constant Prices]]-C11)/C11 -> -0.054330836 | F15: 1556 | G15: =(Table2_1[[#This Row],[Current Prices]]-F14)/F14 -> 0.012625277 | H15: =(Table2_1[[#This Row],[Current Prices]]-F11)/F11 -> 0.025979164
A16: Added value of Agriculture, forestry and fishing sector | B16: Q3 2013 | C16: 1790.4 | D16: =(Table2_1[[#This Row],[Constant Prices]]-C15)/C15 -> 0.02046167 | E16: =(Table2_1[[#This Row],[Constant Prices]]-C12)/C12 -> -0.053499683 | F16: 1585.9 | G16: =(Table2_1[[#This Row],[Current Prices]]-F15)/F15 -> 0.019215938 | H16: =(Table2_1[[#This Row],[Current Prices]]-F12)/F12 -> 0.0152359
A17: Added value of Agriculture, forestry and fishing sector | B17: Q4 2013 | C17: 1838.2 | D17: =(Table2_1[[#This Row],[Constant Prices]]-C16)/C16 -> 0.026697945 | E17: =(Table2_1[[#This Row],[Constant Prices]]-C13)/C13 -> -0.041455911 | F17: 1625 | G17: =(Table2_1[[#This Row],[Current Prices]]-F16)/F16 -> 0.02465477 | H17: =(Table2_1[[#This Row],[Current Prices]]-F13)/F13 -> 0.02672648 | I17: 3
A18: Added value of Agriculture, forestry and fishing sector | B18: Q1 2014 | C18: 1869.7 | D18: =(Table2_1[[#This Row],[Constant Prices]]-C17)/C17 -> 0.017136329 | E18: =(Table2_1[[#This Row],[Constant Prices]]-C14)/C14 -> 0.088300349 | F18: 1747.8 | G18: =(Table2_1[[#This Row],[Current Prices]]-F17)/F17 -> 0.075569231 | H18: =(Table2_1[[#This Row],[Current Prices]]-F14)/F14 -> 0.13744631
A19: Added value of Agriculture, forestry and fishing sector | B19: Q2 2014 | C19: 1932.5 | D19: =(Table2_1[[#This Row],[Constant Prices]]-C18)/C18 -> 0.033588276 | E19: =(Table2_1[[#This Row],[Constant Prices]]-C15)/C15 -> 0.10145341 | F19: 1794 | G19: =(Table2_1[[#This Row],[Current Prices]]-F18)/F18 -> 0.02643323 | H19: =(Table2_1[[#This Row],[Current Prices]]-F15)/F15 -> 0.1529563
A20: Added value of Agriculture, forestry and fishing sector | B20: Q3 2014 | C20: 1971.9 | D20: =(Table2_1[[#This Row],[Constant Prices]]-C19)/C19 -> 0.020388098 | E20: =(Table2_1[[#This Row],[Constant Prices]]-C16)/C16 -> 0.10137399 | F20: 1888.6 | G20: =(Table2_1[[#This Row],[Current Prices]]-F19)/F19 -> 0.052731327 | H20: =(Table2_1[[#This Row],[Current Prices]]-F16)/F16 -> 0.19086954
A21: Added value of Agriculture, forestry and fishing sector | B21: Q4 2014 | C21: 1987.4 | D21: =(Table2_1[[#This Row],[Constant Prices]]-C20)/C20 -> 0.0078604392 | E21: =(Table2_1[[#This Row],[Constant Prices]]-C17)/C17 -> 0.081166358 | F21: 1885.1 | G21: =(Table2_1[[#This Row],[Current Prices]]-F20)/F20 -> -0.0018532246 | H21: =(Table2_1[[#This Row],[Current Prices]]-F17)/F17 -> 0.16006154 | I21: 4
A22: Added value of Agriculture, forestry and fishing sector | B22: Q1 2015 | C22: 2033.7 | D22: =(Table2_1[[#This Row],[Constant Prices]]-C21)/C21 -> 0.02329677 | E22: =(Table2_1[[#This Row],[Constant Prices]]-C18)/C18 -> 0.087714607 | F22: 2006.4 | G22: =(Table2_1[[#This Row],[Current Prices]]-F21)/F21 -> 0.064346719 | H22: =(Table2_1[[#This Row],[Current Prices]]-F18)/F18 -> 0.14795743
A23: Added value of Agriculture, forestry and fishing sector | B23: Q2 2015 | C23: 2043.2 | D23: =(Table2_1[[#This Row],[Constant Prices]]-C22)/C22 -> 0.0046712888 | E23: =(Table2_1[[#This Row],[Constant Prices]]-C19)/C19 -> 0.057283312 | F23: 2006 | G23: =(Table2_1[[#This Row],[Current Prices]]-F22)/F22 -> -0.00019936204 | H23: =(Table2_1[[#This Row],[Current Prices]]-F19)/F19 -> 0.11817168
A24: Added value of Agriculture, forestry and fishing sector | B24: Q3 2015 | C24: 2080.3 | D24: =(Table2_1[[#This Row],[Constant Prices]]-C23)/C23 -> 0.018157792 | E24: =(Table2_1[[#This Row],[Constant Prices]]-C20)/C20 -> 0.054972362 | F24: 2113 | G24: =(Table2_1[[#This Row],[Current Prices]]-F23)/F23 -> 0.05333998 | H24: =(Table2_1[[#This Row],[Current Prices]]-F20)/F20 -> 0.11881817
A25: Added value of Agriculture, forestry and fishing sector | B25: Q4 2015 | C25: 2110 | D25: =(Table2_1[[#This Row],[Constant Prices]]-C24)/C24 -> 0.014276787 | E25: =(Table2_1[[#This Row],[Constant Prices]]-C21)/C21 -> 0.061688638 | F25: 2141.8 | G25: =(Table2_1[[#This Row],[Current Prices]]-F24)/F24 -> 0.01362991 | H25: =(Table2_1[[#This Row],[Current Prices]]-F21)/F21 -> 0.13617315 | I25: 5
A26: Added value of Agriculture, forestry and fishing sector | B26: Q1 2016 | C26: 1848.5 | D26: =(Table2_1[[#This Row],[Constant Prices]]-C25)/C25 -> -0.12393365 | E26: =(Table2_1[[#This Row],[Constant Prices]]-C22)/C22 -> -0.091065546 | F26: 1950.5 | G26: =(Table2_1[[#This Row],[Current Prices]]-F25)/F25 -> -0.089317397 | H26: =(Table2_1[[#This Row],[Current Prices]]-F22)/F22 -> -0.027860845
A27: Added value of Agriculture, forestry and fishing sector | B27: Q2 2016 | C27: 1879.4 | D27: =(Table2_1[[#This Row],[Constant Prices]]-C26)/C26 -> 0.016716256 | E27: =(Table2_1[[#This Row],[Constant Prices]]-C23)/C23 -> -0.080168363 | F27: 1988.8 | G27: =(Table2_1[[#This Row],[Current Prices]]-F26)/F26 -> 0.019635991 | H27: =(Table2_1[[#This Row],[Current Prices]]-F23)/F23 -> -0.0085742772
A28: Added value of Agriculture, forestry and fishing sector | B28: Q3 2016 | C28: 1928.3 | D28: =(Table2_1[[#This Row],[Constant Prices]]-C27)/C27 -> 0.026018942 | E28: =(Table2_1[[#This Row],[Constant Prices]]-C24)/C24 -> -0.073066385 | F28: 2071 | G28: =(Table2_1[[#This Row],[Current Prices]]-F27)/F27 -> 0.041331456 | H28: =(Table2_1[[#This Row],[Current Prices]]-F24)/F24 -> -0.019876952
A29: Added value of Agriculture, forestry and fishing sector | B29: Q4 2016 | C29: 1977.9 | D29: =(Table2_1[[#This Row],[Constant Prices]]-C28)/C28 -> 0.025722139 | E29: =(Table2_1[[#This Row],[Constant Prices]]-C25)/C25 -> -0.062606635 | F29: 2113.4 | G29: =(Table2_1[[#This Row],[Current Prices]]-F28)/F28 -> 0.020473201 | H29: =(Table2_1[[#This Row],[Current Prices]]-F25)/F25 -> -0.013259875 | I29: 6
A30: Added value of Agriculture, forestry and fishing sector | B30: Q1 2017 | C30: 1985.5 | D30: =(Table2_1[[#This Row],[Constant Prices]]-C29)/C29 -> 0.0038424592 | E30: =(Table2_1[[#This Row],[Constant Prices]]-C26)/C26 -> 0.074114147 | F30: 2238.7 | G30: =(Table2_1[[#This Row],[Current Prices]]-F29)/F29 -> 0.059288351 | H30: =(Table2_1[[#This Row],[Current Prices]]-F26)/F26 -> 0.14775699
A31: Added value of Agriculture, forestry and fishing sector | B31: Q2 2017 | C31: 2004.9 | D31: =(Table2_1[[#This Row],[Constant Prices]]-C30)/C30 -> 0.0097708386 | E31: =(Table2_1[[#This Row],[Constant Prices]]-C27)/C27 -> 0.066776631 | F31: 2277.8 | G31: =(Table2_1[[#This Row],[Current Prices]]-F30)/F30 -> 0.017465493 | H31: =(Table2_1[[#This Row],[Current Prices]]-F27)/F27 -> 0.14531376
A32: Added value of Agriculture, forestry and fishing sector | B32: Q3 2017 | C32: 2039.4 | D32: =(Table2_1[[#This Row],[Constant Prices]]-C31)/C31 -> 0.017207841 | E32: =(Table2_1[[#This Row],[Constant Prices]]-C28)/C28 -> 0.057615516 | F32: 2324 | G32: =(Table2_1[[#This Row],[Current Prices]]-F31)/F31 -> 0.020282729 | H32: =(Table2_1[[#This Row],[Current Prices]]-F28)/F28 -> 0.12216321
A33: Added value of Agriculture, forestry and fishing sector | B33: Q4 2017 | C33: 2051.9 | D33: =(Table2_1[[#This Row],[Constant Prices]]-C32)/C32 -> 0.0061292537 | E33: =(Table2_1[[#This Row],[Constant Prices]]-C29)/C29 -> 0.037413418 | F33: 2326.3 | G33: =(Table2_1[[#This Row],[Current Prices]]-F32)/F32 -> 0.00098967298 | H33: =(Table2_1[[#This Row],[Current Prices]]-F29)/F29 -> 0.10073815 | I33: 7
A34: Added value of Agriculture, forestry and fishing sector | B34: Q1 2018 | C34: 2150.9 | D34: =(Table2_1[[#This Row],[Constant Prices]]-C33)/C33 -> 0.048247965 | E34: =(Table2_1[[#This Row],[Constant Prices]]-C30)/C30 -> 0.083303954 | F34: 2844 | G34: =(Table2_1[[#This Row],[Current Prices]]-F33)/F33 -> 0.22254223 | H34: =(Table2_1[[#This Row],[Current Prices]]-F30)/F30 -> 0.27038013
A35: Added value of Agriculture, forestry and fishing sector | B35: Q2 2018 | C35: 2110.6 | D35: =(Table2_1[[#This Row],[Constant Prices]]-C34)/C34 -> -0.018736343 | E35: =(Table2_1[[#This Row],[Constant Prices]]-C31)/C31 -> 0.052720834 | F35: 2756.8 | G35: =(Table2_1[[#This Row],[Current Prices]]-F34)/F34 -> -0.030661041 | H35: =(Table2_1[[#This Row],[Current Prices]]-F31)/F31 -> 0.21029063
A36: Added value of Agriculture, forestry and fishing sector | B36: Q3 2018 | C36: 2109 | D36: =(Table2_1[[#This Row],[Constant Prices]]-C35)/C35 -> -0.00075807827 | E36: =(Table2_1[[#This Row],[Constant Prices]]-C32)/C32 -> 0.034127685 | F36: 2750.1 | G36: =(Table2_1[[#This Row],[Current Prices]]-F35)/F35 -> -0.002430354 | H36: =(Table2_1[[#This Row],[Current Prices]]-F32)/F32 -> 0.18334768
A37: Added value of Agriculture, forestry and fishing sector | B37: Q4 2018 | C37: 2186.1 | D37: =(Table2_1[[#This Row],[Constant Prices]]-C36)/C36 -> 0.03655761 | E37: =(Table2_1[[#This Row],[Constant Prices]]-C33)/C33 -> 0.065402797 | F37: 2821.7 | G37: =(Table2_1[[#This Row],[Current Prices]]-F36)/F36 -> 0.026035417 | H37: =(Table2_1[[#This Row],[Current Prices]]-F33)/F33 -> 0.2129562 | I37: 8
A38: Added value of Agriculture, forestry and fishing sector | B38: Q1 2019 | C38: 2197.2 | D38: =(Table2_1[[#This Row],[Constant Prices]]-C37)/C37 -> 0.0050775353 | E38: =(Table2_1[[#This Row],[Constant Prices]]-C34)/C34 -> 0.021525873 | F38: 2932.7 | G38: =(Table2_1[[#This Row],[Current Prices]]-F37)/F37 -> 0.039337988 | H38: =(Table2_1[[#This Row],[Current Prices]]-F34)/F34 -> 0.031188467
A39: Added value of Agriculture, forestry and fishing sector | B39: Q2 2019 | C39: 2283.6 | D39: =(Table2_1[[#This Row],[Constant Prices]]-C38)/C38 -> 0.039322774 | E39: =(Table2_1[[#This Row],[Constant Prices]]-C35)/C35 -> 0.081967213 | F39: 3007.4 | G39: =(Table2_1[[#This Row],[Current Prices]]-F38)/F38 -> 0.025471409 | H39: =(Table2_1[[#This Row],[Current Prices]]-F35)/F35 -> 0.090902496
A40: Added value of Agriculture, forestry and fishing sector | B40: Q3 2019 | C40: 2310.7 | D40: =(Table2_1[[#This Row],[Constant Prices]]-C39)/C39 -> 0.011867227 | E40: =(Table2_1[[#This Row],[Constant Prices]]-C36)/C36 -> 0.095637743 | F40: 3091 | G40: =(Table2_1[[#This Row],[Current Prices]]-F39)/F39 -> 0.027798098 | H40: =(Table2_1[[#This Row],[Current Prices]]-F36)/F36 -> 0.12395913
A41: Added value of Agriculture, forestry and fishing sector | B41: Q4 2019 | C41: 2272 | D41: =(Table2_1[[#This Row],[Constant Prices]]-C40)/C40 -> -0.016748172 | E41: =(Table2_1[[#This Row],[Constant Prices]]-C37)/C37 -> 0.039293719 | F41: 2978.4 | G41: =(Table2_1[[#This Row],[Current Prices]]-F40)/F40 -> -0.03642834 | H41: =(Table2_1[[#This Row],[Current Prices]]-F37)/F37 -> 0.055533898 | I41: 9
A42: Added value of Agriculture, forestry and fishing sector | B42: Q1 2020 | C42: 2287.5 | D42: =(Table2_1[[#This Row],[Constant Prices]]-C41)/C41 -> 0.0068221831 | E42: =(Table2_1[[#This Row],[Constant Prices]]-C38)/C38 -> 0.041097761 | F42: 3033 | G42: =(Table2_1[[#This Row],[Current Prices]]-F41)/F41 -> 0.01833199 | H42: =(Table2_1[[#This Row],[Current Prices]]-F38)/F38 -> 0.034200566
A43: Added value of Agriculture, forestry and fishing sector | B43: Q2 2020 | C43: 2245.9 | D43: =(Table2_1[[#This Row],[Constant Prices]]-C42)/C42 -> -0.018185792 | E43: =(Table2_1[[#This Row],[Constant Prices]]-C39)/C39 -> -0.016509021 | F43: 3139.9 | G43: =(Table2_1[[#This Row],[Current Prices]]-F42)/F42 -> 0.035245631 | H43: =(Table2_1[[#This Row],[Current Prices]]-F39)/F39 -> 0.04405799
A44: Added value of Agriculture, forestry and fishing sector | B44: Q3 2020 | C44: 2261.7 | D44: =(Table2_1[[#This Row],[Constant Prices]]-C43)/C43 -> 0.0070350416 | E44: =(Table2_1[[#This Row],[Constant Prices]]-C40)/C40 -> -0.021205695 | F44: 3078.6 | G44: =(Table2_1[[#This Row],[Current Prices]]-F43)/F43 -> -0.019522915 | H44: =(Table2_1[[#This Row],[Current Prices]]-F40)/F40 -> -0.0040116467
A45: Added value of Agriculture, forestry and fishing sector | B45: Q4 2020 | C45: 2300.6 | D45: =(Table2_1[[#This Row],[Constant Prices]]-C44)/C44 -> 0.017199452 | E45: =(Table2_1[[#This Row],[Constant Prices]]-C41)/C41 -> 0.012588028 | F45: 3166.8 | G45: =(Table2_1[[#This Row],[Current Prices]]-F44)/F44 -> 0.028649386 | H45: =(Table2_1[[#This Row],[Current Prices]]-F41)/F41 -> 0.063255439 | I45: 10
A46: Added value of Agriculture, forestry and fishing sector | B46: Q1 2021 | C46: 2172.6 | D46: =(Table2_1[[#This Row],[Constant Prices]]-C45)/C45 -> -0.05563766 | E46: =(Table2_1[[#This Row],[Constant Prices]]-C42)/C42 -> -0.050229508 | F46: 3175 | G46: =(Table2_1[[#This Row],[Current Prices]]-F45)/F45 -> 0.0025893647 | H46: =(Table2_1[[#This Row],[Current Prices]]-F42)/F42 -> 0.046818332
A47: Added value of Agriculture, forestry and fishing sector | B47: Q2 2021 | C47: 2191.4 | D47: =(Table2_1[[#This Row],[Constant Prices]]-C46)/C46 -> 0.0086532265 | E47: =(Table2_1[[#This Row],[Constant Prices]]-C43)/C43 -> -0.024266441 | F47: 3314.8 | G47: =(Table2_1[[#This Row],[Current Prices]]-F46)/F46 -> 0.044031496 | H47: =(Table2_1[[#This Row],[Current Prices]]-F43)/F43 -> 0.055702411
A48: Added value of Agriculture, forestry and fishing sector | B48: Q3 2021 | C48: 2257.3 | D48: =(Table2_1[[#This Row],[Constant Prices]]-C47)/C47 -> 0.0300721 | E48: =(Table2_1[[#This Row],[Constant Prices]]-C44)/C44 -> -0.0019454393 | F48: 3385.3 | G48: =(Table2_1[[#This Row],[Current Prices]]-F47)/F47 -> 0.021268251 | H48: =(Table2_1[[#This Row],[Current Prices]]-F44)/F44 -> 0.099623205
A49: Added value of Agriculture, forestry and fishing sector | B49: Q4 2021 | C49: 2262.4 | D49: =(Table2_1[[#This Row],[Constant Prices]]-C48)/C48 -> 0.0022593364 | E49: =(Table2_1[[#This Row],[Constant Prices]]-C45)/C45 -> -0.016604364 | F49: 3397.9 | G49: =(Table2_1[[#This Row],[Current Prices]]-F48)/F48 -> 0.0037219744 | H49: =(Table2_1[[#This Row],[Current Prices]]-F45)/F45 -> 0.072975875 | I49: 11
A50: Added value of Agriculture, forestry and fishing sector | B50: Q1 2022 | C50: 2251.5 | D50: =(Table2_1[[#This Row],[Constant Prices]]-C49)/C49 -> -0.0048178925 | E50: =(Table2_1[[#This Row],[Constant Prices]]-C46)/C46 -> 0.036315935 | F50: 3574.3 | G50: =(Table2_1[[#This Row],[Current Prices]]-F49)/F49 -> 0.051914418 | H50: =(Table2_1[[#This Row],[Current Prices]]-F46)/F46 -> 0.12576378
A51: Added value of Agriculture, forestry and fishing sector | B51: Q2 2022 | C51: 2259.6 | D51: =(Table2_1[[#This Row],[Constant Prices]]-C50)/C50 -> 0.0035976016 | E51: =(Table2_1[[#This Row],[Constant Prices]]-C47)/C47 -> 0.031121657 | F51: 3751.6 | G51: =(Table2_1[[#This Row],[Current Prices]]-F50)/F50 -> 0.049604118 | H51: =(Table2_1[[#This Row],[Current Prices]]-F47)/F47 -> 0.13177266
A52: Added value of Agriculture, forestry and fishing sector | B52: Q3 2022 | C52: 2293.5 | D52: =(Table2_1[[#This Row],[Constant Prices]]-C51)/C51 -> 0.015002655 | E52: =(Table2_1[[#This Row],[Constant Prices]]-C48)/C48 -> 0.016036858 | F52: 3802.4 | G52: =(Table2_1[[#This Row],[Current Prices]]-F51)/F51 -> 0.013540889 | H52: =(Table2_1[[#This Row],[Current Prices]]-F48)/F48 -> 0.12320917
A53: Added value of Agriculture, forestry and fishing sector | B53: Q4 2022 | C53: 2262.4 | D53: =(Table2_1[[#This Row],[Constant Prices]]-C52)/C52 -> -0.013560061 | E53: =(Table2_1[[#This Row],[Constant Prices]]-C49)/C49 -> 0 | F53: 3814.9 | G53: =(Table2_1[[#This Row],[Current Prices]]-F52)/F52 -> 0.0032873974 | H53: =(Table2_1[[#This Row],[Current Prices]]-F49)/F49 -> 0.12272286 | I53: 12
A54: Added value of Agriculture, forestry and fishing sector | B54: Q1 2023 | C54: 1979.9 | D54: =(Table2_1[[#This Row],[Constant Prices]]-C53)/C53 -> -0.1248674 | E54: =(Table2_1[[#This Row],[Constant Prices]]-C50)/C50 -> -0.12063069 | F54: 3514.2 | G54: =(Table2_1[[#This Row],[Current Prices]]-F53)/F53 -> -0.078822512 | H54: =(Table2_1[[#This Row],[Current Prices]]-F50)/F50 -> -0.016814481
A55: Added value of Agriculture, forestry and fishing sector | B55: Q2 2023 | C55: 1877.8 | D55: =(Table2_1[[#This Row],[Constant Prices]]-C54)/C54 -> -0.051568261 | E55: =(Table2_1[[#This Row],[Constant Prices]]-C51)/C51 -> -0.16896796 | F55: 3463.9 | G55: =(Table2_1[[#This Row],[Current Prices]]-F54)/F54 -> -0.014313357 | H55: =(Table2_1[[#This Row],[Current Prices]]-F51)/F51 -> -0.07668728
A56: Added value of Agriculture, forestry and fishing sector | B56: Q3 2023 | C56: 1847.8 | D56: =(Table2_1[[#This Row],[Constant Prices]]-C55)/C55 -> -0.015976142 | E56: =(Table2_1[[#This Row],[Constant Prices]]-C52)/C52 -> -0.19433181 | F56: 3404.8 | G56: =(Table2_1[[#This Row],[Current Prices]]-F55)/F55 -> -0.017061693 | H56: =(Table2_1[[#This Row],[Current Prices]]-F52)/F52 -> -0.10456554
A57: Added value of Agriculture, forestry and fishing sector | B57: Q4 2023 | C57: 1890.1 | D57: =(Table2_1[[#This Row],[Constant Prices]]-C56)/C56 -> 0.022892088 | E57: =(Table2_1[[#This Row],[Constant Prices]]-C53)/C53 -> -0.16455976 | F57: 3586.5 | G57: =(Table2_1[[#This Row],[Current Prices]]-F56)/F56 -> 0.053365836 | H57: =(Table2_1[[#This Row],[Current Prices]]-F53)/F53 -> -0.059870508 | I57: 13
A58: Added value of Agriculture, forestry and fishing sector | B58: Q1 2024 | C58: 2036.2 | D58: =(Table2_1[[#This Row],[Constant Prices]]-C57)/C57 -> 0.077297497 | E58: =(Table2_1[[#This Row],[Constant Prices]]-C54)/C54 -> 0.02843578 | F58: 3709.4 | G58: =(Table2_1[[#This Row],[Current Prices]]-F57)/F57 -> 0.034267392 | H58: =(Table2_1[[#This Row],[Current Prices]]-F54)/F54 -> 0.05554607
A59: Added value of Agriculture, forestry and fishing sector | B59: Q2 2024 | C59: 2052.4 | D59: =(Table2_1[[#This Row],[Constant Prices]]-C58)/C58 -> 0.0079559965 | E59: =(Table2_1[[#This Row],[Constant Prices]]-C55)/C55 -> 0.092981148 | F59: 3843.4 | G59: =(Table2_1[[#This Row],[Current Prices]]-F58)/F58 -> 0.036124441 | H59: =(Table2_1[[#This Row],[Current Prices]]-F55)/F55 -> 0.10955859
A60: Added value of Agriculture, forestry and fishing sector | B60: Q3 2024 | C60: 2060.4 | D60: =(Table2_1[[#This Row],[Constant Prices]]-C59)/C59 -> 0.0038978757 | E60: =(Table2_1[[#This Row],[Constant Prices]]-C56)/C56 -> 0.11505574 | F60: 3856.7 | G60: =(Table2_1[[#This Row],[Current Prices]]-F59)/F59 -> 0.0034604777 | H60: =(Table2_1[[#This Row],[Current Prices]]-F56)/F56 -> 0.13272439
A61: Added value of Agriculture, forestry and fishing sector | B61: Q4 2024 | C61: 2128.7 | D61: =(Table2_1[[#This Row],[Constant Prices]]-C60)/C60 -> 0.033148903 | E61: =(Table2_1[[#This Row],[Constant Prices]]-C57)/C57 -> 0.12623671 | F61: =Table2_1[[#This Row],[Constant Prices]]*AVERAGE(Inflation!$C$72:$C$74)*0.01 -> 3853.6566 | G61: =(Table2_1[[#This Row],[Current Prices]]-F60)/F60 -> -0.00078912888 | H61: =(Table2_1[[#This Row],[Current Prices]]-F57)/F57 -> 0.074489493 | I61: 14
A62: Added value of Agriculture, forestry and fishing sector | B62: Q1 2025 | C62: 2184.6 | D62: =(Table2_1[[#This Row],[Constant Prices]]-C61)/C61 -> 0.026260159 | E62: =(Table2_1[[#This Row],[Constant Prices]]-C58)/C58 -> 0.072880856 | F62: =Table2_1[[#This Row],[Constant Prices]]*AVERAGE(Inflation!$C$75:$C$77)*0.01 -> 3985.4386 | G62: =(Table2_1[[#This Row],[Current Prices]]-F61)/F61 -> 0.034196621 | H62: =(Table2_1[[#This Row],[Current Prices]]-F58)/F58 -> 0.07441597
A63: Added value of Agriculture, forestry and fishing sector | B63: Q2 2025 | C63: 2254.3 | D63: =(Table2_1[[#This Row],[Constant Prices]]-C62)/C62 -> 0.031905154 | E63: =(Table2_1[[#This Row],[Constant Prices]]-C59)/C59 -> 0.098372637 | F63: =Table2_1[[#This Row],[Constant Prices]]*AVERAGE(Inflation!$C$78:$C$80)*0.01 -> 4177.9693 | G63: =(Table2_1[[#This Row],[Current Prices]]-F62)/F62 -> 0.048308543 | H63: =(Table2_1[[#This Row],[Current Prices]]-F59)/F59 -> 0.087050355
A64: Added value of Oil and natural gas extraction sector | B64: Q1 2010 | C64: 1285 | F64: 965.2
A65: Added value of Oil and natural gas extraction sector | B65: Q2 2010 | C65: 1269.4 | D65: =(Table2_1[[#This Row],[Constant Prices]]-C64)/C64 -> -0.012140078 | F65: 975.8 | G65: =(Table2_1[[#This Row],[Current Prices]]-F64)/F64 -> 0.01098218
A66: Added value of Oil and natural gas extraction sector | B66: Q3 2010 | C66: 1287.7 | D66: =(Table2_1[[#This Row],[Constant Prices]]-C65)/C65 -> 0.01441626 | F66: 1033.4 | G66: =(Table2_1[[#This Row],[Current Prices]]-F65)/F65 -> 0.059028489
A67: Added value of Oil and natural gas extraction sector | B67: Q4 2010 | C67: 1071.3 | D67: =(Table2_1[[#This Row],[Constant Prices]]-C66)/C66 -> -0.16805156 | F67: 1058.6 | G67: =(Table2_1[[#This Row],[Current Prices]]-F66)/F66 -> 0.024385524
A68: Added value of Oil and natural gas extraction sector | B68: Q1 2011 | C68: 1021 | D68: =(Table2_1[[#This Row],[Constant Prices]]-C67)/C67 -> -0.046952301 | E68: =(Table2_1[[#This Row],[Constant Prices]]-C64)/C64 -> -0.20544747 | F68: 1149.4 | G68: =(Table2_1[[#This Row],[Current Prices]]-F67)/F67 -> 0.085773663 | H68: =(Table2_1[[#This Row],[Current Prices]]-F64)/F64 -> 0.19084128
A69: Added value of Oil and natural gas extraction sector | B69: Q2 2011 | C69: 1133.4 | D69: =(Table2_1[[#This Row],[Constant Prices]]-C68)/C68 -> 0.11008815 | E69: =(Table2_1[[#This Row],[Constant Prices]]-C65)/C65 -> -0.10713723 | F69: 1173.4 | G69: =(Table2_1[[#This Row],[Current Prices]]-F68)/F68 -> 0.020880459 | H69: =(Table2_1[[#This Row],[Current Prices]]-F65)/F65 -> 0.20250051
A70: Added value of Oil and natural gas extraction sector | B70: Q3 2011 | C70: 1144.2 | D70: =(Table2_1[[#This Row],[Constant Prices]]-C69)/C69 -> 0.0095288512 | E70: =(Table2_1[[#This Row],[Constant Prices]]-C66)/C66 -> -0.111439 | F70: 1198.4 | G70: =(Table2_1[[#This Row],[Current Prices]]-F69)/F69 -> 0.021305608 | H70: =(Table2_1[[#This Row],[Current Prices]]-F66)/F66 -> 0.15966712
A71: Added value of Oil and natural gas extraction sector | B71: Q4 2011 | C71: 989.7 | D71: =(Table2_1[[#This Row],[Constant Prices]]-C70)/C70 -> -0.13502884 | E71: =(Table2_1[[#This Row],[Constant Prices]]-C67)/C67 -> -0.07616914 | F71: 1215.7 | G71: =(Table2_1[[#This Row],[Current Prices]]-F70)/F70 -> 0.014435915 | H71: =(Table2_1[[#This Row],[Current Prices]]-F67)/F67 -> 0.14840355 | I71: 1
A72: Added value of Oil and natural gas extraction sector | B72: Q1 2012 | C72: 1012.2 | D72: =(Table2_1[[#This Row],[Constant Prices]]-C71)/C71 -> 0.022734162 | E72: =(Table2_1[[#This Row],[Constant Prices]]-C68)/C68 -> -0.008619001 | F72: 1256 | G72: =(Table2_1[[#This Row],[Current Prices]]-F71)/F71 -> 0.033149626 | H72: =(Table2_1[[#This Row],[Current Prices]]-F68)/F68 -> 0.09274404
A73: Added value of Oil and natural gas extraction sector | B73: Q2 2012 | C73: 1027.7 | D73: =(Table2_1[[#This Row],[Constant Prices]]-C72)/C72 -> 0.015313179 | E73: =(Table2_1[[#This Row],[Constant Prices]]-C69)/C69 -> -0.09325922 | F73: 1289.6 | G73: =(Table2_1[[#This Row],[Current Prices]]-F72)/F72 -> 0.026751592 | H73: =(Table2_1[[#This Row],[Current Prices]]-F69)/F69 -> 0.099028464
A74: Added value of Oil and natural gas extraction sector | B74: Q3 2012 | C74: 1028.8 | D74: =(Table2_1[[#This Row],[Constant Prices]]-C73)/C73 -> 0.0010703513 | E74: =(Table2_1[[#This Row],[Constant Prices]]-C70)/C70 -> -0.10085649 | F74: 1293.7 | G74: =(Table2_1[[#This Row],[Current Prices]]-F73)/F73 -> 0.0031792804 | H74: =(Table2_1[[#This Row],[Current Prices]]-F70)/F70 -> 0.079522697
A75: Added value of Oil and natural gas extraction sector | B75: Q4 2012 | C75: 1062.2 | D75: =(Table2_1[[#This Row],[Constant Prices]]-C74)/C74 -> 0.032465008 | E75: =(Table2_1[[#This Row],[Constant Prices]]-C71)/C71 -> 0.073254522 | F75: 1361.1 | G75: =(Table2_1[[#This Row],[Current Prices]]-F74)/F74 -> 0.052098632 | H75: =(Table2_1[[#This Row],[Current Prices]]-F71)/F71 -> 0.11960188 | I75: 2
A76: Added value of Oil and natural gas extraction sector | B76: Q1 2013 | C76: 953.2 | D76: =(Table2_1[[#This Row],[Constant Prices]]-C75)/C75 -> -0.10261721 | E76: =(Table2_1[[#This Row],[Constant Prices]]-C72)/C72 -> -0.058288876 | F76: 1331.5 | G76: =(Table2_1[[#This Row],[Current Prices]]-F75)/F75 -> -0.021747116 | H76: =(Table2_1[[#This Row],[Current Prices]]-F72)/F72 -> 0.060111465
A77: Added value of Oil and natural gas extraction sector | B77: Q2 2013 | C77: 921.4 | D77: =(Table2_1[[#This Row],[Constant Prices]]-C76)/C76 -> -0.033361309 | E77: =(Table2_1[[#This Row],[Constant Prices]]-C73)/C73 -> -0.10343485 | F77: 1359.5 | G77: =(Table2_1[[#This Row],[Current Prices]]-F76)/F76 -> 0.021028915 | H77: =(Table2_1[[#This Row],[Current Prices]]-F73)/F73 -> 0.054202854
A78: Added value of Oil and natural gas extraction sector | B78: Q3 2013 | C78: 888.1 | D78: =(Table2_1[[#This Row],[Constant Prices]]-C77)/C77 -> -0.036140656 | E78: =(Table2_1[[#This Row],[Constant Prices]]-C74)/C74 -> -0.13676128 | F78: 1269.4 | G78: =(Table2_1[[#This Row],[Current Prices]]-F77)/F77 -> -0.066274366 | H78: =(Table2_1[[#This Row],[Current Prices]]-F74)/F74 -> -0.018783335
A79: Added value of Oil and natural gas extraction sector | B79: Q4 2013 | C79: 861.6 | D79: =(Table2_1[[#This Row],[Constant Prices]]-C78)/C78 -> -0.029838982 | E79: =(Table2_1[[#This Row],[Constant Prices]]-C75)/C75 -> -0.18885332 | F79: 1172.9 | G79: =(Table2_1[[#This Row],[Current Prices]]-F78)/F78 -> -0.076020167 | H79: =(Table2_1[[#This Row],[Current Prices]]-F75)/F75 -> -0.13827052 | I79: 3
A80: Added value of Oil and natural gas extraction sector | B80: Q1 2014 | C80: 856.8 | D80: =(Table2_1[[#This Row],[Constant Prices]]-C79)/C79 -> -0.0055710306 | E80: =(Table2_1[[#This Row],[Constant Prices]]-C76)/C76 -> -0.10113303 | F80: 1153.2 | G80: =(Table2_1[[#This Row],[Current Prices]]-F79)/F79 -> -0.016795976 | H80: =(Table2_1[[#This Row],[Current Prices]]-F76)/F76 -> -0.13390913
A81: Added value of Oil and natural gas extraction sector | B81: Q2 2014 | C81: 777.5 | D81: =(Table2_1[[#This Row],[Constant Prices]]-C80)/C80 -> -0.092553688 | E81: =(Table2_1[[#This Row],[Constant Prices]]-C77)/C77 -> -0.15617539 | F81: 1005.9 | G81: =(Table2_1[[#This Row],[Current Prices]]-F80)/F80 -> -0.12773153 | H81: =(Table2_1[[#This Row],[Current Prices]]-F77)/F77 -> -0.26009562
A82: Added value of Oil and natural gas extraction sector | B82: Q3 2014 | C82: 810 | D82: =(Table2_1[[#This Row],[Constant Prices]]-C81)/C81 -> 0.041800643 | E82: =(Table2_1[[#This Row],[Constant Prices]]-C78)/C78 -> -0.087940547 | F82: 1067.1 | G82: =(Table2_1[[#This Row],[Current Prices]]-F81)/F81 -> 0.060841038 | H82: =(Table2_1[[#This Row],[Current Prices]]-F78)/F78 -> -0.15936663
A83: Added value of Oil and natural gas extraction sector | B83: Q4 2014 | C83: 814.1 | D83: =(Table2_1[[#This Row],[Constant Prices]]-C82)/C82 -> 0.0050617284 | E83: =(Table2_1[[#This Row],[Constant Prices]]-C79)/C79 -> -0.055129991 | F83: 1008.8 | G83: =(Table2_1[[#This Row],[Current Prices]]-F82)/F82 -> -0.054634055 | H83: =(Table2_1[[#This Row],[Current Prices]]-F79)/F79 -> -0.13990963 | I83: 4
A84: Added value of Oil and natural gas extraction sector | B84: Q1 2015 | C84: 789.8 | D84: =(Table2_1[[#This Row],[Constant Prices]]-C83)/C83 -> -0.029848913 | E84: =(Table2_1[[#This Row],[Constant Prices]]-C80)/C80 -> -0.078197946 | F84: 860.3 | G84: =(Table2_1[[#This Row],[Current Prices]]-F83)/F83 -> -0.1472046 | H84: =(Table2_1[[#This Row],[Current Prices]]-F80)/F80 -> -0.2539889
A85: Added value of Oil and natural gas extraction sector | B85: Q2 2015 | C85: 796.9 | D85: =(Table2_1[[#This Row],[Constant Prices]]-C84)/C84 -> 0.0089896176 | E85: =(Table2_1[[#This Row],[Constant Prices]]-C81)/C81 -> 0.024951768 | F85: 811 | G85: =(Table2_1[[#This Row],[Current Prices]]-F84)/F84 -> -0.057305591 | H85: =(Table2_1[[#This Row],[Current Prices]]-F81)/F81 -> -0.19375683
A86: Added value of Oil and natural gas extraction sector | B86: Q3 2015 | C86: 756.9 | D86: =(Table2_1[[#This Row],[Constant Prices]]-C85)/C85 -> -0.050194504 | E86: =(Table2_1[[#This Row],[Constant Prices]]-C82)/C82 -> -0.065555556 | F86: 735.7 | G86: =(Table2_1[[#This Row],[Current Prices]]-F85)/F85 -> -0.092848335 | H86: =(Table2_1[[#This Row],[Current Prices]]-F82)/F82 -> -0.31056133
A87: Added value of Oil and natural gas extraction sector | B87: Q4 2015 | C87: 706.3 | D87: =(Table2_1[[#This Row],[Constant Prices]]-C86)/C86 -> -0.066851632 | E87: =(Table2_1[[#This Row],[Constant Prices]]-C83)/C83 -> -0.13241617 | F87: 642.8 | G87: =(Table2_1[[#This Row],[Current Prices]]-F86)/F86 -> -0.1262743 | H87: =(Table2_1[[#This Row],[Current Prices]]-F83)/F83 -> -0.3628073 | I87: 5
A88: Added value of Oil and natural gas extraction sector | B88: Q1 2016 | C88: 642.4 | D88: =(Table2_1[[#This Row],[Constant Prices]]-C87)/C87 -> -0.090471471 | E88: =(Table2_1[[#This Row],[Constant Prices]]-C84)/C84 -> -0.18662953 | F88: 693.4 | G88: =(Table2_1[[#This Row],[Current Prices]]-F87)/F87 -> 0.078718108 | H88: =(Table2_1[[#This Row],[Current Prices]]-F84)/F84 -> -0.19400209
A89: Added value of Oil and natural gas extraction sector | B89: Q2 2016 | C89: 667.1 | D89: =(Table2_1[[#This Row],[Constant Prices]]-C88)/C88 -> 0.038449564 | E89: =(Table2_1[[#This Row],[Constant Prices]]-C85)/C85 -> -0.16288116 | F89: 649.1 | G89: =(Table2_1[[#This Row],[Current Prices]]-F88)/F88 -> -0.063888088 | H89: =(Table2_1[[#This Row],[Current Prices]]-F85)/F85 -> -0.19963009
A90: Added value of Oil and natural gas extraction sector | B90: Q3 2016 | C90: 633.8 | D90: =(Table2_1[[#This Row],[Constant Prices]]-C89)/C89 -> -0.049917554 | E90: =(Table2_1[[#This Row],[Constant Prices]]-C86)/C86 -> -0.16263707 | F90: 641.5 | G90: =(Table2_1[[#This Row],[Current Prices]]-F89)/F89 -> -0.011708519 | H90: =(Table2_1[[#This Row],[Current Prices]]-F86)/F86 -> -0.12804132
A91: Added value of Oil and natural gas extraction sector | B91: Q4 2016 | C91: 647.5 | D91: =(Table2_1[[#This Row],[Constant Prices]]-C90)/C90 -> 0.021615652 | E91: =(Table2_1[[#This Row],[Constant Prices]]-C87)/C87 -> -0.083250743 | F91: 639.1 | G91: =(Table2_1[[#This Row],[Current Prices]]-F90)/F90 -> -0.0037412315 | H91: =(Table2_1[[#This Row],[Current Prices]]-F87)/F87 -> -0.0057560672 | I91: 6
A92: Added value of Oil and natural gas extraction sector | B92: Q1 2017 | C92: 610.8 | D92: =(Table2_1[[#This Row],[Constant Prices]]-C91)/C91 -> -0.056679537 | E92: =(Table2_1[[#This Row],[Constant Prices]]-C88)/C88 -> -0.049190535 | F92: 652.4 | G92: =(Table2_1[[#This Row],[Current Prices]]-F91)/F91 -> 0.020810515 | H92: =(Table2_1[[#This Row],[Current Prices]]-F88)/F88 -> -0.05912893
A93: Added value of Oil and natural gas extraction sector | B93: Q2 2017 | C93: 570.9 | D93: =(Table2_1[[#This Row],[Constant Prices]]-C92)/C92 -> -0.065324165 | E93: =(Table2_1[[#This Row],[Constant Prices]]-C89)/C89 -> -0.14420627 | F93: 691.4 | G93: =(Table2_1[[#This Row],[Current Prices]]-F92)/F92 -> 0.059779277 | H93: =(Table2_1[[#This Row],[Current Prices]]-F89)/F89 -> 0.065167155
A94: Added value of Oil and natural gas extraction sector | B94: Q3 2017 | C94: 494 | D94: =(Table2_1[[#This Row],[Constant Prices]]-C93)/C93 -> -0.1346996 | E94: =(Table2_1[[#This Row],[Constant Prices]]-C90)/C90 -> -0.22057431 | F94: 635.7 | G94: =(Table2_1[[#This Row],[Current Prices]]-F93)/F93 -> -0.08056118 | H94: =(Table2_1[[#This Row],[Current Prices]]-F90)/F90 -> -0.0090413094
A95: Added value of Oil and natural gas extraction sector | B95: Q4 2017 | C95: 618.1 | D95: =(Table2_1[[#This Row],[Constant Prices]]-C94)/C94 -> 0.25121457 | E95: =(Table2_1[[#This Row],[Constant Prices]]-C91)/C91 -> -0.045405405 | F95: 799.4 | G95: =(Table2_1[[#This Row],[Current Prices]]-F94)/F94 -> 0.2575114 | H95: =(Table2_1[[#This Row],[Current Prices]]-F91)/F91 -> 0.25082147 | I95: 7
A96: Added value of Oil and natural gas extraction sector | B96: Q1 2018 | C96: 602.7 | D96: =(Table2_1[[#This Row],[Constant Prices]]-C95)/C95 -> -0.024915062 | E96: =(Table2_1[[#This Row],[Constant Prices]]-C92)/C92 -> -0.013261297 | F96: 814.4 | G96: =(Table2_1[[#This Row],[Current Prices]]-F95)/F95 -> 0.018764073 | H96: =(Table2_1[[#This Row],[Current Prices]]-F92)/F92 -> 0.24831392
A97: Added value of Oil and natural gas extraction sector | B97: Q2 2018 | C97: 562.4 | D97: =(Table2_1[[#This Row],[Constant Prices]]-C96)/C96 -> -0.066865771 | E97: =(Table2_1[[#This Row],[Constant Prices]]-C93)/C93 -> -0.014888772 | F97: 856.2 | G97: =(Table2_1[[#This Row],[Current Prices]]-F96)/F96 -> 0.05132613 | H97: =(Table2_1[[#This Row],[Current Prices]]-F93)/F93 -> 0.23835696
A98: Added value of Oil and natural gas extraction sector | B98: Q3 2018 | C98: 539.7 | D98: =(Table2_1[[#This Row],[Constant Prices]]-C97)/C97 -> -0.040362731 | E98: =(Table2_1[[#This Row],[Constant Prices]]-C94)/C94 -> 0.092510121 | F98: 935.9 | G98: =(Table2_1[[#This Row],[Current Prices]]-F97)/F97 -> 0.093085728 | H98: =(Table2_1[[#This Row],[Current Prices]]-F94)/F94 -> 0.47223533
A99: Added value of Oil and natural gas extraction sector | B99: Q4 2018 | C99: 540.8 | D99: =(Table2_1[[#This Row],[Constant Prices]]-C98)/C98 -> 0.0020381694 | E99: =(Table2_1[[#This Row],[Constant Prices]]-C95)/C95 -> -0.12506067 | F99: 897.2 | G99: =(Table2_1[[#This Row],[Current Prices]]-F98)/F98 -> -0.041350572 | H99: =(Table2_1[[#This Row],[Current Prices]]-F95)/F95 -> 0.12234176 | I99: 8
A100: Added value of Oil and natural gas extraction sector | B100: Q1 2019 | C100: 532.6 | D100: =(Table2_1[[#This Row],[Constant Prices]]-C99)/C99 -> -0.015162722 | E100: =(Table2_1[[#This Row],[Constant Prices]]-C96)/C96 -> -0.11630994 | F100: 880.8 | G100: =(Table2_1[[#This Row],[Current Prices]]-F99)/F99 -> -0.018279091 | H100: =(Table2_1[[#This Row],[Current Prices]]-F96)/F96 -> 0.081532417
...

Sheet Annual General Balance
A1: Annual general balance | B1: Attribute | C1: Value | D1: Ratio | E1: YoY change | H1: Investment Ratio | I1: External Factors
A2: Gross Domestic Product | B2: 2015 | C2: 89802.2 | G2: Years | H2: Total Gross Capital Formation ratio | I2: Net Exports | J2: Openess Ratio | K2: Coverage Ratio
A3: Gross Domestic Product | B3: 2016 | C3: 95286.9 | E3: =(Table1_1[[#This Row],[Value]]-C2)/C2 -> 0.061075341 | G3: 2015 | H3: =(C62+C72)/C2 -> 0.21739 | I3: =(C92-C12)/C2 -> -0.10448853 | J3: =(C92+C12)/C2 -> 0.87248531 | K3: =C92/C12 -> 0.78609759
A4: Gross Domestic Product | B4: 2017 | C4: 102011.5 | E4: =(Table1_1[[#This Row],[Value]]-C3)/C3 -> 0.070572135 | G4: 2016 | H4: =(C63+C73)/C3 -> 0.20475008 | I4: =(C93-C13)/C3 -> -0.10502073 | J4: =(C93+C13)/C3 -> 0.87092664 | K4: =C93/C13 -> 0.78478198
A5: Gross Domestic Product | B5: 2018 | C5: 112985.5 | E5: =(Table1_1[[#This Row],[Value]]-C4)/C4 -> 0.10757611 | G5: 2017 | H5: =(C64+C74)/C4 -> 0.2129456 | I5: =(C94-C14)/C4 -> -0.12367625 | J5: =(C94+C14)/C4 -> 0.95809198 | K5: =C94/C14 -> 0.77134427
A6: Gross Domestic Product | B6: 2019 | C6: 122969.3 | E6: =(Table1_1[[#This Row],[Value]]-C5)/C5 -> 0.088363551 | G6: 2018 | H6: =(C65+C75)/C5 -> 0.22963566 | I6: =(C95-C15)/C5 -> -0.12900328 | J6: =(C95+C15)/C5 -> 1.0387182 | K6: =C95/C15 -> 0.77905129
A7: Gross Domestic Product | B7: 2020 | C7: 119502.1 | E7: =(Table1_1[[#This Row],[Value]]-C6)/C6 -> -0.028195655 | G7: 2019 | H7: =(C66+C76)/C6 -> 0.19803398 | I7: =(C96-C16)/C6 -> -0.10431953 | J7: =(C96+C16)/C6 -> 1.0233261 | K7: =C96/C16 -> 0.81497817
A8: Gross Domestic Product | B8: 2021 | C8: 131544.6 | E8: =(Table1_1[[#This Row],[Value]]-C7)/C7 -> 0.10077229 | G8: 2020 | H8: =(C67+C77)/C7 -> 0.12688229 | I8: =(C97-C17)/C7 -> -0.083497277 | J8: =(C97+C17)/C7 -> 0.8433333 | K8: =C97/C17 -> 0.81982192
A9: Gross Domestic Product | B9: 2022 | C9: 139444.5 | E9: =(Table1_1[[#This Row],[Value]]-C8)/C8 -> 0.060054917 | G9: 2021 | H9: =(C68+C78)/C8 -> 0.1584588 | I9: =(C98-C18)/C8 -> -0.10073009 | J9: =(C98+C18)/C8 -> 0.93633414 | K9: =C98/C18 -> 0.80573991
A10: Gross Domestic Product | B10: 2023 | C10: 149733.8 | E10: =(Table1_1[[#This Row],[Value]]-C9)/C9 -> 0.073787779 | G10: 2022 | H10: =(C69+C79)/C9 -> 0.16673802 | I10: =(C99-C19)/C9 -> -0.13443915 | J10: =(C99+C19)/C9 -> 1.1609579 | K10: =C99/C19 -> 0.79243562
A11: Gross Domestic Product | B11: 2024 | C11: 159760.6 | E11: =(Table1_1[[#This Row],[Value]]-C10)/C10 -> 0.066964172 | G11: 2023 | H11: =(C70+C80)/C10 -> 0.082079664 | I11: =(C100-C20)/C10 -> -0.060500702 | J11: =(C100+C20)/C10 -> 1.1212886 | K11: =C100/C20 -> 0.89761169
A12: Imports | B12: 2015 | C12: 43867.2 | D12: =Table1_1[[#This Row],[Value]]/C2 -> 0.48848692 | G12: 2024 | H12: =(C71+C81)/C11 -> 0.078581953 | I12: =(C101-C21)/C11 -> -0.062951691 | J12: =(C101+C21)/C11 -> 1.0629855 | K12: =C101/C21 -> 0.88817903
A13: Imports | B13: 2016 | C13: 46497.5 | D13: =Table1_1[[#This Row],[Value]]/C3 -> 0.48797369 | E13: =(Table1_1[[#This Row],[Value]]-C12)/C12 -> 0.059960517
A14: Imports | B14: 2017 | C14: 55176.4 | D14: =Table1_1[[#This Row],[Value]]/C4 -> 0.54088412 | E14: =(Table1_1[[#This Row],[Value]]-C13)/C13 -> 0.18665305
A15: Imports | B15: 2018 | C15: 65967.8 | D15: =Table1_1[[#This Row],[Value]]/C5 -> 0.58386076 | E15: =(Table1_1[[#This Row],[Value]]-C14)/C14 -> 0.19557999
A16: Imports | B16: 2019 | C16: 69332.9 | D16: =Table1_1[[#This Row],[Value]]/C6 -> 0.56382284 | E16: =(Table1_1[[#This Row],[Value]]-C15)/C15 -> 0.051011251
A17: Imports | B17: 2020 | C17: 55379.1 | D17: =Table1_1[[#This Row],[Value]]/C7 -> 0.46341529 | E17: =(Table1_1[[#This Row],[Value]]-C16)/C16 -> -0.20125799
A18: Imports | B18: 2021 | C18: 68210.1 | D18: =Table1_1[[#This Row],[Value]]/C8 -> 0.51853212 | E18: =(Table1_1[[#This Row],[Value]]-C17)/C17 -> 0.23169391
A19: Imports | B19: 2022 | C19: 90318 | D19: =Table1_1[[#This Row],[Value]]/C9 -> 0.64769855 | E19: =(Table1_1[[#This Row],[Value]]-C18)/C18 -> 0.32411476
A20: Imports | B20: 2023 | C20: 88476.9 | D20: =Table1_1[[#This Row],[Value]]/C10 -> 0.59089464 | E20: =(Table1_1[[#This Row],[Value]]-C19)/C19 -> -0.020384641
A21: Imports | B21: 2024 | C21: 89940.2 | D21: =Table1_1[[#This Row],[Value]]/C11 -> 0.56296859 | E21: =(Table1_1[[#This Row],[Value]]-C20)/C20 -> 0.01653878
A22: Total Resources - Uses | B22: 2015 | C22: 133669.4 | D22: =Table1_1[[#This Row],[Value]]/C2 -> 1.4884869
A23: Total Resources - Uses | B23: 2016 | C23: 141784.5 | D23: =Table1_1[[#This Row],[Value]]/C3 -> 1.4879747
A24: Total Resources - Uses | B24: 2017 | C24: 157187.9 | D24: =Table1_1[[#This Row],[Value]]/C4 -> 1.5408841
A25: Total Resources - Uses | B25: 2018 | C25: 178953.3 | D25: =Table1_1[[#This Row],[Value]]/C5 -> 1.5838608
A26: Total Resources - Uses | B26: 2019 | C26: 192302.1 | D26: =Table1_1[[#This Row],[Value]]/C6 -> 1.563822
A27: Total Resources - Uses | B27: 2020 | C27: 174881.2 | D27: =Table1_1[[#This Row],[Value]]/C7 -> 1.4634153
A28: Total Resources - Uses | B28: 2021 | C28: 199754.7 | D28: =Table1_1[[#This Row],[Value]]/C8 -> 1.5185321
A29: Total Resources - Uses | B29: 2022 | C29: 229762.5 | D29: =Table1_1[[#This Row],[Value]]/C9 -> 1.6476985
A30: Total Resources - Uses | B30: 2023 | C30: 238210.7 | D30: =Table1_1[[#This Row],[Value]]/C10 -> 1.5908946
A31: Total Resources - Uses | B31: 2024 | C31: 249700.9 | D31: =Table1_1[[#This Row],[Value]]/C11 -> 1.5629692
A32: Final Consumption Expenditure | B32: 2015 | C32: 79663.4 | D32: =Table1_1[[#This Row],[Value]]/C2 -> 0.88709853
A33: Final Consumption Expenditure | B33: 2016 | C33: 85784 | D33: =Table1_1[[#This Row],[Value]]/C3 -> 0.90027066 | E33: =(Table1_1[[#This Row],[Value]]-C32)/C32 -> 0.076830765
A34: Final Consumption Expenditure | B34: 2017 | C34: 92905 | D34: =Table1_1[[#This Row],[Value]]/C4 -> 0.91073065 | E34: =(Table1_1[[#This Row],[Value]]-C33)/C33 -> 0.083010818
A35: Final Consumption Expenditure | B35: 2018 | C35: 101615.5 | D35: =Table1_1[[#This Row],[Value]]/C5 -> 0.89936762 | E35: =(Table1_1[[#This Row],[Value]]-C34)/C34 -> 0.093757064
A36: Final Consumption Expenditure | B36: 2019 | C36: 111445.2 | D36: =Table1_1[[#This Row],[Value]]/C6 -> 0.90628474 | E36: =(Table1_1[[#This Row],[Value]]-C35)/C35 -> 0.096734258
A37: Final Consumption Expenditure | B37: 2020 | C37: 114317.6 | D37: =Table1_1[[#This Row],[Value]]/C7 -> 0.95661583 | E37: =(Table1_1[[#This Row],[Value]]-C36)/C36 -> 0.025774102
A38: Final Consumption Expenditure | B38: 2021 | C38: 123950.6 | D38: =Table1_1[[#This Row],[Value]]/C8 -> 0.94227053 | E38: =(Table1_1[[#This Row],[Value]]-C37)/C37 -> 0.08426524
A39: Final Consumption Expenditure | B39: 2022 | C39: 134940.5 | D39: =Table1_1[[#This Row],[Value]]/C9 -> 0.96770041 | E39: =(Table1_1[[#This Row],[Value]]-C38)/C38 -> 0.088663548
A40: Final Consumption Expenditure | B40: 2023 | C40: 146502.7 | D40: =Table1_1[[#This Row],[Value]]/C10 -> 0.97842104 | E40: =(Table1_1[[#This Row],[Value]]-C39)/C39 -> 0.08568369
A41: Final Consumption Expenditure | B41: 2024 | C41: 157263.5 | D41: =Table1_1[[#This Row],[Value]]/C11 -> 0.98436974 | E41: =(Table1_1[[#This Row],[Value]]-C40)/C40 -> 0.073451206
A42: Public Consumption | B42: 2015 | C42: 16079.6 | D42: =Table1_1[[#This Row],[Value]]/C2 -> 0.17905575
A43: Public Consumption | B43: 2016 | C43: 17837 | D43: =Table1_1[[#This Row],[Value]]/C3 -> 0.18719257 | E43: =(Table1_1[[#This Row],[Value]]-C42)/C42 -> 0.10929376
A44: Public Consumption | B44: 2017 | C44: 19509.2 | D44: =Table1_1[[#This Row],[Value]]/C4 -> 0.1912451 | E44: =(Table1_1[[#This Row],[Value]]-C43)/C43 -> 0.093748949
A45: Public Consumption | B45: 2018 | C45: 20775.8 | D45: =Table1_1[[#This Row],[Value]]/C5 -> 0.18388023 | E45: =(Table1_1[[#This Row],[Value]]-C44)/C44 -> 0.064923216
A46: Public Consumption | B46: 2019 | C46: 23138.5 | D46: =Table1_1[[#This Row],[Value]]/C6 -> 0.18816485 | E46: =(Table1_1[[#This Row],[Value]]-C45)/C45 -> 0.11372366
A47: Public Consumption | B47: 2020 | C47: 25854.7 | D47: =Table1_1[[#This Row],[Value]]/C7 -> 0.21635352 | E47: =(Table1_1[[#This Row],[Value]]-C46)/C46 -> 0.11738877
A48: Public Consumption | B48: 2021 | C48: 27369.6 | D48: =Table1_1[[#This Row],[Value]]/C8 -> 0.20806327 | E48: =(Table1_1[[#This Row],[Value]]-C47)/C47 -> 0.058592828
A49: Public Consumption | B49: 2022 | C49: 28403.8 | D49: =Table1_1[[#This Row],[Value]]/C9 -> 0.20369251 | E49: =(Table1_1[[#This Row],[Value]]-C48)/C48 -> 0.037786449
A50: Public Consumption | B50: 2023 | C50: 29076.5 | D50: =Table1_1[[#This Row],[Value]]/C10 -> 0.19418795 | E50: =(Table1_1[[#This Row],[Value]]-C49)/C49 -> 0.023683451
A51: Public Consumption | B51: 2024 | C51: 30254.3 | D51: =Table1_1[[#This Row],[Value]]/C11 -> 0.18937272 | E51: =(Table1_1[[#This Row],[Value]]-C50)/C50 -> 0.040506939
A52: Private Consumption | B52: 2015 | C52: 63583.8 | D52: =Table1_1[[#This Row],[Value]]/C2 -> 0.70804279
A53: Private Consumption | B53: 2016 | C53: 67947 | D53: =Table1_1[[#This Row],[Value]]/C3 -> 0.71307808 | E53: =(Table1_1[[#This Row],[Value]]-C52)/C52 -> 0.068621253
A54: Private Consumption | B54: 2017 | C54: 73395.8 | D54: =Table1_1[[#This Row],[Value]]/C4 -> 0.71948555 | E54: =(Table1_1[[#This Row],[Value]]-C53)/C53 -> 0.080191914
A55: Private Consumption | B55: 2018 | C55: 80839.7 | D55: =Table1_1[[#This Row],[Value]]/C5 -> 0.71548739 | E55: =(Table1_1[[#This Row],[Value]]-C54)/C54 -> 0.10142133
A56: Private Consumption | B56: 2019 | C56: 88306.7 | D56: =Table1_1[[#This Row],[Value]]/C6 -> 0.71811989 | E56: =(Table1_1[[#This Row],[Value]]-C55)/C55 -> 0.092367983
A57: Private Consumption | B57: 2020 | C57: 88462.9 | D57: =Table1_1[[#This Row],[Value]]/C7 -> 0.74026231 | E57: =(Table1_1[[#This Row],[Value]]-C56)/C56 -> 0.0017688352
A58: Private Consumption | B58: 2021 | C58: 96581 | D58: =Table1_1[[#This Row],[Value]]/C8 -> 0.73420726 | E58: =(Table1_1[[#This Row],[Value]]-C57)/C57 -> 0.091768414
A59: Private Consumption | B59: 2022 | C59: 106536.7 | D59: =Table1_1[[#This Row],[Value]]/C9 -> 0.7640079 | E59: =(Table1_1[[#This Row],[Value]]-C58)/C58 -> 0.10308135
A60: Private Consumption | B60: 2023 | C60: 117426.2 | D60: =Table1_1[[#This Row],[Value]]/C10 -> 0.78423309 | E60: =(Table1_1[[#This Row],[Value]]-C59)/C59 -> 0.1022136
A61: Private Consumption | B61: 2024 | C61: 127009.3 | D61: =Table1_1[[#This Row],[Value]]/C11 -> 0.79499764 | E61: =(Table1_1[[#This Row],[Value]]-C60)/C60 -> 0.081609556
A62: Gross Fixed Capital Formation | B62: 2015 | C62: 18841.8 | D62: =Table1_1[[#This Row],[Value]]/C2 -> 0.20981446
A63: Gross Fixed Capital Formation | B63: 2016 | C63: 19531.5 | D63: =Table1_1[[#This Row],[Value]]/C3 -> 0.20497571 | E63: =(Table1_1[[#This Row],[Value]]-C62)/C62 -> 0.036604783
A64: Gross Fixed Capital Formation | B64: 2017 | C64: 20449.5 | D64: =Table1_1[[#This Row],[Value]]/C4 -> 0.20046269 | E64: =(Table1_1[[#This Row],[Value]]-C63)/C63 -> 0.047000998
A65: Gross Fixed Capital Formation | B65: 2018 | C65: 22146.1 | D65: =Table1_1[[#This Row],[Value]]/C5 -> 0.19600834 | E65: =(Table1_1[[#This Row],[Value]]-C64)/C64 -> 0.082965354
A66: Gross Fixed Capital Formation | B66: 2019 | C66: 23898.7 | D66: =Table1_1[[#This Row],[Value]]/C6 -> 0.19434688 | E66: =(Table1_1[[#This Row],[Value]]-C65)/C65 -> 0.079138088
A67: Gross Fixed Capital Formation | B67: 2020 | C67: 18935.8 | D67: =Table1_1[[#This Row],[Value]]/C7 -> 0.15845579 | E67: =(Table1_1[[#This Row],[Value]]-C66)/C66 -> -0.20766402
A68: Gross Fixed Capital Formation | B68: 2021 | C68: 20857.6 | D68: =Table1_1[[#This Row],[Value]]/C8 -> 0.15855915 | E68: =(Table1_1[[#This Row],[Value]]-C67)/C67 -> 0.1014903
A69: Gross Fixed Capital Formation | B69: 2022 | C69: 22750.1 | D69: =Table1_1[[#This Row],[Value]]/C9 -> 0.16314806 | E69: =(Table1_1[[#This Row],[Value]]-C68)/C68 -> 0.090734313
A70: Gross Fixed Capital Formation | B70: 2023 | C70: 23563.4 | D70: =Table1_1[[#This Row],[Value]]/C10 -> 0.15736861 | E70: =(Table1_1[[#This Row],[Value]]-C69)/C69 -> 0.035749293
A71: Gross Fixed Capital Formation | B71: 2024 | C71: 24302.2 | D71: =Table1_1[[#This Row],[Value]]/C11 -> 0.15211635 | E71: =(Table1_1[[#This Row],[Value]]-C70)/C70 -> 0.03135371
A72: Changes in Inventories | B72: 2015 | C72: 680.3 | D72: =Table1_1[[#This Row],[Value]]/C2 -> 0.0075755382
A73: Changes in Inventories | B73: 2016 | C73: -21.5 | D73: =Table1_1[[#This Row],[Value]]/C3 -> -0.00022563437
A74: Changes in Inventories | B74: 2017 | C74: 1273.4 | D74: =Table1_1[[#This Row],[Value]]/C4 -> 0.012482906
A75: Changes in Inventories | B75: 2018 | C75: 3799.4 | D75: =Table1_1[[#This Row],[Value]]/C5 -> 0.033627324
A76: Changes in Inventories | B76: 2019 | C76: 453.4 | D76: =Table1_1[[#This Row],[Value]]/C6 -> 0.0036870991
A77: Changes in Inventories | B77: 2020 | C77: -3773.1 | D77: =Table1_1[[#This Row],[Value]]/C7 -> -0.031573504
A78: Changes in Inventories | B78: 2021 | C78: -13.2 | D78: =Table1_1[[#This Row],[Value]]/C8 -> -0.00010034619
A79: Changes in Inventories | B79: 2022 | C79: 500.6 | D79: =Table1_1[[#This Row],[Value]]/C9 -> 0.0035899587
A80: Changes in Inventories | B80: 2023 | C80: -11273.3 | D80: =Table1_1[[#This Row],[Value]]/C10 -> -0.075288946
A81: Changes in Inventories | B81: 2024 | C81: -11747.9 | D81: =Table1_1[[#This Row],[Value]]/C11 -> -0.073534401
A82: Domestic Demand | B82: 2015 | C82: 99185.5 | D82: =Table1_1[[#This Row],[Value]]/C2 -> 1.1044885
A83: Domestic Demand | B83: 2016 | C83: 105294.1 | D83: =Table1_1[[#This Row],[Value]]/C3 -> 1.1050218
A84: Domestic Demand | B84: 2017 | C84: 114627.9 | D84: =Table1_1[[#This Row],[Value]]/C4 -> 1.1236763
A85: Domestic Demand | B85: 2018 | C85: 127561 | D85: =Table1_1[[#This Row],[Value]]/C5 -> 1.1290033
A86: Domestic Demand | B86: 2019 | C86: 135797.3 | D86: =Table1_1[[#This Row],[Value]]/C6 -> 1.1043187
A87: Domestic Demand | B87: 2020 | C87: 129480.2 | D87: =Table1_1[[#This Row],[Value]]/C7 -> 1.0834973
A88: Domestic Demand | B88: 2021 | C88: 144795 | D88: =Table1_1[[#This Row],[Value]]/C8 -> 1.1007293
A89: Domestic Demand | B89: 2022 | C89: 158191.2 | D89: =Table1_1[[#This Row],[Value]]/C9 -> 1.1344384
A90: Domestic Demand | B90: 2023 | C90: 158792.8 | D90: =Table1_1[[#This Row],[Value]]/C10 -> 1.0605007
A91: Domestic Demand | B91: 2024 | C91: 169817.9 | D91: =Table1_1[[#This Row],[Value]]/C11 -> 1.0629523
A92: Exports | B92: 2015 | C92: 34483.9 | D92: =Table1_1[[#This Row],[Value]]/C2 -> 0.38399839
A93: Exports | B93: 2016 | C93: 36490.4 | D93: =Table1_1[[#This Row],[Value]]/C3 -> 0.38295296 | E93: =(Table1_1[[#This Row],[Ratio]]-D92)/D92 -> -0.0027224901
A94: Exports | B94: 2017 | C94: 42560 | D94: =Table1_1[[#This Row],[Value]]/C4 -> 0.41720786 | E94: =(Table1_1[[#This Row],[Ratio]]-D93)/D93 -> 0.089449389
A95: Exports | B95: 2018 | C95: 51392.3 | D95: =Table1_1[[#This Row],[Value]]/C5 -> 0.45485748 | E95: =(Table1_1[[#This Row],[Ratio]]-D94)/D94 -> 0.09024187
A96: Exports | B96: 2019 | C96: 56504.8 | D96: =Table1_1[[#This Row],[Value]]/C6 -> 0.45950331 | E96: =(Table1_1[[#This Row],[Ratio]]-D95)/D95 -> 0.010213804
A97: Exports | B97: 2020 | C97: 45401 | D97: =Table1_1[[#This Row],[Value]]/C7 -> 0.37991801 | E97: =(Table1_1[[#This Row],[Ratio]]-D96)/D96 -> -0.17319853
A98: Exports | B98: 2021 | C98: 54959.6 | D98: =Table1_1[[#This Row],[Value]]/C8 -> 0.41780202 | E98: =(Table1_1[[#This Row],[Ratio]]-D97)/D97 -> 0.099716287
A99: Exports | B99: 2022 | C99: 71571.2 | D99: =Table1_1[[#This Row],[Value]]/C9 -> 0.5132594 | E99: =(Table1_1[[#This Row],[Ratio]]-D98)/D98 -> 0.22847514
A100: Exports | B100: 2023 | C100: 79417.9 | D100: =Table1_1[[#This Row],[Value]]/C10 -> 0.53039394 | E100: =(Table1_1[[#This Row],[Ratio]]-D99)/D99 -> 0.033383786
...

Sheet Population
A1: Active population | B1: Attribute | C1: Value
A2: Evolution of the active population
A3: Evolution of the active population | B3: Q3 2011 | C3: 3844.6
A4: Evolution of the active population | B4: Q4 2011 | C4: 3909.1
A5: Evolution of the active population | B5: Q1 2012 | C5: 3916.9
A6: Evolution of the active population | B6: Q2 2012 | C6: 3923.2
A7: Evolution of the active population | B7: Q3 2012 | C7: 3907.9
A8: Evolution of the active population | B8: Q4 2012 | C8: 3909.6
A9: Evolution of the active population | B9: Q1 2013 | C9: 3927.3
A10: Evolution of the active population | B10: Q2 2013 | C10: 3943.7
A11: Evolution of the active population | B11: Q3 2013 | C11: 3961.8
A12: Evolution of the active population | B12: Q4 2013 | C12: 3978.6
A13: Evolution of the active population | B13: Q1 2014 | C13: 3998.3
A14: Evolution of the active population | B14: Q2 2014 | C14: 3866.5
... A56: Evolution of the active population | B56: Q1 2025 | C56: 4233.4
A57: Evolution of the active population
A58: Evolution of the male active population | B58: Q3 2011 | C58: 2817.9
A59: Evolution of the male active population | B59: Q4 2011 | C59: 2842.1
A60: Evolution of the male active population | B60: Q1 2012 | C60: 2849.7
A61: Evolution of the male active population | B61: Q2 2012 | C61: 2852.3
A62: Evolution of the male active population | B62: Q3 2012 | C62: 2844.4
A63: Evolution of the male active population | B63: Q4 2012 | C63: 2847.4
A64: Evolution of the male active population | B64: Q1 2013 | C64: 2864.4
A65: Evolution of the male active population | B65: Q2 2013 | C65: 2862
A66: Evolution of the male active population | B66: Q3 2013 | C66: 2870.8
A67: Evolution of the male active population | B67: Q4 2013 | C67: 2872.8
A68: Evolution of the male active population | B68: Q1 2014 | C68: 2879.9
A69: Evolution of the male active population | B69: Q2 2014 | C69: 2654.5
... A111: Evolution of the male active population | B111: Q1 2025 | C111: 2899.7
A112: Evolution of the female active population
A113: Evolution of the female active population | B113: Q3 2011 | C113: 1026.7
A114: Evolution of the female active population | B114: Q4 2011 | C114: 1067
A115: Evolution of the female active population | B115: Q1 2012 | C115: 1067.2
A116: Evolution of the female active population | B116: Q2 2012 | C116: 1070.9
A117: Evolution of the female active population | B117: Q3 2012 | C117: 1063.5
A118: Evolution of the female active population | B118: Q4 2012 | C118: 1062.2
A119: Evolution of the female active population | B119: Q1 2013 | C119: 1062.9
A120: Evolution of the female active population | B120: Q2 2013 | C120: 1081.7
A121: Evolution of the female active population | B121: Q3 2013 | C121: 1091
A122: Evolution of the female active population | B122: Q4 2013 | C122: 1105.8
A123: Evolution of the female active population | B123: Q1 2014 | C123: 1118.4
A124: Evolution of the female active population | B124: Q2 2014 | C124: 1212
... A166: Evolution of the female active population | B166: Q1 2025 | C166: 1333.7

Sheet Unemployment
A1: Unemployment | B1: Attribute | C1: Value | D1: Unemployment rate | E1: Employment rate | F1: Difference in Gender Unemployment Rate
A2: Trends in the unemployed labor force | F2: (Masculin Rate - Feminine Rate)
A3: Trends in the unemployed labor force | B3: Q2 2011 | C3: 704.9 | D3: =Table3_1[[#This Row],[Value]]/Table7_1[[#This Row],[Value]] -> 0.18334807 | E3: =1-Table3_1[[#This Row],[Unemployment rate]] -> 0.81665193 | F3: =D51-D99 -> -0.12339413
A4: Trends in the unemployed labor force | B4: Q4 2011 | C4: 738.4 | D4: =Table3_1[[#This Row],[Value]]/Table7_1[[#This Row],[Value]] -> 0.18889258 | E4: =1-Table3_1[[#This Row],[Unemployment rate]] -> 0.81110742 | F4: =D52-D100 -> -0.12858578
A5: Trends in the unemployed labor force | B5: Q1 2012 | C5: 709.7 | D5: =Table3_1[[#This Row],[Value]]/Table7_1[[#This Row],[Value]] -> 0.18118921 | E5: =1-Table3_1[[#This Row],[Unemployment rate]] -> 0.81881079 | F5: =D53-D101 -> -0.1167328
A6: Trends in the unemployed labor force | B6: Q2 2012 | C6: 691.6 | D6: =Table3_1[[#This Row],[Value]]/Table7_1[[#This Row],[Value]] -> 0.17628467 | E6: =1-Table3_1[[#This Row],[Unemployment rate]] -> 0.82371533 | F6: =D54-D102 -> -0.10970827
A7: Trends in the unemployed labor force | B7: Q3 2012 | C7: 665 | D7: =Table3_1[[#This Row],[Value]]/Table7_1[[#This Row],[Value]] -> 0.17016812 | E7: =1-Table3_1[[#This Row],[Unemployment rate]] -> 0.82983188 | F7: =D55-D103 -> -0.10842086
A8: Trends in the unemployed labor force | B8: Q4 2012 | C8: 653.8 | D8: =Table3_1[[#This Row],[Value]]/Table7_1[[#This Row],[Value]] -> 0.16722938 | E8: =1-Table3_1[[#This Row],[Unemployment rate]] -> 0.83277062 | F8: =D56-D104 -> -0.10311252
A9: Trends in the unemployed labor force | B9: Q1 2013 | C9: 646.1 | D9: =Table3_1[[#This Row],[Value]]/Table7_1[[#This Row],[Value]] -> 0.16451506 | E9: =1-Table3_1[[#This Row],[Unemployment rate]] -> 0.83548494 | F9: =D57-D105 -> -0.093954959
A10: Trends in the unemployed labor force | B10: Q2 2013 | C10: 628.4 | D10: =Table3_1[[#This Row],[Value]]/Table7_1[[#This Row],[Value]] -> 0.15934275 | E10: =1-Table3_1[[#This Row],[Unemployment rate]] -> 0.84065725 | F10: =D58-D106 -> -0.097373799
A11: Trends in the unemployed labor force | B11: Q3 2013 | C11: 620.6 | D11: =Table3_1[[#This Row],[Value]]/Table7_1[[#This Row],[Value]] -> 0.15664597 | E11: =1-Table3_1[[#This Row],[Unemployment rate]] -> 0.84335403 | F11: =D59-D107 -> -0.093856502
A12: Trends in the unemployed labor force | B12: Q4 2013 | C12: 609.9 | D12: =Table3_1[[#This Row],[Value]]/Table7_1[[#This Row],[Value]] -> 0.15329513 | E12: =1-Table3_1[[#This Row],[Unemployment rate]] -> 0.84670487 | F12: =D60-D108 -> -0.091659561
A13: Trends in the unemployed labor force | B13: Q1 2014 | C13: 605.8 | D13: =Table3_1[[#This Row],[Value]]/Table7_1[[#This Row],[Value]] -> 0.15151439 | E13: =1-Table3_1[[#This Row],[Unemployment rate]] -> 0.84848561 | F13: =D61-D109 -> -0.088691207
A14: Trends in the unemployed labor force | B14: Q3 2014 | C14: 602.8 | D14: =Table3_1[[#This Row],[Value]]/Table7_1[[#This Row],[Value]] -> 0.15590327 | E14: =1-Table3_1[[#This Row],[Unemployment rate]] -> 0.84409673 | F14: =D62-D110 -> -0.061226049
... A49: Trends in the unemployed labor force | B49: Q2 2023 | C49: 638.1 | D49: =Table3_1[[#This Row],[Value]]/Table7_1[[#This Row],[Value]] -> 0.15647376 | E49: =1-Table3_1[[#This Row],[Unemployment rate]] -> 0.84352624 | F49: =D97-D145 -> -0.081079085
A50: Male unemployment in the labor force
A51: Male unemployment in the labor force | B51: Q2 2011 | C51: 423.8 | D51: =Table3_1[[#This Row],[Value]]/'[1]Active population 1'!C58 -> 0.15039568 | E51: =1-Table3_1[[#This Row],[Unemployment rate]] -> 0.84960432
A52: Male unemployment in the labor force | B52: Q4 2011 | C52: 437.1 | D52: =Table3_1[[#This Row],[Value]]/'[1]Active population 1'!C59 -> 0.15379473 | E52: =1-Table3_1[[#This Row],[Unemployment rate]] -> 0.84620527
A53: Male unemployment in the labor force | B53: Q1 2012 | C53: 425.7 | D53: =Table3_1[[#This Row],[Value]]/'[1]Active population 1'!C60 -> 0.14938415 | E53: =1-Table3_1[[#This Row],[Unemployment rate]] -> 0.85061585
A54: Male unemployment in the labor force | B54: Q2 2012 | C54: 417.4 | D54: =Table3_1[[#This Row],[Value]]/'[1]Active population 1'!C61 -> 0.14633804 | E54: =1-Table3_1[[#This Row],[Unemployment rate]] -> 0.85366196
A55: Male unemployment in the labor force | B55: Q3 2012 | C55: 400.1 | D55: =Table3_1[[#This Row],[Value]]/'[1]Active population 1'!C62 -> 0.14066235 | E55: =1-Table3_1[[#This Row],[Unemployment rate]] -> 0.85933765
A56: Male unemployment in the labor force | B56: Q4 2012 | C56: 396.4 | D56: =Table3_1[[#This Row],[Value]]/'[1]Active population 1'!C63 -> 0.13921472 | E56: =1-Table3_1[[#This Row],[Unemployment rate]] -> 0.86078528
A57: Male unemployment in the labor force | B57: Q1 2013 | C57: 398.4 | D57: =Table3_1[[#This Row],[Value]]/'[1]Active population 1'!C64 -> 0.13908672 | E57: =1-Table3_1[[#This Row],[Unemployment rate]] -> 0.86091328
A58: Male unemployment in the labor force | B58: Q2 2013 | C58: 379.6 | D58: =Table3_1[[#This Row],[Value]]/'[1]Active population 1'!C65 -> 0.13263452 | E58: =1-Table3_1[[#This Row],[Unemployment rate]] -> 0.86736548
A59: Male unemployment in the labor force | B59: Q3 2013 | C59: 375.5 | D59: =Table3_1[[#This Row],[Value]]/'[1]Active population 1'!C66 -> 0.13079978 | E59: =1-Table3_1[[#This Row],[Unemployment rate]] -> 0.86920022
A60: Male unemployment in the labor force | B60: Q4 2013 | C60: 367.2 | D60: =Table3_1[[#This Row],[Value]]/'[1]Active population 1'!C67 -> 0.12781955 | E60: =1-Table3_1[[#This Row],[Unemployment rate]] -> 0.87218045
A61: Male unemployment in the labor force | B61: Q1 2014 | C61: 364.9 | D61: =Table3_1[[#This Row],[Value]]/'[1]Active population 1'!C68 -> 0.12670579 | E61: =1-Table3_1[[#This Row],[Unemployment rate]] -> 0.87329421
A62: Male unemployment in the labor force | B62: Q3 2014 | C62: 362.9 | D62: =Table3_1[[#This Row],[Value]]/'[1]Active population 1'!C69 -> 0.13671125 | E62: =1-Table3_1[[#This Row],[Unemployment rate]] -> 0.86328875
... A97: Male unemployment in the labor force | B97: Q2 2023 | C97: 377.5 | D97: =Table3_1[[#This Row],[Value]]/'[1]Active population 1'!C104 -> 0.13217787 | E97: =1-Table3_1[[#This Row],[Unemployment rate]] -> 0.86782213
A98: Female unemployed labor force
A99: Female unemployed labor force | B99: Q2 2011 | C99: 281.1 | D99: =Table3_1[[#This Row],[Value]]/'[1]Active population 1'!C113 -> 0.27378981 | E99: =1-Table3_1[[#This Row],[Unemployment rate]] -> 0.72621019
A100: Female unemployed labor force | B100: Q4 2011 | C100: 301.3 | D100: =Table3_1[[#This Row],[Value]]/'[1]Active population 1'!C114 -> 0.28238051 | E100: =1-Table3_1[[#This Row],[Unemployment rate]] -> 0.71761949
A101: Female unemployed labor force | B101: Q1 2012 | C101: 284 | D101: =Table3_1[[#This Row],[Value]]/'[1]Active population 1'!C115 -> 0.26611694 | E101: =1-Table3_1[[#This Row],[Unemployment rate]] -> 0.73388306
A102: Female unemployed labor force | B102: Q2 2012 | C102: 274.2 | D102: =Table3_1[[#This Row],[Value]]/'[1]Active population 1'!C116 -> 0.25604632 | E102: =1-Table3_1[[#This Row],[Unemployment rate]] -> 0.74395368
A103: Female unemployed labor force | B103: Q3 2012 | C103: 264.9 | D103: =Table3_1[[#This Row],[Value]]/'[1]Active population 1'!C117 -> 0.24908322 | E103: =1-Table3_1[[#This Row],[Unemployment rate]] -> 0.75091678
A104: Female unemployed labor force | B104: Q4 2012 | C104: 257.4 | D104: =Table3_1[[#This Row],[Value]]/'[1]Active population 1'!C118 -> 0.24232725 | E104: =1-Table3_1[[#This Row],[Unemployment rate]] -> 0.75767275
A105: Female unemployed labor force | B105: Q1 2013 | C105: 247.7 | D105: =Table3_1[[#This Row],[Value]]/'[1]Active population 1'!C119 -> 0.23304168 | E105: =1-Table3_1[[#This Row],[Unemployment rate]] -> 0.76695832
A106: Female unemployed labor force | B106: Q2 2013 | C106: 248.8 | D106: =Table3_1[[#This Row],[Value]]/'[1]Active population 1'!C120 -> 0.23000832 | E106: =1-Table3_1[[#This Row],[Unemployment rate]] -> 0.76999168
A107: Female unemployed labor force | B107: Q3 2013 | C107: 245.1 | D107: =Table3_1[[#This Row],[Value]]/'[1]Active population 1'!C121 -> 0.22465628 | E107: =1-Table3_1[[#This Row],[Unemployment rate]] -> 0.77534372
A108: Female unemployed labor force | B108: Q4 2013 | C108: 242.7 | D108: =Table3_1[[#This Row],[Value]]/'[1]Active population 1'!C122 -> 0.21947911 | E108: =1-Table3_1[[#This Row],[Unemployment rate]] -> 0.78052089
A109: Female unemployed labor force | B109: Q1 2014 | C109: 240.9 | D109: =Table3_1[[#This Row],[Value]]/'[1]Active population 1'!C123 -> 0.215397 | E109: =1-Table3_1[[#This Row],[Unemployment rate]] -> 0.784603
A110: Female unemployed labor force | B110: Q3 2014 | C110: 239.9 | D110: =Table3_1[[#This Row],[Value]]/'[1]Active population 1'!C124 -> 0.19793729 | E110: =1-Table3_1[[#This Row],[Unemployment rate]] -> 0.80206271
... A145: Female unemployed labor force | B145: Q2 2023 | C145: 260.6 | D145: =Table3_1[[#This Row],[Value]]/'[1]Active population 1'!C159 -> 0.21325696 | E145: =1-Table3_1[[#This Row],[Unemployment rate]] -> 0.78674304

Sheet Interest Rates
A1: money markets | B1: Attribute | C1: Value
A2: Nominal Interest Rate
A3: Nominal Interest Rate | B3: 1994 | C3: 8.81
A4: Nominal Interest Rate | B4: 1995 | C4: 8.81
A5: Nominal Interest Rate | B5: 1996 | C5: 7.81
A6: Nominal Interest Rate | B6: 1997 | C6: 6.88
A7: Nominal Interest Rate | B7: 1998 | C7: 6.88
A8: Nominal Interest Rate | B8: 1999 | C8: 5.88
A9: Nominal Interest Rate | B9: 2000 | C9: 5.88
A10: Nominal Interest Rate | B10: 2001 | C10: 5.94
A11: Nominal Interest Rate | B11: 2002 | C11: 5.91
A12: Nominal Interest Rate | B12: 2003 | C12: 5
A13: Nominal Interest Rate | B13: 2004 | C13: 5
A14: Nominal Interest Rate | B14: 2005 | C14: 5
... A31: Nominal Interest Rate | B31: 2022 | C31: 7.26
A32: Interest Rate on Savings
A33: Interest Rate on Savings | B33: 1994 | C33: 6.88
A34: Interest Rate on Savings | B34: 1995 | C34: 6.88
A35: Interest Rate on Savings | B35: 1996 | C35: 6.13
A36: Interest Rate on Savings | B36: 1997 | C36: 5
A37: Interest Rate on Savings | B37: 1998 | C37: 5
A38: Interest Rate on Savings | B38: 1999 | C38: 3.88
A39: Interest Rate on Savings | B39: 2000 | C39: 3.88
A40: Interest Rate on Savings | B40: 2001 | C40: 4
A41: Interest Rate on Savings | B41: 2002 | C41: 4
A42: Interest Rate on Savings | B42: 2003 | C42: 3
A43: Interest Rate on Savings | B43: 2004 | C43: 3
A44: Interest Rate on Savings | B44: 2005 | C44: 3
... A61: Interest Rate on Savings | B61: 2022 | C61: 6.25
A62: Average Subscription Rate on 5-Year Treasury Bills
A63: Average Subscription Rate on 5-Year Treasury Bills | B63: 1994 | C63: 10.06
A64: Average Subscription Rate on 5-Year Treasury Bills | B64: 1995 | C64: 10.13
A65: Average Subscription Rate on 5-Year Treasury Bills | B65: 1996 | C65: 9.63
A66: Average Subscription Rate on 5-Year Treasury Bills | B66: 1997 | C66: 9.06
A67: Average Subscription Rate on 5-Year Treasury Bills | B67: 1998 | C67: 7.88
A68: Average Subscription Rate on 5-Year Treasury Bills | B68: 1999 | C68: 7.63
A69: Average Subscription Rate on 5-Year Treasury Bills | B69: 2000 | C69: 7.14
A70: Average Subscription Rate on 5-Year Treasury Bills | B70: 2001 | C70: 6.85
A71: Average Subscription Rate on 5-Year Treasury Bills | B71: 2002 | C71: 6.69
A72: Average Subscription Rate on 5-Year Treasury Bills | B72: 2003 | C72: 6.52
A73: Average Subscription Rate on 5-Year Treasury Bills | B73: 2004 | C73: 6.61
A74: Average Subscription Rate on 5-Year Treasury Bills | B74: 2005 | C74: 6.3
... A80: Average Subscription Rate on 5-Year Treasury Bills | B80: 2011 | C80: 6.277
A81: Average Subscription Rate on 5-Year Treasury Bills | B81: 2012
A82: Average Subscription Rate on 5-Year Treasury Bills | B82: 2013
A83: Average Subscription Rate on 5-Year Treasury Bills | B83: 2014
A84: Average Subscription Rate on 5-Year Treasury Bills | B84: 2015
A85: Average Subscription Rate on 5-Year Treasury Bills | B85: 2016
A86: Average Subscription Rate on 5-Year Treasury Bills | B86: 2017
A87: Average Subscription Rate on 5-Year Treasury Bills | B87: 2018
A88: Average Subscription Rate on 5-Year Treasury Bills | B88: 2019
A89: Average Subscription Rate on 5-Year Treasury Bills | B89: 2020
A90: Average Subscription Rate on 5-Year Treasury Bills | B90: 2021
A91: Average Subscription Rate on 5-Year Treasury Bills | B91: 2022
A92: Maximum Overdraft Rate (used to determine the legal interest rate)
A93: Maximum Overdraft Rate (used to determine the legal interest rate) | B93: 1994 | C93: 13.81
A94: Maximum Overdraft Rate (used to determine the legal interest rate) | B94: 1995 | C94: 13.81
A95: Maximum Overdraft Rate (used to determine the legal interest rate) | B95: 1996 | C95: 12.81
A96: Maximum Overdraft Rate (used to determine the legal interest rate) | B96: 1997 | C96: 12.38
A97: Maximum Overdraft Rate (used to determine the legal interest rate) | B97: 1998 | C97: 13.88
A98: Maximum Overdraft Rate (used to determine the legal interest rate) | B98: 1999 | C98: 12.88
A99: Maximum Overdraft Rate (used to determine the legal interest rate) | B99: 2000 | C99: 12.88
A100: Maximum Overdraft Rate (used to determine the legal interest rate) | B100: 2001 | C100: 12.94
A101: Maximum Overdraft Rate (used to determine the legal interest rate) | B101: 2002 | C101: 12.91
A102: Maximum Overdraft Rate (used to determine the legal interest rate) | B102: 2003 | C102: 12
A103: Maximum Overdraft Rate (used to determine the legal interest rate) | B103: 2004 | C103: 12
A104: Maximum Overdraft Rate (used to determine the legal interest rate) | B104: 2005 | C104: 12.3
... A121: Maximum Overdraft Rate (used to determine the legal interest rate) | B121: 2022 | C121: 14.26

Sheet Inflation
A1: Consumer Price Indices | J1: Industrial Sales Price Indices
A2: Consumer Price Indices | B2: Attribute | C2: Value | D2: Inflation | E2: Arithmetic Annual Average | F2: 1+Inflation | G2: Product | H2: Geometric Annual Average | I2: Standard Deviation | J2: Industrial Sales Price Indices | K2: Attribute | L2: Value | M2: CPI-to-PPI Ratio
A3: Trends in the Family Consumer Price Index (Base Year: 2015 = 100) | B3: 43466 | C3: 122 | J3: Indices des prix à la vente industriel (IPVI) (2010 = 100) | K3: Jan-19 | L3: 145.6 | M3: =Table3_19[[#This Row],[Value]]/L3 -> 0.83791209
A4: Trends in the Family Consumer Price Index (Base Year: 2015 = 100) | B4: 43497 | C4: 122.1 | J4: Indices des prix à la vente industriel (IPVI) (2010 = 100) | K4: Feb-19 | L4: 146.6 | M4: =Table3_19[[#This Row],[Value]]/L4 -> 0.83287858
A5: Trends in the Family Consumer Price Index (Base Year: 2015 = 100) | B5: 43525 | C5: 122.6 | J5: Indices des prix à la vente industriel (IPVI) (2010 = 100) | K5: Mar-19 | L5: 146.9 | M5: =Table3_19[[#This Row],[Value]]/L5 -> 0.83458135
A6: Trends in the Family Consumer Price Index (Base Year: 2015 = 100) | B6: 43556 | C6: 123.6 | J6: Indices des prix à la vente industriel (IPVI) (2010 = 100) | K6: Apr-19 | L6: 146.9 | M6: =Table3_19[[#This Row],[Value]]/L6 -> 0.8413887
A7: Trends in the Family Consumer Price Index (Base Year: 2015 = 100) | B7: 43586 | C7: 124.2 | J7: Indices des prix à la vente industriel (IPVI) (2010 = 100) | K7: May-19 | L7: 146.9 | M7: =Table3_19[[#This Row],[Value]]/L7 -> 0.84547311
A8: Trends in the Family Consumer Price Index (Base Year: 2015 = 100) | B8: 43617 | C8: 124.6 | J8: Indices des prix à la vente industriel (IPVI) (2010 = 100) | K8: Jun-19 | L8: 147.2 | M8: =Table3_19[[#This Row],[Value]]/L8 -> 0.84646739
A9: Trends in the Family Consumer Price Index (Base Year: 2015 = 100) | B9: 43647 | C9: 124.9 | J9: Indices des prix à la vente industriel (IPVI) (2010 = 100) | K9: Jul-19 | L9: 146.3 | M9: =Table3_19[[#This Row],[Value]]/L9 -> 0.85372522
A10: Trends in the Family Consumer Price Index (Base Year: 2015 = 100) | B10: 43678 | C10: 125.6 | J10: Indices des prix à la vente industriel (IPVI) (2010 = 100) | K10: Aug-19 | L10: 146.6 | M10: =Table3_19[[#This Row],[Value]]/L10 -> 0.85675307
A11: Trends in the Family Consumer Price Index (Base Year: 2015 = 100) | B11: 43709 | C11: 126.4 | J11: Indices des prix à la vente industriel (IPVI) (2010 = 100) | K11: Sep-19 | L11: 147.6 | M11: =Table3_19[[#This Row],[Value]]/L11 -> 0.85636856
A12: Trends in the Family Consumer Price Index (Base Year: 2015 = 100) | B12: 43739 | C12: 127.4 | J12: Indices des prix à la vente industriel (IPVI) (2010 = 100) | K12: Oct-19 | L12: 148.6 | M12: =Table3_19[[#This Row],[Value]]/L12 -> 0.85733513
A13: Trends in the Family Consumer Price Index (Base Year: 2015 = 100) | B13: 43770 | C13: 128 | J13: Indices des prix à la vente industriel (IPVI) (2010 = 100) | K13: Nov-19 | L13: 149.3 | M13: =Table3_19[[#This Row],[Value]]/L13 -> 0.85733423
A14: Trends in the Family Consumer Price Index (Base Year: 2015 = 100) | B14: 43800 | C14: 128.3 | J14: Indices des prix à la vente industriel (IPVI) (2010 = 100) | K14: Dec-19 | L14: 149.3 | M14: =Table3_19[[#This Row],[Value]]/L14 -> 0.8593436
A15: Trends in the Family Consumer Price Index (Base Year: 2015 = 100) | B15: 43831 | C15: 129.1 | D15: =(Table3_19[[#This Row],[Value]]-C3)/C3 -> 0.058196721 | F15: =1+Table3_19[[#This Row],[Inflation]] -> 1.0581967 | G15: =Table3_19[[#This Row],[1+Inflation]] -> 1.0581967 | J15: Indices des prix à la vente industriel (IPVI) (2010 = 100) | K15: Jan-20 | L15: 147.9 | M15: =Table3_19[[#This Row],[Value]]/L15 -> 0.87288709
A16: Trends in the Family Consumer Price Index (Base Year: 2015 = 100) | B16: 43862 | C16: 129.1 | D16: =(Table3_19[[#This Row],[Value]]-C4)/C4 -> 0.057330057 | F16: =1+Table3_19[[#This Row],[Inflation]] -> 1.0573301 | G16: =Table3_19[[#This Row],[1+Inflation]]*F15 -> 1.1188632 | J16: Indices des prix à la vente industriel (IPVI) (2010 = 100) | K16: Feb-20 | L16: 147.7 | M16: =Table3_19[[#This Row],[Value]]/L16 -> 0.87406906
A17: Trends in the Family Consumer Price Index (Base Year: 2015 = 100) | B17: 43891 | C17: 130.2 | D17: =(Table3_19[[#This Row],[Value]]-C5)/C5 -> 0.061990212 | F17: =1+Table3_19[[#This Row],[Inflation]] -> 1.0619902 | G17: =G16*Table3_19[[#This Row],[1+Inflation]] -> 1.1882218 | J17: Indices des prix à la vente industriel (IPVI) (2010 = 100) | K17: Mar-20 | L17: 147.3 | M17: =Table3_19[[#This Row],[Value]]/L17 -> 0.88391039
A18: Trends in the Family Consumer Price Index (Base Year: 2015 = 100) | B18: 43922 | C18: 131.3 | D18: =(Table3_19[[#This Row],[Value]]-C6)/C6 -> 0.062297735 | F18: =1+Table3_19[[#This Row],[Inflation]] -> 1.0622977 | G18: =G17*Table3_19[[#This Row],[1+Inflation]] -> 1.2622453 | J18: Indices des prix à la vente industriel (IPVI) (2010 = 100) | K18: Apr-20 | L18: 149.2 | M18: =Table3_19[[#This Row],[Value]]/L18 -> 0.88002681
A19: Trends in the Family Consumer Price Index (Base Year: 2015 = 100) | B19: 43952 | C19: 132 | D19: =(Table3_19[[#This Row],[Value]]-C7)/C7 -> 0.062801932 | F19: =1+Table3_19[[#This Row],[Inflation]] -> 1.0628019 | G19: =G18*Table3_19[[#This Row],[1+Inflation]] -> 1.3415167 | J19: Indices des prix à la vente industriel (IPVI) (2010 = 100) | K19: May-20 | L19: 149.3 | M19: =Table3_19[[#This Row],[Value]]/L19 -> 0.88412592
A20: Trends in the Family Consumer Price Index (Base Year: 2015 = 100) | B20: 43983 | C20: 131.8 | D20: =(Table3_19[[#This Row],[Value]]-C8)/C8 -> 0.057784912 | F20: =1+Table3_19[[#This Row],[Inflation]] -> 1.0577849 | G20: =G19*Table3_19[[#This Row],[1+Inflation]] -> 1.4190362 | J20: Indices des prix à la vente industriel (IPVI) (2010 = 100) | K20: Jun-20 | L20: 149.9 | M20: =Table3_19[[#This Row],[Value]]/L20 -> 0.87925284
A21: Trends in the Family Consumer Price Index (Base Year: 2015 = 100) | B21: 44013 | C21: 132 | D21: =(Table3_19[[#This Row],[Value]]-C9)/C9 -> 0.056845476 | F21: =1+Table3_19[[#This Row],[Inflation]] -> 1.0568455 | G21: =G20*Table3_19[[#This Row],[1+Inflation]] -> 1.4997019 | J21: Indices des prix à la vente industriel (IPVI) (2010 = 100) | K21: Jul-20 | L21: 151.1 | M21: =Table3_19[[#This Row],[Value]]/L21 -> 0.87359365
A22: Trends in the Family Consumer Price Index (Base Year: 2015 = 100) | B22: 44044 | C22: 132.4 | D22: =(Table3_19[[#This Row],[Value]]-C10)/C10 -> 0.054140127 | F22: =1+Table3_19[[#This Row],[Inflation]] -> 1.0541401 | G22: =G21*Table3_19[[#This Row],[1+Inflation]] -> 1.580896 | J22: Indices des prix à la vente industriel (IPVI) (2010 = 100) | K22: Aug-20 | L22: 151 | M22: =Table3_19[[#This Row],[Value]]/L22 -> 0.87682119
A23: Trends in the Family Consumer Price Index (Base Year: 2015 = 100) | B23: 44075 | C23: 133.2 | D23: =(Table3_19[[#This Row],[Value]]-C11)/C11 -> 0.053797468 | F23: =1+Table3_19[[#This Row],[Inflation]] -> 1.0537975 | G23: =G22*Table3_19[[#This Row],[1+Inflation]] -> 1.6659442 | J23: Indices des prix à la vente industriel (IPVI) (2010 = 100) | K23: Sep-20 | L23: 151.7 | M23: =Table3_19[[#This Row],[Value]]/L23 -> 0.87804878
A24: Trends in the Family Consumer Price Index (Base Year: 2015 = 100) | B24: 44105 | C24: 134.3 | D24: =(Table3_19[[#This Row],[Value]]-C12)/C12 -> 0.054160126 | F24: =1+Table3_19[[#This Row],[Inflation]] -> 1.0541601 | G24: =G23*Table3_19[[#This Row],[1+Inflation]] -> 1.756172 | J24: Indices des prix à la vente industriel (IPVI) (2010 = 100) | K24: Oct-20 | L24: 154.3 | M24: =Table3_19[[#This Row],[Value]]/L24 -> 0.87038237
A25: Trends in the Family Consumer Price Index (Base Year: 2015 = 100) | B25: 44136 | C25: 134.2 | D25: =(Table3_19[[#This Row],[Value]]-C13)/C13 -> 0.0484375 | F25: =1+Table3_19[[#This Row],[Inflation]] -> 1.0484375 | G25: =G24*Table3_19[[#This Row],[1+Inflation]] -> 1.8412365 | J25: Indices des prix à la vente industriel (IPVI) (2010 = 100) | K25: Nov-20 | L25: 154.4 | M25: =Table3_19[[#This Row],[Value]]/L25 -> 0.86917098
A26: Trends in the Family Consumer Price Index (Base Year: 2015 = 100) | B26: 44166 | C26: 134.6 | D26: =(Table3_19[[#This Row],[Value]]-C14)/C14 -> 0.049103663 | E26: =AVERAGE(D15:D26) -> 0.056407161 | F26: =1+Table3_19[[#This Row],[Inflation]] -> 1.0491037 | G26: =G25*Table3_19[[#This Row],[1+Inflation]] -> 1.931648 | H26: =(Table3_19[[#This Row],[Product]]^(1/12))-1 -> 0.056397421 | I26: =_xlfn.STDEV.P(D15:D26) -> 0.0045347058 | J26: Indices des prix à la vente industriel (IPVI) (2010 = 100) | K26: Dec-20 | L26: 154.1 | M26: =Table3_19[[#This Row],[Value]]/L26 -> 0.87345879
A27: Trends in the Family Consumer Price Index (Base Year: 2015 = 100) | B27: 44197 | C27: 135.5 | D27: =(Table3_19[[#This Row],[Value]]-C15)/C15 -> 0.049573974 | F27: =1+Table3_19[[#This Row],[Inflation]] -> 1.049574 | G27: =Table3_19[[#This Row],[1+Inflation]] -> 1.049574 | J27: Indices des prix à la vente industriel (IPVI) (2010 = 100) | K27: Jan-21 | L27: 157.3 | M27: =Table3_19[[#This Row],[Value]]/L27 -> 0.86141132
A28: Trends in the Family Consumer Price Index (Base Year: 2015 = 100) | B28: 44228 | C28: 135.4 | D28: =(Table3_19[[#This Row],[Value]]-C16)/C16 -> 0.04879938 | F28: =1+Table3_19[[#This Row],[Inflation]] -> 1.0487994 | G28: =Table3_19[[#This Row],[1+Inflation]]*F27 -> 1.1007925 | J28: Indices des prix à la vente industriel (IPVI) (2010 = 100) | K28: Feb-21 | L28: 158.3 | M28: =Table3_19[[#This Row],[Value]]/L28 -> 0.85533797
A29: Trends in the Family Consumer Price Index (Base Year: 2015 = 100) | B29: 44256 | C29: 136.4 | D29: =(Table3_19[[#This Row],[Value]]-C17)/C17 -> 0.047619048 | F29: =1+Table3_19[[#This Row],[Inflation]] -> 1.047619 | G29: =G28*Table3_19[[#This Row],[1+Inflation]] -> 1.1532112 | J29: Indices des prix à la vente industriel (IPVI) (2010 = 100) | K29: Mar-21 | L29: 158.6 | M29: =Table3_19[[#This Row],[Value]]/L29 -> 0.86002522
A30: Trends in the Family Consumer Price Index (Base Year: 2015 = 100) | B30: 44287 | C30: 137.9 | D30: =(Table3_19[[#This Row],[Value]]-C18)/C18 -> 0.050266565 | F30: =1+Table3_19[[#This Row],[Inflation]] -> 1.0502666 | G30: =G29*Table3_19[[#This Row],[1+Inflation]] -> 1.2111792 | J30: Indices des prix à la vente industriel (IPVI) (2010 = 100) | K30: Apr-21 | L30: 162.1 | M30: =Table3_19[[#This Row],[Value]]/L30 -> 0.85070944
A31: Trends in the Family Consumer Price Index (Base Year: 2015 = 100) | B31: 44317 | C31: 138.6 | D31: =(Table3_19[[#This Row],[Value]]-C19)/C19 -> 0.05 | F31: =1+Table3_19[[#This Row],[Inflation]] -> 1.05 | G31: =G30*Table3_19[[#This Row],[1+Inflation]] -> 1.2717382 | J31: Indices des prix à la vente industriel (IPVI) (2010 = 100) | K31: May-21 | L31: 165.3 | M31: =Table3_19[[#This Row],[Value]]/L31 -> 0.8384755
A32: Trends in the Family Consumer Price Index (Base Year: 2015 = 100) | B32: 44348 | C32: 139.3 | D32: =(Table3_19[[#This Row],[Value]]-C20)/C20 -> 0.056904401 | F32: =1+Table3_19[[#This Row],[Inflation]] -> 1.0569044 | G32: =G31*Table3_19[[#This Row],[1+Inflation]] -> 1.3441056 | J32: Indices des prix à la vente industriel (IPVI) (2010 = 100) | K32: Jun-21 | L32: 164.9 | M32: =Table3_19[[#This Row],[Value]]/L32 -> 0.8447544
A33: Trends in the Family Consumer Price Index (Base Year: 2015 = 100) | B33: 44378 | C33: 140.5 | D33: =(Table3_19[[#This Row],[Value]]-C21)/C21 -> 0.064393939 | F33: =1+Table3_19[[#This Row],[Inflation]] -> 1.0643939 | G33: =G32*Table3_19[[#This Row],[1+Inflation]] -> 1.4306579 | J33: Indices des prix à la vente industriel (IPVI) (2010 = 100) | K33: Jul-21 | L33: 168.5 | M33: =Table3_19[[#This Row],[Value]]/L33 -> 0.83382789
A34: Trends in the Family Consumer Price Index (Base Year: 2015 = 100) | B34: 44409 | C34: 140.5 | D34: =(Table3_19[[#This Row],[Value]]-C22)/C22 -> 0.061178248 | F34: =1+Table3_19[[#This Row],[Inflation]] -> 1.0611782 | G34: =G33*Table3_19[[#This Row],[1+Inflation]] -> 1.5181831 | J34: Indices des prix à la vente industriel (IPVI) (2010 = 100) | K34: Aug-21 | L34: 166.2 | M34: =Table3_19[[#This Row],[Value]]/L34 -> 0.84536703
A35: Trends in the Family Consumer Price Index (Base Year: 2015 = 100) | B35: 44440 | C35: 141.4 | D35: =(Table3_19[[#This Row],[Value]]-C23)/C23 -> 0.061561562 | F35: =1+Table3_19[[#This Row],[Inflation]] -> 1.0615616 | G35: =G34*Table3_19[[#This Row],[1+Inflation]] -> 1.6116448 | J35: Indices des prix à la vente industriel (IPVI) (2010 = 100) | K35: Sep-21 | L35: 167.7 | M35: =Table3_19[[#This Row],[Value]]/L35 -> 0.84317233
A36: Trends in the Family Consumer Price Index (Base Year: 2015 = 100) | B36: 44470 | C36: 142.7 | D36: =(Table3_19[[#This Row],[Value]]-C24)/C24 -> 0.062546538 | F36: =1+Table3_19[[#This Row],[Inflation]] -> 1.0625465 | G36: =G35*Table3_19[[#This Row],[1+Inflation]] -> 1.7124476 | J36: Indices des prix à la vente industriel (IPVI) (2010 = 100) | K36: Oct-21 | L36: 168.5 | M36: =Table3_19[[#This Row],[Value]]/L36 -> 0.84688427
A37: Trends in the Family Consumer Price Index (Base Year: 2015 = 100) | B37: 44501 | C37: 142.9 | D37: =(Table3_19[[#This Row],[Value]]-C25)/C25 -> 0.064828614 | F37: =1+Table3_19[[#This Row],[Inflation]] -> 1.0648286 | G37: =G36*Table3_19[[#This Row],[1+Inflation]] -> 1.8234632 | J37: Indices des prix à la vente industriel (IPVI) (2010 = 100) | K37: Nov-21 | L37: 169 | M37: =Table3_19[[#This Row],[Value]]/L37 -> 0.84556213
A38: Trends in the Family Consumer Price Index (Base Year: 2015 = 100) | B38: 44531 | C38: 143.5 | D38: =(Table3_19[[#This Row],[Value]]-C26)/C26 -> 0.066121842 | E38: =AVERAGE(D27:D38) -> 0.056982843 | F38: =1+Table3_19[[#This Row],[Inflation]] -> 1.0661218 | G38: =G37*Table3_19[[#This Row],[1+Inflation]] -> 1.9440339 | H38: =(Table3_19[[#This Row],[Product]]^(1/12))-1 -> 0.056960246 | I38: =_xlfn.STDEV.P(D27:D38) -> 0.0069097653 | J38: Indices des prix à la vente industriel (IPVI) (2010 = 100) | K38: Dec-21 | L38: 169.2 | M38: =Table3_19[[#This Row],[Value]]/L38 -> 0.84810875
A39: Trends in the Family Consumer Price Index (Base Year: 2015 = 100) | B39: 44562 | C39: 144.5 | D39: =(Table3_19[[#This Row],[Value]]-C27)/C27 -> 0.066420664 | F39: =1+Table3_19[[#This Row],[Inflation]] -> 1.0664207 | G39: =Table3_19[[#This Row],[1+Inflation]] -> 1.0664207 | J39: Indices des prix à la vente industriel (IPVI) (2010 = 100) | K39: Jan-22 | L39: 173.2 | M39: =Table3_19[[#This Row],[Value]]/L39 -> 0.83429561
A40: Trends in the Family Consumer Price Index (Base Year: 2015 = 100) | B40: 44593 | C40: 145 | D40: =(Table3_19[[#This Row],[Value]]-C28)/C28 -> 0.070901034 | F40: =1+Table3_19[[#This Row],[Inflation]] -> 1.070901 | G40: =Table3_19[[#This Row],[1+Inflation]]*F39 -> 1.142031 | J40: Indices des prix à la vente industriel (IPVI) (2010 = 100) | K40: Feb-22 | L40: 173.5 | M40: =Table3_19[[#This Row],[Value]]/L40 -> 0.83573487
A41: Trends in the Family Consumer Price Index (Base Year: 2015 = 100) | B41: 44621 | C41: 146.2 | D41: =(Table3_19[[#This Row],[Value]]-C29)/C29 -> 0.071847507 | F41: =1+Table3_19[[#This Row],[Inflation]] -> 1.0718475 | G41: =G40*Table3_19[[#This Row],[1+Inflation]] -> 1.2240831 | J41: Indices des prix à la vente industriel (IPVI) (2010 = 100) | K41: Mar-22 | L41: 176.53 | M41: =Table3_19[[#This Row],[Value]]/L41 -> 0.82818784
A42: Trends in the Family Consumer Price Index (Base Year: 2015 = 100) | B42: 44652 | C42: 148.2 | D42: =(Table3_19[[#This Row],[Value]]-C30)/C30 -> 0.074691806 | F42: =1+Table3_19[[#This Row],[Inflation]] -> 1.0746918 | G42: =G41*Table3_19[[#This Row],[1+Inflation]] -> 1.315512 | J42: Indices des prix à la vente industriel (IPVI) (2010 = 100) | K42: Apr-22 | L42: 180.5 | M42: =Table3_19[[#This Row],[Value]]/L42 -> 0.82105263
A43: Trends in the Family Consumer Price Index (Base Year: 2015 = 100) | B43: 44682 | C43: 149.5 | D43: =(Table3_19[[#This Row],[Value]]-C31)/C31 -> 0.078643579 | F43: =1+Table3_19[[#This Row],[Inflation]] -> 1.0786436 | G43: =G42*Table3_19[[#This Row],[1+Inflation]] -> 1.4189686 | J43: Indices des prix à la vente industriel (IPVI) (2010 = 100) | K43: May-22 | L43: 183.3 | M43: =Table3_19[[#This Row],[Value]]/L43 -> 0.81560284
A44: Trends in the Family Consumer Price Index (Base Year: 2015 = 100) | B44: 44713 | C44: 150.5 | D44: =(Table3_19[[#This Row],[Value]]-C32)/C32 -> 0.08040201 | F44: =1+Table3_19[[#This Row],[Inflation]] -> 1.080402 | G44: =G43*Table3_19[[#This Row],[1+Inflation]] -> 1.5330566 | J44: Indices des prix à la vente industriel (IPVI) (2010 = 100) | K44: Jun-22 | L44: 184 | M44: =Table3_19[[#This Row],[Value]]/L44 -> 0.81793478
A45: Trends in the Family Consumer Price Index (Base Year: 2015 = 100) | B45: 44743 | C45: 152 | D45: =(Table3_19[[#This Row],[Value]]-C33)/C33 -> 0.081850534 | F45: =1+Table3_19[[#This Row],[Inflation]] -> 1.0818505 | G45: =G44*Table3_19[[#This Row],[1+Inflation]] -> 1.658538 | J45: Indices des prix à la vente industriel (IPVI) (2010 = 100) | K45: Jul-22 | L45: 187 | M45: =Table3_19[[#This Row],[Value]]/L45 -> 0.81283422
A46: Trends in the Family Consumer Price Index (Base Year: 2015 = 100) | B46: 44774 | C46: 152.7 | D46: =(Table3_19[[#This Row],[Value]]-C34)/C34 -> 0.08683274 | F46: =1+Table3_19[[#This Row],[Inflation]] -> 1.0868327 | G46: =G45*Table3_19[[#This Row],[1+Inflation]] -> 1.8025535 | J46: Indices des prix à la vente industriel (IPVI) (2010 = 100) | K46: Aug-22 | L46: 187.9 | M46: =Table3_19[[#This Row],[Value]]/L46 -> 0.81266631
A47: Trends in the Family Consumer Price Index (Base Year: 2015 = 100) | B47: 44805 | C47: 154.3 | D47: =(Table3_19[[#This Row],[Value]]-C35)/C35 -> 0.091230552 | F47: =1+Table3_19[[#This Row],[Inflation]] -> 1.0912306 | G47: =G46*Table3_19[[#This Row],[1+Inflation]] -> 1.9670014 | J47: Indices des prix à la vente industriel (IPVI) (2010 = 100) | K47: Sep-22 | L47: 189.1 | M47: =Table3_19[[#This Row],[Value]]/L47 -> 0.81597039
A48: Trends in the Family Consumer Price Index (Base Year: 2015 = 100) | B48: 44835 | C48: 155.9 | D48: =(Table3_19[[#This Row],[Value]]-C36)/C36 -> 0.092501752 | F48: =1+Table3_19[[#This Row],[Inflation]] -> 1.0925018 | G48: =G47*Table3_19[[#This Row],[1+Inflation]] -> 2.1489525 | J48: Indices des prix à la vente industriel (IPVI) (2010 = 100) | K48: Oct-22 | L48: 189.7 | M48: =Table3_19[[#This Row],[Value]]/L48 -> 0.82182393
A49: Trends in the Family Consumer Price Index (Base Year: 2015 = 100) | B49: 44866 | C49: 156.9 | D49: =(Table3_19[[#This Row],[Value]]-C37)/C37 -> 0.097970609 | F49: =1+Table3_19[[#This Row],[Inflation]] -> 1.0979706 | G49: =G48*Table3_19[[#This Row],[1+Inflation]] -> 2.3594867 | J49: Indices des prix à la vente industriel (IPVI) (2010 = 100) | K49: Nov-22 | L49: 186.6 | M49: =Table3_19[[#This Row],[Value]]/L49 -> 0.84083601
A50: Trends in the Family Consumer Price Index (Base Year: 2015 = 100) | B50: 44896 | C50: 158 | D50: =(Table3_19[[#This Row],[Value]]-C38)/C38 -> 0.1010453 | E50: =AVERAGE(D39:D50) -> 0.082861507 | F50: =1+Table3_19[[#This Row],[Inflation]] -> 1.1010453 | G50: =G49*Table3_19[[#This Row],[1+Inflation]] -> 2.5979017 | H50: =(Table3_19[[#This Row],[Product]]^(1/12))-1 -> 0.082809089 | I50: =_xlfn.STDEV.P(D39:D50) -> 0.01066126 | J50: Indices des prix à la vente industriel (IPVI) (2010 = 100) | K50: Dec-22 | L50: 186.4 | M50: =Table3_19[[#This Row],[Value]]/L50 -> 0.84763948
A51: Trends in the Family Consumer Price Index (Base Year: 2015 = 100) | B51: 44927 | C51: 159.3 | D51: =(Table3_19[[#This Row],[Value]]-C39)/C39 -> 0.10242215 | F51: =1+Table3_19[[#This Row],[Inflation]] -> 1.1024221 | G51: =Table3_19[[#This Row],[1+Inflation]] -> 1.1024221 | J51: Indices des prix à la vente industriel (IPVI) (2010 = 100) | K51: Jan-23 | L51: 188.1 | M51: =Table3_19[[#This Row],[Value]]/L51 -> 0.84688995
A52: Trends in the Family Consumer Price Index (Base Year: 2015 = 100) | B52: 44958 | C52: 160.1 | D52: =(Table3_19[[#This Row],[Value]]-C40)/C40 -> 0.10413793 | F52: =1+Table3_19[[#This Row],[Inflation]] -> 1.1041379 | G52: =Table3_19[[#This Row],[1+Inflation]]*F51 -> 1.2172261 | J52: Indices des prix à la vente industriel (IPVI) (2010 = 100) | K52: Feb-23 | L52: 187.7 | M52: =Table3_19[[#This Row],[Value]]/L52 -> 0.85295685
A53: Trends in the Family Consumer Price Index (Base Year: 2015 = 100) | B53: 44986 | C53: 161.2 | D53: =(Table3_19[[#This Row],[Value]]-C41)/C41 -> 0.10259918 | F53: =1+Table3_19[[#This Row],[Inflation]] -> 1.1025992 | G53: =G52*Table3_19[[#This Row],[1+Inflation]] -> 1.3421125 | J53: Indices des prix à la vente industriel (IPVI) (2010 = 100) | K53: Mar-23 | L53: 188.1 | M53: =Table3_19[[#This Row],[Value]]/L53 -> 0.85699096
A54: Trends in the Family Consumer Price Index (Base Year: 2015 = 100) | B54: 45017 | C54: 163.1 | D54: =(Table3_19[[#This Row],[Value]]-C42)/C42 -> 0.10053981 | F54: =1+Table3_19[[#This Row],[Inflation]] -> 1.1005398 | G54: =G53*Table3_19[[#This Row],[1+Inflation]] -> 1.4770482 | J54: Indices des prix à la vente industriel (IPVI) (2010 = 100) | K54: Apr-23 | L54: 187.9 | M54: =Table3_19[[#This Row],[Value]]/L54 -> 0.8680149
A55: Trends in the Family Consumer Price Index (Base Year: 2015 = 100) | B55: 45047 | C55: 163.9 | D55: =(Table3_19[[#This Row],[Value]]-C43)/C43 -> 0.09632107 | F55: =1+Table3_19[[#This Row],[Inflation]] -> 1.0963211 | G55: =G54*Table3_19[[#This Row],[1+Inflation]] -> 1.6193191 | J55: Indices des prix à la vente industriel (IPVI) (2010 = 100) | K55: May-23 | L55: 186.6 | M55: =Table3_19[[#This Row],[Value]]/L55 -> 0.87834941
A56: Trends in the Family Consumer Price Index (Base Year: 2015 = 100) | B56: 45078 | C56: 164.6 | D56: =(Table3_19[[#This Row],[Value]]-C44)/C44 -> 0.093687708 | F56: =1+Table3_19[[#This Row],[Inflation]] -> 1.0936877 | G56: =G55*Table3_19[[#This Row],[1+Inflation]] -> 1.7710294 | J56: Indices des prix à la vente industriel (IPVI) (2010 = 100) | K56: Jun-23 | L56: 188 | M56: =Table3_19[[#This Row],[Value]]/L56 -> 0.87553191
A57: Trends in the Family Consumer Price Index (Base Year: 2015 = 100) | B57: 45108 | C57: 165.8 | D57: =(Table3_19[[#This Row],[Value]]-C45)/C45 -> 0.090789474 | F57: =1+Table3_19[[#This Row],[Inflation]] -> 1.0907895 | G57: =G56*Table3_19[[#This Row],[1+Inflation]] -> 1.9318202 | J57: Indices des prix à la vente industriel (IPVI) (2010 = 100) | K57: Jul-23 | L57: 188.3 | M57: =Table3_19[[#This Row],[Value]]/L57 -> 0.88050982
A58: Trends in the Family Consumer Price Index (Base Year: 2015 = 100) | B58: 45139 | C58: 166.8 | D58: =(Table3_19[[#This Row],[Value]]-C46)/C46 -> 0.092337917 | F58: =1+Table3_19[[#This Row],[Inflation]] -> 1.0923379 | G58: =G57*Table3_19[[#This Row],[1+Inflation]] -> 2.1102005 | J58: Indices des prix à la vente industriel (IPVI) (2010 = 100) | K58: Aug-23 | L58: 187.4 | M58: =Table3_19[[#This Row],[Value]]/L58 -> 0.89007471
A59: Trends in the Family Consumer Price Index (Base Year: 2015 = 100) | B59: 45170 | C59: 168.1 | D59: =(Table3_19[[#This Row],[Value]]-C47)/C47 -> 0.089436163 | F59: =1+Table3_19[[#This Row],[Inflation]] -> 1.0894362 | G59: =G58*Table3_19[[#This Row],[1+Inflation]] -> 2.2989287 | J59: Indices des prix à la vente industriel (IPVI) (2010 = 100) | K59: Sep-23 | L59: 187.9 | M59: =Table3_19[[#This Row],[Value]]/L59 -> 0.8946248
A60: Trends in the Family Consumer Price Index (Base Year: 2015 = 100) | B60: 45200 | C60: 169.4 | D60: =(Table3_19[[#This Row],[Value]]-C48)/C48 -> 0.08659397 | F60: =1+Table3_19[[#This Row],[Inflation]] -> 1.086594 | G60: =G59*Table3_19[[#This Row],[1+Inflation]] -> 2.4980021 | J60: Indices des prix à la vente industriel (IPVI) (2010 = 100) | K60: Oct-23 | L60: 190.9 | M60: =Table3_19[[#This Row],[Value]]/L60 -> 0.88737559
A61: Trends in the Family Consumer Price Index (Base Year: 2015 = 100) | B61: 45231 | C61: 169.8 | D61: =(Table3_19[[#This Row],[Value]]-C49)/C49 -> 0.082217973 | F61: =1+Table3_19[[#This Row],[Inflation]] -> 1.082218 | G61: =G60*Table3_19[[#This Row],[1+Inflation]] -> 2.7033828 | J61: Indices des prix à la vente industriel (IPVI) (2010 = 100) | K61: Nov-23 | L61: 190.8 | M61: =Table3_19[[#This Row],[Value]]/L61 -> 0.88993711
A62: Trends in the Family Consumer Price Index (Base Year: 2015 = 100) | B62: 45261 | C62: 170.8 | D62: =(Table3_19[[#This Row],[Value]]-C50)/C50 -> 0.081012658 | E62: =AVERAGE(D51:D62) -> 0.093508 | F62: =1+Table3_19[[#This Row],[Inflation]] -> 1.0810127 | G62: =G61*Table3_19[[#This Row],[1+Inflation]] -> 2.922391 | H62: =(Table3_19[[#This Row],[Product]]^(1/12))-1 -> 0.093481719 | I62: =_xlfn.STDEV.P(D51:D62) -> 0.0075787004 | J62: Indices des prix à la vente industriel (IPVI) (2010 = 100) | K62: Dec-23 | L62: 190.7 | M62: =Table3_19[[#This Row],[Value]]/L62 -> 0.89564761
A63: Trends in the Family Consumer Price Index (Base Year: 2015 = 100) | B63: 45292 | C63: 171.7 | D63: =(Table3_19[[#This Row],[Value]]-C51)/C51 -> 0.077840552 | F63: =1+Table3_19[[#This Row],[Inflation]] -> 1.0778406 | G63: =Table3_19[[#This Row],[1+Inflation]] -> 1.0778406 | J63: Indices des prix à la vente industriel (IPVI) (2010 = 100) | K63: Jan-24 | L63: 192.8 | M63: =Table3_19[[#This Row],[Value]]/L63 -> 0.89056017
A64: Trends in the Family Consumer Price Index (Base Year: 2015 = 100) | B64: 45323 | C64: 172.1 | D64: =(Table3_19[[#This Row],[Value]]-C52)/C52 -> 0.074953154 | F64: =1+Table3_19[[#This Row],[Inflation]] -> 1.0749532 | G64: =Table3_19[[#This Row],[1+Inflation]]*F63 -> 1.1586281 | J64: Indices des prix à la vente industriel (IPVI) (2010 = 100) | K64: Feb-24 | L64: 193.5 | M64: =Table3_19[[#This Row],[Value]]/L64 -> 0.88940568
A65: Trends in the Family Consumer Price Index (Base Year: 2015 = 100) | B65: 45352 | C65: 173.3 | D65: =(Table3_19[[#This Row],[Value]]-C53)/C53 -> 0.075062035 | F65: =1+Table3_19[[#This Row],[Inflation]] -> 1.075062 | G65: =G64*Table3_19[[#This Row],[1+Inflation]] -> 1.2455971 | J65: Indices des prix à la vente industriel (IPVI) (2010 = 100) | K65: Mar-24 | L65: 193.9 | M65: =Table3_19[[#This Row],[Value]]/L65 -> 0.89375967
A66: Trends in the Family Consumer Price Index (Base Year: 2015 = 100) | B66: 45383 | C66: 174.8 | D66: =(Table3_19[[#This Row],[Value]]-C54)/C54 -> 0.071735132 | F66: =1+Table3_19[[#This Row],[Inflation]] -> 1.0717351 | G66: =G65*Table3_19[[#This Row],[1+Inflation]] -> 1.3349502 | J66: Indices des prix à la vente industriel (IPVI) (2010 = 100) | K66: Apr-24 | L66: 194.6 | M66: =Table3_19[[#This Row],[Value]]/L66 -> 0.89825283
A67: Trends in the Family Consumer Price Index (Base Year: 2015 = 100) | B67: 45413 | C67: 175.7 | D67: =(Table3_19[[#This Row],[Value]]-C55)/C55 -> 0.071995119 | F67: =1+Table3_19[[#This Row],[Inflation]] -> 1.0719951 | G67: =G66*Table3_19[[#This Row],[1+Inflation]] -> 1.4310601 | J67: Indices des prix à la vente industriel (IPVI) (2010 = 100) | K67: May-24 | L67: 194.8 | M67: =Table3_19[[#This Row],[Value]]/L67 -> 0.90195072
A68: Trends in the Family Consumer Price Index (Base Year: 2015 = 100) | B68: 45444 | C68: 176.6 | D68: =(Table3_19[[#This Row],[Value]]-C56)/C56 -> 0.07290401 | F68: =1+Table3_19[[#This Row],[Inflation]] -> 1.072904 | G68: =G67*Table3_19[[#This Row],[1+Inflation]] -> 1.5353901 | J68: Indices des prix à la vente industriel (IPVI) (2010 = 100) | K68: Jun-24 | L68: 195.2 | M68: =Table3_19[[#This Row],[Value]]/L68 -> 0.90471311
A69: Trends in the Family Consumer Price Index (Base Year: 2015 = 100) | B69: 45474 | C69: 177.3 | D69: =(Table3_19[[#This Row],[Value]]-C57)/C57 -> 0.069360676 | F69: =1+Table3_19[[#This Row],[Inflation]] -> 1.0693607 | G69: =G68*Table3_19[[#This Row],[1+Inflation]] -> 1.6418858 | J69: Indices des prix à la vente industriel (IPVI) (2010 = 100) | K69: Jul-24 | L69: 196.5 | M69: =Table3_19[[#This Row],[Value]]/L69 -> 0.90229008
A70: Trends in the Family Consumer Price Index (Base Year: 2015 = 100) | B70: 45505 | C70: 177.9 | D70: =(Table3_19[[#This Row],[Value]]-C58)/C58 -> 0.066546763 | F70: =1+Table3_19[[#This Row],[Inflation]] -> 1.0665468 | G70: =G69*Table3_19[[#This Row],[1+Inflation]] -> 1.7511479 | J70: Indices des prix à la vente industriel (IPVI) (2010 = 100) | K70: Aug-24 | L70: 197.5 | M70: =Table3_19[[#This Row],[Value]]/L70 -> 0.90075949
A71: Trends in the Family Consumer Price Index (Base Year: 2015 = 100) | B71: 45536 | C71: 179.3 | D71: =(Table3_19[[#This Row],[Value]]-C59)/C59 -> 0.066627008 | F71: =1+Table3_19[[#This Row],[Inflation]] -> 1.066627 | G71: =G70*Table3_19[[#This Row],[1+Inflation]] -> 1.8678217 | J71: Indices des prix à la vente industriel (IPVI) (2010 = 100) | K71: Sep-24 | L71: 197.5 | M71: =Table3_19[[#This Row],[Value]]/L71 -> 0.9078481
A72: Trends in the Family Consumer Price Index (Base Year: 2015 = 100) | B72: 45566 | C72: 180.8 | D72: =(Table3_19[[#This Row],[Value]]-C60)/C60 -> 0.06729634 | F72: =1+Table3_19[[#This Row],[Inflation]] -> 1.0672963 | G72: =G71*Table3_19[[#This Row],[1+Inflation]] -> 1.9935193 | J72: Indices des prix à la vente industriel (IPVI) (2010 = 100) | K72: Oct-24 | L72: 199.5 | M72: =Table3_19[[#This Row],[Value]]/L72 -> 0.90626566
A73: Trends in the Family Consumer Price Index (Base Year: 2015 = 100) | B73: 45597 | C73: 181 | D73: =(Table3_19[[#This Row],[Value]]-C61)/C61 -> 0.065959953 | F73: =1+Table3_19[[#This Row],[Inflation]] -> 1.06596 | G73: =G72*Table3_19[[#This Row],[1+Inflation]] -> 2.1250117 | J73: Indices des prix à la vente industriel (IPVI) (2010 = 100) | K73: Nov-24 | L73: 200.4 | M73: =Table3_19[[#This Row],[Value]]/L73 -> 0.90319361
A74: Trends in the Family Consumer Price Index (Base Year: 2015 = 100) | B74: 45627 | C74: 181.3 | D74: =(Table3_19[[#This Row],[Value]]-C62)/C62 -> 0.06147541 | E74: =AVERAGE(D63:D74) -> 0.070146346 | F74: =1+Table3_19[[#This Row],[Inflation]] -> 1.0614754 | G74: =G73*Table3_19[[#This Row],[1+Inflation]] -> 2.2556477 | H74: =(Table3_19[[#This Row],[Product]]^(1/12))-1 -> 0.070136733 | I74: =_xlfn.STDEV.P(D63:D74) -> 0.004535147 | J74: Indices des prix à la vente industriel (IPVI) (2010 = 100) | K74: Dec-24 | L74: 200 | M74: =Table3_19[[#This Row],[Value]]/L74 -> 0.9065
A75: Trends in the Family Consumer Price Index (Base Year: 2015 = 100) | B75: 45658 | C75: 182 | D75: =(Table3_19[[#This Row],[Value]]-C63)/C63 -> 0.059988352 | F75: =1+Table3_19[[#This Row],[Inflation]] -> 1.0599884 | G75: =Table3_19[[#This Row],[1+Inflation]] -> 1.0599884 | J75: Indices des prix à la vente industriel (IPVI) (2010 = 100) | K75: Jan-25 | L75: 201 | M75: =Table3_19[[#This Row],[Value]]/L75 -> 0.90547264
A76: Trends in the Family Consumer Price Index (Base Year: 2015 = 100) | B76: 45689 | C76: 181.8 | D76: =(Table3_19[[#This Row],[Value]]-C64)/C64 -> 0.05636258 | F76: =1+Table3_19[[#This Row],[Inflation]] -> 1.0563626 | G76: =Table3_19[[#This Row],[1+Inflation]]*F75 -> 1.119732 | J76: Indices des prix à la vente industriel (IPVI) (2010 = 100) | K76: Feb-25 | L76: 201.5 | M76: =Table3_19[[#This Row],[Value]]/L76 -> 0.90223325
A77: Trends in the Family Consumer Price Index (Base Year: 2015 = 100) | B77: 45717 | C77: 183.5 | D77: =(Table3_19[[#This Row],[Value]]-C65)/C65 -> 0.058857473 | F77: =1+Table3_19[[#This Row],[Inflation]] -> 1.0588575 | G77: =G76*Table3_19[[#This Row],[1+Inflation]] -> 1.1856366 | J77: Indices des prix à la vente industriel (IPVI) (2010 = 100) | K77: Mar-25 | L77: 201.1 | M77: =Table3_19[[#This Row],[Value]]/L77 -> 0.91248135
A78: Trends in the Family Consumer Price Index (Base Year: 2015 = 100) | B78: 45748 | C78: 184.6 | D78: =(Table3_19[[#This Row],[Value]]-C66)/C66 -> 0.056064073 | F78: =1+Table3_19[[#This Row],[Inflation]] -> 1.0560641 | G78: =G77*Table3_19[[#This Row],[1+Inflation]] -> 1.2521082 | J78: Indices des prix à la vente industriel (IPVI) (2010 = 100) | K78: Apr-25 | L78: 202.3 | M78: =Table3_19[[#This Row],[Value]]/L78 -> 0.91250618
A79: Trends in the Family Consumer Price Index (Base Year: 2015 = 100) | B79: 45778 | C79: 185.3 | D79: =(Table3_19[[#This Row],[Value]]-C67)/C67 -> 0.054638589 | F79: =1+Table3_19[[#This Row],[Inflation]] -> 1.0546386 | G79: =G78*Table3_19[[#This Row],[1+Inflation]] -> 1.3205217 | J79: Indices des prix à la vente industriel (IPVI) (2010 = 100) | K79: May-25 | L79: 202.5 | M79: =Table3_19[[#This Row],[Value]]/L79 -> 0.91506173
A80: Trends in the Family Consumer Price Index (Base Year: 2015 = 100) | B80: 45809 | C80: 186.1 | D80: =(Table3_19[[#This Row],[Value]]-C68)/C68 -> 0.053793884 | F80: =1+Table3_19[[#This Row],[Inflation]] -> 1.0537939 | G80: =G79*Table3_19[[#This Row],[1+Inflation]] -> 1.3915577 | J80: Indices des prix à la vente industriel (IPVI) (2010 = 100) | K80: Jun-25 | L80: 201.9 | M80: =Table3_19[[#This Row],[Value]]/L80 -> 0.92174344
A81: Trends in the Family Consumer Price Index (Base Year: 2015 = 100) | B81: 45839 | C81: 186.7 | D81: =(Table3_19[[#This Row],[Value]]-C69)/C69 -> 0.053017484 | F81: =1+Table3_19[[#This Row],[Inflation]] -> 1.0530175 | G81: =G80*Table3_19[[#This Row],[1+Inflation]] -> 1.4653346
A82: Trends in the Family Consumer Price Index (Base Year: 2015 = 100) | B82: 45870 | C82: 187.2 | D82: =(Table3_19[[#This Row],[Value]]-C70)/C70 -> 0.05227656 | E82: =AVERAGE(D75:D82) -> 0.055624874 | F82: =1+Table3_19[[#This Row],[Inflation]] -> 1.0522766 | G82: =G81*Table3_19[[#This Row],[1+Inflation]] -> 1.5419372 | H82: =(Table3_19[[#This Row],[Product]]^(1/8))-1 -> 0.055621764 | I82: =_xlfn.STDEV.P(D75:D82) -> 0.0025632428
H83: Standard Deviation Inflation | I83: =_xlfn.STDEV.P(D15:D82) -> 0.016130227

Sheet Budget Deficit
B1: 2015 | C1: 2016 | D1: 2017 | E1: 2018 | F1: 2019 | G1: 2020 | H1: 2021 | I1: 2022 | J1: 2023 | K1: 2024
A2: Need Financing / Current and Capital Resources | B2: -17.6 | C2: -18.3 | D2: -19.5 | E2: -19.8 | F2: -14.2 | G2: -11 | H2: -10.1 | I2: -12.2 | J2: -1.3 | K2: -2.5
A3: External Current and Capital Resources | B3: 40447.5 | C3: 42349.7 | D3: 49764.4 | E3: 59161.5 | F3: 65335.8 | G3: 54946.5 | H3: 67175.8 | I3: 87711.7 | J3: 95945.6 | K3: 96083.4
A4: Need Financing | B4: =B2*B3 -> -711876 | C4: =C2*C3 -> -774999.51 | D4: =D2*D3 -> -970405.8 | E4: =E2*E3 -> -1171397.7 | F4: =F2*F3 -> -927768.36 | G4: =G2*G3 -> -604411.5 | H4: =H2*H3 -> -678475.58 | I4: =I2*I3 -> -1070082.7 | ... K4: =K2*K3 -> -240208.5

Sheet Exports by Country
A1: Trade by country | B1: Attribute | C1: Value | D1: Ratio | F1: Exports by Country | G1: 2000 | H1: 2001 | I1: 2002 | J1: 2003 | K1: 2004 | L1: 2005 | M1: 2006 | N1: 2007 | O1: 2008 | P1: 2009 | Q1: 2010 | R1: 2011 | S1: 2012 | T1: 2013 | U1: 2014 | V1: 2015 | W1: 2016 | X1: 2017 | Y1: 2018
A2: Valeur des exportations par pays | F2: Valeur des exportations destinées à l'Algérie | G2: 84.3 | H2: 109 | I2: 126.5 | J2: 133.4 | K2: 135.6 | L2: 237.2 | M2: 250.2 | N2: 367.3 | O2: 499.3 | P2: 608.2 | Q2: 679.7 | R2: 656 | S2: 757 | T2: 789.8 | U2: 1049.5 | V2: 1094.9 | W2: 1426 | X2: 1131.1 | Y2: 1121.7
A3: Valeur des exportations par pays | B3: 2000 | C3: 8004.8 | F3: Valeur des exportations destinées à l'Allemagne | G3: 1001.8 | H3: 1114 | I3: 1109.8 | J3: 1105.6 | K3: 1110.1 | L3: 1156.5 | M3: 1220.3 | N3: 1596.7 | O3: 1637.1 | P3: 1711.8 | Q3: 1987.4 | R3: 2271.4 | S3: 2182.8 | T3: 2489.8 | U3: 2899.7 | V3: 2897.1 | W3: 3072.1 | X3: 3990.9 | Y3: 4918.1
A4: Valeur des exportations par pays | B4: 2001 | C4: 9536.2 | F4: Valeur des exportations destinées à l'Espagne | G4: 434.4 | H4: 460 | I4: 461.5 | J4: 481.8 | K4: 729.4 | L4: 762.4 | M4: 995.4 | N4: 1002.8 | O4: 1157.6 | P4: 656.2 | Q4: 912.2 | R4: 1079.4 | S4: 1150.2 | T4: 1304.2 | U4: 1006.1 | V4: 1372.8 | W4: 1019.7 | X4: 1305.5 | Y4: 2056.4
A5: Valeur des exportations par pays | B5: 2002 | C5: 9648.6 | F5: Valeur des exportations destinées à l'Italie | G5: 1842.2 | H5: 2207 | I5: 2081.1 | J5: 2281.4 | K5: 3105.7 | L5: 3308.2 | M5: 3437 | N5: 4519.2 | O5: 4883.9 | P5: 4095.1 | Q5: 4674.5 | R5: 5432.3 | S5: 5013.4 | T5: 5116.7 | U5: 5433.4 | V5: 5093.6 | W5: 5075.4 | X5: 5670.3 | Y5: 6516.8
A6: Valeur des exportations par pays | B6: 2003 | C6: 10342.6 | F6: Valeur des exportations destinées au Belgique | G6: 406.1 | H6: 464.2 | I6: 415.1 | J6: 405.9 | K6: 369 | L6: 373.8 | M6: 367.6 | N6: 458.4 | O6: 526.1 | P6: 430.7 | Q6: 458.5 | R6: 473.4 | S6: 557.2 | T6: 563.2 | U6: 520.8 | V6: 494.6 | W6: 529.8 | X6: 600.2 | Y6: 664.6
A7: Valeur des exportations par pays | B7: 2004 | C7: 12403.8 | F7: Valeur des exportations destinées au Brésil | G7: 39.9 | H7: 26.6 | I7: 45.8 | J7: 57.1 | K7: 81 | L7: 62 | M7: 94.2 | N7: 144.8 | O7: 232.3 | P7: 134.3 | Q7: 165.4 | R7: 159.8 | S7: 173.8 | T7: 197.8 | U7: 60.2 | V7: 59.1 | W7: 60.7 | X7: 41.6 | Y7: 35.2
A8: Valeur des exportations par pays | B8: 2005 | C8: 13793.6 | F8: Valeur des exportations destinées au Chine populaire | G8: 0.5 | H8: 22.6 | I8: 21.7 | J8: 22.3 | K8: 31.8 | L8: 23.2 | M8: 56.5 | N8: 23.1 | O8: 72.4 | P8: 93.8 | Q8: 67.5 | R8: 57.9 | S8: 131.5 | T8: 67.2 | U8: 104.6 | V8: 55.5 | W8: 61.9 | X8: 75 | Y8: 287.2
A9: Valeur des exportations par pays | B9: 2006 | C9: 15558 | F9: Valeur des exportations destinées au Etats-Unis d'Amérique | G9: 57.6 | H9: 91.3 | I9: 76 | J9: 62.5 | K9: 144.5 | L9: 86.6 | M9: 204.1 | N9: 214 | O9: 395.3 | P9: 265.3 | Q9: 556.3 | R9: 388.9 | S9: 509.2 | T9: 645.3 | U9: 412.8 | V9: 693.7 | W9: 526.5 | X9: 762.9 | Y9: 1120
A10: Valeur des exportations par pays | B10: 2007 | C10: 19409.6 | F10: Valeur des exportations destinées au France | G10: 2145.7 | H10: 2751.3 | I10: 3025 | J10: 3365.5 | K10: 4041.9 | L10: 4525.1 | M10: 5020.7 | N10: 6239.2 | O10: 6735.3 | P10: 5770.7 | Q10: 6749.8 | R10: 7695.4 | S10: 7154.6 | T10: 7305.5 | U10: 8054.1 | V10: 8091.2 | W10: 9314.2 | X10: 10516.7 | Y10: 12011.8
A11: Valeur des exportations par pays | B11: 2008 | C11: 23637 | F11: Valeur des exportations destinées au Japon | G11: 20.1 | H11: 15.7 | I11: 11.5 | J11: 17.7 | K11: 28 | L11: 28 | M11: 35.6 | N11: 48.9 | O11: 89.7 | P11: 73.4 | Q11: 85.7 | R11: 150 | S11: 140.8 | T11: 118.4 | U11: 72.5 | V11: 52 | W11: 69 | X11: 42.1 | Y11: 32.8
A12: Valeur des exportations par pays | B12: 2009 | C12: 19469.2 | F12: Valeur des exportations destinées au Libye | G12: 288.9 | H12: 357.5 | I12: 464.9 | J12: 453.8 | K12: 499.9 | L12: 622.6 | M12: 825.8 | N12: 892.7 | O12: 1065.2 | P12: 1121.2 | Q12: 1048.5 | R12: 1103.3 | S12: 1293.2 | T12: 1411 | U12: 1132.1 | V12: 1059.4 | W12: 950.5 | X12: 954.3 | Y12: 1313.3
A13: Valeur des exportations par pays | B13: 2010 | C13: 23519 | F13: Valeur des exportations destinées au Maroc | G13: 34.8 | H13: 58.7 | I13: 72.2 | J13: 69.7 | K13: 92.4 | L13: 141.9 | M13: 144.6 | N13: 221.3 | O13: 286.5 | P13: 282.2 | Q13: 332.1 | R13: 336.7 | S13: 333 | T13: 312.1 | U13: 304.5 | V13: 353.3 | W13: 363.2 | X13: 448.3 | Y13: 602.3
A14: Valeur des exportations par pays | B14: 2011 | C14: 25091.9 | F14: Valeur des exportations destinées au Pays-Bas | G14: 280.7 | H14: 233.9 | I14: 211.7 | J14: 239.1 | K14: 271.3 | L14: 304.9 | M14: 310.4 | N14: 458.9 | O14: 516.7 | P14: 313.6 | Q14: 515.5 | R14: 587.2 | S14: 894.6 | T14: 989.7 | U14: 778.8 | V14: 469.3 | W14: 454 | X14: 603.8 | Y14: 960.1
... A20: Valeur des exportations par pays | B20: 2017 | C20: 34426.6 | F20: Valeur des exportations par pays | G20: 8004.8 | H20: 9536.2 | I20: 9648.6 | J20: 10342.6 | K20: 12403.8 | L20: 13793.6 | M20: 15558 | N20: 19409.6 | O20: 23637 | P20: 19469.2 | Q20: 23519 | R20: 25091.9 | S20: 26547.7 | T20: 27701.2 | U20: 28406.7 | V20: 27607.2 | W20: 29145.6 | X20: 34426.6 | Y20: 40987.4
A21: Valeur des exportations par pays | B21: 2018 | C21: 40987.4 | F21: Top 5 Partners Share | G21: =SUM(G3:G6,G10)/G20 -> 0.728338 | H21: =SUM(H3:H6,H10)/H20 -> 0.73367798 | I21: =SUM(I3:I5,I10,I12)/I20 -> 0.74024211 | J21: =SUM(J3:J5,J10,J12)/J20 -> 0.74334307 | K21: =SUM(K3:K5,K10,K12)/K20 -> 0.76484626 | L21: =SUM(L3:L5,L10,L12)/L20 -> 0.75214592 | M21: =SUM(M3:M5,M10,M12)/M20 -> 0.73911814 | N21: =SUM(N3:N5,N10,N12)/N20 -> 0.73420369 | O21: =SUM(O3:O5,O10,O16)/O20 -> 0.65631425 | P21: =SUM(P3,P5,P10,P12,P16)/P20 -> 0.69978736 | Q21: =SUM(Q3,Q5,Q10,Q12,Q16)/Q20 -> 0.66504528 | R21: =SUM(R3:R5,R10,R12)/R20 -> 0.70069624 | S21: =SUM(S3,S5,S10,S12,S18)/S20 -> 0.63330533 | T21: =SUM(T3:T5,T10,T12)/T20 -> 0.63633344 | U21: =SUM(U3,U5,U10,U12,U16)/U20 -> 0.65922476 | V21: =SUM(V2:V5,V10)/V20 -> 0.67191168 | W21: =SUM(W2:W5,W10)/W20 -> 0.68303277 | X21: =SUM(X2:X5,X10)/X20 -> 0.65689031 | Y21: =SUM(Y3:Y5,Y10,Y12)/Y20 -> 0.6542596
A22: Valeur des exportations par pays | B22: 2019 | C22: 43855.4
A23: Valeur des exportations par pays | B23: 2020 | C23: 38705.9
A24: Valeur des exportations par pays | B24: 2021 | C24: 46654.2
A25: Valeur des exportations destinées aux pays d'AFRIQUE
A26: Valeur des exportations destinées aux pays d'AFRIQUE | B26: 2000 | C26: 520.9 | D26: =Table5_110[[#This Row],[Value]]/C3 -> 0.065073456
A27: Valeur des exportations destinées aux pays d'AFRIQUE | B27: 2001 | C27: 670.5 | D27: =Table5_110[[#This Row],[Value]]/C4 -> 0.070311025
A28: Valeur des exportations destinées aux pays d'AFRIQUE | B28: 2002 | C28: 810.9 | D28: =Table5_110[[#This Row],[Value]]/C5 -> 0.084043281
A29: Valeur des exportations destinées aux pays d'AFRIQUE | B29: 2003 | C29: 798.2 | D29: =Table5_110[[#This Row],[Value]]/C6 -> 0.077175952
A30: Valeur des exportations destinées aux pays d'AFRIQUE | B30: 2004 | C30: 888.1 | D30: =Table5_110[[#This Row],[Value]]/C7 -> 0.071599026
A31: Valeur des exportations destinées aux pays d'AFRIQUE | B31: 2005 | C31: 1241.9 | D31: =Table5_110[[#This Row],[Value]]/C8 -> 0.090034509
A32: Valeur des exportations destinées aux pays d'AFRIQUE | B32: 2006 | C32: 1518 | D32: =Table5_110[[#This Row],[Value]]/C9 -> 0.097570382
A33: Valeur des exportations destinées aux pays d'AFRIQUE | B33: 2007 | C33: 1892.9 | D33: =Table5_110[[#This Row],[Value]]/C10 -> 0.097523906
A34: Valeur des exportations destinées aux pays d'AFRIQUE | B34: 2008 | C34: 2428.2 | D34: =Table5_110[[#This Row],[Value]]/C11 -> 0.10272877
A35: Valeur des exportations destinées aux pays d'AFRIQUE | B35: 2009 | C35: 2554 | D35: =Table5_110[[#This Row],[Value]]/C12 -> 0.13118156
A36: Valeur des exportations destinées aux pays d'AFRIQUE | B36: 2010 | C36: 2759.2 | D36: =Table5_110[[#This Row],[Value]]/C13 -> 0.11731791
A37: Valeur des exportations destinées aux pays d'AFRIQUE | B37: 2011 | C37: 2844 | D37: =Table5_110[[#This Row],[Value]]/C14 -> 0.11334335
... A47: Valeur des exportations destinées aux pays d'AFRIQUE | B47: 2021 | C47: 4765.6 | D47: =Table5_110[[#This Row],[Value]]/C24 -> 0.10214729
A48: Valeur des exportations destinées à l'Algérie
A49: Valeur des exportations destinées à l'Algérie | B49: 2000 | C49: 84.3 | D49: =Table5_110[[#This Row],[Value]]/C3 -> 0.010531181
A50: Valeur des exportations destinées à l'Algérie | B50: 2001 | C50: 109 | D50: =Table5_110[[#This Row],[Value]]/C4 -> 0.011430129
A51: Valeur des exportations destinées à l'Algérie | B51: 2002 | C51: 126.5 | D51: =Table5_110[[#This Row],[Value]]/C5 -> 0.01311071
A52: Valeur des exportations destinées à l'Algérie | B52: 2003 | C52: 133.4 | D52: =Table5_110[[#This Row],[Value]]/C6 -> 0.012898111
A53: Valeur des exportations destinées à l'Algérie | B53: 2004 | C53: 135.6 | D53: =Table5_110[[#This Row],[Value]]/C7 -> 0.010932134
A54: Valeur des exportations destinées à l'Algérie | B54: 2005 | C54: 237.2 | D54: =Table5_110[[#This Row],[Value]]/C8 -> 0.017196381
A55: Valeur des exportations destinées à l'Algérie | B55: 2006 | C55: 250.2 | D55: =Table5_110[[#This Row],[Value]]/C9 -> 0.016081759
A56: Valeur des exportations destinées à l'Algérie | B56: 2007 | C56: 367.3 | D56: =Table5_110[[#This Row],[Value]]/C10 -> 0.018923625
A57: Valeur des exportations destinées à l'Algérie | B57: 2008 | C57: 499.3 | D57: =Table5_110[[#This Row],[Value]]/C11 -> 0.021123662
A58: Valeur des exportations destinées à l'Algérie | B58: 2009 | C58: 608.2 | D58: =Table5_110[[#This Row],[Value]]/C12 -> 0.031239085
A59: Valeur des exportations destinées à l'Algérie | B59: 2010 | C59: 679.7 | D59: =Table5_110[[#This Row],[Value]]/C13 -> 0.028900038
A60: Valeur des exportations destinées à l'Algérie | B60: 2011 | C60: 656 | D60: =Table5_110[[#This Row],[Value]]/C14 -> 0.026143895
... A67: Valeur des exportations destinées à l'Algérie | B67: 2018 | C67: 1121.7 | D67: =Table5_110[[#This Row],[Value]]/C21 -> 0.027366947
A68: Valeur des exportations destinées à l'Algérie | B68: 2019
A69: Valeur des exportations destinées à l'Algérie | B69: 2020
A70: Valeur des exportations destinées à l'Algérie | B70: 2021
A71: Valeur des exportations destinées au Libye
A72: Valeur des exportations destinées au Libye | B72: 2000 | C72: 288.9 | D72: =Table5_110[[#This Row],[Value]]/C3 -> 0.036090845
A73: Valeur des exportations destinées au Libye | B73: 2001 | C73: 357.5 | D73: =Table5_110[[#This Row],[Value]]/C4 -> 0.037488727
A74: Valeur des exportations destinées au Libye | B74: 2002 | C74: 464.9 | D74: =Table5_110[[#This Row],[Value]]/C5 -> 0.048183156
A75: Valeur des exportations destinées au Libye | B75: 2003 | C75: 453.8 | D75: =Table5_110[[#This Row],[Value]]/C6 -> 0.043876781
A76: Valeur des exportations destinées au Libye | B76: 2004 | C76: 499.9 | D76: =Table5_110[[#This Row],[Value]]/C7 -> 0.040302165
A77: Valeur des exportations destinées au Libye | B77: 2005 | C77: 622.6 | D77: =Table5_110[[#This Row],[Value]]/C8 -> 0.045136875
A78: Valeur des exportations destinées au Libye | B78: 2006 | C78: 825.8 | D78: =Table5_110[[#This Row],[Value]]/C9 -> 0.053078802
A79: Valeur des exportations destinées au Libye | B79: 2007 | C79: 892.7 | D79: =Table5_110[[#This Row],[Value]]/C10 -> 0.045992705
A80: Valeur des exportations destinées au Libye | B80: 2008 | C80: 1065.2 | D80: =Table5_110[[#This Row],[Value]]/C11 -> 0.045064941
A81: Valeur des exportations destinées au Libye | B81: 2009 | C81: 1121.2 | D81: =Table5_110[[#This Row],[Value]]/C12 -> 0.057588396
A82: Valeur des exportations destinées au Libye | B82: 2010 | C82: 1048.5 | D82: =Table5_110[[#This Row],[Value]]/C13 -> 0.044580977
A83: Valeur des exportations destinées au Libye | B83: 2011 | C83: 1103.3 | D83: =Table5_110[[#This Row],[Value]]/C14 -> 0.043970365
... A90: Valeur des exportations destinées au Libye | B90: 2018 | C90: 1313.3 | D90: =Table5_110[[#This Row],[Value]]/C21 -> 0.032041554
A91: Valeur des exportations destinées au Libye | B91: 2019
A92: Valeur des exportations destinées au Libye | B92: 2020
A93: Valeur des exportations destinées au Libye | B93: 2021
A94: Valeur des exportations destinées au Maroc
A95: Valeur des exportations destinées au Maroc | B95: 2000 | C95: 34.8 | D95: =Table5_110[[#This Row],[Value]]/C3 -> 0.0043473916
A96: Valeur des exportations destinées au Maroc | B96: 2001 | C96: 58.7 | D96: =Table5_110[[#This Row],[Value]]/C4 -> 0.0061554917
A97: Valeur des exportations destinées au Maroc | B97: 2002 | C97: 72.2 | D97: =Table5_110[[#This Row],[Value]]/C5 -> 0.0074829509
A98: Valeur des exportations destinées au Maroc | B98: 2003 | C98: 69.7 | D98: =Table5_110[[#This Row],[Value]]/C6 -> 0.0067391178
A99: Valeur des exportations destinées au Maroc | B99: 2004 | C99: 92.4 | D99: =Table5_110[[#This Row],[Value]]/C7 -> 0.00744933
A100: Valeur des exportations destinées au Maroc | B100: 2005 | C100: 141.9 | D100: =Table5_110[[#This Row],[Value]]/C8 -> 0.01028738
A101: Valeur des exportations destinées au Maroc | B101: 2006 | C101: 144.6 | D101: =Table5_110[[#This Row],[Value]]/C9 -> 0.0092942538
A102: Valeur des exportations destinées au Maroc | B102: 2007 | C102: 221.3 | D102: =Table5_110[[#This Row],[Value]]/C10 -> 0.011401574
A103: Valeur des exportations destinées au Maroc | B103: 2008 | C103: 286.5 | D103: =Table5_110[[#This Row],[Value]]/C11 -> 0.012120828
A104: Valeur des exportations destinées au Maroc | B104: 2009 | C104: 282.2 | D104: =Table5_110[[#This Row],[Value]]/C12 -> 0.014494689
A105: Valeur des exportations destinées au Maroc | B105: 2010 | C105: 332.1 | D105: =Table5_110[[#This Row],[Value]]/C13 -> 0.014120498
A106: Valeur des exportations destinées au Maroc | B106: 2011 | C106: 336.7 | D106: =Table5_110[[#This Row],[Value]]/C14 -> 0.013418673
... A113: Valeur des exportations destinées au Maroc | B113: 2018 | C113: 602.3 | D113: =Table5_110[[#This Row],[Value]]/C21 -> 0.01469476
A114: Valeur des exportations destinées au Maroc | B114: 2019
A115: Valeur des exportations destinées au Maroc | B115: 2020
A116: Valeur des exportations destinées au Maroc | B116: 2021
A117: Valeur des exportations destinées au Autres pays d'Afrique
A118: Valeur des exportations destinées au Autres pays d'Afrique | B118: 2000 | C118: 112.9 | D118: =Table5_110[[#This Row],[Value]]/C3 -> 0.014104038
A119: Valeur des exportations destinées au Autres pays d'Afrique | B119: 2001 | C119: 145.3 | D119: =Table5_110[[#This Row],[Value]]/C4 -> 0.015236677
A120: Valeur des exportations destinées au Autres pays d'Afrique | B120: 2002 | C120: 147.3 | D120: =Table5_110[[#This Row],[Value]]/C5 -> 0.015266464
A121: Valeur des exportations destinées au Autres pays d'Afrique | B121: 2003 | C121: 141.3 | D121: =Table5_110[[#This Row],[Value]]/C6 -> 0.013661942
A122: Valeur des exportations destinées au Autres pays d'Afrique | B122: 2004 | C122: 160.2 | D122: =Table5_110[[#This Row],[Value]]/C7 -> 0.012915397
A123: Valeur des exportations destinées au Autres pays d'Afrique | B123: 2005 | C123: 240.2 | D123: =Table5_110[[#This Row],[Value]]/C8 -> 0.017413873
A124: Valeur des exportations destinées au Autres pays d'Afrique | B124: 2006 | C124: 297.4 | D124: =Table5_110[[#This Row],[Value]]/C9 -> 0.019115568
A125: Valeur des exportations destinées au Autres pays d'Afrique | B125: 2007 | C125: 411.6 | D125: =Table5_110[[#This Row],[Value]]/C10 -> 0.021206001
A126: Valeur des exportations destinées au Autres pays d'Afrique | B126: 2008 | C126: 577.2 | D126: =Table5_110[[#This Row],[Value]]/C11 -> 0.024419343
A127: Valeur des exportations destinées au Autres pays d'Afrique | B127: 2009 | C127: 542.4 | D127: =Table5_110[[#This Row],[Value]]/C12 -> 0.027859388
A128: Valeur des exportations destinées au Autres pays d'Afrique | B128: 2010 | C128: 689.9 | D128: =Table5_110[[#This Row],[Value]]/C13 -> 0.02933373
A129: Valeur des exportations destinées au Autres pays d'Afrique | B129: 2011 | C129: 748 | D129: =Table5_110[[#This Row],[Value]]/C14 -> 0.029810417
... A136: Valeur des exportations destinées au Autres pays d'Afrique | B136: 2018 | C136: 1262.9 | D136: =Table5_110[[#This Row],[Value]]/C21 -> 0.030811908
A137: Valeur des exportations destinées au Autres pays d'Afrique | B137: 2019
A138: Valeur des exportations destinées au Autres pays d'Afrique | B138: 2020
...

Sheet Sheet1
